Workbook
Name A: #REF!,#REF!,#REF!
Name A: #REF!,#REF!,#REF!
Name AAA: #REF!,#REF!,#REF!
Name AAA: #REF!,#REF!,#REF!
Name ALl: #REF!
Name ALl: #REF!
Name CHFL: #REF!
Name CHFL: #REF!
Name DHFL: #REF!
Name DHFL: #REF!
Name FLCODE: #REF!
Name FLCODE: #REF!
Name JHFL: #REF!
Name JHFL: #REF!
Name LHFL: #REF!
Name LHFL: #REF!
Name LOCATION: #REF!
Name LOCATION: #REF!
Name MHFL: #REF!
Name MHFL: #REF!
Name MM: #REF!,#REF!,#REF!,#REF!,#REF!,#REF!,#REF!,#REF!,#REF!,#REF!,#REF!,#REF!,#REF!,#REF!,#REF!,#REF!,#REF!,#REF!,#REF!,#REF!,#REF!,#REF!,#REF!,#REF!,#REF!,#REF!,#REF!,#REF!,#REF!,#REF!
Name MM: #REF!,#REF!,#REF!,#REF!,#REF!,#REF!,#REF!,#REF!,#REF!,#REF!,#REF!,#REF!,#REF!,#REF!,#REF!,#REF!,#REF!,#REF!,#REF!,#REF!,#REF!,#REF!,#REF!,#REF!,#REF!,#REF!,#REF!,#REF!,#REF!,#REF!
Name PHFL: #REF!
Name PHFL: #REF!
Name PLFL: #REF!
Name PLFL: #REF!
Name Slicer_Level1: #N/A
Name Slicer_Material_Type: #N/A
Name Slicer_Material_Type1: #N/A
Name Slicer_Section1: #N/A
Name Slicer_Sub_Element: #N/A
Name Slicer_Sub_Element1: #N/A
Name Slicer_Sub_Section1: #N/A
Name test: #REF!,#REF!,#REF!,#REF!,#REF!,#REF!,#REF!,#REF!,#REF!,#REF!,#REF!,#REF!,#REF!,#REF!,#REF!,#REF!,#REF!,#REF!,#REF!,#REF!,#REF!,#REF!,#REF!,#REF!,#REF!,#REF!,#REF!,#REF!,#REF!,#REF!,#REF!,#REF!,#REF!
Name test: #REF!,#REF!,#REF!,#REF!,#REF!,#REF!,#REF!,#REF!,#REF!,#REF!,#REF!,#REF!,#REF!,#REF!,#REF!,#REF!,#REF!,#REF!,#REF!,#REF!,#REF!,#REF!,#REF!,#REF!,#REF!,#REF!,#REF!,#REF!,#REF!,#REF!,#REF!,#REF!,#REF!

Sheet Cover
B1: TENDER COST SUMMARY
B2: Structure + Architecture + Preliminaries — For Submission to Client — For Approval
B4: Project Name | C4: 10-Storey School Building
B5: Scope | C5: Structure + Architecture + Preliminaries
B6: Client | C6: ( client name )
B7: Location | C7: Phnom Penh, Cambodia
B8: Contractor | C8: ( your company )
B9: Tender Ref. | C9: SCH-COMB-002
B10: Date | C10: ( dd/mm/yyyy )
B12: 1. ELEMENTAL COST SUMMARY
B13: Code | C13: Description | D13: Amount ($) | E13: Remark
B14: A.00 | C14: Early Work | D14: — | E14: Excluded
B15: B.01 | C15: Piling Work | D15: =SUMIF('Raw Data'!$D:$D,"B.01",'Raw Data'!$Z:$Z) -> 105084.37 | E15: Priced
B16: B.03 | C16: Ground Floor / Foundation | D16: =SUMIF('Raw Data'!$D:$D,"B.03",'Raw Data'!$Z:$Z) -> 95210.475 | E16: Priced
B17: B.04 | C17: Super Structure | D17: =SUMIF('Raw Data'!$D:$D,"B.04",'Raw Data'!$Z:$Z) -> 1124399.7 | E17: Priced
B18: C.01 | C18: Exterior Wall & Partition | D18: =SUMIF('Raw Data'!$D:$D,"C.01",'Raw Data'!$Z:$Z) -> 103864.41 | E18: Priced
B19: C.02 | C19: Exterior Wall Finishes | D19: =SUMIF('Raw Data'!$D:$D,"C.02",'Raw Data'!$Z:$Z) -> 97761.364 | E19: Priced
B20: C.04 | C20: Exterior Window & Louver | D20: =SUMIF('Raw Data'!$D:$D,"C.04",'Raw Data'!$Z:$Z) -> 95868.192 | E20: Priced
B21: C.09 | C21: Interior Wall & Partition | D21: =SUMIF('Raw Data'!$D:$D,"C.09",'Raw Data'!$Z:$Z) -> 100365.77 | E21: Priced
B22: C.10 | C22: Interior Door / Windows | D22: =SUMIF('Raw Data'!$D:$D,"C.10",'Raw Data'!$Z:$Z) -> 44984.8 | E22: Priced
B23: D.01 | C23: Interior Wall Finishes | D23: =SUMIF('Raw Data'!$D:$D,"D.01",'Raw Data'!$Z:$Z) -> 139757.64 | E23: Priced
B24: D.02 | C24: Interior Floor Finishes | D24: =SUMIF('Raw Data'!$D:$D,"D.02",'Raw Data'!$Z:$Z) -> 43665.44 | E24: Priced
B25: D.03 | C25: Ceiling Finishes | D25: =SUMIF('Raw Data'!$D:$D,"D.03",'Raw Data'!$Z:$Z) -> 72072 | E25: Priced
B26: E.04 | C26: Signage | D26: =SUMIF('Raw Data'!$D:$D,"E.04",'Raw Data'!$Z:$Z) -> 6600 | E26: Priced
B27: F.00 | C27: MEP Services | D27: — | E27: Excluded
B28: G.00 | C28: External Works | D28: — | E28: Excluded
B29: X.00 | C29: Authority & Insurance | D29: — | E29: Excluded
B30: DIRECT WORKS COST (A) | D30: =D15+D16+D17+D18+D19+D20+D21+D22+D23+D24+D25+D26 -> 2029634.1
B32: 2. COMMERCIAL BUILD-UP TO TENDER PRICE
B33: Item | C33: % (input) | D33: Amount ($)
B34: Direct Works Cost (A) | D34: =D30 -> 2029634.1
B35: Add: Preliminaries & General (Z) | C35: (itemized, 22 items) | D35: =Preliminaries!$F$27 -> 403700
B36: Subtotal | D36: =D34+D35 -> 2433334.1
B37: Add: Head Office Overhead | C37: 0.05 | D37: =D36*C37 -> 121666.71
B38: Add: Risk & Contingency | C38: 0.03 | D38: =D36*C38 -> 73000.024
B39: Add: Profit | C39: 0.08 | D39: =D36*C39 -> 194666.73
B40: Subtotal before VAT | D40: =D36+D37+D38+D39 -> 2822667.6
B41: Add: VAT | C41: 0.1 | D41: =D40*C41 -> 282266.76
B42: TENDER PRICE (USD) | D42: =D40+D41 -> 3104934.3
B43: Amount in words: ____________________________________________________________
B45: 3. APPROVAL
B46: Prepared by (QS / Estimator) | D46: Checked by (QS Manager)
B48: Name / Signature / Date | D48: Name / Signature / Date
B50: Approved by (Contractor) | D50: Accepted by (Client)
B52: Name / Signature / Date | D52: Name / Signature / Date

Sheet BoQ Breakdown
A1: BILL OF QUANTITIES — STRUCTURE + ARCHITECTURE — DETAILED BREAKDOWN
A2: 10-Storey School Building | Phnom Penh, Cambodia | USD ($)
A3: Quantities & amounts roll up live from Raw Data; rates flow from the Price List (70 items).
A5: Item | B5: Description | C5: Unit | D5: Quantity | E5: Labor Rate ($) | F5: Material Rate ($) | G5: Total Rate ($) | H5: Amount ($)
A6: B.01 — PILING WORK
A7: Bored Pile
A8: B.01.01 | B8: Pile Head Cutting up to required level D1000mm | C8: Nos | D8: =SUMIFS('Raw Data'!$Q:$Q,'Raw Data'!$D:$D,"B.01",'Raw Data'!$H:$H,"Bored Pile",'Raw Data'!$J:$J,"Pile Head Cutting up to required level D1000mm") -> 5 | E8: =IFERROR(INDEX('Price List'!$I$5:$I$74,MATCH("Pile Head Cutting up to required level D1000mm|Nos",'Price List'!$O$5:$O$74,0)),0) -> 66 | F8: =IFERROR(INDEX('Price List'!$L$5:$L$74,MATCH("Pile Head Cutting up to required level D1000mm|Nos",'Price List'!$O$5:$O$74,0)),0) -> 0 | G8: =E8+F8 -> 66 | H8: =SUMIFS('Raw Data'!$Z:$Z,'Raw Data'!$D:$D,"B.01",'Raw Data'!$H:$H,"Bored Pile",'Raw Data'!$J:$J,"Pile Head Cutting up to required level D1000mm") -> 330
A9: B.01.02 | B9: Pile Head Cutting up to required level D800mm | C9: Nos | D9: =SUMIFS('Raw Data'!$Q:$Q,'Raw Data'!$D:$D,"B.01",'Raw Data'!$H:$H,"Bored Pile",'Raw Data'!$J:$J,"Pile Head Cutting up to required level D800mm") -> 17 | E9: =IFERROR(INDEX('Price List'!$I$5:$I$74,MATCH("Pile Head Cutting up to required level D800mm|Nos",'Price List'!$O$5:$O$74,0)),0) -> 48 | F9: =IFERROR(INDEX('Price List'!$L$5:$L$74,MATCH("Pile Head Cutting up to required level D800mm|Nos",'Price List'!$O$5:$O$74,0)),0) -> 0 | G9: =E9+F9 -> 48 | H9: =SUMIFS('Raw Data'!$Z:$Z,'Raw Data'!$D:$D,"B.01",'Raw Data'!$H:$H,"Bored Pile",'Raw Data'!$J:$J,"Pile Head Cutting up to required level D800mm") -> 816
A10: B.01.03 | B10: Sonic Logging Test (SLT) | C10: Nos | D10: =SUMIFS('Raw Data'!$Q:$Q,'Raw Data'!$D:$D,"B.01",'Raw Data'!$H:$H,"Bored Pile",'Raw Data'!$J:$J,"Sonic Logging Test (SLT)") -> 22 | E10: =IFERROR(INDEX('Price List'!$I$5:$I$74,MATCH("Sonic Logging Test (SLT)|Nos",'Price List'!$O$5:$O$74,0)),0) -> 0 | F10: =IFERROR(INDEX('Price List'!$L$5:$L$74,MATCH("Sonic Logging Test (SLT)|Nos",'Price List'!$O$5:$O$74,0)),0) -> 55 | G10: =E10+F10 -> 55 | H10: =SUMIFS('Raw Data'!$Z:$Z,'Raw Data'!$D:$D,"B.01",'Raw Data'!$H:$H,"Bored Pile",'Raw Data'!$J:$J,"Sonic Logging Test (SLT)") -> 1210
A11: B.01.04 | B11: Soil Coring for Bored Pile D1000mm, Depth 30m | C11: Nos | D11: =SUMIFS('Raw Data'!$Q:$Q,'Raw Data'!$D:$D,"B.01",'Raw Data'!$H:$H,"Bored Pile",'Raw Data'!$J:$J,"Soil Coring for Bored Pile D1000mm, Depth 30m") -> 5 | E11: =IFERROR(INDEX('Price List'!$I$5:$I$74,MATCH("Soil Coring for Bored Pile D1000mm, Depth 30m|Nos",'Price List'!$O$5:$O$74,0)),0) -> 0 | F11: =IFERROR(INDEX('Price List'!$L$5:$L$74,MATCH("Soil Coring for Bored Pile D1000mm, Depth 30m|Nos",'Price List'!$O$5:$O$74,0)),0) -> 385 | G11: =E11+F11 -> 385 | H11: =SUMIFS('Raw Data'!$Z:$Z,'Raw Data'!$D:$D,"B.01",'Raw Data'!$H:$H,"Bored Pile",'Raw Data'!$J:$J,"Soil Coring for Bored Pile D1000mm, Depth 30m") -> 1925
A12: B.01.05 | B12: Soil Coring for Bored Pile D800mm, Depth 30m | C12: Nos | D12: =SUMIFS('Raw Data'!$Q:$Q,'Raw Data'!$D:$D,"B.01",'Raw Data'!$H:$H,"Bored Pile",'Raw Data'!$J:$J,"Soil Coring for Bored Pile D800mm, Depth 30m") -> 17 | E12: =IFERROR(INDEX('Price List'!$I$5:$I$74,MATCH("Soil Coring for Bored Pile D800mm, Depth 30m|Nos",'Price List'!$O$5:$O$74,0)),0) -> 0 | F12: =IFERROR(INDEX('Price List'!$L$5:$L$74,MATCH("Soil Coring for Bored Pile D800mm, Depth 30m|Nos",'Price List'!$O$5:$O$74,0)),0) -> 330 | G12: =E12+F12 -> 330 | H12: =SUMIFS('Raw Data'!$Z:$Z,'Raw Data'!$D:$D,"B.01",'Raw Data'!$H:$H,"Bored Pile",'Raw Data'!$J:$J,"Soil Coring for Bored Pile D800mm, Depth 30m") -> 5610
A13: B.01.06 | B13: Normal Concrete, 35Mpa (Cylinder), Slump 15+-2.5 | C13: m3 | D13: =SUMIFS('Raw Data'!$Q:$Q,'Raw Data'!$D:$D,"B.01",'Raw Data'!$H:$H,"Bored Pile",'Raw Data'!$J:$J,"Normal Concrete, 35Mpa (Cylinder), Slump 15+-2.5") -> 374.16369 | E13: =IFERROR(INDEX('Price List'!$I$5:$I$74,MATCH("Normal Concrete, 35Mpa (Cylinder), Slump 15+-2.5|m3",'Price List'!$O$5:$O$74,0)),0) -> 9.6 | F13: =IFERROR(INDEX('Price List'!$L$5:$L$74,MATCH("Normal Concrete, 35Mpa (Cylinder), Slump 15+-2.5|m3",'Price List'!$O$5:$O$74,0)),0) -> 109.76 | G13: =E13+F13 -> 119.36 | H13: =SUMIFS('Raw Data'!$Z:$Z,'Raw Data'!$D:$D,"B.01",'Raw Data'!$H:$H,"Bored Pile",'Raw Data'!$J:$J,"Normal Concrete, 35Mpa (Cylinder), Slump 15+-2.5") -> 44660.177
A14: B.01.07 | B14: Deform Bar, DB10(fy=390 Mpa) | C14: kg | D14: =SUMIFS('Raw Data'!$Q:$Q,'Raw Data'!$D:$D,"B.01",'Raw Data'!$H:$H,"Bored Pile",'Raw Data'!$J:$J,"Deform Bar, DB10(fy=390 Mpa)") -> 2553.8864 | E14: =IFERROR(INDEX('Price List'!$I$5:$I$74,MATCH("Deform Bar, DB10(fy=390 Mpa)|kg",'Price List'!$O$5:$O$74,0)),0) -> 0.144 | F14: =IFERROR(INDEX('Price List'!$L$5:$L$74,MATCH("Deform Bar, DB10(fy=390 Mpa)|kg",'Price List'!$O$5:$O$74,0)),0) -> 0.8736 | G14: =E14+F14 -> 1.0176 | H14: =SUMIFS('Raw Data'!$Z:$Z,'Raw Data'!$D:$D,"B.01",'Raw Data'!$H:$H,"Bored Pile",'Raw Data'!$J:$J,"Deform Bar, DB10(fy=390 Mpa)") -> 2598.8348
A15: B.01.08 | B15: Deform Bar, DB25(fy=390 Mpa) | C15: kg | D15: =SUMIFS('Raw Data'!$Q:$Q,'Raw Data'!$D:$D,"B.01",'Raw Data'!$H:$H,"Bored Pile",'Raw Data'!$J:$J,"Deform Bar, DB25(fy=390 Mpa)") -> 33921.812 | E15: =IFERROR(INDEX('Price List'!$I$5:$I$74,MATCH("Deform Bar, DB25(fy=390 Mpa)|kg",'Price List'!$O$5:$O$74,0)),0) -> 0.096 | F15: =IFERROR(INDEX('Price List'!$L$5:$L$74,MATCH("Deform Bar, DB25(fy=390 Mpa)|kg",'Price List'!$O$5:$O$74,0)),0) -> 0.8064 | G15: =E15+F15 -> 0.9024 | H15: =SUMIFS('Raw Data'!$Z:$Z,'Raw Data'!$D:$D,"B.01",'Raw Data'!$H:$H,"Bored Pile",'Raw Data'!$J:$J,"Deform Bar, DB25(fy=390 Mpa)") -> 30611.043
A16: B.01.09 | B16: Steel Tie Wire 1mm (Estimated 4% of Total Rebar Weight) | C16: kg | D16: =SUMIFS('Raw Data'!$Q:$Q,'Raw Data'!$D:$D,"B.01",'Raw Data'!$H:$H,"Bored Pile",'Raw Data'!$J:$J,"Steel Tie Wire 1mm (Estimated 4% of Total Rebar Weight)") -> 1459.0279 | E16: =IFERROR(INDEX('Price List'!$I$5:$I$74,MATCH("Steel Tie Wire 1mm (Estimated 4% of Total Rebar Weight)|kg",'Price List'!$O$5:$O$74,0)),0) -> 0.06 | F16: =IFERROR(INDEX('Price List'!$L$5:$L$74,MATCH("Steel Tie Wire 1mm (Estimated 4% of Total Rebar Weight)|kg",'Price List'!$O$5:$O$74,0)),0) -> 1.344 | G16: =E16+F16 -> 1.404 | H16: =SUMIFS('Raw Data'!$Z:$Z,'Raw Data'!$D:$D,"B.01",'Raw Data'!$H:$H,"Bored Pile",'Raw Data'!$J:$J,"Steel Tie Wire 1mm (Estimated 4% of Total Rebar Weight)") -> 2048.4752
A17: B.01.10 | B17: Steel Round Pipe (D49x2mm) with rush primer and paint | C17: m | D17: =SUMIFS('Raw Data'!$Q:$Q,'Raw Data'!$D:$D,"B.01",'Raw Data'!$H:$H,"Bored Pile",'Raw Data'!$J:$J,"Steel Round Pipe (D49x2mm) with rush primer and paint") -> 2201 | E17: =IFERROR(INDEX('Price List'!$I$5:$I$74,MATCH("Steel Round Pipe (D49x2mm) with rush primer and paint|m",'Price List'!$O$5:$O$74,0)),0) -> 1.8 | F17: =IFERROR(INDEX('Price List'!$L$5:$L$74,MATCH("Steel Round Pipe (D49x2mm) with rush primer and paint|m",'Price List'!$O$5:$O$74,0)),0) -> 5.04 | G17: =E17+F17 -> 6.84 | H17: =SUMIFS('Raw Data'!$Z:$Z,'Raw Data'!$D:$D,"B.01",'Raw Data'!$H:$H,"Bored Pile",'Raw Data'!$J:$J,"Steel Round Pipe (D49x2mm) with rush primer and paint") -> 15054.84
A18: B.01.11 | B18: Rebar Testing as per Specification | C18: Lot | D18: =SUMIFS('Raw Data'!$Q:$Q,'Raw Data'!$D:$D,"B.01",'Raw Data'!$H:$H,"Bored Pile",'Raw Data'!$J:$J,"Rebar Testing as per Specification") -> 1 | E18: =IFERROR(INDEX('Price List'!$I$5:$I$74,MATCH("Rebar Testing as per Specification|Lot",'Price List'!$O$5:$O$74,0)),0) -> 0 | F18: =IFERROR(INDEX('Price List'!$L$5:$L$74,MATCH("Rebar Testing as per Specification|Lot",'Price List'!$O$5:$O$74,0)),0) -> 220 | G18: =E18+F18 -> 220 | H18: =SUMIFS('Raw Data'!$Z:$Z,'Raw Data'!$D:$D,"B.01",'Raw Data'!$H:$H,"Bored Pile",'Raw Data'!$J:$J,"Rebar Testing as per Specification") -> 220
B19: Subtotal — Bored Pile | H19: =SUM(H8:H18) -> 105084.37
B20: SUBTOTAL B.01 | H20: =SUMIFS('Raw Data'!$Z:$Z,'Raw Data'!$D:$D,"B.01") -> 105084.37
A22: B.03 — GROUND FLOOR / FOUNDATION
A23: Pile Cap & Stump
A24: B.03.01 | B24: Soil Excavation | C24: m3 | D24: =SUMIFS('Raw Data'!$Q:$Q,'Raw Data'!$D:$D,"B.03",'Raw Data'!$H:$H,"Pile Cap & Stump",'Raw Data'!$J:$J,"Soil Excavation") -> 1283.17 | E24: =IFERROR(INDEX('Price List'!$I$5:$I$74,MATCH("Soil Excavation|m3",'Price List'!$O$5:$O$74,0)),0) -> 3.6 | F24: =IFERROR(INDEX('Price List'!$L$5:$L$74,MATCH("Soil Excavation|m3",'Price List'!$O$5:$O$74,0)),0) -> 0 | G24: =E24+F24 -> 3.6 | H24: =SUMIFS('Raw Data'!$Z:$Z,'Raw Data'!$D:$D,"B.03",'Raw Data'!$H:$H,"Pile Cap & Stump",'Raw Data'!$J:$J,"Soil Excavation") -> 4619.412
A25: B.03.02 | B25: Soil Disposal | C25: m3 | D25: =SUMIFS('Raw Data'!$Q:$Q,'Raw Data'!$D:$D,"B.03",'Raw Data'!$H:$H,"Pile Cap & Stump",'Raw Data'!$J:$J,"Soil Disposal") -> 1283.17 | E25: =IFERROR(INDEX('Price List'!$I$5:$I$74,MATCH("Soil Disposal|m3",'Price List'!$O$5:$O$74,0)),0) -> 4.8 | F25: =IFERROR(INDEX('Price List'!$L$5:$L$74,MATCH("Soil Disposal|m3",'Price List'!$O$5:$O$74,0)),0) -> 0 | G25: =E25+F25 -> 4.8 | H25: =SUMIFS('Raw Data'!$Z:$Z,'Raw Data'!$D:$D,"B.03",'Raw Data'!$H:$H,"Pile Cap & Stump",'Raw Data'!$J:$J,"Soil Disposal") -> 6159.216
A26: B.03.03 | B26: Soil Backfill | C26: m3 | D26: =SUMIFS('Raw Data'!$Q:$Q,'Raw Data'!$D:$D,"B.03",'Raw Data'!$H:$H,"Pile Cap & Stump",'Raw Data'!$J:$J,"Soil Backfill") -> 1148.424 | E26: =IFERROR(INDEX('Price List'!$I$5:$I$74,MATCH("Soil Backfill|m3",'Price List'!$O$5:$O$74,0)),0) -> 4.8 | F26: =IFERROR(INDEX('Price List'!$L$5:$L$74,MATCH("Soil Backfill|m3",'Price List'!$O$5:$O$74,0)),0) -> 0 | G26: =E26+F26 -> 4.8 | H26: =SUMIFS('Raw Data'!$Z:$Z,'Raw Data'!$D:$D,"B.03",'Raw Data'!$H:$H,"Pile Cap & Stump",'Raw Data'!$J:$J,"Soil Backfill") -> 5512.4352
A27: B.03.04 | B27: Normal Concrete, 35Mpa (Cylinder), Slump 13+-2.5 | C27: m3 | D27: =SUMIFS('Raw Data'!$Q:$Q,'Raw Data'!$D:$D,"B.03",'Raw Data'!$H:$H,"Pile Cap & Stump",'Raw Data'!$J:$J,"Normal Concrete, 35Mpa (Cylinder), Slump 13+-2.5") -> 134.746 | E27: =IFERROR(INDEX('Price List'!$I$5:$I$74,MATCH("Normal Concrete, 35Mpa (Cylinder), Slump 13+-2.5|m3",'Price List'!$O$5:$O$74,0)),0) -> 12 | F27: =IFERROR(INDEX('Price List'!$L$5:$L$74,MATCH("Normal Concrete, 35Mpa (Cylinder), Slump 13+-2.5|m3",'Price List'!$O$5:$O$74,0)),0) -> 109.76 | G27: =E27+F27 -> 121.76 | H27: =SUMIFS('Raw Data'!$Z:$Z,'Raw Data'!$D:$D,"B.03",'Raw Data'!$H:$H,"Pile Cap & Stump",'Raw Data'!$J:$J,"Normal Concrete, 35Mpa (Cylinder), Slump 13+-2.5") -> 16406.673
A28: B.03.05 | B28: Formwork | C28: m2 | D28: =SUMIFS('Raw Data'!$Q:$Q,'Raw Data'!$D:$D,"B.03",'Raw Data'!$H:$H,"Pile Cap & Stump",'Raw Data'!$J:$J,"Formwork") -> 200.935 | E28: =IFERROR(INDEX('Price List'!$I$5:$I$74,MATCH("Formwork|m2",'Price List'!$O$5:$O$74,0)),0) -> 7.2 | F28: =IFERROR(INDEX('Price List'!$L$5:$L$74,MATCH("Formwork|m2",'Price List'!$O$5:$O$74,0)),0) -> 5.6 | G28: =E28+F28 -> 12.8 | H28: =SUMIFS('Raw Data'!$Z:$Z,'Raw Data'!$D:$D,"B.03",'Raw Data'!$H:$H,"Pile Cap & Stump",'Raw Data'!$J:$J,"Formwork") -> 2571.968
A29: B.03.06 | B29: Deform Bar, DB10(fy=390 Mpa) | C29: kg | D29: =SUMIFS('Raw Data'!$Q:$Q,'Raw Data'!$D:$D,"B.03",'Raw Data'!$H:$H,"Pile Cap & Stump",'Raw Data'!$J:$J,"Deform Bar, DB10(fy=390 Mpa)") -> 34.55 | E29: =IFERROR(INDEX('Price List'!$I$5:$I$74,MATCH("Deform Bar, DB10(fy=390 Mpa)|kg",'Price List'!$O$5:$O$74,0)),0) -> 0.144 | F29: =IFERROR(INDEX('Price List'!$L$5:$L$74,MATCH("Deform Bar, DB10(fy=390 Mpa)|kg",'Price List'!$O$5:$O$74,0)),0) -> 0.8736 | G29: =E29+F29 -> 1.0176 | H29: =SUMIFS('Raw Data'!$Z:$Z,'Raw Data'!$D:$D,"B.03",'Raw Data'!$H:$H,"Pile Cap & Stump",'Raw Data'!$J:$J,"Deform Bar, DB10(fy=390 Mpa)") -> 35.15808
A30: B.03.07 | B30: Deform Bar, DB12(fy=390 Mpa) | C30: kg | D30: =SUMIFS('Raw Data'!$Q:$Q,'Raw Data'!$D:$D,"B.03",'Raw Data'!$H:$H,"Pile Cap & Stump",'Raw Data'!$J:$J,"Deform Bar, DB12(fy=390 Mpa)") -> 2639.1376 | E30: =IFERROR(INDEX('Price List'!$I$5:$I$74,MATCH("Deform Bar, DB12(fy=390 Mpa)|kg",'Price List'!$O$5:$O$74,0)),0) -> 0.132 | F30: =IFERROR(INDEX('Price List'!$L$5:$L$74,MATCH("Deform Bar, DB12(fy=390 Mpa)|kg",'Price List'!$O$5:$O$74,0)),0) -> 0.8512 | G30: =E30+F30 -> 0.9832 | H30: =SUMIFS('Raw Data'!$Z:$Z,'Raw Data'!$D:$D,"B.03",'Raw Data'!$H:$H,"Pile Cap & Stump",'Raw Data'!$J:$J,"Deform Bar, DB12(fy=390 Mpa)") -> 2594.8001
A31: B.03.08 | B31: Deform Bar, DB16(fy=390 Mpa) | C31: kg | D31: =SUMIFS('Raw Data'!$Q:$Q,'Raw Data'!$D:$D,"B.03",'Raw Data'!$H:$H,"Pile Cap & Stump",'Raw Data'!$J:$J,"Deform Bar, DB16(fy=390 Mpa)") -> 1372.388 | E31: =IFERROR(INDEX('Price List'!$I$5:$I$74,MATCH("Deform Bar, DB16(fy=390 Mpa)|kg",'Price List'!$O$5:$O$74,0)),0) -> 0.12 | F31: =IFERROR(INDEX('Price List'!$L$5:$L$74,MATCH("Deform Bar, DB16(fy=390 Mpa)|kg",'Price List'!$O$5:$O$74,0)),0) -> 0.8288 | G31: =E31+F31 -> 0.9488 | H31: =SUMIFS('Raw Data'!$Z:$Z,'Raw Data'!$D:$D,"B.03",'Raw Data'!$H:$H,"Pile Cap & Stump",'Raw Data'!$J:$J,"Deform Bar, DB16(fy=390 Mpa)") -> 1302.1217
A32: B.03.09 | B32: Deform Bar, DB20(fy=390 Mpa) | C32: kg | D32: =SUMIFS('Raw Data'!$Q:$Q,'Raw Data'!$D:$D,"B.03",'Raw Data'!$H:$H,"Pile Cap & Stump",'Raw Data'!$J:$J,"Deform Bar, DB20(fy=390 Mpa)") -> 11795.979 | E32: =IFERROR(INDEX('Price List'!$I$5:$I$74,MATCH("Deform Bar, DB20(fy=390 Mpa)|kg",'Price List'!$O$5:$O$74,0)),0) -> 0.108 | F32: =IFERROR(INDEX('Price List'!$L$5:$L$74,MATCH("Deform Bar, DB20(fy=390 Mpa)|kg",'Price List'!$O$5:$O$74,0)),0) -> 0.8176 | G32: =E32+F32 -> 0.9256 | H32: =SUMIFS('Raw Data'!$Z:$Z,'Raw Data'!$D:$D,"B.03",'Raw Data'!$H:$H,"Pile Cap & Stump",'Raw Data'!$J:$J,"Deform Bar, DB20(fy=390 Mpa)") -> 10918.358
A33: B.03.10 | B33: Deform Bar, DB25(fy=390 Mpa) | C33: kg | D33: =SUMIFS('Raw Data'!$Q:$Q,'Raw Data'!$D:$D,"B.03",'Raw Data'!$H:$H,"Pile Cap & Stump",'Raw Data'!$J:$J,"Deform Bar, DB25(fy=390 Mpa)") -> 1694 | E33: =IFERROR(INDEX('Price List'!$I$5:$I$74,MATCH("Deform Bar, DB25(fy=390 Mpa)|kg",'Price List'!$O$5:$O$74,0)),0) -> 0.096 | F33: =IFERROR(INDEX('Price List'!$L$5:$L$74,MATCH("Deform Bar, DB25(fy=390 Mpa)|kg",'Price List'!$O$5:$O$74,0)),0) -> 0.8064 | G33: =E33+F33 -> 0.9024 | H33: =SUMIFS('Raw Data'!$Z:$Z,'Raw Data'!$D:$D,"B.03",'Raw Data'!$H:$H,"Pile Cap & Stump",'Raw Data'!$J:$J,"Deform Bar, DB25(fy=390 Mpa)") -> 1528.6656
A34: B.03.11 | B34: Deform Bar, DB32(fy=390 Mpa) | C34: kg | D34: =SUMIFS('Raw Data'!$Q:$Q,'Raw Data'!$D:$D,"B.03",'Raw Data'!$H:$H,"Pile Cap & Stump",'Raw Data'!$J:$J,"Deform Bar, DB32(fy=390 Mpa)") -> 10611.798 | E34: =IFERROR(INDEX('Price List'!$I$5:$I$74,MATCH("Deform Bar, DB32(fy=390 Mpa)|kg",'Price List'!$O$5:$O$74,0)),0) -> 0.096 | F34: =IFERROR(INDEX('Price List'!$L$5:$L$74,MATCH("Deform Bar, DB32(fy=390 Mpa)|kg",'Price List'!$O$5:$O$74,0)),0) -> 0.7952 | G34: =E34+F34 -> 0.8912 | H34: =SUMIFS('Raw Data'!$Z:$Z,'Raw Data'!$D:$D,"B.03",'Raw Data'!$H:$H,"Pile Cap & Stump",'Raw Data'!$J:$J,"Deform Bar, DB32(fy=390 Mpa)") -> 9457.2344
A35: B.03.12 | B35: Steel Tie Wire 1mm (Estimated 4% of Total Rebar Weight) | C35: kg | D35: =SUMIFS('Raw Data'!$Q:$Q,'Raw Data'!$D:$D,"B.03",'Raw Data'!$H:$H,"Pile Cap & Stump",'Raw Data'!$J:$J,"Steel Tie Wire 1mm (Estimated 4% of Total Rebar Weight)") -> 1069.6366 | E35: =IFERROR(INDEX('Price List'!$I$5:$I$74,MATCH("Steel Tie Wire 1mm (Estimated 4% of Total Rebar Weight)|kg",'Price List'!$O$5:$O$74,0)),0) -> 0.06 | F35: =IFERROR(INDEX('Price List'!$L$5:$L$74,MATCH("Steel Tie Wire 1mm (Estimated 4% of Total Rebar Weight)|kg",'Price List'!$O$5:$O$74,0)),0) -> 1.344 | G35: =E35+F35 -> 1.404 | H35: =SUMIFS('Raw Data'!$Z:$Z,'Raw Data'!$D:$D,"B.03",'Raw Data'!$H:$H,"Pile Cap & Stump",'Raw Data'!$J:$J,"Steel Tie Wire 1mm (Estimated 4% of Total Rebar Weight)") -> 1501.7698
A36: B.03.13 | B36: Well Soil Compact | C36: m2 | D36: =SUMIFS('Raw Data'!$Q:$Q,'Raw Data'!$D:$D,"B.03",'Raw Data'!$H:$H,"Pile Cap & Stump",'Raw Data'!$J:$J,"Well Soil Compact") -> 131.43 | E36: =IFERROR(INDEX('Price List'!$I$5:$I$74,MATCH("Well Soil Compact|m2",'Price List'!$O$5:$O$74,0)),0) -> 2.4 | F36: =IFERROR(INDEX('Price List'!$L$5:$L$74,MATCH("Well Soil Compact|m2",'Price List'!$O$5:$O$74,0)),0) -> 0 | G36: =E36+F36 -> 2.4 | H36: =SUMIFS('Raw Data'!$Z:$Z,'Raw Data'!$D:$D,"B.03",'Raw Data'!$H:$H,"Pile Cap & Stump",'Raw Data'!$J:$J,"Well Soil Compact") -> 315.432
A37: B.03.14 | B37: Lean Concrete, 15Mpa (Cylinder) | C37: m3 | D37: =SUMIFS('Raw Data'!$Q:$Q,'Raw Data'!$D:$D,"B.03",'Raw Data'!$H:$H,"Pile Cap & Stump",'Raw Data'!$J:$J,"Lean Concrete, 15Mpa (Cylinder)") -> 14.8565 | E37: =IFERROR(INDEX('Price List'!$I$5:$I$74,MATCH("Lean Concrete, 15Mpa (Cylinder)|m3",'Price List'!$O$5:$O$74,0)),0) -> 8.4 | F37: =IFERROR(INDEX('Price List'!$L$5:$L$74,MATCH("Lean Concrete, 15Mpa (Cylinder)|m3",'Price List'!$O$5:$O$74,0)),0) -> 84 | G37: =E37+F37 -> 92.4 | H37: =SUMIFS('Raw Data'!$Z:$Z,'Raw Data'!$D:$D,"B.03",'Raw Data'!$H:$H,"Pile Cap & Stump",'Raw Data'!$J:$J,"Lean Concrete, 15Mpa (Cylinder)") -> 1372.7406
A38: B.03.15 | B38: PVC Waterbar® V VN 20 (Width 200mm) | C38: m | D38: =SUMIFS('Raw Data'!$Q:$Q,'Raw Data'!$D:$D,"B.03",'Raw Data'!$H:$H,"Pile Cap & Stump",'Raw Data'!$J:$J,"PVC Waterbar® V VN 20 (Width 200mm)") -> 18 | E38: =IFERROR(INDEX('Price List'!$I$5:$I$74,MATCH("PVC Waterbar® V VN 20 (Width 200mm)|m",'Price List'!$O$5:$O$74,0)),0) -> 1.8 | F38: =IFERROR(INDEX('Price List'!$L$5:$L$74,MATCH("PVC Waterbar® V VN 20 (Width 200mm)|m",'Price List'!$O$5:$O$74,0)),0) -> 4.48 | G38: =E38+F38 -> 6.28 | H38: =SUMIFS('Raw Data'!$Z:$Z,'Raw Data'!$D:$D,"B.03",'Raw Data'!$H:$H,"Pile Cap & Stump",'Raw Data'!$J:$J,"PVC Waterbar® V VN 20 (Width 200mm)") -> 113.04
A39: B.03.16 | B39: Membrance sheet 2mm thk | C39: m2 | D39: =SUMIFS('Raw Data'!$Q:$Q,'Raw Data'!$D:$D,"B.03",'Raw Data'!$H:$H,"Pile Cap & Stump",'Raw Data'!$J:$J,"Membrance sheet 2mm thk") -> 7.2695 | E39: =IFERROR(INDEX('Price List'!$I$5:$I$74,MATCH("Membrance sheet 2mm thk|m2",'Price List'!$O$5:$O$74,0)),0) -> 2.4 | F39: =IFERROR(INDEX('Price List'!$L$5:$L$74,MATCH("Membrance sheet 2mm thk|m2",'Price List'!$O$5:$O$74,0)),0) -> 7.28 | G39: =E39+F39 -> 9.68 | H39: =SUMIFS('Raw Data'!$Z:$Z,'Raw Data'!$D:$D,"B.03",'Raw Data'!$H:$H,"Pile Cap & Stump",'Raw Data'!$J:$J,"Membrance sheet 2mm thk") -> 70.36876
B40: Subtotal — Pile Cap & Stump | H40: =SUM(H24:H39) -> 64479.393
A41: Septic tank
A42: B.03.17 | B42: Soil Excavation | C42: m3 | D42: =SUMIFS('Raw Data'!$Q:$Q,'Raw Data'!$D:$D,"B.03",'Raw Data'!$H:$H,"Septic tank",'Raw Data'!$J:$J,"Soil Excavation") -> 288 | E42: =IFERROR(INDEX('Price List'!$I$5:$I$74,MATCH("Soil Excavation|m3",'Price List'!$O$5:$O$74,0)),0) -> 3.6 | F42: =IFERROR(INDEX('Price List'!$L$5:$L$74,MATCH("Soil Excavation|m3",'Price List'!$O$5:$O$74,0)),0) -> 0 | G42: =E42+F42 -> 3.6 | H42: =SUMIFS('Raw Data'!$Z:$Z,'Raw Data'!$D:$D,"B.03",'Raw Data'!$H:$H,"Septic tank",'Raw Data'!$J:$J,"Soil Excavation") -> 1036.8
A43: B.03.18 | B43: Soil Disposal | C43: m3 | D43: =SUMIFS('Raw Data'!$Q:$Q,'Raw Data'!$D:$D,"B.03",'Raw Data'!$H:$H,"Septic tank",'Raw Data'!$J:$J,"Soil Disposal") -> 288 | E43: =IFERROR(INDEX('Price List'!$I$5:$I$74,MATCH("Soil Disposal|m3",'Price List'!$O$5:$O$74,0)),0) -> 4.8 | F43: =IFERROR(INDEX('Price List'!$L$5:$L$74,MATCH("Soil Disposal|m3",'Price List'!$O$5:$O$74,0)),0) -> 0 | G43: =E43+F43 -> 4.8 | H43: =SUMIFS('Raw Data'!$Z:$Z,'Raw Data'!$D:$D,"B.03",'Raw Data'!$H:$H,"Septic tank",'Raw Data'!$J:$J,"Soil Disposal") -> 1382.4
A44: B.03.19 | B44: Soil Backfill | C44: m3 | D44: =SUMIFS('Raw Data'!$Q:$Q,'Raw Data'!$D:$D,"B.03",'Raw Data'!$H:$H,"Septic tank",'Raw Data'!$J:$J,"Soil Backfill") -> 222 | E44: =IFERROR(INDEX('Price List'!$I$5:$I$74,MATCH("Soil Backfill|m3",'Price List'!$O$5:$O$74,0)),0) -> 4.8 | F44: =IFERROR(INDEX('Price List'!$L$5:$L$74,MATCH("Soil Backfill|m3",'Price List'!$O$5:$O$74,0)),0) -> 0 | G44: =E44+F44 -> 4.8 | H44: =SUMIFS('Raw Data'!$Z:$Z,'Raw Data'!$D:$D,"B.03",'Raw Data'!$H:$H,"Septic tank",'Raw Data'!$J:$J,"Soil Backfill") -> 1065.6
A45: B.03.20 | B45: Normal Concrete, 35Mpa (Cylinder), Slump 13+-2.5 | C45: m3 | D45: =SUMIFS('Raw Data'!$Q:$Q,'Raw Data'!$D:$D,"B.03",'Raw Data'!$H:$H,"Septic tank",'Raw Data'!$J:$J,"Normal Concrete, 35Mpa (Cylinder), Slump 13+-2.5") -> 66 | E45: =IFERROR(INDEX('Price List'!$I$5:$I$74,MATCH("Normal Concrete, 35Mpa (Cylinder), Slump 13+-2.5|m3",'Price List'!$O$5:$O$74,0)),0) -> 12 | F45: =IFERROR(INDEX('Price List'!$L$5:$L$74,MATCH("Normal Concrete, 35Mpa (Cylinder), Slump 13+-2.5|m3",'Price List'!$O$5:$O$74,0)),0) -> 109.76 | G45: =E45+F45 -> 121.76 | H45: =SUMIFS('Raw Data'!$Z:$Z,'Raw Data'!$D:$D,"B.03",'Raw Data'!$H:$H,"Septic tank",'Raw Data'!$J:$J,"Normal Concrete, 35Mpa (Cylinder), Slump 13+-2.5") -> 8036.16
A46: B.03.21 | B46: Formwork | C46: m2 | D46: =SUMIFS('Raw Data'!$Q:$Q,'Raw Data'!$D:$D,"B.03",'Raw Data'!$H:$H,"Septic tank",'Raw Data'!$J:$J,"Formwork") -> 556 | E46: =IFERROR(INDEX('Price List'!$I$5:$I$74,MATCH("Formwork|m2",'Price List'!$O$5:$O$74,0)),0) -> 7.2 | F46: =IFERROR(INDEX('Price List'!$L$5:$L$74,MATCH("Formwork|m2",'Price List'!$O$5:$O$74,0)),0) -> 5.6 | G46: =E46+F46 -> 12.8 | H46: =SUMIFS('Raw Data'!$Z:$Z,'Raw Data'!$D:$D,"B.03",'Raw Data'!$H:$H,"Septic tank",'Raw Data'!$J:$J,"Formwork") -> 7116.8
A47: B.03.22 | B47: Well Soil Compact | C47: m2 | D47: =SUMIFS('Raw Data'!$Q:$Q,'Raw Data'!$D:$D,"B.03",'Raw Data'!$H:$H,"Septic tank",'Raw Data'!$J:$J,"Well Soil Compact") -> 70 | E47: =IFERROR(INDEX('Price List'!$I$5:$I$74,MATCH("Well Soil Compact|m2",'Price List'!$O$5:$O$74,0)),0) -> 2.4 | F47: =IFERROR(INDEX('Price List'!$L$5:$L$74,MATCH("Well Soil Compact|m2",'Price List'!$O$5:$O$74,0)),0) -> 0 | G47: =E47+F47 -> 2.4 | H47: =SUMIFS('Raw Data'!$Z:$Z,'Raw Data'!$D:$D,"B.03",'Raw Data'!$H:$H,"Septic tank",'Raw Data'!$J:$J,"Well Soil Compact") -> 168
A48: B.03.23 | B48: Lean Concrete, 15Mpa (Cylinder) | C48: m3 | D48: =SUMIFS('Raw Data'!$Q:$Q,'Raw Data'!$D:$D,"B.03",'Raw Data'!$H:$H,"Septic tank",'Raw Data'!$J:$J,"Lean Concrete, 15Mpa (Cylinder)") -> 3.5 | E48: =IFERROR(INDEX('Price List'!$I$5:$I$74,MATCH("Lean Concrete, 15Mpa (Cylinder)|m3",'Price List'!$O$5:$O$74,0)),0) -> 8.4 | F48: =IFERROR(INDEX('Price List'!$L$5:$L$74,MATCH("Lean Concrete, 15Mpa (Cylinder)|m3",'Price List'!$O$5:$O$74,0)),0) -> 84 | G48: =E48+F48 -> 92.4 | H48: =SUMIFS('Raw Data'!$Z:$Z,'Raw Data'!$D:$D,"B.03",'Raw Data'!$H:$H,"Septic tank",'Raw Data'!$J:$J,"Lean Concrete, 15Mpa (Cylinder)") -> 323.4
A49: B.03.24 | B49: Crush Stone 40x60mm 150mm Thk. | C49: m3 | D49: =SUMIFS('Raw Data'!$Q:$Q,'Raw Data'!$D:$D,"B.03",'Raw Data'!$H:$H,"Septic tank",'Raw Data'!$J:$J,"Crush Stone 40x60mm 150mm Thk.") -> 10.5 | E49: =IFERROR(INDEX('Price List'!$I$5:$I$74,MATCH("Crush Stone 40x60mm 150mm Thk.|m3",'Price List'!$O$5:$O$74,0)),0) -> 3.6 | F49: =IFERROR(INDEX('Price List'!$L$5:$L$74,MATCH("Crush Stone 40x60mm 150mm Thk.|m3",'Price List'!$O$5:$O$74,0)),0) -> 20.16 | G49: =E49+F49 -> 23.76 | H49: =SUMIFS('Raw Data'!$Z:$Z,'Raw Data'!$D:$D,"B.03",'Raw Data'!$H:$H,"Septic tank",'Raw Data'!$J:$J,"Crush Stone 40x60mm 150mm Thk.") -> 249.48
A50: B.03.25 | B50: PVC Waterbar® V VN 20 (Width 200mm) | C50: m | D50: =SUMIFS('Raw Data'!$Q:$Q,'Raw Data'!$D:$D,"B.03",'Raw Data'!$H:$H,"Septic tank",'Raw Data'!$J:$J,"PVC Waterbar® V VN 20 (Width 200mm)") -> 60 | E50: =IFERROR(INDEX('Price List'!$I$5:$I$74,MATCH("PVC Waterbar® V VN 20 (Width 200mm)|m",'Price List'!$O$5:$O$74,0)),0) -> 1.8 | F50: =IFERROR(INDEX('Price List'!$L$5:$L$74,MATCH("PVC Waterbar® V VN 20 (Width 200mm)|m",'Price List'!$O$5:$O$74,0)),0) -> 4.48 | G50: =E50+F50 -> 6.28 | H50: =SUMIFS('Raw Data'!$Z:$Z,'Raw Data'!$D:$D,"B.03",'Raw Data'!$H:$H,"Septic tank",'Raw Data'!$J:$J,"PVC Waterbar® V VN 20 (Width 200mm)") -> 376.8
A51: B.03.26 | B51: Deform Bar, DB12(fy=390 Mpa) | C51: kg | D51: =SUMIFS('Raw Data'!$Q:$Q,'Raw Data'!$D:$D,"B.03",'Raw Data'!$H:$H,"Septic tank",'Raw Data'!$J:$J,"Deform Bar, DB12(fy=390 Mpa)") -> 10560 | E51: =IFERROR(INDEX('Price List'!$I$5:$I$74,MATCH("Deform Bar, DB12(fy=390 Mpa)|kg",'Price List'!$O$5:$O$74,0)),0) -> 0.132 | F51: =IFERROR(INDEX('Price List'!$L$5:$L$74,MATCH("Deform Bar, DB12(fy=390 Mpa)|kg",'Price List'!$O$5:$O$74,0)),0) -> 0.8512 | G51: =E51+F51 -> 0.9832 | H51: =SUMIFS('Raw Data'!$Z:$Z,'Raw Data'!$D:$D,"B.03",'Raw Data'!$H:$H,"Septic tank",'Raw Data'!$J:$J,"Deform Bar, DB12(fy=390 Mpa)") -> 10382.592
A52: B.03.27 | B52: Steel Tie Wire 1mm (Estimated 4% of Total Rebar Weight) | C52: kg | D52: =SUMIFS('Raw Data'!$Q:$Q,'Raw Data'!$D:$D,"B.03",'Raw Data'!$H:$H,"Septic tank",'Raw Data'!$J:$J,"Steel Tie Wire 1mm (Estimated 4% of Total Rebar Weight)") -> 422.4 | E52: =IFERROR(INDEX('Price List'!$I$5:$I$74,MATCH("Steel Tie Wire 1mm (Estimated 4% of Total Rebar Weight)|kg",'Price List'!$O$5:$O$74,0)),0) -> 0.06 | F52: =IFERROR(INDEX('Price List'!$L$5:$L$74,MATCH("Steel Tie Wire 1mm (Estimated 4% of Total Rebar Weight)|kg",'Price List'!$O$5:$O$74,0)),0) -> 1.344 | G52: =E52+F52 -> 1.404 | H52: =SUMIFS('Raw Data'!$Z:$Z,'Raw Data'!$D:$D,"B.03",'Raw Data'!$H:$H,"Septic tank",'Raw Data'!$J:$J,"Steel Tie Wire 1mm (Estimated 4% of Total Rebar Weight)") -> 593.0496
B53: Subtotal — Septic tank | H53: =SUM(H42:H52) -> 30731.082
B54: SUBTOTAL B.03 | H54: =SUMIFS('Raw Data'!$Z:$Z,'Raw Data'!$D:$D,"B.03") -> 95210.475
A56: B.04 — SUPER STRUCTURE
A57: Structural Beam
A58: B.04.01 | B58: Normal Concrete, 35Mpa (Cylinder), Slump 13+-2.5 | C58: m3 | D58: =SUMIFS('Raw Data'!$Q:$Q,'Raw Data'!$D:$D,"B.04",'Raw Data'!$H:$H,"Structural Beam",'Raw Data'!$J:$J,"Normal Concrete, 35Mpa (Cylinder), Slump 13+-2.5") -> 585.68675 | E58: =IFERROR(INDEX('Price List'!$I$5:$I$74,MATCH("Normal Concrete, 35Mpa (Cylinder), Slump 13+-2.5|m3",'Price List'!$O$5:$O$74,0)),0) -> 12 | F58: =IFERROR(INDEX('Price List'!$L$5:$L$74,MATCH("Normal Concrete, 35Mpa (Cylinder), Slump 13+-2.5|m3",'Price List'!$O$5:$O$74,0)),0) -> 109.76 | G58: =E58+F58 -> 121.76 | H58: =SUMIFS('Raw Data'!$Z:$Z,'Raw Data'!$D:$D,"B.04",'Raw Data'!$H:$H,"Structural Beam",'Raw Data'!$J:$J,"Normal Concrete, 35Mpa (Cylinder), Slump 13+-2.5") -> 71313.219
A59: B.04.02 | B59: Formwork | C59: m2 | D59: =SUMIFS('Raw Data'!$Q:$Q,'Raw Data'!$D:$D,"B.04",'Raw Data'!$H:$H,"Structural Beam",'Raw Data'!$J:$J,"Formwork") -> 5571.87 | E59: =IFERROR(INDEX('Price List'!$I$5:$I$74,MATCH("Formwork|m2",'Price List'!$O$5:$O$74,0)),0) -> 7.2 | F59: =IFERROR(INDEX('Price List'!$L$5:$L$74,MATCH("Formwork|m2",'Price List'!$O$5:$O$74,0)),0) -> 5.6 | G59: =E59+F59 -> 12.8 | H59: =SUMIFS('Raw Data'!$Z:$Z,'Raw Data'!$D:$D,"B.04",'Raw Data'!$H:$H,"Structural Beam",'Raw Data'!$J:$J,"Formwork") -> 71319.936
A60: B.04.03 | B60: Round Bar, RB8(fy=250 Mpa) | C60: kg | D60: =SUMIFS('Raw Data'!$Q:$Q,'Raw Data'!$D:$D,"B.04",'Raw Data'!$H:$H,"Structural Beam",'Raw Data'!$J:$J,"Round Bar, RB8(fy=250 Mpa)") -> 7795.0459 | E60: =IFERROR(INDEX('Price List'!$I$5:$I$74,MATCH("Round Bar, RB8(fy=250 Mpa)|kg",'Price List'!$O$5:$O$74,0)),0) -> 0.144 | F60: =IFERROR(INDEX('Price List'!$L$5:$L$74,MATCH("Round Bar, RB8(fy=250 Mpa)|kg",'Price List'!$O$5:$O$74,0)),0) -> 0.8624 | G60: =E60+F60 -> 1.0064 | H60: =SUMIFS('Raw Data'!$Z:$Z,'Raw Data'!$D:$D,"B.04",'Raw Data'!$H:$H,"Structural Beam",'Raw Data'!$J:$J,"Round Bar, RB8(fy=250 Mpa)") -> 7844.9342
A61: B.04.04 | B61: Deform Bar, DB10(fy=390 Mpa) | C61: kg | D61: =SUMIFS('Raw Data'!$Q:$Q,'Raw Data'!$D:$D,"B.04",'Raw Data'!$H:$H,"Structural Beam",'Raw Data'!$J:$J,"Deform Bar, DB10(fy=390 Mpa)") -> 34080.168 | E61: =IFERROR(INDEX('Price List'!$I$5:$I$74,MATCH("Deform Bar, DB10(fy=390 Mpa)|kg",'Price List'!$O$5:$O$74,0)),0) -> 0.144 | F61: =IFERROR(INDEX('Price List'!$L$5:$L$74,MATCH("Deform Bar, DB10(fy=390 Mpa)|kg",'Price List'!$O$5:$O$74,0)),0) -> 0.8736 | G61: =E61+F61 -> 1.0176 | H61: =SUMIFS('Raw Data'!$Z:$Z,'Raw Data'!$D:$D,"B.04",'Raw Data'!$H:$H,"Structural Beam",'Raw Data'!$J:$J,"Deform Bar, DB10(fy=390 Mpa)") -> 34679.978
A62: B.04.05 | B62: Deform Bar, DB12(fy=390 Mpa) | C62: kg | D62: =SUMIFS('Raw Data'!$Q:$Q,'Raw Data'!$D:$D,"B.04",'Raw Data'!$H:$H,"Structural Beam",'Raw Data'!$J:$J,"Deform Bar, DB12(fy=390 Mpa)") -> 3925.4928 | E62: =IFERROR(INDEX('Price List'!$I$5:$I$74,MATCH("Deform Bar, DB12(fy=390 Mpa)|kg",'Price List'!$O$5:$O$74,0)),0) -> 0.132 | F62: =IFERROR(INDEX('Price List'!$L$5:$L$74,MATCH("Deform Bar, DB12(fy=390 Mpa)|kg",'Price List'!$O$5:$O$74,0)),0) -> 0.8512 | G62: =E62+F62 -> 0.9832 | H62: =SUMIFS('Raw Data'!$Z:$Z,'Raw Data'!$D:$D,"B.04",'Raw Data'!$H:$H,"Structural Beam",'Raw Data'!$J:$J,"Deform Bar, DB12(fy=390 Mpa)") -> 3859.5445
A63: B.04.06 | B63: Deform Bar, DB16(fy=390 Mpa) | C63: kg | D63: =SUMIFS('Raw Data'!$Q:$Q,'Raw Data'!$D:$D,"B.04",'Raw Data'!$H:$H,"Structural Beam",'Raw Data'!$J:$J,"Deform Bar, DB16(fy=390 Mpa)") -> 28624.289 | E63: =IFERROR(INDEX('Price List'!$I$5:$I$74,MATCH("Deform Bar, DB16(fy=390 Mpa)|kg",'Price List'!$O$5:$O$74,0)),0) -> 0.12 | F63: =IFERROR(INDEX('Price List'!$L$5:$L$74,MATCH("Deform Bar, DB16(fy=390 Mpa)|kg",'Price List'!$O$5:$O$74,0)),0) -> 0.8288 | G63: =E63+F63 -> 0.9488 | H63: =SUMIFS('Raw Data'!$Z:$Z,'Raw Data'!$D:$D,"B.04",'Raw Data'!$H:$H,"Structural Beam",'Raw Data'!$J:$J,"Deform Bar, DB16(fy=390 Mpa)") -> 27158.725
A64: B.04.07 | B64: Deform Bar, DB20(fy=390 Mpa) | C64: kg | D64: =SUMIFS('Raw Data'!$Q:$Q,'Raw Data'!$D:$D,"B.04",'Raw Data'!$H:$H,"Structural Beam",'Raw Data'!$J:$J,"Deform Bar, DB20(fy=390 Mpa)") -> 28124.73 | E64: =IFERROR(INDEX('Price List'!$I$5:$I$74,MATCH("Deform Bar, DB20(fy=390 Mpa)|kg",'Price List'!$O$5:$O$74,0)),0) -> 0.108 | F64: =IFERROR(INDEX('Price List'!$L$5:$L$74,MATCH("Deform Bar, DB20(fy=390 Mpa)|kg",'Price List'!$O$5:$O$74,0)),0) -> 0.8176 | G64: =E64+F64 -> 0.9256 | H64: =SUMIFS('Raw Data'!$Z:$Z,'Raw Data'!$D:$D,"B.04",'Raw Data'!$H:$H,"Structural Beam",'Raw Data'!$J:$J,"Deform Bar, DB20(fy=390 Mpa)") -> 26032.25
A65: B.04.08 | B65: Steel Tie Wire 1mm (Estimated 4% of Total Rebar Weight) | C65: kg | D65: =SUMIFS('Raw Data'!$Q:$Q,'Raw Data'!$D:$D,"B.04",'Raw Data'!$H:$H,"Structural Beam",'Raw Data'!$J:$J,"Steel Tie Wire 1mm (Estimated 4% of Total Rebar Weight)") -> 7583.2379 | E65: =IFERROR(INDEX('Price List'!$I$5:$I$74,MATCH("Steel Tie Wire 1mm (Estimated 4% of Total Rebar Weight)|kg",'Price List'!$O$5:$O$74,0)),0) -> 0.06 | F65: =IFERROR(INDEX('Price List'!$L$5:$L$74,MATCH("Steel Tie Wire 1mm (Estimated 4% of Total Rebar Weight)|kg",'Price List'!$O$5:$O$74,0)),0) -> 1.344 | G65: =E65+F65 -> 1.404 | H65: =SUMIFS('Raw Data'!$Z:$Z,'Raw Data'!$D:$D,"B.04",'Raw Data'!$H:$H,"Structural Beam",'Raw Data'!$J:$J,"Steel Tie Wire 1mm (Estimated 4% of Total Rebar Weight)") -> 10646.866
A66: B.04.09 | B66: Lean Concrete, 15Mpa (Cylinder) | C66: m3 | D66: =SUMIFS('Raw Data'!$Q:$Q,'Raw Data'!$D:$D,"B.04",'Raw Data'!$H:$H,"Structural Beam",'Raw Data'!$J:$J,"Lean Concrete, 15Mpa (Cylinder)") -> 7.3 | E66: =IFERROR(INDEX('Price List'!$I$5:$I$74,MATCH("Lean Concrete, 15Mpa (Cylinder)|m3",'Price List'!$O$5:$O$74,0)),0) -> 8.4 | F66: =IFERROR(INDEX('Price List'!$L$5:$L$74,MATCH("Lean Concrete, 15Mpa (Cylinder)|m3",'Price List'!$O$5:$O$74,0)),0) -> 84 | G66: =E66+F66 -> 92.4 | H66: =SUMIFS('Raw Data'!$Z:$Z,'Raw Data'!$D:$D,"B.04",'Raw Data'!$H:$H,"Structural Beam",'Raw Data'!$J:$J,"Lean Concrete, 15Mpa (Cylinder)") -> 674.52
A67: B.04.10 | B67: Crush Stone 40x60mm 100mm Thk. | C67: m3 | D67: =SUMIFS('Raw Data'!$Q:$Q,'Raw Data'!$D:$D,"B.04",'Raw Data'!$H:$H,"Structural Beam",'Raw Data'!$J:$J,"Crush Stone 40x60mm 100mm Thk.") -> 14.56 | E67: =IFERROR(INDEX('Price List'!$I$5:$I$74,MATCH("Crush Stone 40x60mm 100mm Thk.|m3",'Price List'!$O$5:$O$74,0)),0) -> 3.6 | F67: =IFERROR(INDEX('Price List'!$L$5:$L$74,MATCH("Crush Stone 40x60mm 100mm Thk.|m3",'Price List'!$O$5:$O$74,0)),0) -> 20.16 | G67: =E67+F67 -> 23.76 | H67: =SUMIFS('Raw Data'!$Z:$Z,'Raw Data'!$D:$D,"B.04",'Raw Data'!$H:$H,"Structural Beam",'Raw Data'!$J:$J,"Crush Stone 40x60mm 100mm Thk.") -> 345.9456
A68: B.04.11 | B68: Anti-Termite with Plastic Membrane | C68: m2 | D68: =SUMIFS('Raw Data'!$Q:$Q,'Raw Data'!$D:$D,"B.04",'Raw Data'!$H:$H,"Structural Beam",'Raw Data'!$J:$J,"Anti-Termite with Plastic Membrane") -> 145.57 | E68: =IFERROR(INDEX('Price List'!$I$5:$I$74,MATCH("Anti-Termite with Plastic Membrane|m2",'Price List'!$O$5:$O$74,0)),0) -> 1.2 | F68: =IFERROR(INDEX('Price List'!$L$5:$L$74,MATCH("Anti-Termite with Plastic Membrane|m2",'Price List'!$O$5:$O$74,0)),0) -> 2.8 | G68: =E68+F68 -> 4 | H68: =SUMIFS('Raw Data'!$Z:$Z,'Raw Data'!$D:$D,"B.04",'Raw Data'!$H:$H,"Structural Beam",'Raw Data'!$J:$J,"Anti-Termite with Plastic Membrane") -> 582.28
A69: B.04.12 | B69: Deform Bar, DB25(fy=390 Mpa) | C69: kg | D69: =SUMIFS('Raw Data'!$Q:$Q,'Raw Data'!$D:$D,"B.04",'Raw Data'!$H:$H,"Structural Beam",'Raw Data'!$J:$J,"Deform Bar, DB25(fy=390 Mpa)") -> 87497.006 | E69: =IFERROR(INDEX('Price List'!$I$5:$I$74,MATCH("Deform Bar, DB25(fy=390 Mpa)|kg",'Price List'!$O$5:$O$74,0)),0) -> 0.096 | F69: =IFERROR(INDEX('Price List'!$L$5:$L$74,MATCH("Deform Bar, DB25(fy=390 Mpa)|kg",'Price List'!$O$5:$O$74,0)),0) -> 0.8064 | G69: =E69+F69 -> 0.9024 | H69: =SUMIFS('Raw Data'!$Z:$Z,'Raw Data'!$D:$D,"B.04",'Raw Data'!$H:$H,"Structural Beam",'Raw Data'!$J:$J,"Deform Bar, DB25(fy=390 Mpa)") -> 78957.299
B70: Subtotal — Structural Beam | H70: =SUM(H58:H69) -> 333415.5
A71: Structural Slab
A72: B.04.13 | B72: Normal Concrete, 35Mpa (Cylinder), Slump 13+-2.5 | C72: m3 | D72: =SUMIFS('Raw Data'!$Q:$Q,'Raw Data'!$D:$D,"B.04",'Raw Data'!$H:$H,"Structural Slab",'Raw Data'!$J:$J,"Normal Concrete, 35Mpa (Cylinder), Slump 13+-2.5") -> 1093.212 | E72: =IFERROR(INDEX('Price List'!$I$5:$I$74,MATCH("Normal Concrete, 35Mpa (Cylinder), Slump 13+-2.5|m3",'Price List'!$O$5:$O$74,0)),0) -> 12 | F72: =IFERROR(INDEX('Price List'!$L$5:$L$74,MATCH("Normal Concrete, 35Mpa (Cylinder), Slump 13+-2.5|m3",'Price List'!$O$5:$O$74,0)),0) -> 109.76 | G72: =E72+F72 -> 121.76 | H72: =SUMIFS('Raw Data'!$Z:$Z,'Raw Data'!$D:$D,"B.04",'Raw Data'!$H:$H,"Structural Slab",'Raw Data'!$J:$J,"Normal Concrete, 35Mpa (Cylinder), Slump 13+-2.5") -> 133109.49
A73: B.04.14 | B73: Formwork | C73: m2 | D73: =SUMIFS('Raw Data'!$Q:$Q,'Raw Data'!$D:$D,"B.04",'Raw Data'!$H:$H,"Structural Slab",'Raw Data'!$J:$J,"Formwork") -> 6615.7 | E73: =IFERROR(INDEX('Price List'!$I$5:$I$74,MATCH("Formwork|m2",'Price List'!$O$5:$O$74,0)),0) -> 7.2 | F73: =IFERROR(INDEX('Price List'!$L$5:$L$74,MATCH("Formwork|m2",'Price List'!$O$5:$O$74,0)),0) -> 5.6 | G73: =E73+F73 -> 12.8 | H73: =SUMIFS('Raw Data'!$Z:$Z,'Raw Data'!$D:$D,"B.04",'Raw Data'!$H:$H,"Structural Slab",'Raw Data'!$J:$J,"Formwork") -> 84680.96
A74: B.04.15 | B74: Deform Bar, DB10(fy=390 Mpa) | C74: kg | D74: =SUMIFS('Raw Data'!$Q:$Q,'Raw Data'!$D:$D,"B.04",'Raw Data'!$H:$H,"Structural Slab",'Raw Data'!$J:$J,"Deform Bar, DB10(fy=390 Mpa)") -> 143630.18 | E74: =IFERROR(INDEX('Price List'!$I$5:$I$74,MATCH("Deform Bar, DB10(fy=390 Mpa)|kg",'Price List'!$O$5:$O$74,0)),0) -> 0.144 | F74: =IFERROR(INDEX('Price List'!$L$5:$L$74,MATCH("Deform Bar, DB10(fy=390 Mpa)|kg",'Price List'!$O$5:$O$74,0)),0) -> 0.8736 | G74: =E74+F74 -> 1.0176 | H74: =SUMIFS('Raw Data'!$Z:$Z,'Raw Data'!$D:$D,"B.04",'Raw Data'!$H:$H,"Structural Slab",'Raw Data'!$J:$J,"Deform Bar, DB10(fy=390 Mpa)") -> 146158.07
A75: B.04.16 | B75: Deform Bar, DB12(fy=390 Mpa) | C75: kg | D75: =SUMIFS('Raw Data'!$Q:$Q,'Raw Data'!$D:$D,"B.04",'Raw Data'!$H:$H,"Structural Slab",'Raw Data'!$J:$J,"Deform Bar, DB12(fy=390 Mpa)") -> 2510.82 | E75: =IFERROR(INDEX('Price List'!$I$5:$I$74,MATCH("Deform Bar, DB12(fy=390 Mpa)|kg",'Price List'!$O$5:$O$74,0)),0) -> 0.132 | F75: =IFERROR(INDEX('Price List'!$L$5:$L$74,MATCH("Deform Bar, DB12(fy=390 Mpa)|kg",'Price List'!$O$5:$O$74,0)),0) -> 0.8512 | G75: =E75+F75 -> 0.9832 | H75: =SUMIFS('Raw Data'!$Z:$Z,'Raw Data'!$D:$D,"B.04",'Raw Data'!$H:$H,"Structural Slab",'Raw Data'!$J:$J,"Deform Bar, DB12(fy=390 Mpa)") -> 2468.6382
A76: B.04.17 | B76: Steel Tie Wire 1mm (Estimated 4% of Total Rebar Weight) | C76: kg | D76: =SUMIFS('Raw Data'!$Q:$Q,'Raw Data'!$D:$D,"B.04",'Raw Data'!$H:$H,"Structural Slab",'Raw Data'!$J:$J,"Steel Tie Wire 1mm (Estimated 4% of Total Rebar Weight)") -> 5378.3998 | E76: =IFERROR(INDEX('Price List'!$I$5:$I$74,MATCH("Steel Tie Wire 1mm (Estimated 4% of Total Rebar Weight)|kg",'Price List'!$O$5:$O$74,0)),0) -> 0.06 | F76: =IFERROR(INDEX('Price List'!$L$5:$L$74,MATCH("Steel Tie Wire 1mm (Estimated 4% of Total Rebar Weight)|kg",'Price List'!$O$5:$O$74,0)),0) -> 1.344 | G76: =E76+F76 -> 1.404 | H76: =SUMIFS('Raw Data'!$Z:$Z,'Raw Data'!$D:$D,"B.04",'Raw Data'!$H:$H,"Structural Slab",'Raw Data'!$J:$J,"Steel Tie Wire 1mm (Estimated 4% of Total Rebar Weight)") -> 7551.2734
A77: B.04.18 | B77: Lean Concrete, 15Mpa (Cylinder) | C77: m3 | D77: =SUMIFS('Raw Data'!$Q:$Q,'Raw Data'!$D:$D,"B.04",'Raw Data'!$H:$H,"Structural Slab",'Raw Data'!$J:$J,"Lean Concrete, 15Mpa (Cylinder)") -> 27.6 | E77: =IFERROR(INDEX('Price List'!$I$5:$I$74,MATCH("Lean Concrete, 15Mpa (Cylinder)|m3",'Price List'!$O$5:$O$74,0)),0) -> 8.4 | F77: =IFERROR(INDEX('Price List'!$L$5:$L$74,MATCH("Lean Concrete, 15Mpa (Cylinder)|m3",'Price List'!$O$5:$O$74,0)),0) -> 84 | G77: =E77+F77 -> 92.4 | H77: =SUMIFS('Raw Data'!$Z:$Z,'Raw Data'!$D:$D,"B.04",'Raw Data'!$H:$H,"Structural Slab",'Raw Data'!$J:$J,"Lean Concrete, 15Mpa (Cylinder)") -> 2550.24
A78: B.04.19 | B78: Crush Stone 40x60mm 100mm Thk. | C78: m3 | D78: =SUMIFS('Raw Data'!$Q:$Q,'Raw Data'!$D:$D,"B.04",'Raw Data'!$H:$H,"Structural Slab",'Raw Data'!$J:$J,"Crush Stone 40x60mm 100mm Thk.") -> 55.2 | E78: =IFERROR(INDEX('Price List'!$I$5:$I$74,MATCH("Crush Stone 40x60mm 100mm Thk.|m3",'Price List'!$O$5:$O$74,0)),0) -> 3.6 | F78: =IFERROR(INDEX('Price List'!$L$5:$L$74,MATCH("Crush Stone 40x60mm 100mm Thk.|m3",'Price List'!$O$5:$O$74,0)),0) -> 20.16 | G78: =E78+F78 -> 23.76 | H78: =SUMIFS('Raw Data'!$Z:$Z,'Raw Data'!$D:$D,"B.04",'Raw Data'!$H:$H,"Structural Slab",'Raw Data'!$J:$J,"Crush Stone 40x60mm 100mm Thk.") -> 1311.552
A79: B.04.20 | B79: Anti-Termite with Plastic Membrane | C79: m2 | D79: =SUMIFS('Raw Data'!$Q:$Q,'Raw Data'!$D:$D,"B.04",'Raw Data'!$H:$H,"Structural Slab",'Raw Data'!$J:$J,"Anti-Termite with Plastic Membrane") -> 552 | E79: =IFERROR(INDEX('Price List'!$I$5:$I$74,MATCH("Anti-Termite with Plastic Membrane|m2",'Price List'!$O$5:$O$74,0)),0) -> 1.2 | F79: =IFERROR(INDEX('Price List'!$L$5:$L$74,MATCH("Anti-Termite with Plastic Membrane|m2",'Price List'!$O$5:$O$74,0)),0) -> 2.8 | G79: =E79+F79 -> 4 | H79: =SUMIFS('Raw Data'!$Z:$Z,'Raw Data'!$D:$D,"B.04",'Raw Data'!$H:$H,"Structural Slab",'Raw Data'!$J:$J,"Anti-Termite with Plastic Membrane") -> 2208
B80: Subtotal — Structural Slab | H80: =SUM(H72:H79) -> 380038.22
A81: Structural Column
A82: B.04.21 | B82: Normal Concrete, 35Mpa (Cylinder), Slump 13+-2.5 | C82: m3 | D82: =SUMIFS('Raw Data'!$Q:$Q,'Raw Data'!$D:$D,"B.04",'Raw Data'!$H:$H,"Structural Column",'Raw Data'!$J:$J,"Normal Concrete, 35Mpa (Cylinder), Slump 13+-2.5") -> 524.328 | E82: =IFERROR(INDEX('Price List'!$I$5:$I$74,MATCH("Normal Concrete, 35Mpa (Cylinder), Slump 13+-2.5|m3",'Price List'!$O$5:$O$74,0)),0) -> 12 | F82: =IFERROR(INDEX('Price List'!$L$5:$L$74,MATCH("Normal Concrete, 35Mpa (Cylinder), Slump 13+-2.5|m3",'Price List'!$O$5:$O$74,0)),0) -> 109.76 | G82: =E82+F82 -> 121.76 | H82: =SUMIFS('Raw Data'!$Z:$Z,'Raw Data'!$D:$D,"B.04",'Raw Data'!$H:$H,"Structural Column",'Raw Data'!$J:$J,"Normal Concrete, 35Mpa (Cylinder), Slump 13+-2.5") -> 63842.177
A83: B.04.22 | B83: Formwork | C83: m2 | D83: =SUMIFS('Raw Data'!$Q:$Q,'Raw Data'!$D:$D,"B.04",'Raw Data'!$H:$H,"Structural Column",'Raw Data'!$J:$J,"Formwork") -> 2691.6 | E83: =IFERROR(INDEX('Price List'!$I$5:$I$74,MATCH("Formwork|m2",'Price List'!$O$5:$O$74,0)),0) -> 7.2 | F83: =IFERROR(INDEX('Price List'!$L$5:$L$74,MATCH("Formwork|m2",'Price List'!$O$5:$O$74,0)),0) -> 5.6 | G83: =E83+F83 -> 12.8 | H83: =SUMIFS('Raw Data'!$Z:$Z,'Raw Data'!$D:$D,"B.04",'Raw Data'!$H:$H,"Structural Column",'Raw Data'!$J:$J,"Formwork") -> 34452.48
A84: B.04.23 | B84: Deform Bar, DB12(fy=390 Mpa) | C84: kg | D84: =SUMIFS('Raw Data'!$Q:$Q,'Raw Data'!$D:$D,"B.04",'Raw Data'!$H:$H,"Structural Column",'Raw Data'!$J:$J,"Deform Bar, DB12(fy=390 Mpa)") -> 20883.06 | E84: =IFERROR(INDEX('Price List'!$I$5:$I$74,MATCH("Deform Bar, DB12(fy=390 Mpa)|kg",'Price List'!$O$5:$O$74,0)),0) -> 0.132 | F84: =IFERROR(INDEX('Price List'!$L$5:$L$74,MATCH("Deform Bar, DB12(fy=390 Mpa)|kg",'Price List'!$O$5:$O$74,0)),0) -> 0.8512 | G84: =E84+F84 -> 0.9832 | H84: =SUMIFS('Raw Data'!$Z:$Z,'Raw Data'!$D:$D,"B.04",'Raw Data'!$H:$H,"Structural Column",'Raw Data'!$J:$J,"Deform Bar, DB12(fy=390 Mpa)") -> 20532.225
A85: B.04.24 | B85: Deform Bar, DB25(fy=390 Mpa) | C85: kg | D85: =SUMIFS('Raw Data'!$Q:$Q,'Raw Data'!$D:$D,"B.04",'Raw Data'!$H:$H,"Structural Column",'Raw Data'!$J:$J,"Deform Bar, DB25(fy=390 Mpa)") -> 28929.523 | E85: =IFERROR(INDEX('Price List'!$I$5:$I$74,MATCH("Deform Bar, DB25(fy=390 Mpa)|kg",'Price List'!$O$5:$O$74,0)),0) -> 0.096 | F85: =IFERROR(INDEX('Price List'!$L$5:$L$74,MATCH("Deform Bar, DB25(fy=390 Mpa)|kg",'Price List'!$O$5:$O$74,0)),0) -> 0.8064 | G85: =E85+F85 -> 0.9024 | H85: =SUMIFS('Raw Data'!$Z:$Z,'Raw Data'!$D:$D,"B.04",'Raw Data'!$H:$H,"Structural Column",'Raw Data'!$J:$J,"Deform Bar, DB25(fy=390 Mpa)") -> 26106.002
A86: B.04.25 | B86: Deform Bar, DB32(fy=390 Mpa) | C86: kg | D86: =SUMIFS('Raw Data'!$Q:$Q,'Raw Data'!$D:$D,"B.04",'Raw Data'!$H:$H,"Structural Column",'Raw Data'!$J:$J,"Deform Bar, DB32(fy=390 Mpa)") -> 40852.48 | E86: =IFERROR(INDEX('Price List'!$I$5:$I$74,MATCH("Deform Bar, DB32(fy=390 Mpa)|kg",'Price List'!$O$5:$O$74,0)),0) -> 0.096 | F86: =IFERROR(INDEX('Price List'!$L$5:$L$74,MATCH("Deform Bar, DB32(fy=390 Mpa)|kg",'Price List'!$O$5:$O$74,0)),0) -> 0.7952 | G86: =E86+F86 -> 0.8912 | H86: =SUMIFS('Raw Data'!$Z:$Z,'Raw Data'!$D:$D,"B.04",'Raw Data'!$H:$H,"Structural Column",'Raw Data'!$J:$J,"Deform Bar, DB32(fy=390 Mpa)") -> 36407.73
A87: B.04.26 | B87: Steel Tie Wire 1mm (Estimated 4% of Total Rebar Weight) | C87: kg | D87: =SUMIFS('Raw Data'!$Q:$Q,'Raw Data'!$D:$D,"B.04",'Raw Data'!$H:$H,"Structural Column",'Raw Data'!$J:$J,"Steel Tie Wire 1mm (Estimated 4% of Total Rebar Weight)") -> 5225.1488 | E87: =IFERROR(INDEX('Price List'!$I$5:$I$74,MATCH("Steel Tie Wire 1mm (Estimated 4% of Total Rebar Weight)|kg",'Price List'!$O$5:$O$74,0)),0) -> 0.06 | F87: =IFERROR(INDEX('Price List'!$L$5:$L$74,MATCH("Steel Tie Wire 1mm (Estimated 4% of Total Rebar Weight)|kg",'Price List'!$O$5:$O$74,0)),0) -> 1.344 | G87: =E87+F87 -> 1.404 | H87: =SUMIFS('Raw Data'!$Z:$Z,'Raw Data'!$D:$D,"B.04",'Raw Data'!$H:$H,"Structural Column",'Raw Data'!$J:$J,"Steel Tie Wire 1mm (Estimated 4% of Total Rebar Weight)") -> 7336.1089
A88: B.04.27 | B88: Deform Bar, DB20(fy=390 Mpa) | C88: kg | D88: =SUMIFS('Raw Data'!$Q:$Q,'Raw Data'!$D:$D,"B.04",'Raw Data'!$H:$H,"Structural Column",'Raw Data'!$J:$J,"Deform Bar, DB20(fy=390 Mpa)") -> 29031.725 | E88: =IFERROR(INDEX('Price List'!$I$5:$I$74,MATCH("Deform Bar, DB20(fy=390 Mpa)|kg",'Price List'!$O$5:$O$74,0)),0) -> 0.108 | F88: =IFERROR(INDEX('Price List'!$L$5:$L$74,MATCH("Deform Bar, DB20(fy=390 Mpa)|kg",'Price List'!$O$5:$O$74,0)),0) -> 0.8176 | G88: =E88+F88 -> 0.9256 | H88: =SUMIFS('Raw Data'!$Z:$Z,'Raw Data'!$D:$D,"B.04",'Raw Data'!$H:$H,"Structural Column",'Raw Data'!$J:$J,"Deform Bar, DB20(fy=390 Mpa)") -> 26871.764
A89: B.04.28 | B89: Deform Bar, DB10(fy=390 Mpa) | C89: kg | D89: =SUMIFS('Raw Data'!$Q:$Q,'Raw Data'!$D:$D,"B.04",'Raw Data'!$H:$H,"Structural Column",'Raw Data'!$J:$J,"Deform Bar, DB10(fy=390 Mpa)") -> 10704.21 | E89: =IFERROR(INDEX('Price List'!$I$5:$I$74,MATCH("Deform Bar, DB10(fy=390 Mpa)|kg",'Price List'!$O$5:$O$74,0)),0) -> 0.144 | F89: =IFERROR(INDEX('Price List'!$L$5:$L$74,MATCH("Deform Bar, DB10(fy=390 Mpa)|kg",'Price List'!$O$5:$O$74,0)),0) -> 0.8736 | G89: =E89+F89 -> 1.0176 | H89: =SUMIFS('Raw Data'!$Z:$Z,'Raw Data'!$D:$D,"B.04",'Raw Data'!$H:$H,"Structural Column",'Raw Data'!$J:$J,"Deform Bar, DB10(fy=390 Mpa)") -> 10892.604
B90: Subtotal — Structural Column | H90: =SUM(H82:H89) -> 226441.09
A91: Structural Wall
A92: B.04.29 | B92: Normal Concrete, 35Mpa (Cylinder), Slump 13+-2.5 | C92: m3 | D92: =SUMIFS('Raw Data'!$Q:$Q,'Raw Data'!$D:$D,"B.04",'Raw Data'!$H:$H,"Structural Wall",'Raw Data'!$J:$J,"Normal Concrete, 35Mpa (Cylinder), Slump 13+-2.5") -> 302.25 | E92: =IFERROR(INDEX('Price List'!$I$5:$I$74,MATCH("Normal Concrete, 35Mpa (Cylinder), Slump 13+-2.5|m3",'Price List'!$O$5:$O$74,0)),0) -> 12 | F92: =IFERROR(INDEX('Price List'!$L$5:$L$74,MATCH("Normal Concrete, 35Mpa (Cylinder), Slump 13+-2.5|m3",'Price List'!$O$5:$O$74,0)),0) -> 109.76 | G92: =E92+F92 -> 121.76 | H92: =SUMIFS('Raw Data'!$Z:$Z,'Raw Data'!$D:$D,"B.04",'Raw Data'!$H:$H,"Structural Wall",'Raw Data'!$J:$J,"Normal Concrete, 35Mpa (Cylinder), Slump 13+-2.5") -> 36801.96
A93: B.04.30 | B93: Formwork | C93: m2 | D93: =SUMIFS('Raw Data'!$Q:$Q,'Raw Data'!$D:$D,"B.04",'Raw Data'!$H:$H,"Structural Wall",'Raw Data'!$J:$J,"Formwork") -> 1801.7 | E93: =IFERROR(INDEX('Price List'!$I$5:$I$74,MATCH("Formwork|m2",'Price List'!$O$5:$O$74,0)),0) -> 7.2 | F93: =IFERROR(INDEX('Price List'!$L$5:$L$74,MATCH("Formwork|m2",'Price List'!$O$5:$O$74,0)),0) -> 5.6 | G93: =E93+F93 -> 12.8 | H93: =SUMIFS('Raw Data'!$Z:$Z,'Raw Data'!$D:$D,"B.04",'Raw Data'!$H:$H,"Structural Wall",'Raw Data'!$J:$J,"Formwork") -> 23061.76
A94: B.04.31 | B94: Deform Bar, DB10(fy=390 Mpa) | C94: kg | D94: =SUMIFS('Raw Data'!$Q:$Q,'Raw Data'!$D:$D,"B.04",'Raw Data'!$H:$H,"Structural Wall",'Raw Data'!$J:$J,"Deform Bar, DB10(fy=390 Mpa)") -> 3126.956 | E94: =IFERROR(INDEX('Price List'!$I$5:$I$74,MATCH("Deform Bar, DB10(fy=390 Mpa)|kg",'Price List'!$O$5:$O$74,0)),0) -> 0.144 | F94: =IFERROR(INDEX('Price List'!$L$5:$L$74,MATCH("Deform Bar, DB10(fy=390 Mpa)|kg",'Price List'!$O$5:$O$74,0)),0) -> 0.8736 | G94: =E94+F94 -> 1.0176 | H94: =SUMIFS('Raw Data'!$Z:$Z,'Raw Data'!$D:$D,"B.04",'Raw Data'!$H:$H,"Structural Wall",'Raw Data'!$J:$J,"Deform Bar, DB10(fy=390 Mpa)") -> 3181.9904
A95: B.04.32 | B95: Deform Bar, DB12(fy=390 Mpa) | C95: kg | D95: =SUMIFS('Raw Data'!$Q:$Q,'Raw Data'!$D:$D,"B.04",'Raw Data'!$H:$H,"Structural Wall",'Raw Data'!$J:$J,"Deform Bar, DB12(fy=390 Mpa)") -> 13854.754 | E95: =IFERROR(INDEX('Price List'!$I$5:$I$74,MATCH("Deform Bar, DB12(fy=390 Mpa)|kg",'Price List'!$O$5:$O$74,0)),0) -> 0.132 | F95: =IFERROR(INDEX('Price List'!$L$5:$L$74,MATCH("Deform Bar, DB12(fy=390 Mpa)|kg",'Price List'!$O$5:$O$74,0)),0) -> 0.8512 | G95: =E95+F95 -> 0.9832 | H95: =SUMIFS('Raw Data'!$Z:$Z,'Raw Data'!$D:$D,"B.04",'Raw Data'!$H:$H,"Structural Wall",'Raw Data'!$J:$J,"Deform Bar, DB12(fy=390 Mpa)") -> 13621.994
A96: B.04.33 | B96: Deform Bar, DB16(fy=390 Mpa) | C96: kg | D96: =SUMIFS('Raw Data'!$Q:$Q,'Raw Data'!$D:$D,"B.04",'Raw Data'!$H:$H,"Structural Wall",'Raw Data'!$J:$J,"Deform Bar, DB16(fy=390 Mpa)") -> 8106.664 | E96: =IFERROR(INDEX('Price List'!$I$5:$I$74,MATCH("Deform Bar, DB16(fy=390 Mpa)|kg",'Price List'!$O$5:$O$74,0)),0) -> 0.12 | F96: =IFERROR(INDEX('Price List'!$L$5:$L$74,MATCH("Deform Bar, DB16(fy=390 Mpa)|kg",'Price List'!$O$5:$O$74,0)),0) -> 0.8288 | G96: =E96+F96 -> 0.9488 | H96: =SUMIFS('Raw Data'!$Z:$Z,'Raw Data'!$D:$D,"B.04",'Raw Data'!$H:$H,"Structural Wall",'Raw Data'!$J:$J,"Deform Bar, DB16(fy=390 Mpa)") -> 7691.6028
A97: B.04.34 | B97: Deform Bar, DB20(fy=390 Mpa) | C97: kg | D97: =SUMIFS('Raw Data'!$Q:$Q,'Raw Data'!$D:$D,"B.04",'Raw Data'!$H:$H,"Structural Wall",'Raw Data'!$J:$J,"Deform Bar, DB20(fy=390 Mpa)") -> 10607.168 | E97: =IFERROR(INDEX('Price List'!$I$5:$I$74,MATCH("Deform Bar, DB20(fy=390 Mpa)|kg",'Price List'!$O$5:$O$74,0)),0) -> 0.108 | F97: =IFERROR(INDEX('Price List'!$L$5:$L$74,MATCH("Deform Bar, DB20(fy=390 Mpa)|kg",'Price List'!$O$5:$O$74,0)),0) -> 0.8176 | G97: =E97+F97 -> 0.9256 | H97: =SUMIFS('Raw Data'!$Z:$Z,'Raw Data'!$D:$D,"B.04",'Raw Data'!$H:$H,"Structural Wall",'Raw Data'!$J:$J,"Deform Bar, DB20(fy=390 Mpa)") -> 9817.9947
A98: B.04.35 | B98: Steel Tie Wire 1mm (Estimated 4% of Total Rebar Weight) | C98: kg | D98: =SUMIFS('Raw Data'!$Q:$Q,'Raw Data'!$D:$D,"B.04",'Raw Data'!$H:$H,"Structural Wall",'Raw Data'!$J:$J,"Steel Tie Wire 1mm (Estimated 4% of Total Rebar Weight)") -> 1831.2625 | E98: =IFERROR(INDEX('Price List'!$I$5:$I$74,MATCH("Steel Tie Wire 1mm (Estimated 4% of Total Rebar Weight)|kg",'Price List'!$O$5:$O$74,0)),0) -> 0.06 | F98: =IFERROR(INDEX('Price List'!$L$5:$L$74,MATCH("Steel Tie Wire 1mm (Estimated 4% of Total Rebar Weight)|kg",'Price List'!$O$5:$O$74,0)),0) -> 1.344 | G98: =E98+F98 -> 1.404 | H98: =SUMIFS('Raw Data'!$Z:$Z,'Raw Data'!$D:$D,"B.04",'Raw Data'!$H:$H,"Structural Wall",'Raw Data'!$J:$J,"Steel Tie Wire 1mm (Estimated 4% of Total Rebar Weight)") -> 2571.0926
A99: B.04.36 | B99: Deform Bar, DB14(fy=390 Mpa) | C99: kg | D99: =SUMIFS('Raw Data'!$Q:$Q,'Raw Data'!$D:$D,"B.04",'Raw Data'!$H:$H,"Structural Wall",'Raw Data'!$J:$J,"Deform Bar, DB14(fy=390 Mpa)") -> 10086.022 | E99: =IFERROR(INDEX('Price List'!$I$5:$I$74,MATCH("Deform Bar, DB14(fy=390 Mpa)|kg",'Price List'!$O$5:$O$74,0)),0) -> 0.12 | F99: =IFERROR(INDEX('Price List'!$L$5:$L$74,MATCH("Deform Bar, DB14(fy=390 Mpa)|kg",'Price List'!$O$5:$O$74,0)),0) -> 0.84 | G99: =E99+F99 -> 0.96 | H99: =SUMIFS('Raw Data'!$Z:$Z,'Raw Data'!$D:$D,"B.04",'Raw Data'!$H:$H,"Structural Wall",'Raw Data'!$J:$J,"Deform Bar, DB14(fy=390 Mpa)") -> 9682.5807
B100: Subtotal — Structural Wall | H100: =SUM(H92:H99) -> 106430.97
A101: Structural Staircase
A102: B.04.37 | B102: Normal Concrete, 35Mpa (Cylinder), Slump 13+-2.5 | C102: m3 | D102: =SUMIFS('Raw Data'!$Q:$Q,'Raw Data'!$D:$D,"B.04",'Raw Data'!$H:$H,"Structural Staircase",'Raw Data'!$J:$J,"Normal Concrete, 35Mpa (Cylinder), Slump 13+-2.5") -> 99.03264 | E102: =IFERROR(INDEX('Price List'!$I$5:$I$74,MATCH("Normal Concrete, 35Mpa (Cylinder), Slump 13+-2.5|m3",'Price List'!$O$5:$O$74,0)),0) -> 12 | F102: =IFERROR(INDEX('Price List'!$L$5:$L$74,MATCH("Normal Concrete, 35Mpa (Cylinder), Slump 13+-2.5|m3",'Price List'!$O$5:$O$74,0)),0) -> 109.76 | G102: =E102+F102 -> 121.76 | H102: =SUMIFS('Raw Data'!$Z:$Z,'Raw Data'!$D:$D,"B.04",'Raw Data'!$H:$H,"Structural Staircase",'Raw Data'!$J:$J,"Normal Concrete, 35Mpa (Cylinder), Slump 13+-2.5") -> 12058.214
A103: B.04.38 | B103: Formwork | C103: m2 | D103: =SUMIFS('Raw Data'!$Q:$Q,'Raw Data'!$D:$D,"B.04",'Raw Data'!$H:$H,"Structural Staircase",'Raw Data'!$J:$J,"Formwork") -> 1485.4896 | E103: =IFERROR(INDEX('Price List'!$I$5:$I$74,MATCH("Formwork|m2",'Price List'!$O$5:$O$74,0)),0) -> 7.2 | F103: =IFERROR(INDEX('Price List'!$L$5:$L$74,MATCH("Formwork|m2",'Price List'!$O$5:$O$74,0)),0) -> 5.6 | G103: =E103+F103 -> 12.8 | H103: =SUMIFS('Raw Data'!$Z:$Z,'Raw Data'!$D:$D,"B.04",'Raw Data'!$H:$H,"Structural Staircase",'Raw Data'!$J:$J,"Formwork") -> 19014.267
...

Sheet Project Budget
B1: PROJECT BUDGET & PROFIT PLAN
B2: INTERNAL DOCUMENT — FOR COST MANAGEMENT ONLY — NOT FOR CLIENT ISSUE
B3: 10-Storey School Building | Phnom Penh, Cambodia | USD ($) | Linked live to Raw Data, Price List, Preliminaries & Cover
B5: 1. COST PLAN BY ELEMENT (Original Budget vs Selling)
B6: Code | C6: Element | D6: Cost Budget (Net) ($) | E6: Selling / BoQ ($) | F6: Embedded Margin ($) | G6: Margin %
B7: B.01 | C7: Piling Work | D7: =SUMPRODUCT(('Raw Data'!$D$2:$D$832=$B7)*'Raw Data'!$Q$2:$Q$832*('Raw Data'!$T$2:$T$832+'Raw Data'!$W$2:$W$832)) -> 93232.083 | E7: =SUMIF('Raw Data'!$D:$D,$B7,'Raw Data'!$Z:$Z) -> 105084.37 | F7: =E7-D7 -> 11852.288 | G7: =IF(E7=0,0,F7/E7) -> 0.1127883
B8: B.03 | C8: Ground Floor / Foundation | D8: =SUMPRODUCT(('Raw Data'!$D$2:$D$832=$B8)*'Raw Data'!$Q$2:$Q$832*('Raw Data'!$T$2:$T$832+'Raw Data'!$W$2:$W$832)) -> 83049.542 | E8: =SUMIF('Raw Data'!$D:$D,$B8,'Raw Data'!$Z:$Z) -> 95210.475 | F8: =E8-D8 -> 12160.933 | G8: =IF(E8=0,0,F8/E8) -> 0.12772683
B9: B.04 | C9: Super Structure | D9: =SUMPRODUCT(('Raw Data'!$D$2:$D$832=$B9)*'Raw Data'!$Q$2:$Q$832*('Raw Data'!$T$2:$T$832+'Raw Data'!$W$2:$W$832)) -> 989807.64 | E9: =SUMIF('Raw Data'!$D:$D,$B9,'Raw Data'!$Z:$Z) -> 1124399.7 | F9: =E9-D9 -> 134592.02 | G9: =IF(E9=0,0,F9/E9) -> 0.11970123
B10: C.01 | C10: Exterior Wall & Partition | D10: =SUMPRODUCT(('Raw Data'!$D$2:$D$832=$B10)*'Raw Data'!$Q$2:$Q$832*('Raw Data'!$T$2:$T$832+'Raw Data'!$W$2:$W$832)) -> 90902.306 | E10: =SUMIF('Raw Data'!$D:$D,$B10,'Raw Data'!$Z:$Z) -> 103864.41 | F10: =E10-D10 -> 12962.104 | G10: =IF(E10=0,0,F10/E10) -> 0.12479832
B11: C.02 | C11: Exterior Wall Finishes | D11: =SUMPRODUCT(('Raw Data'!$D$2:$D$832=$B11)*'Raw Data'!$Q$2:$Q$832*('Raw Data'!$T$2:$T$832+'Raw Data'!$W$2:$W$832)) -> 84448.333 | E11: =SUMIF('Raw Data'!$D:$D,$B11,'Raw Data'!$Z:$Z) -> 97761.364 | F11: =E11-D11 -> 13313.031 | G11: =IF(E11=0,0,F11/E11) -> 0.13617886
B12: C.04 | C12: Exterior Window & Louver | D12: =SUMPRODUCT(('Raw Data'!$D$2:$D$832=$B12)*'Raw Data'!$Q$2:$Q$832*('Raw Data'!$T$2:$T$832+'Raw Data'!$W$2:$W$832)) -> 85596.6 | E12: =SUMIF('Raw Data'!$D:$D,$B12,'Raw Data'!$Z:$Z) -> 95868.192 | F12: =E12-D12 -> 10271.592 | G12: =IF(E12=0,0,F12/E12) -> 0.10714286
B13: C.09 | C13: Interior Wall & Partition | D13: =SUMPRODUCT(('Raw Data'!$D$2:$D$832=$B13)*'Raw Data'!$Q$2:$Q$832*('Raw Data'!$T$2:$T$832+'Raw Data'!$W$2:$W$832)) -> 87764.899 | E13: =SUMIF('Raw Data'!$D:$D,$B13,'Raw Data'!$Z:$Z) -> 100365.77 | F13: =E13-D13 -> 12600.871 | G13: =IF(E13=0,0,F13/E13) -> 0.12554949
B14: C.10 | C14: Interior Door / Windows | D14: =SUMPRODUCT(('Raw Data'!$D$2:$D$832=$B14)*'Raw Data'!$Q$2:$Q$832*('Raw Data'!$T$2:$T$832+'Raw Data'!$W$2:$W$832)) -> 40165 | E14: =SUMIF('Raw Data'!$D:$D,$B14,'Raw Data'!$Z:$Z) -> 44984.8 | F14: =E14-D14 -> 4819.8 | G14: =IF(E14=0,0,F14/E14) -> 0.10714286
B15: D.01 | C15: Interior Wall Finishes | D15: =SUMPRODUCT(('Raw Data'!$D$2:$D$832=$B15)*'Raw Data'!$Q$2:$Q$832*('Raw Data'!$T$2:$T$832+'Raw Data'!$W$2:$W$832)) -> 120957.16 | E15: =SUMIF('Raw Data'!$D:$D,$B15,'Raw Data'!$Z:$Z) -> 139757.64 | F15: =E15-D15 -> 18800.473 | G15: =IF(E15=0,0,F15/E15) -> 0.13452198
B16: D.02 | C16: Interior Floor Finishes | D16: =SUMPRODUCT(('Raw Data'!$D$2:$D$832=$B16)*'Raw Data'!$Q$2:$Q$832*('Raw Data'!$T$2:$T$832+'Raw Data'!$W$2:$W$832)) -> 38545 | E16: =SUMIF('Raw Data'!$D:$D,$B16,'Raw Data'!$Z:$Z) -> 43665.44 | F16: =E16-D16 -> 5120.44 | G16: =IF(E16=0,0,F16/E16) -> 0.11726528
B17: D.03 | C17: Ceiling Finishes | D17: =SUMPRODUCT(('Raw Data'!$D$2:$D$832=$B17)*'Raw Data'!$Q$2:$Q$832*('Raw Data'!$T$2:$T$832+'Raw Data'!$W$2:$W$832)) -> 63000 | E17: =SUMIF('Raw Data'!$D:$D,$B17,'Raw Data'!$Z:$Z) -> 72072 | F17: =E17-D17 -> 9072 | G17: =IF(E17=0,0,F17/E17) -> 0.12587413
B18: E.04 | C18: Signage | D18: =SUMPRODUCT(('Raw Data'!$D$2:$D$832=$B18)*'Raw Data'!$Q$2:$Q$832*('Raw Data'!$T$2:$T$832+'Raw Data'!$W$2:$W$832)) -> 6000 | E18: =SUMIF('Raw Data'!$D:$D,$B18,'Raw Data'!$Z:$Z) -> 6600 | F18: =E18-D18 -> 600 | G18: =IF(E18=0,0,F18/E18) -> 0.090909091
C19: DIRECT WORKS TOTAL | D19: =SUM(D7:D18) -> 1783468.6 | E19: =SUM(E7:E18) -> 2029634.1 | F19: =E19-D19 -> 246165.55 | G19: =IF(E19=0,0,F19/E19) -> 0.12128568
B20: Z | C20: Preliminaries & General (at cost) | D20: =Preliminaries!$F$27 -> 403700 | E20: =Preliminaries!$F$27 -> 403700 | F20: 0 | G20: 0
B22: 2. PROJECT TOTALS & PROFIT PLAN
B23: CONTRACT VALUE — Tender Price (incl. VAT) | E23: =Cover!$D$42 -> 3104934.3
B24: less: VAT payable to tax authority (pass-through) | E24: =-Cover!$D$41 -> -282266.76
B25: REVENUE (excl. VAT) | E25: =Cover!$D$40 -> 2822667.6
B26: ORIGINAL COST BUDGET (what the project should cost):
B27: Direct works at net cost (labor + material, no margin) | E27: =D19 -> 1783468.6
B28: Preliminaries at cost | E28: =D20 -> 403700
B29: Head office overhead (real cost, per Cover %) | E29: =Cover!$D$37 -> 121666.71
B30: TOTAL ORIGINAL BUDGET | E30: =E27+E28+E29 -> 2308835.3
B31: PROFIT PLAN (where the margin lives):
B32: Embedded margin inside unit rates | E32: =F19 -> 246165.55
B33: Explicit profit line on Cover | E33: =Cover!$D$39 -> 194666.73
B34: Risk & contingency (becomes profit only if unused) | E34: =Cover!$D$38 -> 73000.024
B35: PLANNED GROSS PROFIT (if risk unused) | E35: =E25-E30 -> 513832.31 | F35: =E35/E25 -> 0.18203784
B36: TARGET GROSS PROFIT (risk held in reserve) | E36: =E35-E34 -> 440832.28 | F36: =E36/E25 -> 0.15617577
B38: Check: Revenue − Budget − Embedded − Profit − Risk = $0 → | F38: =E25-E30-E32-E33-E34 -> -6.4028427e-10
B40: 3. HOW TO USE THIS SHEET FOR COST CONTROL
B41: 1. The "Cost Budget (Net)" column is your baseline: every purchase order and subcontract for an element is tracked against it.
B42: 2. Each month, record Committed Cost (orders placed) and Actual Cost (invoices) per code vs this budget — overrun on any code eats the embedded margin first, then profit.
B43: 3. Risk & Contingency is NOT profit yet: hold it against variations, rework and escalation; release to profit only at final account.
B44: 4. VAT is collected from the client and paid to GDT — never count it as project money.
B45: 5. When real supplier quotations replace benchmark rates in the Price List, this sheet re-baselines automatically.

Sheet Floor Code (2)
A1: Floor Code
A2: Building Code | B2: Sequence Number | C2: Level Code on Design | D2: Floor Code
A3: BA | B3: 01 | C3: U01 | D3: =CONCATENATE(A3,"-",B3,"-",C3) -> BA-01-U01
A4: BA | B4: 02 | C4: B02 | D4: =CONCATENATE(A4,"-",B4,"-",C4) -> BA-02-B02
A5: BA | B5: 03 | C5: B01 | D5: =CONCATENATE(A5,"-",B5,"-",C5) -> BA-03-B01
A6: BA | B6: 04 | C6: L00 | D6: =CONCATENATE(A6,"-",B6,"-",C6) -> BA-04-L00
A7: BA | B7: 05 | C7: L01 | D7: =CONCATENATE(A7,"-",B7,"-",C7) -> BA-05-L01
A8: BA | B8: 06 | C8: L02 | D8: =CONCATENATE(A8,"-",B8,"-",C8) -> BA-06-L02
A9: BA | B9: 07 | C9: L03 | D9: =CONCATENATE(A9,"-",B9,"-",C9) -> BA-07-L03
A10: BA | B10: 08 | C10: L04 | D10: =CONCATENATE(A10,"-",B10,"-",C10) -> BA-08-L04
A11: BA | B11: 09 | C11: L05 | D11: =CONCATENATE(A11,"-",B11,"-",C11) -> BA-09-L05

Sheet Floor Code
A1: Floor Naming
A2: Building Name | B2: Level | C2: Level Function | D2: CFA (m2) | E2: Building Code | F2: Sequence Number | G2: Level Code | H2: Floor Code

Sheet CS BoQ Level
A1: Civil and Structure Level Breakdown
A2: Discipline | B2: Section | C2: Sub Section | D2: Material Type | E2: Unit
A3: Civil and Structure | B3: Foundation | C3: Pile | D3: D1000 Concrete Grade C30/37 | E3: m
D4: D400 Concrete Grade C30/37 | E4: m
D5: D600 Concrete Grade C30/37 | E5: m
D6: D800 Concrete Grade C30/37 | E6: m
C7: Pile Caps | D7: Anti-Termite | E7: m2
D8: Concrete Grade C40/50 | E8: m3
D9: Rebar DB10 SD390 | E9: kg
D10: Rebar DB12 SD390 | E10: kg
D11: Rebar DB16 SD390 | E11: kg
D12: Rebar DB20 SD390 | E12: kg
D13: Rebar DB25 SD390 | E13: kg
D14: Rebar DB8 SD235 | E14: kg
D15: Excavation | E15: m3
D16: Gravel 4x6cm Compaction 100mm thk. & Concrete Grade C25/30 50mm thk. | E16: m3
D17: Plywood Formwork | E17: m2
C18: Temperary Protection | D18: H-Beam(400x400x13x21)mm, SD365 | E18: kg
D19: Steel sheet piles (6x0.75)m | E19: m
B20: Sub Structure | C20: Sewage Treatment Plant (STP) | D20: Normal Concrete, C35/45 Mpa | E20: m3
D21: Rebar DB10 SD390 | E21: kg
D22: Gravel 4x6cm Compaction 100mm thk. & Concrete Grade C25/30 50mm thk. | E22: m3
D23: Plywood Formwork | E23: m2
C24: Retaining Wall | D24: Concrete Grade C40/50 | E24: m3
D25: Rebar DB10 SD390 | E25: kg
D26: Rebar DB20 SD390 | E26: kg
D27: Rebar DB25 SD390 | E27: kg
D28: Rebar DB8 SD235 | E28: kg
D29: Plywood Formwork | E29: m2
D30: Sika Waterbar | E30: m
C31: Water Tank | D31: Concrete Grade C35/45 | E31: m3
D32: Rebar DB12 SD390 | E32: kg
D33: Plywood Formwork | E33: m2
B34: Super Structure | C34: Beam | D34: Concrete Grade C40/50 | E34: m3
D35: Rebar DB10 SD390 | E35: kg
D36: Rebar DB12 SD390 | E36: kg
D37: Rebar DB16 SD390 | E37: kg
D38: Rebar DB20 SD390 | E38: kg
D39: Rebar DB25 SD390 | E39: kg
D40: Rebar DB8 SD235 | E40: kg
D41: Plywood Formwork | E41: m2
D42: W(8x10)cm Steel ASTM A992 | E42: kg
C43: Column | D43: Concrete Grade C35/45 | E43: m3
D44: Concrete Grade C40/50 | E44: m3
D45: Rebar DB12 SD390 | E45: kg
D46: Rebar DB16 SD390 | E46: kg
D47: Rebar DB20 SD390 | E47: kg
D48: Rebar DB25 SD390 | E48: kg
D49: Rebar DB8 SD235 | E49: kg
D50: Plywood Formwork | E50: m2
D51: W(150x29)cm Steel ASTM A992 | E51: kg
C52: Floor | D52: Concrete Grade C35/45 | E52: m3
D53: Rebar DB10 SD390 | E53: kg
D54: Rebar DB12 SD390 | E54: kg
D55: Rebar DB16 SD390 | E55: kg
D56: Rebar DB20 SD390 | E56: kg
D57: Rebar DB25 SD390 | E57: kg
D58: Rebar RB8 SD235 | E58: kg
D59: Plywood Formwork | E59: m2
C60: Stair | D60: Concrete Grade C35/45 | E60: m3
D61: Rebar DB10 SD390 | E61: kg
D62: Plywood Formwork | E62: m2
C63: Structural Walls | D63: Concrete Grade C35/45 | E63: m3
D64: Concrete Grade C40/50 | E64: m3
D65: Rebar DB10 SD390 | E65: kg
D66: Rebar DB16 SD390 | E66: kg
D67: Rebar DB20 SD390 | E67: kg
D68: Rebar DB25 SD390 | E68: kg
D69: Rebar DB8 SD235 | E69: kg
D70: Plywood Formwork | E70: m2
B71: External Work | C71: Canopy
C72: Roofing
C73: U-Drain
C74: Manhole
C75: Road
C76: Permanent Fence
C77: Logo Support

Sheet RFQ_Rawdata
A1: Design Data | F1: RFQ DATA | N1: Remark
A2: Sub Section | B2: Sub Element | C2: Material Type | D2: Unit | E2: Designated Brand | F2: Supplier ID | G2: Proposed Brand | H2: Specification | I2: Labor Rate | J2: Material Rate | K2: RQF No | L2: Submit by | M2: Submit Date
A3: Bored Pile | B3: Preliminary Works | C3: Mobilization and Demobilization | D3: lot | I3: 13000 | J3: 0
A4: Bored Pile | B4: Preliminary Works | C4: Management fee and field engineer | D4: lot | I4: 28000 | J4: 0
A5: Bored Pile | B5: Preliminary Works | C5: Survey and setting out & As-Built drawing | D5: lot | I5: 3470 | J5: 0
A6: Bored Pile | B6: Preliminary Works | C6: Casing length 6m and Steel plate | D6: lot
A7: Bored Pile | B7: Coring Works | C7: Bentonite | D7: lot
A8: Bored Pile | B8: Coring Works | C8: Rock Coring for Bored Pile D1500mm | D8: m | I8: 260 | J8: 0
A9: Bored Pile | B9: Coring Works | C9: Soil Coring for Bored Pile D1500mm | D9: m | I9: 60 | J9: 0
A10: Bored Pile | B10: Concrete | C10: Normal Concrete, C35/45 Mpa | D10: m3 | I10: 16 | J10: 63
A11: Bored Pile | B11: Rebar | C11: Deform Bar, DB10 SD500 Mpa | D11: kg | I11: 0.07 | J11: 0.78
A12: Bored Pile | B12: Rebar | C12: Deform Bar, DB16 SD500 Mpa | D12: kg | I12: 0.07 | J12: 0.78
A13: Bored Pile | B13: Rebar | C13: Deform Bar, DB20 SD500 Mpa | D13: kg | I13: 0.07 | J13: 0.78
A14: Bored Pile | B14: Steel Wire | C14: Steel Tie Wire 1mm | D14: kg | I14: 0.12 | J14: 0.908
A15: Bored Pile | B15: Steel Tube | C15: Steel Tube D49x1.9mm with Anti rust and black paint finish | D15: m | I15: 3.7 | J15: 0
A16: Bored Pile | B16: Grouting works | C16: Grouting works after sonic logging test | D16: m | I16: 3.5 | J16: 0
A17: Bored Pile | B17: Pile Load Testing | C17: Mobilization and demobilization | D17: ls | I17: 13000 | J17: 0
A18: Bored Pile | B18: Pile Head Cutting & Preparation | C18: Pile Head Cutting & Preparation for bored pile D1500mm | D18: nos | I18: 150 | J18: 0
A19: Bored Pile | B19: Pile Load Testing | C19: Working Load Test and Ultimate Load Test, TL=2550Tons & 4250Tons, FS=1.5 & 2.5 with Kengledge method. Included : Mobiliztion and crane service | D19: nos | I19: 22000 | J19: 0
... A33: Pile Caps | B33: Base Preparation | C33: Well Soil Compact | D33: m2 | I33: 1.8 | J33: 0
A34: Pile Caps | B34: Polyethylene Sheet | C34: Polyethylene Sheet, 2m width x 100m length | D34: m2
A35: Pile Caps | B35: Crush Stone | C35: Gravel 40x60mm Compaction 150mm thk. | D35: m3 | I35: 11 | J35: 52
A36: Pile Caps | B36: Lean Concrete | C36: Lean Concrete Grade C20/25 50mm thk. | D36: m3 | I36: 11 | J36: 52
A37: Pile Caps | B37: Concrete | C37: Normal Concrete, C35/45 Mpa | D37: m3 | I37: 11 | J37: 63
A38: Pile Caps | B38: Formwork | C38: Formwork | D38: m2 | I38: 14 | J38: 12
A39: Pile Caps | B39: Rebar | C39: Deform Bar, DB10 SD500 Mpa | D39: kg | I39: 0.145 | J39: 0.78
A40: Pile Caps | B40: Rebar | C40: Deform Bar, DB12 SD500 Mpa | D40: kg | I40: 0.145 | J40: 0.78
A41: Pile Caps | B41: Rebar | C41: Deform Bar, DB16 SD500 Mpa | D41: kg | I41: 0.145 | J41: 0.78
A42: Pile Caps | B42: Rebar | C42: Deform Bar, DB20 SD500 Mpa | D42: kg | I42: 0.145 | J42: 0.78
A43: Pile Caps | B43: Rebar | C43: Deform Bar, DB25 SD500 Mpa | D43: kg | I43: 0.145 | J43: 0.78
A44: Pile Caps | B44: Rebar | C44: Deform Bar, DB32 SD500 Mpa | D44: kg | I44: 0.145 | J44: 0.78
A45: Pile Caps | B45: Steel Wire | C45: Steel Tie Wire 1mm | D45: kg | I45: 0.12 | J45: 0.908
A46: Pile Caps | B46: Testing | C46: Rebar Testing as per approved Specification | D46: lot | I46: 0.12 | J46: 0.12
... A49: Sewage Treatment Plant (STP) | B49: Soil Back Fill | C49: Soil Back Fill (Use the existing excavation material) | D49: m3 | I49: 3.5 | J49: 0
A50: Sewage Treatment Plant (STP) | B50: Base Preparation | C50: Well Soil Compact | D50: m2
A51: Sewage Treatment Plant (STP) | B51: Crush Stone | C51: Gravel 40x60mm Compaction 100mm thk. | D51: m3 | I51: 11 | J51: 50
A52: Sewage Treatment Plant (STP) | B52: Lean Concrete | C52: Lean Concrete Grade C20/25 50mm thk. | D52: m3 | I52: 11 | J52: 50
A53: Sewage Treatment Plant (STP) | B53: Concrete | C53: Normal Concrete, C35/45 Mpa | D53: m3 | I53: 11 | J53: 63
A54: Sewage Treatment Plant (STP) | B54: Formwork | C54: Formwork | D54: m2 | I54: 14 | J54: 12
A55: Sewage Treatment Plant (STP) | B55: Rebar | C55: Deform Bar, DB10 SD500 Mpa | D55: kg | I55: 0.145 | J55: 0.78
A56: Sewage Treatment Plant (STP) | B56: Rebar | C56: Deform Bar, DB12 SD500 Mpa | D56: kg | I56: 0.145 | J56: 0.78
A57: Sewage Treatment Plant (STP) | B57: Rebar | C57: Deform Bar, DB14 SD500 Mpa | D57: kg | I57: 0.145 | J57: 0.78
A58: Sewage Treatment Plant (STP) | B58: Steel Wire | C58: Steel Tie Wire 1mm | D58: kg | I58: 0.12 | J58: 0.908
A59: Sewage Treatment Plant (STP) | B59: Water Stop | C59: Sika Waterbar V VN 20=20m (Width 200mm) | D59: m | I59: 0 | J59: 11.75
A60: Water Tank | B60: Soil Excavation | C60: Soil Excavation | D60: m3 | I60: 3.5 | J60: 4.7
A61: Water Tank | B61: Soil Disposal | C61: Soil Disposal | D61: m3 | I61: 3.5 | J61: 4.7
A62: Water Tank | B62: Soil Back Fill | C62: Soil Back Fill (Use the existing excavation material) | D62: m3 | I62: 3.5 | J62: 0
... A136: Structural Canopy | B136: Steel Structure | C136: Tube-(100x100x6)mm x 1.8mm thk grade 235 Mpa | D136: kg | I136: 0.5 | J136: 1.15

Sheet Preliminaries
A1: PRELIMINARIES & GENERAL (Z)
A2: 10-Storey School Building | Phnom Penh, Cambodia | USD ($). Yellow = input (Qty & Rate). Time items assume ~18-month programme.
A4: Code | B4: Description | C4: Unit | D4: Qty | E4: Rate ($) | F4: Amount ($)
A5: Z.01 | B5: Site office, store & welfare facilities | C5: Month | D5: 18 | E5: 1200 | F5: =D5*E5 -> 21600
A6: Z.02 | B6: Site management & supervision staff | C6: Month | D6: 18 | E6: 5000 | F6: =D6*E6 -> 90000
A7: Z.03 | B7: Temporary fencing & hoarding | C7: Item | D7: 1 | E7: 8000 | F7: =D7*E7 -> 8000
A8: Z.04 | B8: Temporary water supply | C8: Month | D8: 18 | E8: 300 | F8: =D8*E8 -> 5400
A9: Z.05 | B9: Temporary electricity supply | C9: Month | D9: 18 | E9: 800 | F9: =D9*E9 -> 14400
A10: Z.06 | B10: Health, safety & PPE | C10: Month | D10: 18 | E10: 500 | F10: =D10*E10 -> 9000
A11: Z.07 | B11: Site security | C11: Month | D11: 18 | E11: 900 | F11: =D11*E11 -> 16200
A12: Z.08 | B12: Site cleaning & waste removal | C12: Month | D12: 18 | E12: 600 | F12: =D12*E12 -> 10800
A13: Z.09 | B13: Setting out & survey | C13: Month | D13: 18 | E13: 400 | F13: =D13*E13 -> 7200
A14: Z.10 | B14: Material & concrete testing | C14: Item | D14: 1 | E14: 8000 | F14: =D14*E14 -> 8000
A15: Z.11 | B15: Insurance (CAR / third party) | C15: Item | D15: 1 | E15: 12000 | F15: =D15*E15 -> 12000
A16: Z.12 | B16: Performance bond / guarantees | C16: Item | D16: 1 | E16: 6000 | F16: =D16*E16 -> 6000
... A26: Z.22 | B26: Temporary sheet pile length 6m | C26: m | D26: 95 | E26: 180 | F26: =D26*E26 -> 17100
B27: TOTAL PRELIMINARIES (Z) | F27: =SUM(F5:F26) -> 403700
B29: Note: Benchmark inputs for a ~18-month programme — adjust Qty (months/no.) and Rate per your resourcing & quotations.

Sheet Raw Data
A1: Nº | B1: PTB Code | C1: Discipline | D1: Budget Code | E1: Building Code | F1: Level | G1: Section | H1: Sub Section | I1: Sub Element | J1: Material Type | K1: Element group | L1: Element ID | M1: Description | N1: Brand | O1: Supplier | P1: Unit | Q1: Quantity | R1: Actual Q.ty | S1: % | T1: Labor Net Cost ($) | U1: Labor Margin (%) | V1: Labor Rate | W1: Material Net Cost ($) | X1: Material Margin (%) | Y1: Material Rate | Z1: Amount | AA1: Package Name
C2: Civil and Structure | D2: =IFERROR(IF(TRIM($G2)="Sub Structure",IF(TRIM($H2)="Bored Pile","B.01","B.03"),IF(TRIM($G2)="Super Structure","B.04",IF(OR(TRIM($G2)="Exterior Wall and Partition",TRIM($G2)="External Wall and Partition"),"C.01",IF(TRIM($G2)="Exterior Wall Finishes","C.02",IF(TRIM($G2)="Interior Wall and Partition","C.09",IF(TRIM($G2)="Interior Door","C.10",IF(TRIM($G2)="External Windows and Louvers","C.04",IF(OR(TRIM($G2)="Interior Floor Finishes",TRIM($G2)="Internal Floor Finishes"),"D.02",IF(OR(TRIM($G2)="Interior Wall Finishes",TRIM($G2)="Internal Wall Finishes"),"D.01",IF(OR(TRIM($G2)="Ceiling Finshes",TRIM($G2)="Ceiling Finishes"),"D.03",IF(TRIM($G2)="Fittings, furnishings and equipment","E.04","")))))))))))," ") -> B.01 | E2: BA | F2: 01.UG | G2: Sub Structure | H2: Bored Pile | I2: Bored Pile Head Cutting | J2: Pile Head Cutting up to required level D1000mm | P2: Nos | Q2: =R2 -> 5 | R2: 5 | S2: 0 | T2: =IFERROR(INDEX('Price List'!$G$5:$G$74,MATCH(TRIM(J2)&"|"&TRIM(P2),'Price List'!$O$5:$O$74,0)),0) -> 55 | U2: =IFERROR(INDEX('Price List'!$H$5:$H$74,MATCH(TRIM(J2)&"|"&TRIM(P2),'Price List'!$O$5:$O$74,0)),0) -> 0.2 | V2: =T2*(1+U2) -> 66 | W2: =IFERROR(INDEX('Price List'!$J$5:$J$74,MATCH(TRIM(J2)&"|"&TRIM(P2),'Price List'!$O$5:$O$74,0)),0) -> 0 | X2: =IFERROR(INDEX('Price List'!$K$5:$K$74,MATCH(TRIM(J2)&"|"&TRIM(P2),'Price List'!$O$5:$O$74,0)),0) -> 0 | Y2: =W2*(1+X2) -> 0 | Z2: =Q2*(V2+Y2) -> 330
C3: Civil and Structure | D3: =IFERROR(IF(TRIM($G3)="Sub Structure",IF(TRIM($H3)="Bored Pile","B.01","B.03"),IF(TRIM($G3)="Super Structure","B.04",IF(OR(TRIM($G3)="Exterior Wall and Partition",TRIM($G3)="External Wall and Partition"),"C.01",IF(TRIM($G3)="Exterior Wall Finishes","C.02",IF(TRIM($G3)="Interior Wall and Partition","C.09",IF(TRIM($G3)="Interior Door","C.10",IF(TRIM($G3)="External Windows and Louvers","C.04",IF(OR(TRIM($G3)="Interior Floor Finishes",TRIM($G3)="Internal Floor Finishes"),"D.02",IF(OR(TRIM($G3)="Interior Wall Finishes",TRIM($G3)="Internal Wall Finishes"),"D.01",IF(OR(TRIM($G3)="Ceiling Finshes",TRIM($G3)="Ceiling Finishes"),"D.03",IF(TRIM($G3)="Fittings, furnishings and equipment","E.04","")))))))))))," ") -> B.01 | E3: BA | F3: 01.UG | G3: Sub Structure | H3: Bored Pile | I3: Bored Pile Head Cutting | J3: Pile Head Cutting up to required level D800mm | P3: Nos | Q3: =R3 -> 17 | R3: 17 | S3: 0 | T3: =IFERROR(INDEX('Price List'!$G$5:$G$74,MATCH(TRIM(J3)&"|"&TRIM(P3),'Price List'!$O$5:$O$74,0)),0) -> 40 | U3: =IFERROR(INDEX('Price List'!$H$5:$H$74,MATCH(TRIM(J3)&"|"&TRIM(P3),'Price List'!$O$5:$O$74,0)),0) -> 0.2 | V3: =T3*(1+U3) -> 48 | W3: =IFERROR(INDEX('Price List'!$J$5:$J$74,MATCH(TRIM(J3)&"|"&TRIM(P3),'Price List'!$O$5:$O$74,0)),0) -> 0 | X3: =IFERROR(INDEX('Price List'!$K$5:$K$74,MATCH(TRIM(J3)&"|"&TRIM(P3),'Price List'!$O$5:$O$74,0)),0) -> 0 | Y3: =W3*(1+X3) -> 0 | Z3: =Q3*(V3+Y3) -> 816
C4: Civil and Structure | D4: =IFERROR(IF(TRIM($G4)="Sub Structure",IF(TRIM($H4)="Bored Pile","B.01","B.03"),IF(TRIM($G4)="Super Structure","B.04",IF(OR(TRIM($G4)="Exterior Wall and Partition",TRIM($G4)="External Wall and Partition"),"C.01",IF(TRIM($G4)="Exterior Wall Finishes","C.02",IF(TRIM($G4)="Interior Wall and Partition","C.09",IF(TRIM($G4)="Interior Door","C.10",IF(TRIM($G4)="External Windows and Louvers","C.04",IF(OR(TRIM($G4)="Interior Floor Finishes",TRIM($G4)="Internal Floor Finishes"),"D.02",IF(OR(TRIM($G4)="Interior Wall Finishes",TRIM($G4)="Internal Wall Finishes"),"D.01",IF(OR(TRIM($G4)="Ceiling Finshes",TRIM($G4)="Ceiling Finishes"),"D.03",IF(TRIM($G4)="Fittings, furnishings and equipment","E.04","")))))))))))," ") -> B.01 | E4: BA | F4: 01.UG | G4: Sub Structure | H4: Bored Pile | I4: Bored Pile Testing | J4: Sonic Logging Test (SLT) | P4: Nos | Q4: =R4 -> 22 | R4: 22 | S4: 0 | T4: =IFERROR(INDEX('Price List'!$G$5:$G$74,MATCH(TRIM(J4)&"|"&TRIM(P4),'Price List'!$O$5:$O$74,0)),0) -> 0 | U4: =IFERROR(INDEX('Price List'!$H$5:$H$74,MATCH(TRIM(J4)&"|"&TRIM(P4),'Price List'!$O$5:$O$74,0)),0) -> 0 | V4: =T4*(1+U4) -> 0 | W4: =IFERROR(INDEX('Price List'!$J$5:$J$74,MATCH(TRIM(J4)&"|"&TRIM(P4),'Price List'!$O$5:$O$74,0)),0) -> 50 | X4: =IFERROR(INDEX('Price List'!$K$5:$K$74,MATCH(TRIM(J4)&"|"&TRIM(P4),'Price List'!$O$5:$O$74,0)),0) -> 0.1 | Y4: =W4*(1+X4) -> 55 | Z4: =Q4*(V4+Y4) -> 1210
C5: Civil and Structure | D5: =IFERROR(IF(TRIM($G5)="Sub Structure",IF(TRIM($H5)="Bored Pile","B.01","B.03"),IF(TRIM($G5)="Super Structure","B.04",IF(OR(TRIM($G5)="Exterior Wall and Partition",TRIM($G5)="External Wall and Partition"),"C.01",IF(TRIM($G5)="Exterior Wall Finishes","C.02",IF(TRIM($G5)="Interior Wall and Partition","C.09",IF(TRIM($G5)="Interior Door","C.10",IF(TRIM($G5)="External Windows and Louvers","C.04",IF(OR(TRIM($G5)="Interior Floor Finishes",TRIM($G5)="Internal Floor Finishes"),"D.02",IF(OR(TRIM($G5)="Interior Wall Finishes",TRIM($G5)="Internal Wall Finishes"),"D.01",IF(OR(TRIM($G5)="Ceiling Finshes",TRIM($G5)="Ceiling Finishes"),"D.03",IF(TRIM($G5)="Fittings, furnishings and equipment","E.04","")))))))))))," ") -> B.01 | E5: BA | F5: 01.UG | G5: Sub Structure | H5: Bored Pile | I5: Bored Pile Coring | J5: Soil Coring for Bored Pile D1000mm, Depth 30m | P5: Nos | Q5: =R5 -> 5 | R5: 5 | S5: 0 | T5: =IFERROR(INDEX('Price List'!$G$5:$G$74,MATCH(TRIM(J5)&"|"&TRIM(P5),'Price List'!$O$5:$O$74,0)),0) -> 0 | U5: =IFERROR(INDEX('Price List'!$H$5:$H$74,MATCH(TRIM(J5)&"|"&TRIM(P5),'Price List'!$O$5:$O$74,0)),0) -> 0 | V5: =T5*(1+U5) -> 0 | W5: =IFERROR(INDEX('Price List'!$J$5:$J$74,MATCH(TRIM(J5)&"|"&TRIM(P5),'Price List'!$O$5:$O$74,0)),0) -> 350 | X5: =IFERROR(INDEX('Price List'!$K$5:$K$74,MATCH(TRIM(J5)&"|"&TRIM(P5),'Price List'!$O$5:$O$74,0)),0) -> 0.1 | Y5: =W5*(1+X5) -> 385 | Z5: =Q5*(V5+Y5) -> 1925
C6: Civil and Structure | D6: =IFERROR(IF(TRIM($G6)="Sub Structure",IF(TRIM($H6)="Bored Pile","B.01","B.03"),IF(TRIM($G6)="Super Structure","B.04",IF(OR(TRIM($G6)="Exterior Wall and Partition",TRIM($G6)="External Wall and Partition"),"C.01",IF(TRIM($G6)="Exterior Wall Finishes","C.02",IF(TRIM($G6)="Interior Wall and Partition","C.09",IF(TRIM($G6)="Interior Door","C.10",IF(TRIM($G6)="External Windows and Louvers","C.04",IF(OR(TRIM($G6)="Interior Floor Finishes",TRIM($G6)="Internal Floor Finishes"),"D.02",IF(OR(TRIM($G6)="Interior Wall Finishes",TRIM($G6)="Internal Wall Finishes"),"D.01",IF(OR(TRIM($G6)="Ceiling Finshes",TRIM($G6)="Ceiling Finishes"),"D.03",IF(TRIM($G6)="Fittings, furnishings and equipment","E.04","")))))))))))," ") -> B.01 | E6: BA | F6: 01.UG | G6: Sub Structure | H6: Bored Pile | I6: Bored Pile Coring | J6: Soil Coring for Bored Pile D800mm, Depth 30m | P6: Nos | Q6: =R6 -> 17 | R6: 17 | S6: 0 | T6: =IFERROR(INDEX('Price List'!$G$5:$G$74,MATCH(TRIM(J6)&"|"&TRIM(P6),'Price List'!$O$5:$O$74,0)),0) -> 0 | U6: =IFERROR(INDEX('Price List'!$H$5:$H$74,MATCH(TRIM(J6)&"|"&TRIM(P6),'Price List'!$O$5:$O$74,0)),0) -> 0 | V6: =T6*(1+U6) -> 0 | W6: =IFERROR(INDEX('Price List'!$J$5:$J$74,MATCH(TRIM(J6)&"|"&TRIM(P6),'Price List'!$O$5:$O$74,0)),0) -> 300 | X6: =IFERROR(INDEX('Price List'!$K$5:$K$74,MATCH(TRIM(J6)&"|"&TRIM(P6),'Price List'!$O$5:$O$74,0)),0) -> 0.1 | Y6: =W6*(1+X6) -> 330 | Z6: =Q6*(V6+Y6) -> 5610
C7: Civil and Structure | D7: =IFERROR(IF(TRIM($G7)="Sub Structure",IF(TRIM($H7)="Bored Pile","B.01","B.03"),IF(TRIM($G7)="Super Structure","B.04",IF(OR(TRIM($G7)="Exterior Wall and Partition",TRIM($G7)="External Wall and Partition"),"C.01",IF(TRIM($G7)="Exterior Wall Finishes","C.02",IF(TRIM($G7)="Interior Wall and Partition","C.09",IF(TRIM($G7)="Interior Door","C.10",IF(TRIM($G7)="External Windows and Louvers","C.04",IF(OR(TRIM($G7)="Interior Floor Finishes",TRIM($G7)="Internal Floor Finishes"),"D.02",IF(OR(TRIM($G7)="Interior Wall Finishes",TRIM($G7)="Internal Wall Finishes"),"D.01",IF(OR(TRIM($G7)="Ceiling Finshes",TRIM($G7)="Ceiling Finishes"),"D.03",IF(TRIM($G7)="Fittings, furnishings and equipment","E.04","")))))))))))," ") -> B.01 | E7: BA | F7: 01.UG | G7: Sub Structure | H7: Bored Pile | I7: Concrete | J7: Normal Concrete, 35Mpa (Cylinder), Slump 15+-2.5 | P7: m3 | Q7: =R7 -> 374.16369 | R7: =((PI()*0.4^2)*30*17)+((PI()*0.5^2)*30*5) -> 374.16369 | T7: =IFERROR(INDEX('Price List'!$G$5:$G$74,MATCH(TRIM(J7)&"|"&TRIM(P7),'Price List'!$O$5:$O$74,0)),0) -> 8 | U7: =IFERROR(INDEX('Price List'!$H$5:$H$74,MATCH(TRIM(J7)&"|"&TRIM(P7),'Price List'!$O$5:$O$74,0)),0) -> 0.2 | V7: =T7*(1+U7) -> 9.6 | W7: =IFERROR(INDEX('Price List'!$J$5:$J$74,MATCH(TRIM(J7)&"|"&TRIM(P7),'Price List'!$O$5:$O$74,0)),0) -> 98 | X7: =IFERROR(INDEX('Price List'!$K$5:$K$74,MATCH(TRIM(J7)&"|"&TRIM(P7),'Price List'!$O$5:$O$74,0)),0) -> 0.12 | Y7: =W7*(1+X7) -> 109.76 | Z7: =Q7*(V7+Y7) -> 44660.177
C8: Civil and Structure | D8: =IFERROR(IF(TRIM($G8)="Sub Structure",IF(TRIM($H8)="Bored Pile","B.01","B.03"),IF(TRIM($G8)="Super Structure","B.04",IF(OR(TRIM($G8)="Exterior Wall and Partition",TRIM($G8)="External Wall and Partition"),"C.01",IF(TRIM($G8)="Exterior Wall Finishes","C.02",IF(TRIM($G8)="Interior Wall and Partition","C.09",IF(TRIM($G8)="Interior Door","C.10",IF(TRIM($G8)="External Windows and Louvers","C.04",IF(OR(TRIM($G8)="Interior Floor Finishes",TRIM($G8)="Internal Floor Finishes"),"D.02",IF(OR(TRIM($G8)="Interior Wall Finishes",TRIM($G8)="Internal Wall Finishes"),"D.01",IF(OR(TRIM($G8)="Ceiling Finshes",TRIM($G8)="Ceiling Finishes"),"D.03",IF(TRIM($G8)="Fittings, furnishings and equipment","E.04","")))))))))))," ") -> B.01 | E8: BA | F8: 01.UG | G8: Sub Structure | H8: Bored Pile | I8: Rebar | J8: Deform Bar, DB10(fy=390 Mpa) | P8: kg | Q8: =R8 -> 2553.8864 | R8: 2553.8864 | T8: =IFERROR(INDEX('Price List'!$G$5:$G$74,MATCH(TRIM(J8)&"|"&TRIM(P8),'Price List'!$O$5:$O$74,0)),0) -> 0.12 | U8: =IFERROR(INDEX('Price List'!$H$5:$H$74,MATCH(TRIM(J8)&"|"&TRIM(P8),'Price List'!$O$5:$O$74,0)),0) -> 0.2 | V8: =T8*(1+U8) -> 0.144 | W8: =IFERROR(INDEX('Price List'!$J$5:$J$74,MATCH(TRIM(J8)&"|"&TRIM(P8),'Price List'!$O$5:$O$74,0)),0) -> 0.78 | X8: =IFERROR(INDEX('Price List'!$K$5:$K$74,MATCH(TRIM(J8)&"|"&TRIM(P8),'Price List'!$O$5:$O$74,0)),0) -> 0.12 | Y8: =W8*(1+X8) -> 0.8736 | Z8: =Q8*(V8+Y8) -> 2598.8348
C9: Civil and Structure | D9: =IFERROR(IF(TRIM($G9)="Sub Structure",IF(TRIM($H9)="Bored Pile","B.01","B.03"),IF(TRIM($G9)="Super Structure","B.04",IF(OR(TRIM($G9)="Exterior Wall and Partition",TRIM($G9)="External Wall and Partition"),"C.01",IF(TRIM($G9)="Exterior Wall Finishes","C.02",IF(TRIM($G9)="Interior Wall and Partition","C.09",IF(TRIM($G9)="Interior Door","C.10",IF(TRIM($G9)="External Windows and Louvers","C.04",IF(OR(TRIM($G9)="Interior Floor Finishes",TRIM($G9)="Internal Floor Finishes"),"D.02",IF(OR(TRIM($G9)="Interior Wall Finishes",TRIM($G9)="Internal Wall Finishes"),"D.01",IF(OR(TRIM($G9)="Ceiling Finshes",TRIM($G9)="Ceiling Finishes"),"D.03",IF(TRIM($G9)="Fittings, furnishings and equipment","E.04","")))))))))))," ") -> B.01 | E9: BA | F9: 01.UG | G9: Sub Structure | H9: Bored Pile | I9: Rebar | J9: Deform Bar, DB25(fy=390 Mpa) | P9: kg | Q9: =R9 -> 33921.812 | R9: 33921.812 | T9: =IFERROR(INDEX('Price List'!$G$5:$G$74,MATCH(TRIM(J9)&"|"&TRIM(P9),'Price List'!$O$5:$O$74,0)),0) -> 0.08 | U9: =IFERROR(INDEX('Price List'!$H$5:$H$74,MATCH(TRIM(J9)&"|"&TRIM(P9),'Price List'!$O$5:$O$74,0)),0) -> 0.2 | V9: =T9*(1+U9) -> 0.096 | W9: =IFERROR(INDEX('Price List'!$J$5:$J$74,MATCH(TRIM(J9)&"|"&TRIM(P9),'Price List'!$O$5:$O$74,0)),0) -> 0.72 | X9: =IFERROR(INDEX('Price List'!$K$5:$K$74,MATCH(TRIM(J9)&"|"&TRIM(P9),'Price List'!$O$5:$O$74,0)),0) -> 0.12 | Y9: =W9*(1+X9) -> 0.8064 | Z9: =Q9*(V9+Y9) -> 30611.043
C10: Civil and Structure | D10: =IFERROR(IF(TRIM($G10)="Sub Structure",IF(TRIM($H10)="Bored Pile","B.01","B.03"),IF(TRIM($G10)="Super Structure","B.04",IF(OR(TRIM($G10)="Exterior Wall and Partition",TRIM($G10)="External Wall and Partition"),"C.01",IF(TRIM($G10)="Exterior Wall Finishes","C.02",IF(TRIM($G10)="Interior Wall and Partition","C.09",IF(TRIM($G10)="Interior Door","C.10",IF(TRIM($G10)="External Windows and Louvers","C.04",IF(OR(TRIM($G10)="Interior Floor Finishes",TRIM($G10)="Internal Floor Finishes"),"D.02",IF(OR(TRIM($G10)="Interior Wall Finishes",TRIM($G10)="Internal Wall Finishes"),"D.01",IF(OR(TRIM($G10)="Ceiling Finshes",TRIM($G10)="Ceiling Finishes"),"D.03",IF(TRIM($G10)="Fittings, furnishings and equipment","E.04","")))))))))))," ") -> B.01 | E10: BA | F10: 01.UG | G10: Sub Structure | H10: Bored Pile | I10: Steel Tie Wire | J10: Steel Tie Wire 1mm (Estimated 4% of Total Rebar Weight) | P10: kg | Q10: =R10 -> 1459.0279 | R10: =(R8+R9)*4% -> 1459.0279 | T10: =IFERROR(INDEX('Price List'!$G$5:$G$74,MATCH(TRIM(J10)&"|"&TRIM(P10),'Price List'!$O$5:$O$74,0)),0) -> 0.05 | U10: =IFERROR(INDEX('Price List'!$H$5:$H$74,MATCH(TRIM(J10)&"|"&TRIM(P10),'Price List'!$O$5:$O$74,0)),0) -> 0.2 | V10: =T10*(1+U10) -> 0.06 | W10: =IFERROR(INDEX('Price List'!$J$5:$J$74,MATCH(TRIM(J10)&"|"&TRIM(P10),'Price List'!$O$5:$O$74,0)),0) -> 1.2 | X10: =IFERROR(INDEX('Price List'!$K$5:$K$74,MATCH(TRIM(J10)&"|"&TRIM(P10),'Price List'!$O$5:$O$74,0)),0) -> 0.12 | Y10: =W10*(1+X10) -> 1.344 | Z10: =Q10*(V10+Y10) -> 2048.4752
C11: Civil and Structure | D11: =IFERROR(IF(TRIM($G11)="Sub Structure",IF(TRIM($H11)="Bored Pile","B.01","B.03"),IF(TRIM($G11)="Super Structure","B.04",IF(OR(TRIM($G11)="Exterior Wall and Partition",TRIM($G11)="External Wall and Partition"),"C.01",IF(TRIM($G11)="Exterior Wall Finishes","C.02",IF(TRIM($G11)="Interior Wall and Partition","C.09",IF(TRIM($G11)="Interior Door","C.10",IF(TRIM($G11)="External Windows and Louvers","C.04",IF(OR(TRIM($G11)="Interior Floor Finishes",TRIM($G11)="Internal Floor Finishes"),"D.02",IF(OR(TRIM($G11)="Interior Wall Finishes",TRIM($G11)="Internal Wall Finishes"),"D.01",IF(OR(TRIM($G11)="Ceiling Finshes",TRIM($G11)="Ceiling Finishes"),"D.03",IF(TRIM($G11)="Fittings, furnishings and equipment","E.04","")))))))))))," ") -> B.01 | E11: BA | F11: 01.UG | G11: Sub Structure | H11: Bored Pile | I11: Steel Round Pipe | J11: Steel Round Pipe (D49x2mm) with rush primer and paint | P11: m | Q11: =R11 -> 2201 | R11: =(3*17*31)+(4*5*31) -> 2201 | T11: =IFERROR(INDEX('Price List'!$G$5:$G$74,MATCH(TRIM(J11)&"|"&TRIM(P11),'Price List'!$O$5:$O$74,0)),0) -> 1.5 | U11: =IFERROR(INDEX('Price List'!$H$5:$H$74,MATCH(TRIM(J11)&"|"&TRIM(P11),'Price List'!$O$5:$O$74,0)),0) -> 0.2 | V11: =T11*(1+U11) -> 1.8 | W11: =IFERROR(INDEX('Price List'!$J$5:$J$74,MATCH(TRIM(J11)&"|"&TRIM(P11),'Price List'!$O$5:$O$74,0)),0) -> 4.5 | X11: =IFERROR(INDEX('Price List'!$K$5:$K$74,MATCH(TRIM(J11)&"|"&TRIM(P11),'Price List'!$O$5:$O$74,0)),0) -> 0.12 | Y11: =W11*(1+X11) -> 5.04 | Z11: =Q11*(V11+Y11) -> 15054.84
C12: Civil and Structure | D12: =IFERROR(IF(TRIM($G12)="Sub Structure",IF(TRIM($H12)="Bored Pile","B.01","B.03"),IF(TRIM($G12)="Super Structure","B.04",IF(OR(TRIM($G12)="Exterior Wall and Partition",TRIM($G12)="External Wall and Partition"),"C.01",IF(TRIM($G12)="Exterior Wall Finishes","C.02",IF(TRIM($G12)="Interior Wall and Partition","C.09",IF(TRIM($G12)="Interior Door","C.10",IF(TRIM($G12)="External Windows and Louvers","C.04",IF(OR(TRIM($G12)="Interior Floor Finishes",TRIM($G12)="Internal Floor Finishes"),"D.02",IF(OR(TRIM($G12)="Interior Wall Finishes",TRIM($G12)="Internal Wall Finishes"),"D.01",IF(OR(TRIM($G12)="Ceiling Finshes",TRIM($G12)="Ceiling Finishes"),"D.03",IF(TRIM($G12)="Fittings, furnishings and equipment","E.04","")))))))))))," ") -> B.01 | E12: BA | F12: 01.UG | G12: Sub Structure | H12: Bored Pile | I12: Rebar Testing | J12: Rebar Testing as per Specification | P12: Lot | Q12: =R12 -> 1 | R12: 1 | S12: 0 | T12: =IFERROR(INDEX('Price List'!$G$5:$G$74,MATCH(TRIM(J12)&"|"&TRIM(P12),'Price List'!$O$5:$O$74,0)),0) -> 0 | U12: =IFERROR(INDEX('Price List'!$H$5:$H$74,MATCH(TRIM(J12)&"|"&TRIM(P12),'Price List'!$O$5:$O$74,0)),0) -> 0 | V12: =T12*(1+U12) -> 0 | W12: =IFERROR(INDEX('Price List'!$J$5:$J$74,MATCH(TRIM(J12)&"|"&TRIM(P12),'Price List'!$O$5:$O$74,0)),0) -> 200 | X12: =IFERROR(INDEX('Price List'!$K$5:$K$74,MATCH(TRIM(J12)&"|"&TRIM(P12),'Price List'!$O$5:$O$74,0)),0) -> 0.1 | Y12: =W12*(1+X12) -> 220 | Z12: =Q12*(V12+Y12) -> 220
C13: Civil and Structure | D13: =IFERROR(IF(TRIM($G13)="Sub Structure",IF(TRIM($H13)="Bored Pile","B.01","B.03"),IF(TRIM($G13)="Super Structure","B.04",IF(OR(TRIM($G13)="Exterior Wall and Partition",TRIM($G13)="External Wall and Partition"),"C.01",IF(TRIM($G13)="Exterior Wall Finishes","C.02",IF(TRIM($G13)="Interior Wall and Partition","C.09",IF(TRIM($G13)="Interior Door","C.10",IF(TRIM($G13)="External Windows and Louvers","C.04",IF(OR(TRIM($G13)="Interior Floor Finishes",TRIM($G13)="Internal Floor Finishes"),"D.02",IF(OR(TRIM($G13)="Interior Wall Finishes",TRIM($G13)="Internal Wall Finishes"),"D.01",IF(OR(TRIM($G13)="Ceiling Finshes",TRIM($G13)="Ceiling Finishes"),"D.03",IF(TRIM($G13)="Fittings, furnishings and equipment","E.04","")))))))))))," ") -> B.03 | E13: BA | F13: 01.UG | G13: Sub Structure | H13: Pile Cap & Stump | I13: Earthwork | J13: Soil Excavation | P13: m3 | Q13: =R13 -> 1283.17 | R13: 1283.17 | T13: =IFERROR(INDEX('Price List'!$G$5:$G$74,MATCH(TRIM(J13)&"|"&TRIM(P13),'Price List'!$O$5:$O$74,0)),0) -> 3 | U13: =IFERROR(INDEX('Price List'!$H$5:$H$74,MATCH(TRIM(J13)&"|"&TRIM(P13),'Price List'!$O$5:$O$74,0)),0) -> 0.2 | V13: =T13*(1+U13) -> 3.6 | W13: =IFERROR(INDEX('Price List'!$J$5:$J$74,MATCH(TRIM(J13)&"|"&TRIM(P13),'Price List'!$O$5:$O$74,0)),0) -> 0 | X13: =IFERROR(INDEX('Price List'!$K$5:$K$74,MATCH(TRIM(J13)&"|"&TRIM(P13),'Price List'!$O$5:$O$74,0)),0) -> 0 | Y13: =W13*(1+X13) -> 0 | Z13: =Q13*(V13+Y13) -> 4619.412
C14: Civil and Structure | D14: =IFERROR(IF(TRIM($G14)="Sub Structure",IF(TRIM($H14)="Bored Pile","B.01","B.03"),IF(TRIM($G14)="Super Structure","B.04",IF(OR(TRIM($G14)="Exterior Wall and Partition",TRIM($G14)="External Wall and Partition"),"C.01",IF(TRIM($G14)="Exterior Wall Finishes","C.02",IF(TRIM($G14)="Interior Wall and Partition","C.09",IF(TRIM($G14)="Interior Door","C.10",IF(TRIM($G14)="External Windows and Louvers","C.04",IF(OR(TRIM($G14)="Interior Floor Finishes",TRIM($G14)="Internal Floor Finishes"),"D.02",IF(OR(TRIM($G14)="Interior Wall Finishes",TRIM($G14)="Internal Wall Finishes"),"D.01",IF(OR(TRIM($G14)="Ceiling Finshes",TRIM($G14)="Ceiling Finishes"),"D.03",IF(TRIM($G14)="Fittings, furnishings and equipment","E.04","")))))))))))," ") -> B.03 | E14: BA | F14: 01.UG | G14: Sub Structure | H14: Pile Cap & Stump | I14: Earthwork | J14: Soil Disposal | P14: m3 | Q14: =R14 -> 1283.17 | R14: =R13 -> 1283.17 | T14: =IFERROR(INDEX('Price List'!$G$5:$G$74,MATCH(TRIM(J14)&"|"&TRIM(P14),'Price List'!$O$5:$O$74,0)),0) -> 4 | U14: =IFERROR(INDEX('Price List'!$H$5:$H$74,MATCH(TRIM(J14)&"|"&TRIM(P14),'Price List'!$O$5:$O$74,0)),0) -> 0.2 | V14: =T14*(1+U14) -> 4.8 | W14: =IFERROR(INDEX('Price List'!$J$5:$J$74,MATCH(TRIM(J14)&"|"&TRIM(P14),'Price List'!$O$5:$O$74,0)),0) -> 0 | X14: =IFERROR(INDEX('Price List'!$K$5:$K$74,MATCH(TRIM(J14)&"|"&TRIM(P14),'Price List'!$O$5:$O$74,0)),0) -> 0 | Y14: =W14*(1+X14) -> 0 | Z14: =Q14*(V14+Y14) -> 6159.216
C15: Civil and Structure | D15: =IFERROR(IF(TRIM($G15)="Sub Structure",IF(TRIM($H15)="Bored Pile","B.01","B.03"),IF(TRIM($G15)="Super Structure","B.04",IF(OR(TRIM($G15)="Exterior Wall and Partition",TRIM($G15)="External Wall and Partition"),"C.01",IF(TRIM($G15)="Exterior Wall Finishes","C.02",IF(TRIM($G15)="Interior Wall and Partition","C.09",IF(TRIM($G15)="Interior Door","C.10",IF(TRIM($G15)="External Windows and Louvers","C.04",IF(OR(TRIM($G15)="Interior Floor Finishes",TRIM($G15)="Internal Floor Finishes"),"D.02",IF(OR(TRIM($G15)="Interior Wall Finishes",TRIM($G15)="Internal Wall Finishes"),"D.01",IF(OR(TRIM($G15)="Ceiling Finshes",TRIM($G15)="Ceiling Finishes"),"D.03",IF(TRIM($G15)="Fittings, furnishings and equipment","E.04","")))))))))))," ") -> B.03 | E15: BA | F15: 01.UG | G15: Sub Structure | H15: Pile Cap & Stump | I15: Earthwork | J15: Soil Backfill | P15: m3 | Q15: =R15 -> 1148.424 | R15: =R13-R16 -> 1148.424 | T15: =IFERROR(INDEX('Price List'!$G$5:$G$74,MATCH(TRIM(J15)&"|"&TRIM(P15),'Price List'!$O$5:$O$74,0)),0) -> 4 | U15: =IFERROR(INDEX('Price List'!$H$5:$H$74,MATCH(TRIM(J15)&"|"&TRIM(P15),'Price List'!$O$5:$O$74,0)),0) -> 0.2 | V15: =T15*(1+U15) -> 4.8 | W15: =IFERROR(INDEX('Price List'!$J$5:$J$74,MATCH(TRIM(J15)&"|"&TRIM(P15),'Price List'!$O$5:$O$74,0)),0) -> 0 | X15: =IFERROR(INDEX('Price List'!$K$5:$K$74,MATCH(TRIM(J15)&"|"&TRIM(P15),'Price List'!$O$5:$O$74,0)),0) -> 0 | Y15: =W15*(1+X15) -> 0 | Z15: =Q15*(V15+Y15) -> 5512.4352
C16: Civil and Structure | D16: =IFERROR(IF(TRIM($G16)="Sub Structure",IF(TRIM($H16)="Bored Pile","B.01","B.03"),IF(TRIM($G16)="Super Structure","B.04",IF(OR(TRIM($G16)="Exterior Wall and Partition",TRIM($G16)="External Wall and Partition"),"C.01",IF(TRIM($G16)="Exterior Wall Finishes","C.02",IF(TRIM($G16)="Interior Wall and Partition","C.09",IF(TRIM($G16)="Interior Door","C.10",IF(TRIM($G16)="External Windows and Louvers","C.04",IF(OR(TRIM($G16)="Interior Floor Finishes",TRIM($G16)="Internal Floor Finishes"),"D.02",IF(OR(TRIM($G16)="Interior Wall Finishes",TRIM($G16)="Internal Wall Finishes"),"D.01",IF(OR(TRIM($G16)="Ceiling Finshes",TRIM($G16)="Ceiling Finishes"),"D.03",IF(TRIM($G16)="Fittings, furnishings and equipment","E.04","")))))))))))," ") -> B.03 | E16: BA | F16: 01.UG | G16: Sub Structure | H16: Pile Cap & Stump | I16: Concrete | J16: Normal Concrete, 35Mpa (Cylinder), Slump 13+-2.5 | P16: m3 | Q16: =R16 -> 134.746 | R16: =124.282+(6.54*1.6) -> 134.746 | T16: =IFERROR(INDEX('Price List'!$G$5:$G$74,MATCH(TRIM(J16)&"|"&TRIM(P16),'Price List'!$O$5:$O$74,0)),0) -> 10 | U16: =IFERROR(INDEX('Price List'!$H$5:$H$74,MATCH(TRIM(J16)&"|"&TRIM(P16),'Price List'!$O$5:$O$74,0)),0) -> 0.2 | V16: =T16*(1+U16) -> 12 | W16: =IFERROR(INDEX('Price List'!$J$5:$J$74,MATCH(TRIM(J16)&"|"&TRIM(P16),'Price List'!$O$5:$O$74,0)),0) -> 98 | X16: =IFERROR(INDEX('Price List'!$K$5:$K$74,MATCH(TRIM(J16)&"|"&TRIM(P16),'Price List'!$O$5:$O$74,0)),0) -> 0.12 | Y16: =W16*(1+X16) -> 109.76 | Z16: =Q16*(V16+Y16) -> 16406.673
C17: Civil and Structure | D17: =IFERROR(IF(TRIM($G17)="Sub Structure",IF(TRIM($H17)="Bored Pile","B.01","B.03"),IF(TRIM($G17)="Super Structure","B.04",IF(OR(TRIM($G17)="Exterior Wall and Partition",TRIM($G17)="External Wall and Partition"),"C.01",IF(TRIM($G17)="Exterior Wall Finishes","C.02",IF(TRIM($G17)="Interior Wall and Partition","C.09",IF(TRIM($G17)="Interior Door","C.10",IF(TRIM($G17)="External Windows and Louvers","C.04",IF(OR(TRIM($G17)="Interior Floor Finishes",TRIM($G17)="Internal Floor Finishes"),"D.02",IF(OR(TRIM($G17)="Interior Wall Finishes",TRIM($G17)="Internal Wall Finishes"),"D.01",IF(OR(TRIM($G17)="Ceiling Finshes",TRIM($G17)="Ceiling Finishes"),"D.03",IF(TRIM($G17)="Fittings, furnishings and equipment","E.04","")))))))))))," ") -> B.03 | E17: BA | F17: 01.UG | G17: Sub Structure | H17: Pile Cap & Stump | I17: Formwork | J17: Formwork | P17: m2 | Q17: =R17 -> 200.935 | R17: 200.935 | T17: =IFERROR(INDEX('Price List'!$G$5:$G$74,MATCH(TRIM(J17)&"|"&TRIM(P17),'Price List'!$O$5:$O$74,0)),0) -> 6 | U17: =IFERROR(INDEX('Price List'!$H$5:$H$74,MATCH(TRIM(J17)&"|"&TRIM(P17),'Price List'!$O$5:$O$74,0)),0) -> 0.2 | V17: =T17*(1+U17) -> 7.2 | W17: =IFERROR(INDEX('Price List'!$J$5:$J$74,MATCH(TRIM(J17)&"|"&TRIM(P17),'Price List'!$O$5:$O$74,0)),0) -> 5 | X17: =IFERROR(INDEX('Price List'!$K$5:$K$74,MATCH(TRIM(J17)&"|"&TRIM(P17),'Price List'!$O$5:$O$74,0)),0) -> 0.12 | Y17: =W17*(1+X17) -> 5.6 | Z17: =Q17*(V17+Y17) -> 2571.968
C18: Civil and Structure | D18: =IFERROR(IF(TRIM($G18)="Sub Structure",IF(TRIM($H18)="Bored Pile","B.01","B.03"),IF(TRIM($G18)="Super Structure","B.04",IF(OR(TRIM($G18)="Exterior Wall and Partition",TRIM($G18)="External Wall and Partition"),"C.01",IF(TRIM($G18)="Exterior Wall Finishes","C.02",IF(TRIM($G18)="Interior Wall and Partition","C.09",IF(TRIM($G18)="Interior Door","C.10",IF(TRIM($G18)="External Windows and Louvers","C.04",IF(OR(TRIM($G18)="Interior Floor Finishes",TRIM($G18)="Internal Floor Finishes"),"D.02",IF(OR(TRIM($G18)="Interior Wall Finishes",TRIM($G18)="Internal Wall Finishes"),"D.01",IF(OR(TRIM($G18)="Ceiling Finshes",TRIM($G18)="Ceiling Finishes"),"D.03",IF(TRIM($G18)="Fittings, furnishings and equipment","E.04","")))))))))))," ") -> B.03 | E18: BA | F18: 01.UG | G18: Sub Structure | H18: Pile Cap & Stump | I18: Rebar | J18: Deform Bar, DB10(fy=390 Mpa) | P18: kg | Q18: =R18 -> 34.55 | R18: 34.55 | T18: =IFERROR(INDEX('Price List'!$G$5:$G$74,MATCH(TRIM(J18)&"|"&TRIM(P18),'Price List'!$O$5:$O$74,0)),0) -> 0.12 | U18: =IFERROR(INDEX('Price List'!$H$5:$H$74,MATCH(TRIM(J18)&"|"&TRIM(P18),'Price List'!$O$5:$O$74,0)),0) -> 0.2 | V18: =T18*(1+U18) -> 0.144 | W18: =IFERROR(INDEX('Price List'!$J$5:$J$74,MATCH(TRIM(J18)&"|"&TRIM(P18),'Price List'!$O$5:$O$74,0)),0) -> 0.78 | X18: =IFERROR(INDEX('Price List'!$K$5:$K$74,MATCH(TRIM(J18)&"|"&TRIM(P18),'Price List'!$O$5:$O$74,0)),0) -> 0.12 | Y18: =W18*(1+X18) -> 0.8736 | Z18: =Q18*(V18+Y18) -> 35.15808
C19: Civil and Structure | D19: =IFERROR(IF(TRIM($G19)="Sub Structure",IF(TRIM($H19)="Bored Pile","B.01","B.03"),IF(TRIM($G19)="Super Structure","B.04",IF(OR(TRIM($G19)="Exterior Wall and Partition",TRIM($G19)="External Wall and Partition"),"C.01",IF(TRIM($G19)="Exterior Wall Finishes","C.02",IF(TRIM($G19)="Interior Wall and Partition","C.09",IF(TRIM($G19)="Interior Door","C.10",IF(TRIM($G19)="External Windows and Louvers","C.04",IF(OR(TRIM($G19)="Interior Floor Finishes",TRIM($G19)="Internal Floor Finishes"),"D.02",IF(OR(TRIM($G19)="Interior Wall Finishes",TRIM($G19)="Internal Wall Finishes"),"D.01",IF(OR(TRIM($G19)="Ceiling Finshes",TRIM($G19)="Ceiling Finishes"),"D.03",IF(TRIM($G19)="Fittings, furnishings and equipment","E.04","")))))))))))," ") -> B.03 | E19: BA | F19: 01.UG | G19: Sub Structure | H19: Pile Cap & Stump | I19: Rebar | J19: Deform Bar, DB12(fy=390 Mpa) | P19: kg | Q19: =R19 -> 2639.1376 | R19: =909.4896+1346.92+382.728 -> 2639.1376 | T19: =IFERROR(INDEX('Price List'!$G$5:$G$74,MATCH(TRIM(J19)&"|"&TRIM(P19),'Price List'!$O$5:$O$74,0)),0) -> 0.11 | U19: =IFERROR(INDEX('Price List'!$H$5:$H$74,MATCH(TRIM(J19)&"|"&TRIM(P19),'Price List'!$O$5:$O$74,0)),0) -> 0.2 | V19: =T19*(1+U19) -> 0.132 | W19: =IFERROR(INDEX('Price List'!$J$5:$J$74,MATCH(TRIM(J19)&"|"&TRIM(P19),'Price List'!$O$5:$O$74,0)),0) -> 0.76 | X19: =IFERROR(INDEX('Price List'!$K$5:$K$74,MATCH(TRIM(J19)&"|"&TRIM(P19),'Price List'!$O$5:$O$74,0)),0) -> 0.12 | Y19: =W19*(1+X19) -> 0.8512 | Z19: =Q19*(V19+Y19) -> 2594.8001
C20: Civil and Structure | D20: =IFERROR(IF(TRIM($G20)="Sub Structure",IF(TRIM($H20)="Bored Pile","B.01","B.03"),IF(TRIM($G20)="Super Structure","B.04",IF(OR(TRIM($G20)="Exterior Wall and Partition",TRIM($G20)="External Wall and Partition"),"C.01",IF(TRIM($G20)="Exterior Wall Finishes","C.02",IF(TRIM($G20)="Interior Wall and Partition","C.09",IF(TRIM($G20)="Interior Door","C.10",IF(TRIM($G20)="External Windows and Louvers","C.04",IF(OR(TRIM($G20)="Interior Floor Finishes",TRIM($G20)="Internal Floor Finishes"),"D.02",IF(OR(TRIM($G20)="Interior Wall Finishes",TRIM($G20)="Internal Wall Finishes"),"D.01",IF(OR(TRIM($G20)="Ceiling Finshes",TRIM($G20)="Ceiling Finishes"),"D.03",IF(TRIM($G20)="Fittings, furnishings and equipment","E.04","")))))))))))," ") -> B.03 | E20: BA | F20: 01.UG | G20: Sub Structure | H20: Pile Cap & Stump | I20: Rebar | J20: Deform Bar, DB16(fy=390 Mpa) | P20: kg | Q20: =R20 -> 1372.388 | R20: 1372.388 | T20: =IFERROR(INDEX('Price List'!$G$5:$G$74,MATCH(TRIM(J20)&"|"&TRIM(P20),'Price List'!$O$5:$O$74,0)),0) -> 0.1 | U20: =IFERROR(INDEX('Price List'!$H$5:$H$74,MATCH(TRIM(J20)&"|"&TRIM(P20),'Price List'!$O$5:$O$74,0)),0) -> 0.2 | V20: =T20*(1+U20) -> 0.12 | W20: =IFERROR(INDEX('Price List'!$J$5:$J$74,MATCH(TRIM(J20)&"|"&TRIM(P20),'Price List'!$O$5:$O$74,0)),0) -> 0.74 | X20: =IFERROR(INDEX('Price List'!$K$5:$K$74,MATCH(TRIM(J20)&"|"&TRIM(P20),'Price List'!$O$5:$O$74,0)),0) -> 0.12 | Y20: =W20*(1+X20) -> 0.8288 | Z20: =Q20*(V20+Y20) -> 1302.1217
C21: Civil and Structure | D21: =IFERROR(IF(TRIM($G21)="Sub Structure",IF(TRIM($H21)="Bored Pile","B.01","B.03"),IF(TRIM($G21)="Super Structure","B.04",IF(OR(TRIM($G21)="Exterior Wall and Partition",TRIM($G21)="External Wall and Partition"),"C.01",IF(TRIM($G21)="Exterior Wall Finishes","C.02",IF(TRIM($G21)="Interior Wall and Partition","C.09",IF(TRIM($G21)="Interior Door","C.10",IF(TRIM($G21)="External Windows and Louvers","C.04",IF(OR(TRIM($G21)="Interior Floor Finishes",TRIM($G21)="Internal Floor Finishes"),"D.02",IF(OR(TRIM($G21)="Interior Wall Finishes",TRIM($G21)="Internal Wall Finishes"),"D.01",IF(OR(TRIM($G21)="Ceiling Finshes",TRIM($G21)="Ceiling Finishes"),"D.03",IF(TRIM($G21)="Fittings, furnishings and equipment","E.04","")))))))))))," ") -> B.03 | E21: BA | F21: 01.UG | G21: Sub Structure | H21: Pile Cap & Stump | I21: Rebar | J21: Deform Bar, DB20(fy=390 Mpa) | P21: kg | Q21: =R21 -> 11795.979 | R21: =11116.235+679.744 -> 11795.979 | T21: =IFERROR(INDEX('Price List'!$G$5:$G$74,MATCH(TRIM(J21)&"|"&TRIM(P21),'Price List'!$O$5:$O$74,0)),0) -> 0.09 | U21: =IFERROR(INDEX('Price List'!$H$5:$H$74,MATCH(TRIM(J21)&"|"&TRIM(P21),'Price List'!$O$5:$O$74,0)),0) -> 0.2 | V21: =T21*(1+U21) -> 0.108 | W21: =IFERROR(INDEX('Price List'!$J$5:$J$74,MATCH(TRIM(J21)&"|"&TRIM(P21),'Price List'!$O$5:$O$74,0)),0) -> 0.73 | X21: =IFERROR(INDEX('Price List'!$K$5:$K$74,MATCH(TRIM(J21)&"|"&TRIM(P21),'Price List'!$O$5:$O$74,0)),0) -> 0.12 | Y21: =W21*(1+X21) -> 0.8176 | Z21: =Q21*(V21+Y21) -> 10918.358
C22: Civil and Structure | D22: =IFERROR(IF(TRIM($G22)="Sub Structure",IF(TRIM($H22)="Bored Pile","B.01","B.03"),IF(TRIM($G22)="Super Structure","B.04",IF(OR(TRIM($G22)="Exterior Wall and Partition",TRIM($G22)="External Wall and Partition"),"C.01",IF(TRIM($G22)="Exterior Wall Finishes","C.02",IF(TRIM($G22)="Interior Wall and Partition","C.09",IF(TRIM($G22)="Interior Door","C.10",IF(TRIM($G22)="External Windows and Louvers","C.04",IF(OR(TRIM($G22)="Interior Floor Finishes",TRIM($G22)="Internal Floor Finishes"),"D.02",IF(OR(TRIM($G22)="Interior Wall Finishes",TRIM($G22)="Internal Wall Finishes"),"D.01",IF(OR(TRIM($G22)="Ceiling Finshes",TRIM($G22)="Ceiling Finishes"),"D.03",IF(TRIM($G22)="Fittings, furnishings and equipment","E.04","")))))))))))," ") -> B.03 | E22: BA | F22: 01.UG | G22: Sub Structure | H22: Pile Cap & Stump | I22: Rebar | J22: Deform Bar, DB25(fy=390 Mpa) | P22: kg | Q22: =R22 -> 1694 | R22: 1694 | T22: =IFERROR(INDEX('Price List'!$G$5:$G$74,MATCH(TRIM(J22)&"|"&TRIM(P22),'Price List'!$O$5:$O$74,0)),0) -> 0.08 | U22: =IFERROR(INDEX('Price List'!$H$5:$H$74,MATCH(TRIM(J22)&"|"&TRIM(P22),'Price List'!$O$5:$O$74,0)),0) -> 0.2 | V22: =T22*(1+U22) -> 0.096 | W22: =IFERROR(INDEX('Price List'!$J$5:$J$74,MATCH(TRIM(J22)&"|"&TRIM(P22),'Price List'!$O$5:$O$74,0)),0) -> 0.72 | X22: =IFERROR(INDEX('Price List'!$K$5:$K$74,MATCH(TRIM(J22)&"|"&TRIM(P22),'Price List'!$O$5:$O$74,0)),0) -> 0.12 | Y22: =W22*(1+X22) -> 0.8064 | Z22: =Q22*(V22+Y22) -> 1528.6656
C23: Civil and Structure | D23: =IFERROR(IF(TRIM($G23)="Sub Structure",IF(TRIM($H23)="Bored Pile","B.01","B.03"),IF(TRIM($G23)="Super Structure","B.04",IF(OR(TRIM($G23)="Exterior Wall and Partition",TRIM($G23)="External Wall and Partition"),"C.01",IF(TRIM($G23)="Exterior Wall Finishes","C.02",IF(TRIM($G23)="Interior Wall and Partition","C.09",IF(TRIM($G23)="Interior Door","C.10",IF(TRIM($G23)="External Windows and Louvers","C.04",IF(OR(TRIM($G23)="Interior Floor Finishes",TRIM($G23)="Internal Floor Finishes"),"D.02",IF(OR(TRIM($G23)="Interior Wall Finishes",TRIM($G23)="Internal Wall Finishes"),"D.01",IF(OR(TRIM($G23)="Ceiling Finshes",TRIM($G23)="Ceiling Finishes"),"D.03",IF(TRIM($G23)="Fittings, furnishings and equipment","E.04","")))))))))))," ") -> B.03 | E23: BA | F23: 01.UG | G23: Sub Structure | H23: Pile Cap & Stump | I23: Rebar | J23: Deform Bar, DB32(fy=390 Mpa) | P23: kg | Q23: =R23 -> 10611.798 | R23: =1268.31+9343.488 -> 10611.798 | T23: =IFERROR(INDEX('Price List'!$G$5:$G$74,MATCH(TRIM(J23)&"|"&TRIM(P23),'Price List'!$O$5:$O$74,0)),0) -> 0.08 | U23: =IFERROR(INDEX('Price List'!$H$5:$H$74,MATCH(TRIM(J23)&"|"&TRIM(P23),'Price List'!$O$5:$O$74,0)),0) -> 0.2 | V23: =T23*(1+U23) -> 0.096 | W23: =IFERROR(INDEX('Price List'!$J$5:$J$74,MATCH(TRIM(J23)&"|"&TRIM(P23),'Price List'!$O$5:$O$74,0)),0) -> 0.71 | X23: =IFERROR(INDEX('Price List'!$K$5:$K$74,MATCH(TRIM(J23)&"|"&TRIM(P23),'Price List'!$O$5:$O$74,0)),0) -> 0.12 | Y23: =W23*(1+X23) -> 0.7952 | Z23: =Q23*(V23+Y23) -> 9457.2344
C24: Civil and Structure | D24: =IFERROR(IF(TRIM($G24)="Sub Structure",IF(TRIM($H24)="Bored Pile","B.01","B.03"),IF(TRIM($G24)="Super Structure","B.04",IF(OR(TRIM($G24)="Exterior Wall and Partition",TRIM($G24)="External Wall and Partition"),"C.01",IF(TRIM($G24)="Exterior Wall Finishes","C.02",IF(TRIM($G24)="Interior Wall and Partition","C.09",IF(TRIM($G24)="Interior Door","C.10",IF(TRIM($G24)="External Windows and Louvers","C.04",IF(OR(TRIM($G24)="Interior Floor Finishes",TRIM($G24)="Internal Floor Finishes"),"D.02",IF(OR(TRIM($G24)="Interior Wall Finishes",TRIM($G24)="Internal Wall Finishes"),"D.01",IF(OR(TRIM($G24)="Ceiling Finshes",TRIM($G24)="Ceiling Finishes"),"D.03",IF(TRIM($G24)="Fittings, furnishings and equipment","E.04","")))))))))))," ") -> B.03 | E24: BA | F24: 01.UG | G24: Sub Structure | H24: Pile Cap & Stump | I24: Steel Tie Wire | J24: Steel Tie Wire 1mm (Estimated 4% of Total Rebar Weight) | P24: kg | Q24: =R24 -> 1069.6366 | R24: =(R19+R21+R23+R22)*4% -> 1069.6366 | T24: =IFERROR(INDEX('Price List'!$G$5:$G$74,MATCH(TRIM(J24)&"|"&TRIM(P24),'Price List'!$O$5:$O$74,0)),0) -> 0.05 | U24: =IFERROR(INDEX('Price List'!$H$5:$H$74,MATCH(TRIM(J24)&"|"&TRIM(P24),'Price List'!$O$5:$O$74,0)),0) -> 0.2 | V24: =T24*(1+U24) -> 0.06 | W24: =IFERROR(INDEX('Price List'!$J$5:$J$74,MATCH(TRIM(J24)&"|"&TRIM(P24),'Price List'!$O$5:$O$74,0)),0) -> 1.2 | X24: =IFERROR(INDEX('Price List'!$K$5:$K$74,MATCH(TRIM(J24)&"|"&TRIM(P24),'Price List'!$O$5:$O$74,0)),0) -> 0.12 | Y24: =W24*(1+X24) -> 1.344 | Z24: =Q24*(V24+Y24) -> 1501.7698
C25: Civil and Structure | D25: =IFERROR(IF(TRIM($G25)="Sub Structure",IF(TRIM($H25)="Bored Pile","B.01","B.03"),IF(TRIM($G25)="Super Structure","B.04",IF(OR(TRIM($G25)="Exterior Wall and Partition",TRIM($G25)="External Wall and Partition"),"C.01",IF(TRIM($G25)="Exterior Wall Finishes","C.02",IF(TRIM($G25)="Interior Wall and Partition","C.09",IF(TRIM($G25)="Interior Door","C.10",IF(TRIM($G25)="External Windows and Louvers","C.04",IF(OR(TRIM($G25)="Interior Floor Finishes",TRIM($G25)="Internal Floor Finishes"),"D.02",IF(OR(TRIM($G25)="Interior Wall Finishes",TRIM($G25)="Internal Wall Finishes"),"D.01",IF(OR(TRIM($G25)="Ceiling Finshes",TRIM($G25)="Ceiling Finishes"),"D.03",IF(TRIM($G25)="Fittings, furnishings and equipment","E.04","")))))))))))," ") -> B.03 | E25: BA | F25: 01.UG | G25: Sub Structure | H25: Pile Cap & Stump | I25: Base Preparation | J25: Well Soil Compact | P25: m2 | Q25: =R25 -> 131.43 | R25: =(5.76*11)+(6.76*5)+(34.27) -> 131.43 | T25: =IFERROR(INDEX('Price List'!$G$5:$G$74,MATCH(TRIM(J25)&"|"&TRIM(P25),'Price List'!$O$5:$O$74,0)),0) -> 2 | U25: =IFERROR(INDEX('Price List'!$H$5:$H$74,MATCH(TRIM(J25)&"|"&TRIM(P25),'Price List'!$O$5:$O$74,0)),0) -> 0.2 | V25: =T25*(1+U25) -> 2.4 | W25: =IFERROR(INDEX('Price List'!$J$5:$J$74,MATCH(TRIM(J25)&"|"&TRIM(P25),'Price List'!$O$5:$O$74,0)),0) -> 0 | X25: =IFERROR(INDEX('Price List'!$K$5:$K$74,MATCH(TRIM(J25)&"|"&TRIM(P25),'Price List'!$O$5:$O$74,0)),0) -> 0 | Y25: =W25*(1+X25) -> 0 | Z25: =Q25*(V25+Y25) -> 315.432
C26: Civil and Structure | D26: =IFERROR(IF(TRIM($G26)="Sub Structure",IF(TRIM($H26)="Bored Pile","B.01","B.03"),IF(TRIM($G26)="Super Structure","B.04",IF(OR(TRIM($G26)="Exterior Wall and Partition",TRIM($G26)="External Wall and Partition"),"C.01",IF(TRIM($G26)="Exterior Wall Finishes","C.02",IF(TRIM($G26)="Interior Wall and Partition","C.09",IF(TRIM($G26)="Interior Door","C.10",IF(TRIM($G26)="External Windows and Louvers","C.04",IF(OR(TRIM($G26)="Interior Floor Finishes",TRIM($G26)="Internal Floor Finishes"),"D.02",IF(OR(TRIM($G26)="Interior Wall Finishes",TRIM($G26)="Internal Wall Finishes"),"D.01",IF(OR(TRIM($G26)="Ceiling Finshes",TRIM($G26)="Ceiling Finishes"),"D.03",IF(TRIM($G26)="Fittings, furnishings and equipment","E.04","")))))))))))," ") -> B.03 | E26: BA | F26: 01.UG | G26: Sub Structure | H26: Pile Cap & Stump | I26: Lean Concrete | J26: Lean Concrete, 15Mpa (Cylinder) | P26: m3 | Q26: =R26 -> 14.8565 | R26: =(5.76*11*0.1)+(6.76*5*0.1)+(34.27*0.15) -> 14.8565 | T26: =IFERROR(INDEX('Price List'!$G$5:$G$74,MATCH(TRIM(J26)&"|"&TRIM(P26),'Price List'!$O$5:$O$74,0)),0) -> 7 | U26: =IFERROR(INDEX('Price List'!$H$5:$H$74,MATCH(TRIM(J26)&"|"&TRIM(P26),'Price List'!$O$5:$O$74,0)),0) -> 0.2 | V26: =T26*(1+U26) -> 8.4 | W26: =IFERROR(INDEX('Price List'!$J$5:$J$74,MATCH(TRIM(J26)&"|"&TRIM(P26),'Price List'!$O$5:$O$74,0)),0) -> 75 | X26: =IFERROR(INDEX('Price List'!$K$5:$K$74,MATCH(TRIM(J26)&"|"&TRIM(P26),'Price List'!$O$5:$O$74,0)),0) -> 0.12 | Y26: =W26*(1+X26) -> 84 | Z26: =Q26*(V26+Y26) -> 1372.7406
C27: Civil and Structure | D27: =IFERROR(IF(TRIM($G27)="Sub Structure",IF(TRIM($H27)="Bored Pile","B.01","B.03"),IF(TRIM($G27)="Super Structure","B.04",IF(OR(TRIM($G27)="Exterior Wall and Partition",TRIM($G27)="External Wall and Partition"),"C.01",IF(TRIM($G27)="Exterior Wall Finishes","C.02",IF(TRIM($G27)="Interior Wall and Partition","C.09",IF(TRIM($G27)="Interior Door","C.10",IF(TRIM($G27)="External Windows and Louvers","C.04",IF(OR(TRIM($G27)="Interior Floor Finishes",TRIM($G27)="Internal Floor Finishes"),"D.02",IF(OR(TRIM($G27)="Interior Wall Finishes",TRIM($G27)="Internal Wall Finishes"),"D.01",IF(OR(TRIM($G27)="Ceiling Finshes",TRIM($G27)="Ceiling Finishes"),"D.03",IF(TRIM($G27)="Fittings, furnishings and equipment","E.04","")))))))))))," ") -> B.03 | E27: BA | F27: 01.UG | G27: Sub Structure | H27: Pile Cap & Stump | I27: Water Stop | J27: PVC Waterbar® V VN 20 (Width 200mm) | P27: m | Q27: =R27 -> 18 | R27: 18 | S27: 0 | T27: =IFERROR(INDEX('Price List'!$G$5:$G$74,MATCH(TRIM(J27)&"|"&TRIM(P27),'Price List'!$O$5:$O$74,0)),0) -> 1.5 | U27: =IFERROR(INDEX('Price List'!$H$5:$H$74,MATCH(TRIM(J27)&"|"&TRIM(P27),'Price List'!$O$5:$O$74,0)),0) -> 0.2 | V27: =T27*(1+U27) -> 1.8 | W27: =IFERROR(INDEX('Price List'!$J$5:$J$74,MATCH(TRIM(J27)&"|"&TRIM(P27),'Price List'!$O$5:$O$74,0)),0) -> 4 | X27: =IFERROR(INDEX('Price List'!$K$5:$K$74,MATCH(TRIM(J27)&"|"&TRIM(P27),'Price List'!$O$5:$O$74,0)),0) -> 0.12 | Y27: =W27*(1+X27) -> 4.48 | Z27: =Q27*(V27+Y27) -> 113.04
C28: Civil and Structure | D28: =IFERROR(IF(TRIM($G28)="Sub Structure",IF(TRIM($H28)="Bored Pile","B.01","B.03"),IF(TRIM($G28)="Super Structure","B.04",IF(OR(TRIM($G28)="Exterior Wall and Partition",TRIM($G28)="External Wall and Partition"),"C.01",IF(TRIM($G28)="Exterior Wall Finishes","C.02",IF(TRIM($G28)="Interior Wall and Partition","C.09",IF(TRIM($G28)="Interior Door","C.10",IF(TRIM($G28)="External Windows and Louvers","C.04",IF(OR(TRIM($G28)="Interior Floor Finishes",TRIM($G28)="Internal Floor Finishes"),"D.02",IF(OR(TRIM($G28)="Interior Wall Finishes",TRIM($G28)="Internal Wall Finishes"),"D.01",IF(OR(TRIM($G28)="Ceiling Finshes",TRIM($G28)="Ceiling Finishes"),"D.03",IF(TRIM($G28)="Fittings, furnishings and equipment","E.04","")))))))))))," ") -> B.03 | E28: BA | F28: 01.UG | G28: Sub Structure | H28: Pile Cap & Stump | I28: Waterproofing | J28: Membrance sheet 2mm thk | P28: m2 | Q28: =R28 -> 7.2695 | R28: =2.17*3.35 -> 7.2695 | T28: =IFERROR(INDEX('Price List'!$G$5:$G$74,MATCH(TRIM(J28)&"|"&TRIM(P28),'Price List'!$O$5:$O$74,0)),0) -> 2 | U28: =IFERROR(INDEX('Price List'!$H$5:$H$74,MATCH(TRIM(J28)&"|"&TRIM(P28),'Price List'!$O$5:$O$74,0)),0) -> 0.2 | V28: =T28*(1+U28) -> 2.4 | W28: =IFERROR(INDEX('Price List'!$J$5:$J$74,MATCH(TRIM(J28)&"|"&TRIM(P28),'Price List'!$O$5:$O$74,0)),0) -> 6.5 | X28: =IFERROR(INDEX('Price List'!$K$5:$K$74,MATCH(TRIM(J28)&"|"&TRIM(P28),'Price List'!$O$5:$O$74,0)),0) -> 0.12 | Y28: =W28*(1+X28) -> 7.28 | Z28: =Q28*(V28+Y28) -> 70.36876
C29: Civil and Structure | D29: =IFERROR(IF(TRIM($G29)="Sub Structure",IF(TRIM($H29)="Bored Pile","B.01","B.03"),IF(TRIM($G29)="Super Structure","B.04",IF(OR(TRIM($G29)="Exterior Wall and Partition",TRIM($G29)="External Wall and Partition"),"C.01",IF(TRIM($G29)="Exterior Wall Finishes","C.02",IF(TRIM($G29)="Interior Wall and Partition","C.09",IF(TRIM($G29)="Interior Door","C.10",IF(TRIM($G29)="External Windows and Louvers","C.04",IF(OR(TRIM($G29)="Interior Floor Finishes",TRIM($G29)="Internal Floor Finishes"),"D.02",IF(OR(TRIM($G29)="Interior Wall Finishes",TRIM($G29)="Internal Wall Finishes"),"D.01",IF(OR(TRIM($G29)="Ceiling Finshes",TRIM($G29)="Ceiling Finishes"),"D.03",IF(TRIM($G29)="Fittings, furnishings and equipment","E.04","")))))))))))," ") -> B.03 | E29: BA | F29: 01.UG | G29: Sub Structure | H29: Septic tank | I29: Earthwork | J29: Soil Excavation | P29: m3 | Q29: =R29 -> 288 | R29: =90*3.2 -> 288 | T29: =IFERROR(INDEX('Price List'!$G$5:$G$74,MATCH(TRIM(J29)&"|"&TRIM(P29),'Price List'!$O$5:$O$74,0)),0) -> 3 | U29: =IFERROR(INDEX('Price List'!$H$5:$H$74,MATCH(TRIM(J29)&"|"&TRIM(P29),'Price List'!$O$5:$O$74,0)),0) -> 0.2 | V29: =T29*(1+U29) -> 3.6 | W29: =IFERROR(INDEX('Price List'!$J$5:$J$74,MATCH(TRIM(J29)&"|"&TRIM(P29),'Price List'!$O$5:$O$74,0)),0) -> 0 | X29: =IFERROR(INDEX('Price List'!$K$5:$K$74,MATCH(TRIM(J29)&"|"&TRIM(P29),'Price List'!$O$5:$O$74,0)),0) -> 0 | Y29: =W29*(1+X29) -> 0 | Z29: =Q29*(V29+Y29) -> 1036.8
C30: Civil and Structure | D30: =IFERROR(IF(TRIM($G30)="Sub Structure",IF(TRIM($H30)="Bored Pile","B.01","B.03"),IF(TRIM($G30)="Super Structure","B.04",IF(OR(TRIM($G30)="Exterior Wall and Partition",TRIM($G30)="External Wall and Partition"),"C.01",IF(TRIM($G30)="Exterior Wall Finishes","C.02",IF(TRIM($G30)="Interior Wall and Partition","C.09",IF(TRIM($G30)="Interior Door","C.10",IF(TRIM($G30)="External Windows and Louvers","C.04",IF(OR(TRIM($G30)="Interior Floor Finishes",TRIM($G30)="Internal Floor Finishes"),"D.02",IF(OR(TRIM($G30)="Interior Wall Finishes",TRIM($G30)="Internal Wall Finishes"),"D.01",IF(OR(TRIM($G30)="Ceiling Finshes",TRIM($G30)="Ceiling Finishes"),"D.03",IF(TRIM($G30)="Fittings, furnishings and equipment","E.04","")))))))))))," ") -> B.03 | E30: BA | F30: 01.UG | G30: Sub Structure | H30: Septic tank | I30: Earthwork | J30: Soil Disposal | P30: m3 | Q30: =R30 -> 288 | R30: =R29 -> 288 | T30: =IFERROR(INDEX('Price List'!$G$5:$G$74,MATCH(TRIM(J30)&"|"&TRIM(P30),'Price List'!$O$5:$O$74,0)),0) -> 4 | U30: =IFERROR(INDEX('Price List'!$H$5:$H$74,MATCH(TRIM(J30)&"|"&TRIM(P30),'Price List'!$O$5:$O$74,0)),0) -> 0.2 | V30: =T30*(1+U30) -> 4.8 | W30: =IFERROR(INDEX('Price List'!$J$5:$J$74,MATCH(TRIM(J30)&"|"&TRIM(P30),'Price List'!$O$5:$O$74,0)),0) -> 0 | X30: =IFERROR(INDEX('Price List'!$K$5:$K$74,MATCH(TRIM(J30)&"|"&TRIM(P30),'Price List'!$O$5:$O$74,0)),0) -> 0 | Y30: =W30*(1+X30) -> 0 | Z30: =Q30*(V30+Y30) -> 1382.4
C31: Civil and Structure | D31: =IFERROR(IF(TRIM($G31)="Sub Structure",IF(TRIM($H31)="Bored Pile","B.01","B.03"),IF(TRIM($G31)="Super Structure","B.04",IF(OR(TRIM($G31)="Exterior Wall and Partition",TRIM($G31)="External Wall and Partition"),"C.01",IF(TRIM($G31)="Exterior Wall Finishes","C.02",IF(TRIM($G31)="Interior Wall and Partition","C.09",IF(TRIM($G31)="Interior Door","C.10",IF(TRIM($G31)="External Windows and Louvers","C.04",IF(OR(TRIM($G31)="Interior Floor Finishes",TRIM($G31)="Internal Floor Finishes"),"D.02",IF(OR(TRIM($G31)="Interior Wall Finishes",TRIM($G31)="Internal Wall Finishes"),"D.01",IF(OR(TRIM($G31)="Ceiling Finshes",TRIM($G31)="Ceiling Finishes"),"D.03",IF(TRIM($G31)="Fittings, furnishings and equipment","E.04","")))))))))))," ") -> B.03 | E31: BA | F31: 01.UG | G31: Sub Structure | H31: Septic tank | I31: Earthwork | J31: Soil Backfill | P31: m3 | Q31: =R31 -> 222 | R31: =R29-R32 -> 222 | T31: =IFERROR(INDEX('Price List'!$G$5:$G$74,MATCH(TRIM(J31)&"|"&TRIM(P31),'Price List'!$O$5:$O$74,0)),0) -> 4 | U31: =IFERROR(INDEX('Price List'!$H$5:$H$74,MATCH(TRIM(J31)&"|"&TRIM(P31),'Price List'!$O$5:$O$74,0)),0) -> 0.2 | V31: =T31*(1+U31) -> 4.8 | W31: =IFERROR(INDEX('Price List'!$J$5:$J$74,MATCH(TRIM(J31)&"|"&TRIM(P31),'Price List'!$O$5:$O$74,0)),0) -> 0 | X31: =IFERROR(INDEX('Price List'!$K$5:$K$74,MATCH(TRIM(J31)&"|"&TRIM(P31),'Price List'!$O$5:$O$74,0)),0) -> 0 | Y31: =W31*(1+X31) -> 0 | Z31: =Q31*(V31+Y31) -> 1065.6
C32: Civil and Structure | D32: =IFERROR(IF(TRIM($G32)="Sub Structure",IF(TRIM($H32)="Bored Pile","B.01","B.03"),IF(TRIM($G32)="Super Structure","B.04",IF(OR(TRIM($G32)="Exterior Wall and Partition",TRIM($G32)="External Wall and Partition"),"C.01",IF(TRIM($G32)="Exterior Wall Finishes","C.02",IF(TRIM($G32)="Interior Wall and Partition","C.09",IF(TRIM($G32)="Interior Door","C.10",IF(TRIM($G32)="External Windows and Louvers","C.04",IF(OR(TRIM($G32)="Interior Floor Finishes",TRIM($G32)="Internal Floor Finishes"),"D.02",IF(OR(TRIM($G32)="Interior Wall Finishes",TRIM($G32)="Internal Wall Finishes"),"D.01",IF(OR(TRIM($G32)="Ceiling Finshes",TRIM($G32)="Ceiling Finishes"),"D.03",IF(TRIM($G32)="Fittings, furnishings and equipment","E.04","")))))))))))," ") -> B.03 | E32: BA | F32: 01.UG | G32: Sub Structure | H32: Septic tank | I32: Concrete | J32: Normal Concrete, 35Mpa (Cylinder), Slump 13+-2.5 | P32: m3 | Q32: =R32 -> 66 | R32: 66 | T32: =IFERROR(INDEX('Price List'!$G$5:$G$74,MATCH(TRIM(J32)&"|"&TRIM(P32),'Price List'!$O$5:$O$74,0)),0) -> 10 | U32: =IFERROR(INDEX('Price List'!$H$5:$H$74,MATCH(TRIM(J32)&"|"&TRIM(P32),'Price List'!$O$5:$O$74,0)),0) -> 0.2 | V32: =T32*(1+U32) -> 12 | W32: =IFERROR(INDEX('Price List'!$J$5:$J$74,MATCH(TRIM(J32)&"|"&TRIM(P32),'Price List'!$O$5:$O$74,0)),0) -> 98 | X32: =IFERROR(INDEX('Price List'!$K$5:$K$74,MATCH(TRIM(J32)&"|"&TRIM(P32),'Price List'!$O$5:$O$74,0)),0) -> 0.12 | Y32: =W32*(1+X32) -> 109.76 | Z32: =Q32*(V32+Y32) -> 8036.16
C33: Civil and Structure | D33: =IFERROR(IF(TRIM($G33)="Sub Structure",IF(TRIM($H33)="Bored Pile","B.01","B.03"),IF(TRIM($G33)="Super Structure","B.04",IF(OR(TRIM($G33)="Exterior Wall and Partition",TRIM($G33)="External Wall and Partition"),"C.01",IF(TRIM($G33)="Exterior Wall Finishes","C.02",IF(TRIM($G33)="Interior Wall and Partition","C.09",IF(TRIM($G33)="Interior Door","C.10",IF(TRIM($G33)="External Windows and Louvers","C.04",IF(OR(TRIM($G33)="Interior Floor Finishes",TRIM($G33)="Internal Floor Finishes"),"D.02",IF(OR(TRIM($G33)="Interior Wall Finishes",TRIM($G33)="Internal Wall Finishes"),"D.01",IF(OR(TRIM($G33)="Ceiling Finshes",TRIM($G33)="Ceiling Finishes"),"D.03",IF(TRIM($G33)="Fittings, furnishings and equipment","E.04","")))))))))))," ") -> B.03 | E33: BA | F33: 01.UG | G33: Sub Structure | H33: Septic tank | I33: Formwork | J33: Formwork | P33: m2 | Q33: =R33 -> 556 | R33: 556 | T33: =IFERROR(INDEX('Price List'!$G$5:$G$74,MATCH(TRIM(J33)&"|"&TRIM(P33),'Price List'!$O$5:$O$74,0)),0) -> 6 | U33: =IFERROR(INDEX('Price List'!$H$5:$H$74,MATCH(TRIM(J33)&"|"&TRIM(P33),'Price List'!$O$5:$O$74,0)),0) -> 0.2 | V33: =T33*(1+U33) -> 7.2 | W33: =IFERROR(INDEX('Price List'!$J$5:$J$74,MATCH(TRIM(J33)&"|"&TRIM(P33),'Price List'!$O$5:$O$74,0)),0) -> 5 | X33: =IFERROR(INDEX('Price List'!$K$5:$K$74,MATCH(TRIM(J33)&"|"&TRIM(P33),'Price List'!$O$5:$O$74,0)),0) -> 0.12 | Y33: =W33*(1+X33) -> 5.6 | Z33: =Q33*(V33+Y33) -> 7116.8
C34: Civil and Structure | D34: =IFERROR(IF(TRIM($G34)="Sub Structure",IF(TRIM($H34)="Bored Pile","B.01","B.03"),IF(TRIM($G34)="Super Structure","B.04",IF(OR(TRIM($G34)="Exterior Wall and Partition",TRIM($G34)="External Wall and Partition"),"C.01",IF(TRIM($G34)="Exterior Wall Finishes","C.02",IF(TRIM($G34)="Interior Wall and Partition","C.09",IF(TRIM($G34)="Interior Door","C.10",IF(TRIM($G34)="External Windows and Louvers","C.04",IF(OR(TRIM($G34)="Interior Floor Finishes",TRIM($G34)="Internal Floor Finishes"),"D.02",IF(OR(TRIM($G34)="Interior Wall Finishes",TRIM($G34)="Internal Wall Finishes"),"D.01",IF(OR(TRIM($G34)="Ceiling Finshes",TRIM($G34)="Ceiling Finishes"),"D.03",IF(TRIM($G34)="Fittings, furnishings and equipment","E.04","")))))))))))," ") -> B.03 | E34: BA | F34: 01.UG | G34: Sub Structure | H34: Septic tank | I34: Base Preparation | J34: Well Soil Compact | P34: m2 | Q34: =R34 -> 70 | R34: 70 | T34: =IFERROR(INDEX('Price List'!$G$5:$G$74,MATCH(TRIM(J34)&"|"&TRIM(P34),'Price List'!$O$5:$O$74,0)),0) -> 2 | U34: =IFERROR(INDEX('Price List'!$H$5:$H$74,MATCH(TRIM(J34)&"|"&TRIM(P34),'Price List'!$O$5:$O$74,0)),0) -> 0.2 | V34: =T34*(1+U34) -> 2.4 | W34: =IFERROR(INDEX('Price List'!$J$5:$J$74,MATCH(TRIM(J34)&"|"&TRIM(P34),'Price List'!$O$5:$O$74,0)),0) -> 0 | X34: =IFERROR(INDEX('Price List'!$K$5:$K$74,MATCH(TRIM(J34)&"|"&TRIM(P34),'Price List'!$O$5:$O$74,0)),0) -> 0 | Y34: =W34*(1+X34) -> 0 | Z34: =Q34*(V34+Y34) -> 168
C35: Civil and Structure | D35: =IFERROR(IF(TRIM($G35)="Sub Structure",IF(TRIM($H35)="Bored Pile","B.01","B.03"),IF(TRIM($G35)="Super Structure","B.04",IF(OR(TRIM($G35)="Exterior Wall and Partition",TRIM($G35)="External Wall and Partition"),"C.01",IF(TRIM($G35)="Exterior Wall Finishes","C.02",IF(TRIM($G35)="Interior Wall and Partition","C.09",IF(TRIM($G35)="Interior Door","C.10",IF(TRIM($G35)="External Windows and Louvers","C.04",IF(OR(TRIM($G35)="Interior Floor Finishes",TRIM($G35)="Internal Floor Finishes"),"D.02",IF(OR(TRIM($G35)="Interior Wall Finishes",TRIM($G35)="Internal Wall Finishes"),"D.01",IF(OR(TRIM($G35)="Ceiling Finshes",TRIM($G35)="Ceiling Finishes"),"D.03",IF(TRIM($G35)="Fittings, furnishings and equipment","E.04","")))))))))))," ") -> B.03 | E35: BA | F35: 01.UG | G35: Sub Structure | H35: Septic tank | I35: Lean Concrete | J35: Lean Concrete, 15Mpa (Cylinder) | P35: m3 | Q35: =R35 -> 3.5 | R35: =R34*0.05 -> 3.5 | T35: =IFERROR(INDEX('Price List'!$G$5:$G$74,MATCH(TRIM(J35)&"|"&TRIM(P35),'Price List'!$O$5:$O$74,0)),0) -> 7 | U35: =IFERROR(INDEX('Price List'!$H$5:$H$74,MATCH(TRIM(J35)&"|"&TRIM(P35),'Price List'!$O$5:$O$74,0)),0) -> 0.2 | V35: =T35*(1+U35) -> 8.4 | W35: =IFERROR(INDEX('Price List'!$J$5:$J$74,MATCH(TRIM(J35)&"|"&TRIM(P35),'Price List'!$O$5:$O$74,0)),0) -> 75 | X35: =IFERROR(INDEX('Price List'!$K$5:$K$74,MATCH(TRIM(J35)&"|"&TRIM(P35),'Price List'!$O$5:$O$74,0)),0) -> 0.12 | Y35: =W35*(1+X35) -> 84 | Z35: =Q35*(V35+Y35) -> 323.4
C36: Civil and Structure | D36: =IFERROR(IF(TRIM($G36)="Sub Structure",IF(TRIM($H36)="Bored Pile","B.01","B.03"),IF(TRIM($G36)="Super Structure","B.04",IF(OR(TRIM($G36)="Exterior Wall and Partition",TRIM($G36)="External Wall and Partition"),"C.01",IF(TRIM($G36)="Exterior Wall Finishes","C.02",IF(TRIM($G36)="Interior Wall and Partition","C.09",IF(TRIM($G36)="Interior Door","C.10",IF(TRIM($G36)="External Windows and Louvers","C.04",IF(OR(TRIM($G36)="Interior Floor Finishes",TRIM($G36)="Internal Floor Finishes"),"D.02",IF(OR(TRIM($G36)="Interior Wall Finishes",TRIM($G36)="Internal Wall Finishes"),"D.01",IF(OR(TRIM($G36)="Ceiling Finshes",TRIM($G36)="Ceiling Finishes"),"D.03",IF(TRIM($G36)="Fittings, furnishings and equipment","E.04","")))))))))))," ") -> B.03 | E36: BA | F36: 01.UG | G36: Sub Structure | H36: Septic tank | I36: Crush Stone | J36: Crush Stone 40x60mm 150mm Thk. | P36: m3 | Q36: =R36 -> 10.5 | R36: =R34*0.15 -> 10.5 | T36: =IFERROR(INDEX('Price List'!$G$5:$G$74,MATCH(TRIM(J36)&"|"&TRIM(P36),'Price List'!$O$5:$O$74,0)),0) -> 3 | U36: =IFERROR(INDEX('Price List'!$H$5:$H$74,MATCH(TRIM(J36)&"|"&TRIM(P36),'Price List'!$O$5:$O$74,0)),0) -> 0.2 | V36: =T36*(1+U36) -> 3.6 | W36: =IFERROR(INDEX('Price List'!$J$5:$J$74,MATCH(TRIM(J36)&"|"&TRIM(P36),'Price List'!$O$5:$O$74,0)),0) -> 18 | X36: =IFERROR(INDEX('Price List'!$K$5:$K$74,MATCH(TRIM(J36)&"|"&TRIM(P36),'Price List'!$O$5:$O$74,0)),0) -> 0.12 | Y36: =W36*(1+X36) -> 20.16 | Z36: =Q36*(V36+Y36) -> 249.48
C37: Civil and Structure | D37: =IFERROR(IF(TRIM($G37)="Sub Structure",IF(TRIM($H37)="Bored Pile","B.01","B.03"),IF(TRIM($G37)="Super Structure","B.04",IF(OR(TRIM($G37)="Exterior Wall and Partition",TRIM($G37)="External Wall and Partition"),"C.01",IF(TRIM($G37)="Exterior Wall Finishes","C.02",IF(TRIM($G37)="Interior Wall and Partition","C.09",IF(TRIM($G37)="Interior Door","C.10",IF(TRIM($G37)="External Windows and Louvers","C.04",IF(OR(TRIM($G37)="Interior Floor Finishes",TRIM($G37)="Internal Floor Finishes"),"D.02",IF(OR(TRIM($G37)="Interior Wall Finishes",TRIM($G37)="Internal Wall Finishes"),"D.01",IF(OR(TRIM($G37)="Ceiling Finshes",TRIM($G37)="Ceiling Finishes"),"D.03",IF(TRIM($G37)="Fittings, furnishings and equipment","E.04","")))))))))))," ") -> B.03 | E37: BA | F37: 01.UG | G37: Sub Structure | H37: Septic tank | I37: Water Stop | J37: PVC Waterbar® V VN 20 (Width 200mm) | P37: m | Q37: 60 | R37: 18 | S37: 0 | T37: =IFERROR(INDEX('Price List'!$G$5:$G$74,MATCH(TRIM(J37)&"|"&TRIM(P37),'Price List'!$O$5:$O$74,0)),0) -> 1.5 | U37: =IFERROR(INDEX('Price List'!$H$5:$H$74,MATCH(TRIM(J37)&"|"&TRIM(P37),'Price List'!$O$5:$O$74,0)),0) -> 0.2 | V37: =T37*(1+U37) -> 1.8 | W37: =IFERROR(INDEX('Price List'!$J$5:$J$74,MATCH(TRIM(J37)&"|"&TRIM(P37),'Price List'!$O$5:$O$74,0)),0) -> 4 | X37: =IFERROR(INDEX('Price List'!$K$5:$K$74,MATCH(TRIM(J37)&"|"&TRIM(P37),'Price List'!$O$5:$O$74,0)),0) -> 0.12 | Y37: =W37*(1+X37) -> 4.48 | Z37: =Q37*(V37+Y37) -> 376.8
C38: Civil and Structure | D38: =IFERROR(IF(TRIM($G38)="Sub Structure",IF(TRIM($H38)="Bored Pile","B.01","B.03"),IF(TRIM($G38)="Super Structure","B.04",IF(OR(TRIM($G38)="Exterior Wall and Partition",TRIM($G38)="External Wall and Partition"),"C.01",IF(TRIM($G38)="Exterior Wall Finishes","C.02",IF(TRIM($G38)="Interior Wall and Partition","C.09",IF(TRIM($G38)="Interior Door","C.10",IF(TRIM($G38)="External Windows and Louvers","C.04",IF(OR(TRIM($G38)="Interior Floor Finishes",TRIM($G38)="Internal Floor Finishes"),"D.02",IF(OR(TRIM($G38)="Interior Wall Finishes",TRIM($G38)="Internal Wall Finishes"),"D.01",IF(OR(TRIM($G38)="Ceiling Finshes",TRIM($G38)="Ceiling Finishes"),"D.03",IF(TRIM($G38)="Fittings, furnishings and equipment","E.04","")))))))))))," ") -> B.03 | E38: BA | F38: 01.UG | G38: Sub Structure | H38: Septic tank | I38: Rebar | J38: Deform Bar, DB12(fy=390 Mpa) | P38: kg | Q38: =R38 -> 10560 | R38: =R32*160 -> 10560 | T38: =IFERROR(INDEX('Price List'!$G$5:$G$74,MATCH(TRIM(J38)&"|"&TRIM(P38),'Price List'!$O$5:$O$74,0)),0) -> 0.11 | U38: =IFERROR(INDEX('Price List'!$H$5:$H$74,MATCH(TRIM(J38)&"|"&TRIM(P38),'Price List'!$O$5:$O$74,0)),0) -> 0.2 | V38: =T38*(1+U38) -> 0.132 | W38: =IFERROR(INDEX('Price List'!$J$5:$J$74,MATCH(TRIM(J38)&"|"&TRIM(P38),'Price List'!$O$5:$O$74,0)),0) -> 0.76 | X38: =IFERROR(INDEX('Price List'!$K$5:$K$74,MATCH(TRIM(J38)&"|"&TRIM(P38),'Price List'!$O$5:$O$74,0)),0) -> 0.12 | Y38: =W38*(1+X38) -> 0.8512 | Z38: =Q38*(V38+Y38) -> 10382.592
C39: Civil and Structure | D39: =IFERROR(IF(TRIM($G39)="Sub Structure",IF(TRIM($H39)="Bored Pile","B.01","B.03"),IF(TRIM($G39)="Super Structure","B.04",IF(OR(TRIM($G39)="Exterior Wall and Partition",TRIM($G39)="External Wall and Partition"),"C.01",IF(TRIM($G39)="Exterior Wall Finishes","C.02",IF(TRIM($G39)="Interior Wall and Partition","C.09",IF(TRIM($G39)="Interior Door","C.10",IF(TRIM($G39)="External Windows and Louvers","C.04",IF(OR(TRIM($G39)="Interior Floor Finishes",TRIM($G39)="Internal Floor Finishes"),"D.02",IF(OR(TRIM($G39)="Interior Wall Finishes",TRIM($G39)="Internal Wall Finishes"),"D.01",IF(OR(TRIM($G39)="Ceiling Finshes",TRIM($G39)="Ceiling Finishes"),"D.03",IF(TRIM($G39)="Fittings, furnishings and equipment","E.04","")))))))))))," ") -> B.03 | E39: BA | F39: 01.UG | G39: Sub Structure | H39: Septic tank | I39: Steel Tie Wire | J39: Steel Tie Wire 1mm (Estimated 4% of Total Rebar Weight) | P39: kg | Q39: =R39 -> 422.4 | R39: =(R38)*4% -> 422.4 | T39: =IFERROR(INDEX('Price List'!$G$5:$G$74,MATCH(TRIM(J39)&"|"&TRIM(P39),'Price List'!$O$5:$O$74,0)),0) -> 0.05 | U39: =IFERROR(INDEX('Price List'!$H$5:$H$74,MATCH(TRIM(J39)&"|"&TRIM(P39),'Price List'!$O$5:$O$74,0)),0) -> 0.2 | V39: =T39*(1+U39) -> 0.06 | W39: =IFERROR(INDEX('Price List'!$J$5:$J$74,MATCH(TRIM(J39)&"|"&TRIM(P39),'Price List'!$O$5:$O$74,0)),0) -> 1.2 | X39: =IFERROR(INDEX('Price List'!$K$5:$K$74,MATCH(TRIM(J39)&"|"&TRIM(P39),'Price List'!$O$5:$O$74,0)),0) -> 0.12 | Y39: =W39*(1+X39) -> 1.344 | Z39: =Q39*(V39+Y39) -> 593.0496
C40: Civil and Structure | D40: =IFERROR(IF(TRIM($G40)="Sub Structure",IF(TRIM($H40)="Bored Pile","B.01","B.03"),IF(TRIM($G40)="Super Structure","B.04",IF(OR(TRIM($G40)="Exterior Wall and Partition",TRIM($G40)="External Wall and Partition"),"C.01",IF(TRIM($G40)="Exterior Wall Finishes","C.02",IF(TRIM($G40)="Interior Wall and Partition","C.09",IF(TRIM($G40)="Interior Door","C.10",IF(TRIM($G40)="External Windows and Louvers","C.04",IF(OR(TRIM($G40)="Interior Floor Finishes",TRIM($G40)="Internal Floor Finishes"),"D.02",IF(OR(TRIM($G40)="Interior Wall Finishes",TRIM($G40)="Internal Wall Finishes"),"D.01",IF(OR(TRIM($G40)="Ceiling Finshes",TRIM($G40)="Ceiling Finishes"),"D.03",IF(TRIM($G40)="Fittings, furnishings and equipment","E.04","")))))))))))," ") -> B.04 | E40: BA | F40: 02.GF | G40: Super Structure | H40: Structural Beam | I40: Concrete | J40: Normal Concrete, 35Mpa (Cylinder), Slump 13+-2.5 | P40: m3 | Q40: =R40 -> 38.42 | R40: 38.42 | T40: =IFERROR(INDEX('Price List'!$G$5:$G$74,MATCH(TRIM(J40)&"|"&TRIM(P40),'Price List'!$O$5:$O$74,0)),0) -> 10 | U40: =IFERROR(INDEX('Price List'!$H$5:$H$74,MATCH(TRIM(J40)&"|"&TRIM(P40),'Price List'!$O$5:$O$74,0)),0) -> 0.2 | V40: =T40*(1+U40) -> 12 | W40: =IFERROR(INDEX('Price List'!$J$5:$J$74,MATCH(TRIM(J40)&"|"&TRIM(P40),'Price List'!$O$5:$O$74,0)),0) -> 98 | X40: =IFERROR(INDEX('Price List'!$K$5:$K$74,MATCH(TRIM(J40)&"|"&TRIM(P40),'Price List'!$O$5:$O$74,0)),0) -> 0.12 | Y40: =W40*(1+X40) -> 109.76 | Z40: =Q40*(V40+Y40) -> 4678.0192
C41: Civil and Structure | D41: =IFERROR(IF(TRIM($G41)="Sub Structure",IF(TRIM($H41)="Bored Pile","B.01","B.03"),IF(TRIM($G41)="Super Structure","B.04",IF(OR(TRIM($G41)="Exterior Wall and Partition",TRIM($G41)="External Wall and Partition"),"C.01",IF(TRIM($G41)="Exterior Wall Finishes","C.02",IF(TRIM($G41)="Interior Wall and Partition","C.09",IF(TRIM($G41)="Interior Door","C.10",IF(TRIM($G41)="External Windows and Louvers","C.04",IF(OR(TRIM($G41)="Interior Floor Finishes",TRIM($G41)="Internal Floor Finishes"),"D.02",IF(OR(TRIM($G41)="Interior Wall Finishes",TRIM($G41)="Internal Wall Finishes"),"D.01",IF(OR(TRIM($G41)="Ceiling Finshes",TRIM($G41)="Ceiling Finishes"),"D.03",IF(TRIM($G41)="Fittings, furnishings and equipment","E.04","")))))))))))," ") -> B.04 | E41: BA | F41: 02.GF | G41: Super Structure | H41: Structural Beam | I41: Formwork | J41: Formwork | P41: m2 | Q41: =R41 -> 359.03 | R41: 359.03 | T41: =IFERROR(INDEX('Price List'!$G$5:$G$74,MATCH(TRIM(J41)&"|"&TRIM(P41),'Price List'!$O$5:$O$74,0)),0) -> 6 | U41: =IFERROR(INDEX('Price List'!$H$5:$H$74,MATCH(TRIM(J41)&"|"&TRIM(P41),'Price List'!$O$5:$O$74,0)),0) -> 0.2 | V41: =T41*(1+U41) -> 7.2 | W41: =IFERROR(INDEX('Price List'!$J$5:$J$74,MATCH(TRIM(J41)&"|"&TRIM(P41),'Price List'!$O$5:$O$74,0)),0) -> 5 | X41: =IFERROR(INDEX('Price List'!$K$5:$K$74,MATCH(TRIM(J41)&"|"&TRIM(P41),'Price List'!$O$5:$O$74,0)),0) -> 0.12 | Y41: =W41*(1+X41) -> 5.6 | Z41: =Q41*(V41+Y41) -> 4595.584
C42: Civil and Structure | D42: =IFERROR(IF(TRIM($G42)="Sub Structure",IF(TRIM($H42)="Bored Pile","B.01","B.03"),IF(TRIM($G42)="Super Structure","B.04",IF(OR(TRIM($G42)="Exterior Wall and Partition",TRIM($G42)="External Wall and Partition"),"C.01",IF(TRIM($G42)="Exterior Wall Finishes","C.02",IF(TRIM($G42)="Interior Wall and Partition","C.09",IF(TRIM($G42)="Interior Door","C.10",IF(TRIM($G42)="External Windows and Louvers","C.04",IF(OR(TRIM($G42)="Interior Floor Finishes",TRIM($G42)="Internal Floor Finishes"),"D.02",IF(OR(TRIM($G42)="Interior Wall Finishes",TRIM($G42)="Internal Wall Finishes"),"D.01",IF(OR(TRIM($G42)="Ceiling Finshes",TRIM($G42)="Ceiling Finishes"),"D.03",IF(TRIM($G42)="Fittings, furnishings and equipment","E.04","")))))))))))," ") -> B.04 | E42: BA | F42: 02.GF | G42: Super Structure | H42: Structural Beam | I42: Rebar | J42: Round Bar, RB8(fy=250 Mpa) | P42: kg | Q42: =R42 -> 487.00867 | R42: 487.00867 | T42: =IFERROR(INDEX('Price List'!$G$5:$G$74,MATCH(TRIM(J42)&"|"&TRIM(P42),'Price List'!$O$5:$O$74,0)),0) -> 0.12 | U42: =IFERROR(INDEX('Price List'!$H$5:$H$74,MATCH(TRIM(J42)&"|"&TRIM(P42),'Price List'!$O$5:$O$74,0)),0) -> 0.2 | V42: =T42*(1+U42) -> 0.144 | W42: =IFERROR(INDEX('Price List'!$J$5:$J$74,MATCH(TRIM(J42)&"|"&TRIM(P42),'Price List'!$O$5:$O$74,0)),0) -> 0.77 | X42: =IFERROR(INDEX('Price List'!$K$5:$K$74,MATCH(TRIM(J42)&"|"&TRIM(P42),'Price List'!$O$5:$O$74,0)),0) -> 0.12 | Y42: =W42*(1+X42) -> 0.8624 | Z42: =Q42*(V42+Y42) -> 490.12552
C43: Civil and Structure | D43: =IFERROR(IF(TRIM($G43)="Sub Structure",IF(TRIM($H43)="Bored Pile","B.01","B.03"),IF(TRIM($G43)="Super Structure","B.04",IF(OR(TRIM($G43)="Exterior Wall and Partition",TRIM($G43)="External Wall and Partition"),"C.01",IF(TRIM($G43)="Exterior Wall Finishes","C.02",IF(TRIM($G43)="Interior Wall and Partition","C.09",IF(TRIM($G43)="Interior Door","C.10",IF(TRIM($G43)="External Windows and Louvers","C.04",IF(OR(TRIM($G43)="Interior Floor Finishes",TRIM($G43)="Internal Floor Finishes"),"D.02",IF(OR(TRIM($G43)="Interior Wall Finishes",TRIM($G43)="Internal Wall Finishes"),"D.01",IF(OR(TRIM($G43)="Ceiling Finshes",TRIM($G43)="Ceiling Finishes"),"D.03",IF(TRIM($G43)="Fittings, furnishings and equipment","E.04","")))))))))))," ") -> B.04 | E43: BA | F43: 02.GF | G43: Super Structure | H43: Structural Beam | I43: Rebar | J43: Deform Bar, DB10(fy=390 Mpa) | P43: kg | Q43: =R43 -> 1072.3333 | R43: 1072.3333 | T43: =IFERROR(INDEX('Price List'!$G$5:$G$74,MATCH(TRIM(J43)&"|"&TRIM(P43),'Price List'!$O$5:$O$74,0)),0) -> 0.12 | U43: =IFERROR(INDEX('Price List'!$H$5:$H$74,MATCH(TRIM(J43)&"|"&TRIM(P43),'Price List'!$O$5:$O$74,0)),0) -> 0.2 | V43: =T43*(1+U43) -> 0.144 | W43: =IFERROR(INDEX('Price List'!$J$5:$J$74,MATCH(TRIM(J43)&"|"&TRIM(P43),'Price List'!$O$5:$O$74,0)),0) -> 0.78 | X43: =IFERROR(INDEX('Price List'!$K$5:$K$74,MATCH(TRIM(J43)&"|"&TRIM(P43),'Price List'!$O$5:$O$74,0)),0) -> 0.12 | Y43: =W43*(1+X43) -> 0.8736 | Z43: =Q43*(V43+Y43) -> 1091.2064
C44: Civil and Structure | D44: =IFERROR(IF(TRIM($G44)="Sub Structure",IF(TRIM($H44)="Bored Pile","B.01","B.03"),IF(TRIM($G44)="Super Structure","B.04",IF(OR(TRIM($G44)="Exterior Wall and Partition",TRIM($G44)="External Wall and Partition"),"C.01",IF(TRIM($G44)="Exterior Wall Finishes","C.02",IF(TRIM($G44)="Interior Wall and Partition","C.09",IF(TRIM($G44)="Interior Door","C.10",IF(TRIM($G44)="External Windows and Louvers","C.04",IF(OR(TRIM($G44)="Interior Floor Finishes",TRIM($G44)="Internal Floor Finishes"),"D.02",IF(OR(TRIM($G44)="Interior Wall Finishes",TRIM($G44)="Internal Wall Finishes"),"D.01",IF(OR(TRIM($G44)="Ceiling Finshes",TRIM($G44)="Ceiling Finishes"),"D.03",IF(TRIM($G44)="Fittings, furnishings and equipment","E.04","")))))))))))," ") -> B.04 | E44: BA | F44: 02.GF | G44: Super Structure | H44: Structural Beam | I44: Rebar | J44: Deform Bar, DB12(fy=390 Mpa) | P44: kg | Q44: =R44 -> 174.3144 | R44: 174.3144 | T44: =IFERROR(INDEX('Price List'!$G$5:$G$74,MATCH(TRIM(J44)&"|"&TRIM(P44),'Price List'!$O$5:$O$74,0)),0) -> 0.11 | U44: =IFERROR(INDEX('Price List'!$H$5:$H$74,MATCH(TRIM(J44)&"|"&TRIM(P44),'Price List'!$O$5:$O$74,0)),0) -> 0.2 | V44: =T44*(1+U44) -> 0.132 | W44: =IFERROR(INDEX('Price List'!$J$5:$J$74,MATCH(TRIM(J44)&"|"&TRIM(P44),'Price List'!$O$5:$O$74,0)),0) -> 0.76 | X44: =IFERROR(INDEX('Price List'!$K$5:$K$74,MATCH(TRIM(J44)&"|"&TRIM(P44),'Price List'!$O$5:$O$74,0)),0) -> 0.12 | Y44: =W44*(1+X44) -> 0.8512 | Z44: =Q44*(V44+Y44) -> 171.38592
C45: Civil and Structure | D45: =IFERROR(IF(TRIM($G45)="Sub Structure",IF(TRIM($H45)="Bored Pile","B.01","B.03"),IF(TRIM($G45)="Super Structure","B.04",IF(OR(TRIM($G45)="Exterior Wall and Partition",TRIM($G45)="External Wall and Partition"),"C.01",IF(TRIM($G45)="Exterior Wall Finishes","C.02",IF(TRIM($G45)="Interior Wall and Partition","C.09",IF(TRIM($G45)="Interior Door","C.10",IF(TRIM($G45)="External Windows and Louvers","C.04",IF(OR(TRIM($G45)="Interior Floor Finishes",TRIM($G45)="Internal Floor Finishes"),"D.02",IF(OR(TRIM($G45)="Interior Wall Finishes",TRIM($G45)="Internal Wall Finishes"),"D.01",IF(OR(TRIM($G45)="Ceiling Finshes",TRIM($G45)="Ceiling Finishes"),"D.03",IF(TRIM($G45)="Fittings, furnishings and equipment","E.04","")))))))))))," ") -> B.04 | E45: BA | F45: 02.GF | G45: Super Structure | H45: Structural Beam | I45: Rebar | J45: Deform Bar, DB16(fy=390 Mpa) | P45: kg | Q45: =R45 -> 1016.8632 | R45: 1016.8632 | T45: =IFERROR(INDEX('Price List'!$G$5:$G$74,MATCH(TRIM(J45)&"|"&TRIM(P45),'Price List'!$O$5:$O$74,0)),0) -> 0.1 | U45: =IFERROR(INDEX('Price List'!$H$5:$H$74,MATCH(TRIM(J45)&"|"&TRIM(P45),'Price List'!$O$5:$O$74,0)),0) -> 0.2 | V45: =T45*(1+U45) -> 0.12 | W45: =IFERROR(INDEX('Price List'!$J$5:$J$74,MATCH(TRIM(J45)&"|"&TRIM(P45),'Price List'!$O$5:$O$74,0)),0) -> 0.74 | X45: =IFERROR(INDEX('Price List'!$K$5:$K$74,MATCH(TRIM(J45)&"|"&TRIM(P45),'Price List'!$O$5:$O$74,0)),0) -> 0.12 | Y45: =W45*(1+X45) -> 0.8288 | Z45: =Q45*(V45+Y45) -> 964.7998
C46: Civil and Structure | D46: =IFERROR(IF(TRIM($G46)="Sub Structure",IF(TRIM($H46)="Bored Pile","B.01","B.03"),IF(TRIM($G46)="Super Structure","B.04",IF(OR(TRIM($G46)="Exterior Wall and Partition",TRIM($G46)="External Wall and Partition"),"C.01",IF(TRIM($G46)="Exterior Wall Finishes","C.02",IF(TRIM($G46)="Interior Wall and Partition","C.09",IF(TRIM($G46)="Interior Door","C.10",IF(TRIM($G46)="External Windows and Louvers","C.04",IF(OR(TRIM($G46)="Interior Floor Finishes",TRIM($G46)="Internal Floor Finishes"),"D.02",IF(OR(TRIM($G46)="Interior Wall Finishes",TRIM($G46)="Internal Wall Finishes"),"D.01",IF(OR(TRIM($G46)="Ceiling Finshes",TRIM($G46)="Ceiling Finishes"),"D.03",IF(TRIM($G46)="Fittings, furnishings and equipment","E.04","")))))))))))," ") -> B.04 | E46: BA | F46: 02.GF | G46: Super Structure | H46: Structural Beam | I46: Rebar | J46: Deform Bar, DB20(fy=390 Mpa) | P46: kg | Q46: =R46 -> 5312.997 | R46: 5312.997 | T46: =IFERROR(INDEX('Price List'!$G$5:$G$74,MATCH(TRIM(J46)&"|"&TRIM(P46),'Price List'!$O$5:$O$74,0)),0) -> 0.09 | U46: =IFERROR(INDEX('Price List'!$H$5:$H$74,MATCH(TRIM(J46)&"|"&TRIM(P46),'Price List'!$O$5:$O$74,0)),0) -> 0.2 | V46: =T46*(1+U46) -> 0.108 | W46: =IFERROR(INDEX('Price List'!$J$5:$J$74,MATCH(TRIM(J46)&"|"&TRIM(P46),'Price List'!$O$5:$O$74,0)),0) -> 0.73 | X46: =IFERROR(INDEX('Price List'!$K$5:$K$74,MATCH(TRIM(J46)&"|"&TRIM(P46),'Price List'!$O$5:$O$74,0)),0) -> 0.12 | Y46: =W46*(1+X46) -> 0.8176 | Z46: =Q46*(V46+Y46) -> 4917.71
C47: Civil and Structure | D47: =IFERROR(IF(TRIM($G47)="Sub Structure",IF(TRIM($H47)="Bored Pile","B.01","B.03"),IF(TRIM($G47)="Super Structure","B.04",IF(OR(TRIM($G47)="Exterior Wall and Partition",TRIM($G47)="External Wall and Partition"),"C.01",IF(TRIM($G47)="Exterior Wall Finishes","C.02",IF(TRIM($G47)="Interior Wall and Partition","C.09",IF(TRIM($G47)="Interior Door","C.10",IF(TRIM($G47)="External Windows and Louvers","C.04",IF(OR(TRIM($G47)="Interior Floor Finishes",TRIM($G47)="Internal Floor Finishes"),"D.02",IF(OR(TRIM($G47)="Interior Wall Finishes",TRIM($G47)="Internal Wall Finishes"),"D.01",IF(OR(TRIM($G47)="Ceiling Finshes",TRIM($G47)="Ceiling Finishes"),"D.03",IF(TRIM($G47)="Fittings, furnishings and equipment","E.04","")))))))))))," ") -> B.04 | E47: BA | F47: 02.GF | G47: Super Structure | H47: Structural Beam | I47: Steel Tie Wire | J47: Steel Tie Wire 1mm (Estimated 4% of Total Rebar Weight) | P47: kg | Q47: =R47 -> 322.54066 | R47: =(R42+R44+R46+R45+R43)*4% -> 322.54066 | T47: =IFERROR(INDEX('Price List'!$G$5:$G$74,MATCH(TRIM(J47)&"|"&TRIM(P47),'Price List'!$O$5:$O$74,0)),0) -> 0.05 | U47: =IFERROR(INDEX('Price List'!$H$5:$H$74,MATCH(TRIM(J47)&"|"&TRIM(P47),'Price List'!$O$5:$O$74,0)),0) -> 0.2 | V47: =T47*(1+U47) -> 0.06 | W47: =IFERROR(INDEX('Price List'!$J$5:$J$74,MATCH(TRIM(J47)&"|"&TRIM(P47),'Price List'!$O$5:$O$74,0)),0) -> 1.2 | X47: =IFERROR(INDEX('Price List'!$K$5:$K$74,MATCH(TRIM(J47)&"|"&TRIM(P47),'Price List'!$O$5:$O$74,0)),0) -> 0.12 | Y47: =W47*(1+X47) -> 1.344 | Z47: =Q47*(V47+Y47) -> 452.84709
C48: Civil and Structure | D48: =IFERROR(IF(TRIM($G48)="Sub Structure",IF(TRIM($H48)="Bored Pile","B.01","B.03"),IF(TRIM($G48)="Super Structure","B.04",IF(OR(TRIM($G48)="Exterior Wall and Partition",TRIM($G48)="External Wall and Partition"),"C.01",IF(TRIM($G48)="Exterior Wall Finishes","C.02",IF(TRIM($G48)="Interior Wall and Partition","C.09",IF(TRIM($G48)="Interior Door","C.10",IF(TRIM($G48)="External Windows and Louvers","C.04",IF(OR(TRIM($G48)="Interior Floor Finishes",TRIM($G48)="Internal Floor Finishes"),"D.02",IF(OR(TRIM($G48)="Interior Wall Finishes",TRIM($G48)="Internal Wall Finishes"),"D.01",IF(OR(TRIM($G48)="Ceiling Finshes",TRIM($G48)="Ceiling Finishes"),"D.03",IF(TRIM($G48)="Fittings, furnishings and equipment","E.04","")))))))))))," ") -> B.04 | E48: BA | F48: 02.GF | G48: Super Structure | H48: Structural Beam | I48: Lean Concrete | J48: Lean Concrete, 15Mpa (Cylinder) | P48: m3 | Q48: =R48 -> 7.3 | R48: 7.3 | T48: =IFERROR(INDEX('Price List'!$G$5:$G$74,MATCH(TRIM(J48)&"|"&TRIM(P48),'Price List'!$O$5:$O$74,0)),0) -> 7 | U48: =IFERROR(INDEX('Price List'!$H$5:$H$74,MATCH(TRIM(J48)&"|"&TRIM(P48),'Price List'!$O$5:$O$74,0)),0) -> 0.2 | V48: =T48*(1+U48) -> 8.4 | W48: =IFERROR(INDEX('Price List'!$J$5:$J$74,MATCH(TRIM(J48)&"|"&TRIM(P48),'Price List'!$O$5:$O$74,0)),0) -> 75 | X48: =IFERROR(INDEX('Price List'!$K$5:$K$74,MATCH(TRIM(J48)&"|"&TRIM(P48),'Price List'!$O$5:$O$74,0)),0) -> 0.12 | Y48: =W48*(1+X48) -> 84 | Z48: =Q48*(V48+Y48) -> 674.52
C49: Civil and Structure | D49: =IFERROR(IF(TRIM($G49)="Sub Structure",IF(TRIM($H49)="Bored Pile","B.01","B.03"),IF(TRIM($G49)="Super Structure","B.04",IF(OR(TRIM($G49)="Exterior Wall and Partition",TRIM($G49)="External Wall and Partition"),"C.01",IF(TRIM($G49)="Exterior Wall Finishes","C.02",IF(TRIM($G49)="Interior Wall and Partition","C.09",IF(TRIM($G49)="Interior Door","C.10",IF(TRIM($G49)="External Windows and Louvers","C.04",IF(OR(TRIM($G49)="Interior Floor Finishes",TRIM($G49)="Internal Floor Finishes"),"D.02",IF(OR(TRIM($G49)="Interior Wall Finishes",TRIM($G49)="Internal Wall Finishes"),"D.01",IF(OR(TRIM($G49)="Ceiling Finshes",TRIM($G49)="Ceiling Finishes"),"D.03",IF(TRIM($G49)="Fittings, furnishings and equipment","E.04","")))))))))))," ") -> B.04 | E49: BA | F49: 02.GF | G49: Super Structure | H49: Structural Beam | I49: Crush Stone | J49: Crush Stone 40x60mm 100mm Thk. | P49: m3 | Q49: =R49 -> 14.56 | R49: 14.56 | T49: =IFERROR(INDEX('Price List'!$G$5:$G$74,MATCH(TRIM(J49)&"|"&TRIM(P49),'Price List'!$O$5:$O$74,0)),0) -> 3 | U49: =IFERROR(INDEX('Price List'!$H$5:$H$74,MATCH(TRIM(J49)&"|"&TRIM(P49),'Price List'!$O$5:$O$74,0)),0) -> 0.2 | V49: =T49*(1+U49) -> 3.6 | W49: =IFERROR(INDEX('Price List'!$J$5:$J$74,MATCH(TRIM(J49)&"|"&TRIM(P49),'Price List'!$O$5:$O$74,0)),0) -> 18 | X49: =IFERROR(INDEX('Price List'!$K$5:$K$74,MATCH(TRIM(J49)&"|"&TRIM(P49),'Price List'!$O$5:$O$74,0)),0) -> 0.12 | Y49: =W49*(1+X49) -> 20.16 | Z49: =Q49*(V49+Y49) -> 345.9456
C50: Civil and Structure | D50: =IFERROR(IF(TRIM($G50)="Sub Structure",IF(TRIM($H50)="Bored Pile","B.01","B.03"),IF(TRIM($G50)="Super Structure","B.04",IF(OR(TRIM($G50)="Exterior Wall and Partition",TRIM($G50)="External Wall and Partition"),"C.01",IF(TRIM($G50)="Exterior Wall Finishes","C.02",IF(TRIM($G50)="Interior Wall and Partition","C.09",IF(TRIM($G50)="Interior Door","C.10",IF(TRIM($G50)="External Windows and Louvers","C.04",IF(OR(TRIM($G50)="Interior Floor Finishes",TRIM($G50)="Internal Floor Finishes"),"D.02",IF(OR(TRIM($G50)="Interior Wall Finishes",TRIM($G50)="Internal Wall Finishes"),"D.01",IF(OR(TRIM($G50)="Ceiling Finshes",TRIM($G50)="Ceiling Finishes"),"D.03",IF(TRIM($G50)="Fittings, furnishings and equipment","E.04","")))))))))))," ") -> B.04 | E50: BA | F50: 02.GF | G50: Super Structure | H50: Structural Beam | I50: Anti-Termite | J50: Anti-Termite with Plastic Membrane | P50: m2 | Q50: =R50 -> 145.57 | R50: 145.57 | T50: =IFERROR(INDEX('Price List'!$G$5:$G$74,MATCH(TRIM(J50)&"|"&TRIM(P50),'Price List'!$O$5:$O$74,0)),0) -> 1 | U50: =IFERROR(INDEX('Price List'!$H$5:$H$74,MATCH(TRIM(J50)&"|"&TRIM(P50),'Price List'!$O$5:$O$74,0)),0) -> 0.2 | V50: =T50*(1+U50) -> 1.2 | W50: =IFERROR(INDEX('Price List'!$J$5:$J$74,MATCH(TRIM(J50)&"|"&TRIM(P50),'Price List'!$O$5:$O$74,0)),0) -> 2.5 | X50: =IFERROR(INDEX('Price List'!$K$5:$K$74,MATCH(TRIM(J50)&"|"&TRIM(P50),'Price List'!$O$5:$O$74,0)),0) -> 0.12 | Y50: =W50*(1+X50) -> 2.8 | Z50: =Q50*(V50+Y50) -> 582.28
C51: Civil and Structure | D51: =IFERROR(IF(TRIM($G51)="Sub Structure",IF(TRIM($H51)="Bored Pile","B.01","B.03"),IF(TRIM($G51)="Super Structure","B.04",IF(OR(TRIM($G51)="Exterior Wall and Partition",TRIM($G51)="External Wall and Partition"),"C.01",IF(TRIM($G51)="Exterior Wall Finishes","C.02",IF(TRIM($G51)="Interior Wall and Partition","C.09",IF(TRIM($G51)="Interior Door","C.10",IF(TRIM($G51)="External Windows and Louvers","C.04",IF(OR(TRIM($G51)="Interior Floor Finishes",TRIM($G51)="Internal Floor Finishes"),"D.02",IF(OR(TRIM($G51)="Interior Wall Finishes",TRIM($G51)="Internal Wall Finishes"),"D.01",IF(OR(TRIM($G51)="Ceiling Finshes",TRIM($G51)="Ceiling Finishes"),"D.03",IF(TRIM($G51)="Fittings, furnishings and equipment","E.04","")))))))))))," ") -> B.04 | E51: BA | F51: 02.GF | G51: Super Structure | H51: Structural Slab | I51: Concrete | J51: Normal Concrete, 35Mpa (Cylinder), Slump 13+-2.5 | P51: m3 | Q51: =R51 -> 103.737 | R51: =(0.15*110.94)+(0.2*435.48) -> 103.737 | T51: =IFERROR(INDEX('Price List'!$G$5:$G$74,MATCH(TRIM(J51)&"|"&TRIM(P51),'Price List'!$O$5:$O$74,0)),0) -> 10 | U51: =IFERROR(INDEX('Price List'!$H$5:$H$74,MATCH(TRIM(J51)&"|"&TRIM(P51),'Price List'!$O$5:$O$74,0)),0) -> 0.2 | V51: =T51*(1+U51) -> 12 | W51: =IFERROR(INDEX('Price List'!$J$5:$J$74,MATCH(TRIM(J51)&"|"&TRIM(P51),'Price List'!$O$5:$O$74,0)),0) -> 98 | X51: =IFERROR(INDEX('Price List'!$K$5:$K$74,MATCH(TRIM(J51)&"|"&TRIM(P51),'Price List'!$O$5:$O$74,0)),0) -> 0.12 | Y51: =W51*(1+X51) -> 109.76 | Z51: =Q51*(V51+Y51) -> 12631.017
C52: Civil and Structure | D52: =IFERROR(IF(TRIM($G52)="Sub Structure",IF(TRIM($H52)="Bored Pile","B.01","B.03"),IF(TRIM($G52)="Super Structure","B.04",IF(OR(TRIM($G52)="Exterior Wall and Partition",TRIM($G52)="External Wall and Partition"),"C.01",IF(TRIM($G52)="Exterior Wall Finishes","C.02",IF(TRIM($G52)="Interior Wall and Partition","C.09",IF(TRIM($G52)="Interior Door","C.10",IF(TRIM($G52)="External Windows and Louvers","C.04",IF(OR(TRIM($G52)="Interior Floor Finishes",TRIM($G52)="Internal Floor Finishes"),"D.02",IF(OR(TRIM($G52)="Interior Wall Finishes",TRIM($G52)="Internal Wall Finishes"),"D.01",IF(OR(TRIM($G52)="Ceiling Finshes",TRIM($G52)="Ceiling Finishes"),"D.03",IF(TRIM($G52)="Fittings, furnishings and equipment","E.04","")))))))))))," ") -> B.04 | E52: BA | F52: 02.GF | G52: Super Structure | H52: Structural Slab | I52: Formwork | J52: Formwork | P52: m2 | Q52: =R52 -> 19.2 | R52: =96*0.2 -> 19.2 | T52: =IFERROR(INDEX('Price List'!$G$5:$G$74,MATCH(TRIM(J52)&"|"&TRIM(P52),'Price List'!$O$5:$O$74,0)),0) -> 6 | U52: =IFERROR(INDEX('Price List'!$H$5:$H$74,MATCH(TRIM(J52)&"|"&TRIM(P52),'Price List'!$O$5:$O$74,0)),0) -> 0.2 | V52: =T52*(1+U52) -> 7.2 | W52: =IFERROR(INDEX('Price List'!$J$5:$J$74,MATCH(TRIM(J52)&"|"&TRIM(P52),'Price List'!$O$5:$O$74,0)),0) -> 5 | X52: =IFERROR(INDEX('Price List'!$K$5:$K$74,MATCH(TRIM(J52)&"|"&TRIM(P52),'Price List'!$O$5:$O$74,0)),0) -> 0.12 | Y52: =W52*(1+X52) -> 5.6 | Z52: =Q52*(V52+Y52) -> 245.76
C53: Civil and Structure | D53: =IFERROR(IF(TRIM($G53)="Sub Structure",IF(TRIM($H53)="Bored Pile","B.01","B.03"),IF(TRIM($G53)="Super Structure","B.04",IF(OR(TRIM($G53)="Exterior Wall and Partition",TRIM($G53)="External Wall and Partition"),"C.01",IF(TRIM($G53)="Exterior Wall Finishes","C.02",IF(TRIM($G53)="Interior Wall and Partition","C.09",IF(TRIM($G53)="Interior Door","C.10",IF(TRIM($G53)="External Windows and Louvers","C.04",IF(OR(TRIM($G53)="Interior Floor Finishes",TRIM($G53)="Internal Floor Finishes"),"D.02",IF(OR(TRIM($G53)="Interior Wall Finishes",TRIM($G53)="Internal Wall Finishes"),"D.01",IF(OR(TRIM($G53)="Ceiling Finshes",TRIM($G53)="Ceiling Finishes"),"D.03",IF(TRIM($G53)="Fittings, furnishings and equipment","E.04","")))))))))))," ") -> B.04 | E53: BA | F53: 02.GF | G53: Super Structure | H53: Structural Slab | I53: Rebar | J53: Deform Bar, DB10(fy=390 Mpa) | P53: kg | Q53: =R53 -> 12843.426 | R53: =0.617*(((22.3+1)*171)*2)+(((25.6+1)*149)*2) -> 12843.426 | T53: =IFERROR(INDEX('Price List'!$G$5:$G$74,MATCH(TRIM(J53)&"|"&TRIM(P53),'Price List'!$O$5:$O$74,0)),0) -> 0.12 | U53: =IFERROR(INDEX('Price List'!$H$5:$H$74,MATCH(TRIM(J53)&"|"&TRIM(P53),'Price List'!$O$5:$O$74,0)),0) -> 0.2 | V53: =T53*(1+U53) -> 0.144 | W53: =IFERROR(INDEX('Price List'!$J$5:$J$74,MATCH(TRIM(J53)&"|"&TRIM(P53),'Price List'!$O$5:$O$74,0)),0) -> 0.78 | X53: =IFERROR(INDEX('Price List'!$K$5:$K$74,MATCH(TRIM(J53)&"|"&TRIM(P53),'Price List'!$O$5:$O$74,0)),0) -> 0.12 | Y53: =W53*(1+X53) -> 0.8736 | Z53: =Q53*(V53+Y53) -> 13069.471
C54: Civil and Structure | D54: =IFERROR(IF(TRIM($G54)="Sub Structure",IF(TRIM($H54)="Bored Pile","B.01","B.03"),IF(TRIM($G54)="Super Structure","B.04",IF(OR(TRIM($G54)="Exterior Wall and Partition",TRIM($G54)="External Wall and Partition"),"C.01",IF(TRIM($G54)="Exterior Wall Finishes","C.02",IF(TRIM($G54)="Interior Wall and Partition","C.09",IF(TRIM($G54)="Interior Door","C.10",IF(TRIM($G54)="External Windows and Louvers","C.04",IF(OR(TRIM($G54)="Interior Floor Finishes",TRIM($G54)="Internal Floor Finishes"),"D.02",IF(OR(TRIM($G54)="Interior Wall Finishes",TRIM($G54)="Internal Wall Finishes"),"D.01",IF(OR(TRIM($G54)="Ceiling Finshes",TRIM($G54)="Ceiling Finishes"),"D.03",IF(TRIM($G54)="Fittings, furnishings and equipment","E.04","")))))))))))," ") -> B.04 | E54: BA | F54: 02.GF | G54: Super Structure | H54: Structural Slab | I54: Rebar | J54: Deform Bar, DB12(fy=390 Mpa) | P54: kg | Q54: =R54 -> 372.96 | R54: =0.888*((2.5*31*3)+(2.5*10*3)+(2.5*15*3)) -> 372.96 | T54: =IFERROR(INDEX('Price List'!$G$5:$G$74,MATCH(TRIM(J54)&"|"&TRIM(P54),'Price List'!$O$5:$O$74,0)),0) -> 0.11 | U54: =IFERROR(INDEX('Price List'!$H$5:$H$74,MATCH(TRIM(J54)&"|"&TRIM(P54),'Price List'!$O$5:$O$74,0)),0) -> 0.2 | V54: =T54*(1+U54) -> 0.132 | W54: =IFERROR(INDEX('Price List'!$J$5:$J$74,MATCH(TRIM(J54)&"|"&TRIM(P54),'Price List'!$O$5:$O$74,0)),0) -> 0.76 | X54: =IFERROR(INDEX('Price List'!$K$5:$K$74,MATCH(TRIM(J54)&"|"&TRIM(P54),'Price List'!$O$5:$O$74,0)),0) -> 0.12 | Y54: =W54*(1+X54) -> 0.8512 | Z54: =Q54*(V54+Y54) -> 366.69427
C55: Civil and Structure | D55: =IFERROR(IF(TRIM($G55)="Sub Structure",IF(TRIM($H55)="Bored Pile","B.01","B.03"),IF(TRIM($G55)="Super Structure","B.04",IF(OR(TRIM($G55)="Exterior Wall and Partition",TRIM($G55)="External Wall and Partition"),"C.01",IF(TRIM($G55)="Exterior Wall Finishes","C.02",IF(TRIM($G55)="Interior Wall and Partition","C.09",IF(TRIM($G55)="Interior Door","C.10",IF(TRIM($G55)="External Windows and Louvers","C.04",IF(OR(TRIM($G55)="Interior Floor Finishes",TRIM($G55)="Internal Floor Finishes"),"D.02",IF(OR(TRIM($G55)="Interior Wall Finishes",TRIM($G55)="Internal Wall Finishes"),"D.01",IF(OR(TRIM($G55)="Ceiling Finshes",TRIM($G55)="Ceiling Finishes"),"D.03",IF(TRIM($G55)="Fittings, furnishings and equipment","E.04","")))))))))))," ") -> B.04 | E55: BA | F55: 02.GF | G55: Super Structure | H55: Structural Slab | I55: Steel Tie Wire | J55: Steel Tie Wire 1mm (Estimated 4% of Total Rebar Weight) | P55: kg | Q55: =R55 -> 528.65545 | R55: =(R53+R54)*4% -> 528.65545 | T55: =IFERROR(INDEX('Price List'!$G$5:$G$74,MATCH(TRIM(J55)&"|"&TRIM(P55),'Price List'!$O$5:$O$74,0)),0) -> 0.05 | U55: =IFERROR(INDEX('Price List'!$H$5:$H$74,MATCH(TRIM(J55)&"|"&TRIM(P55),'Price List'!$O$5:$O$74,0)),0) -> 0.2 | V55: =T55*(1+U55) -> 0.06 | W55: =IFERROR(INDEX('Price List'!$J$5:$J$74,MATCH(TRIM(J55)&"|"&TRIM(P55),'Price List'!$O$5:$O$74,0)),0) -> 1.2 | X55: =IFERROR(INDEX('Price List'!$K$5:$K$74,MATCH(TRIM(J55)&"|"&TRIM(P55),'Price List'!$O$5:$O$74,0)),0) -> 0.12 | Y55: =W55*(1+X55) -> 1.344 | Z55: =Q55*(V55+Y55) -> 742.23225
C56: Civil and Structure | D56: =IFERROR(IF(TRIM($G56)="Sub Structure",IF(TRIM($H56)="Bored Pile","B.01","B.03"),IF(TRIM($G56)="Super Structure","B.04",IF(OR(TRIM($G56)="Exterior Wall and Partition",TRIM($G56)="External Wall and Partition"),"C.01",IF(TRIM($G56)="Exterior Wall Finishes","C.02",IF(TRIM($G56)="Interior Wall and Partition","C.09",IF(TRIM($G56)="Interior Door","C.10",IF(TRIM($G56)="External Windows and Louvers","C.04",IF(OR(TRIM($G56)="Interior Floor Finishes",TRIM($G56)="Internal Floor Finishes"),"D.02",IF(OR(TRIM($G56)="Interior Wall Finishes",TRIM($G56)="Internal Wall Finishes"),"D.01",IF(OR(TRIM($G56)="Ceiling Finshes",TRIM($G56)="Ceiling Finishes"),"D.03",IF(TRIM($G56)="Fittings, furnishings and equipment","E.04","")))))))))))," ") -> B.04 | E56: BA | F56: 02.GF | G56: Super Structure | H56: Structural Slab | I56: Lean Concrete | J56: Lean Concrete, 15Mpa (Cylinder) | P56: m3 | Q56: =R56 -> 27.6 | R56: =552*0.05 -> 27.6 | T56: =IFERROR(INDEX('Price List'!$G$5:$G$74,MATCH(TRIM(J56)&"|"&TRIM(P56),'Price List'!$O$5:$O$74,0)),0) -> 7 | U56: =IFERROR(INDEX('Price List'!$H$5:$H$74,MATCH(TRIM(J56)&"|"&TRIM(P56),'Price List'!$O$5:$O$74,0)),0) -> 0.2 | V56: =T56*(1+U56) -> 8.4 | W56: =IFERROR(INDEX('Price List'!$J$5:$J$74,MATCH(TRIM(J56)&"|"&TRIM(P56),'Price List'!$O$5:$O$74,0)),0) -> 75 | X56: =IFERROR(INDEX('Price List'!$K$5:$K$74,MATCH(TRIM(J56)&"|"&TRIM(P56),'Price List'!$O$5:$O$74,0)),0) -> 0.12 | Y56: =W56*(1+X56) -> 84 | Z56: =Q56*(V56+Y56) -> 2550.24
C57: Civil and Structure | D57: =IFERROR(IF(TRIM($G57)="Sub Structure",IF(TRIM($H57)="Bored Pile","B.01","B.03"),IF(TRIM($G57)="Super Structure","B.04",IF(OR(TRIM($G57)="Exterior Wall and Partition",TRIM($G57)="External Wall and Partition"),"C.01",IF(TRIM($G57)="Exterior Wall Finishes","C.02",IF(TRIM($G57)="Interior Wall and Partition","C.09",IF(TRIM($G57)="Interior Door","C.10",IF(TRIM($G57)="External Windows and Louvers","C.04",IF(OR(TRIM($G57)="Interior Floor Finishes",TRIM($G57)="Internal Floor Finishes"),"D.02",IF(OR(TRIM($G57)="Interior Wall Finishes",TRIM($G57)="Internal Wall Finishes"),"D.01",IF(OR(TRIM($G57)="Ceiling Finshes",TRIM($G57)="Ceiling Finishes"),"D.03",IF(TRIM($G57)="Fittings, furnishings and equipment","E.04","")))))))))))," ") -> B.04 | E57: BA | F57: 02.GF | G57: Super Structure | H57: Structural Slab | I57: Crush Stone | J57: Crush Stone 40x60mm 100mm Thk. | P57: m3 | Q57: =R57 -> 55.2 | R57: =552*0.1 -> 55.2 | T57: =IFERROR(INDEX('Price List'!$G$5:$G$74,MATCH(TRIM(J57)&"|"&TRIM(P57),'Price List'!$O$5:$O$74,0)),0) -> 3 | U57: =IFERROR(INDEX('Price List'!$H$5:$H$74,MATCH(TRIM(J57)&"|"&TRIM(P57),'Price List'!$O$5:$O$74,0)),0) -> 0.2 | V57: =T57*(1+U57) -> 3.6 | W57: =IFERROR(INDEX('Price List'!$J$5:$J$74,MATCH(TRIM(J57)&"|"&TRIM(P57),'Price List'!$O$5:$O$74,0)),0) -> 18 | X57: =IFERROR(INDEX('Price List'!$K$5:$K$74,MATCH(TRIM(J57)&"|"&TRIM(P57),'Price List'!$O$5:$O$74,0)),0) -> 0.12 | Y57: =W57*(1+X57) -> 20.16 | Z57: =Q57*(V57+Y57) -> 1311.552
C58: Civil and Structure | D58: =IFERROR(IF(TRIM($G58)="Sub Structure",IF(TRIM($H58)="Bored Pile","B.01","B.03"),IF(TRIM($G58)="Super Structure","B.04",IF(OR(TRIM($G58)="Exterior Wall and Partition",TRIM($G58)="External Wall and Partition"),"C.01",IF(TRIM($G58)="Exterior Wall Finishes","C.02",IF(TRIM($G58)="Interior Wall and Partition","C.09",IF(TRIM($G58)="Interior Door","C.10",IF(TRIM($G58)="External Windows and Louvers","C.04",IF(OR(TRIM($G58)="Interior Floor Finishes",TRIM($G58)="Internal Floor Finishes"),"D.02",IF(OR(TRIM($G58)="Interior Wall Finishes",TRIM($G58)="Internal Wall Finishes"),"D.01",IF(OR(TRIM($G58)="Ceiling Finshes",TRIM($G58)="Ceiling Finishes"),"D.03",IF(TRIM($G58)="Fittings, furnishings and equipment","E.04","")))))))))))," ") -> B.04 | E58: BA | F58: 02.GF | G58: Super Structure | H58: Structural Slab | I58: Anti-Termite | J58: Anti-Termite with Plastic Membrane | P58: m2 | Q58: =R58 -> 552 | R58: =552 -> 552 | T58: =IFERROR(INDEX('Price List'!$G$5:$G$74,MATCH(TRIM(J58)&"|"&TRIM(P58),'Price List'!$O$5:$O$74,0)),0) -> 1 | U58: =IFERROR(INDEX('Price List'!$H$5:$H$74,MATCH(TRIM(J58)&"|"&TRIM(P58),'Price List'!$O$5:$O$74,0)),0) -> 0.2 | V58: =T58*(1+U58) -> 1.2 | W58: =IFERROR(INDEX('Price List'!$J$5:$J$74,MATCH(TRIM(J58)&"|"&TRIM(P58),'Price List'!$O$5:$O$74,0)),0) -> 2.5 | X58: =IFERROR(INDEX('Price List'!$K$5:$K$74,MATCH(TRIM(J58)&"|"&TRIM(P58),'Price List'!$O$5:$O$74,0)),0) -> 0.12 | Y58: =W58*(1+X58) -> 2.8 | Z58: =Q58*(V58+Y58) -> 2208
C59: Civil and Structure | D59: =IFERROR(IF(TRIM($G59)="Sub Structure",IF(TRIM($H59)="Bored Pile","B.01","B.03"),IF(TRIM($G59)="Super Structure","B.04",IF(OR(TRIM($G59)="Exterior Wall and Partition",TRIM($G59)="External Wall and Partition"),"C.01",IF(TRIM($G59)="Exterior Wall Finishes","C.02",IF(TRIM($G59)="Interior Wall and Partition","C.09",IF(TRIM($G59)="Interior Door","C.10",IF(TRIM($G59)="External Windows and Louvers","C.04",IF(OR(TRIM($G59)="Interior Floor Finishes",TRIM($G59)="Internal Floor Finishes"),"D.02",IF(OR(TRIM($G59)="Interior Wall Finishes",TRIM($G59)="Internal Wall Finishes"),"D.01",IF(OR(TRIM($G59)="Ceiling Finshes",TRIM($G59)="Ceiling Finishes"),"D.03",IF(TRIM($G59)="Fittings, furnishings and equipment","E.04","")))))))))))," ") -> B.04 | E59: BA | F59: 02.GF | G59: Super Structure | H59: Structural Column | I59: Concrete | J59: Normal Concrete, 35Mpa (Cylinder), Slump 13+-2.5 | P59: m3 | Q59: =R59 -> 45.864 | R59: 45.864 | T59: =IFERROR(INDEX('Price List'!$G$5:$G$74,MATCH(TRIM(J59)&"|"&TRIM(P59),'Price List'!$O$5:$O$74,0)),0) -> 10 | U59: =IFERROR(INDEX('Price List'!$H$5:$H$74,MATCH(TRIM(J59)&"|"&TRIM(P59),'Price List'!$O$5:$O$74,0)),0) -> 0.2 | V59: =T59*(1+U59) -> 12 | W59: =IFERROR(INDEX('Price List'!$J$5:$J$74,MATCH(TRIM(J59)&"|"&TRIM(P59),'Price List'!$O$5:$O$74,0)),0) -> 98 | X59: =IFERROR(INDEX('Price List'!$K$5:$K$74,MATCH(TRIM(J59)&"|"&TRIM(P59),'Price List'!$O$5:$O$74,0)),0) -> 0.12 | Y59: =W59*(1+X59) -> 109.76 | Z59: =Q59*(V59+Y59) -> 5584.4006
C60: Civil and Structure | D60: =IFERROR(IF(TRIM($G60)="Sub Structure",IF(TRIM($H60)="Bored Pile","B.01","B.03"),IF(TRIM($G60)="Super Structure","B.04",IF(OR(TRIM($G60)="Exterior Wall and Partition",TRIM($G60)="External Wall and Partition"),"C.01",IF(TRIM($G60)="Exterior Wall Finishes","C.02",IF(TRIM($G60)="Interior Wall and Partition","C.09",IF(TRIM($G60)="Interior Door","C.10",IF(TRIM($G60)="External Windows and Louvers","C.04",IF(OR(TRIM($G60)="Interior Floor Finishes",TRIM($G60)="Internal Floor Finishes"),"D.02",IF(OR(TRIM($G60)="Interior Wall Finishes",TRIM($G60)="Internal Wall Finishes"),"D.01",IF(OR(TRIM($G60)="Ceiling Finshes",TRIM($G60)="Ceiling Finishes"),"D.03",IF(TRIM($G60)="Fittings, furnishings and equipment","E.04","")))))))))))," ") -> B.04 | E60: BA | F60: 02.GF | G60: Super Structure | H60: Structural Column | I60: Formwork | J60: Formwork | P60: m2 | Q60: =R60 -> 221.76 | R60: 221.76 | T60: =IFERROR(INDEX('Price List'!$G$5:$G$74,MATCH(TRIM(J60)&"|"&TRIM(P60),'Price List'!$O$5:$O$74,0)),0) -> 6 | U60: =IFERROR(INDEX('Price List'!$H$5:$H$74,MATCH(TRIM(J60)&"|"&TRIM(P60),'Price List'!$O$5:$O$74,0)),0) -> 0.2 | V60: =T60*(1+U60) -> 7.2 | W60: =IFERROR(INDEX('Price List'!$J$5:$J$74,MATCH(TRIM(J60)&"|"&TRIM(P60),'Price List'!$O$5:$O$74,0)),0) -> 5 | X60: =IFERROR(INDEX('Price List'!$K$5:$K$74,MATCH(TRIM(J60)&"|"&TRIM(P60),'Price List'!$O$5:$O$74,0)),0) -> 0.12 | Y60: =W60*(1+X60) -> 5.6 | Z60: =Q60*(V60+Y60) -> 2838.528
C61: Civil and Structure | D61: =IFERROR(IF(TRIM($G61)="Sub Structure",IF(TRIM($H61)="Bored Pile","B.01","B.03"),IF(TRIM($G61)="Super Structure","B.04",IF(OR(TRIM($G61)="Exterior Wall and Partition",TRIM($G61)="External Wall and Partition"),"C.01",IF(TRIM($G61)="Exterior Wall Finishes","C.02",IF(TRIM($G61)="Interior Wall and Partition","C.09",IF(TRIM($G61)="Interior Door","C.10",IF(TRIM($G61)="External Windows and Louvers","C.04",IF(OR(TRIM($G61)="Interior Floor Finishes",TRIM($G61)="Internal Floor Finishes"),"D.02",IF(OR(TRIM($G61)="Interior Wall Finishes",TRIM($G61)="Internal Wall Finishes"),"D.01",IF(OR(TRIM($G61)="Ceiling Finshes",TRIM($G61)="Ceiling Finishes"),"D.03",IF(TRIM($G61)="Fittings, furnishings and equipment","E.04","")))))))))))," ") -> B.04 | E61: BA | F61: 02.GF | G61: Super Structure | H61: Structural Column | I61: Rebar | J61: Deform Bar, DB12(fy=390 Mpa) | P61: kg | Q61: =R61 -> 3061.2557 | R61: 3061.2557 | T61: =IFERROR(INDEX('Price List'!$G$5:$G$74,MATCH(TRIM(J61)&"|"&TRIM(P61),'Price List'!$O$5:$O$74,0)),0) -> 0.11 | U61: =IFERROR(INDEX('Price List'!$H$5:$H$74,MATCH(TRIM(J61)&"|"&TRIM(P61),'Price List'!$O$5:$O$74,0)),0) -> 0.2 | V61: =T61*(1+U61) -> 0.132 | W61: =IFERROR(INDEX('Price List'!$J$5:$J$74,MATCH(TRIM(J61)&"|"&TRIM(P61),'Price List'!$O$5:$O$74,0)),0) -> 0.76 | X61: =IFERROR(INDEX('Price List'!$K$5:$K$74,MATCH(TRIM(J61)&"|"&TRIM(P61),'Price List'!$O$5:$O$74,0)),0) -> 0.12 | Y61: =W61*(1+X61) -> 0.8512 | Z61: =Q61*(V61+Y61) -> 3009.8266
C62: Civil and Structure | D62: =IFERROR(IF(TRIM($G62)="Sub Structure",IF(TRIM($H62)="Bored Pile","B.01","B.03"),IF(TRIM($G62)="Super Structure","B.04",IF(OR(TRIM($G62)="Exterior Wall and Partition",TRIM($G62)="External Wall and Partition"),"C.01",IF(TRIM($G62)="Exterior Wall Finishes","C.02",IF(TRIM($G62)="Interior Wall and Partition","C.09",IF(TRIM($G62)="Interior Door","C.10",IF(TRIM($G62)="External Windows and Louvers","C.04",IF(OR(TRIM($G62)="Interior Floor Finishes",TRIM($G62)="Internal Floor Finishes"),"D.02",IF(OR(TRIM($G62)="Interior Wall Finishes",TRIM($G62)="Internal Wall Finishes"),"D.01",IF(OR(TRIM($G62)="Ceiling Finshes",TRIM($G62)="Ceiling Finishes"),"D.03",IF(TRIM($G62)="Fittings, furnishings and equipment","E.04","")))))))))))," ") -> B.04 | E62: BA | F62: 02.GF | G62: Super Structure | H62: Structural Column | I62: Rebar | J62: Deform Bar, DB25(fy=390 Mpa) | P62: kg | Q62: =R62 -> 1921.92 | R62: 1921.92 | T62: =IFERROR(INDEX('Price List'!$G$5:$G$74,MATCH(TRIM(J62)&"|"&TRIM(P62),'Price List'!$O$5:$O$74,0)),0) -> 0.08 | U62: =IFERROR(INDEX('Price List'!$H$5:$H$74,MATCH(TRIM(J62)&"|"&TRIM(P62),'Price List'!$O$5:$O$74,0)),0) -> 0.2 | V62: =T62*(1+U62) -> 0.096 | W62: =IFERROR(INDEX('Price List'!$J$5:$J$74,MATCH(TRIM(J62)&"|"&TRIM(P62),'Price List'!$O$5:$O$74,0)),0) -> 0.72 | X62: =IFERROR(INDEX('Price List'!$K$5:$K$74,MATCH(TRIM(J62)&"|"&TRIM(P62),'Price List'!$O$5:$O$74,0)),0) -> 0.12 | Y62: =W62*(1+X62) -> 0.8064 | Z62: =Q62*(V62+Y62) -> 1734.3406
C63: Civil and Structure | D63: =IFERROR(IF(TRIM($G63)="Sub Structure",IF(TRIM($H63)="Bored Pile","B.01","B.03"),IF(TRIM($G63)="Super Structure","B.04",IF(OR(TRIM($G63)="Exterior Wall and Partition",TRIM($G63)="External Wall and Partition"),"C.01",IF(TRIM($G63)="Exterior Wall Finishes","C.02",IF(TRIM($G63)="Interior Wall and Partition","C.09",IF(TRIM($G63)="Interior Door","C.10",IF(TRIM($G63)="External Windows and Louvers","C.04",IF(OR(TRIM($G63)="Interior Floor Finishes",TRIM($G63)="Internal Floor Finishes"),"D.02",IF(OR(TRIM($G63)="Interior Wall Finishes",TRIM($G63)="Internal Wall Finishes"),"D.01",IF(OR(TRIM($G63)="Ceiling Finshes",TRIM($G63)="Ceiling Finishes"),"D.03",IF(TRIM($G63)="Fittings, furnishings and equipment","E.04","")))))))))))," ") -> B.04 | E63: BA | F63: 02.GF | G63: Super Structure | H63: Structural Column | I63: Rebar | J63: Deform Bar, DB32(fy=390 Mpa) | P63: kg | Q63: =R63 -> 10516.48 | R63: 10516.48 | T63: =IFERROR(INDEX('Price List'!$G$5:$G$74,MATCH(TRIM(J63)&"|"&TRIM(P63),'Price List'!$O$5:$O$74,0)),0) -> 0.08 | U63: =IFERROR(INDEX('Price List'!$H$5:$H$74,MATCH(TRIM(J63)&"|"&TRIM(P63),'Price List'!$O$5:$O$74,0)),0) -> 0.2 | V63: =T63*(1+U63) -> 0.096 | W63: =IFERROR(INDEX('Price List'!$J$5:$J$74,MATCH(TRIM(J63)&"|"&TRIM(P63),'Price List'!$O$5:$O$74,0)),0) -> 0.71 | X63: =IFERROR(INDEX('Price List'!$K$5:$K$74,MATCH(TRIM(J63)&"|"&TRIM(P63),'Price List'!$O$5:$O$74,0)),0) -> 0.12 | Y63: =W63*(1+X63) -> 0.7952 | Z63: =Q63*(V63+Y63) -> 9372.287
C64: Civil and Structure | D64: =IFERROR(IF(TRIM($G64)="Sub Structure",IF(TRIM($H64)="Bored Pile","B.01","B.03"),IF(TRIM($G64)="Super Structure","B.04",IF(OR(TRIM($G64)="Exterior Wall and Partition",TRIM($G64)="External Wall and Partition"),"C.01",IF(TRIM($G64)="Exterior Wall Finishes","C.02",IF(TRIM($G64)="Interior Wall and Partition","C.09",IF(TRIM($G64)="Interior Door","C.10",IF(TRIM($G64)="External Windows and Louvers","C.04",IF(OR(TRIM($G64)="Interior Floor Finishes",TRIM($G64)="Internal Floor Finishes"),"D.02",IF(OR(TRIM($G64)="Interior Wall Finishes",TRIM($G64)="Internal Wall Finishes"),"D.01",IF(OR(TRIM($G64)="Ceiling Finshes",TRIM($G64)="Ceiling Finishes"),"D.03",IF(TRIM($G64)="Fittings, furnishings and equipment","E.04","")))))))))))," ") -> B.04 | E64: BA | F64: 02.GF | G64: Super Structure | H64: Structural Column | I64: Steel Tie Wire | J64: Steel Tie Wire 1mm (Estimated 4% of Total Rebar Weight) | P64: kg | Q64: =R64 -> 619.98623 | R64: =(R62+R63+R61)*4% -> 619.98623 | T64: =IFERROR(INDEX('Price List'!$G$5:$G$74,MATCH(TRIM(J64)&"|"&TRIM(P64),'Price List'!$O$5:$O$74,0)),0) -> 0.05 | U64: =IFERROR(INDEX('Price List'!$H$5:$H$74,MATCH(TRIM(J64)&"|"&TRIM(P64),'Price List'!$O$5:$O$74,0)),0) -> 0.2 | V64: =T64*(1+U64) -> 0.06 | W64: =IFERROR(INDEX('Price List'!$J$5:$J$74,MATCH(TRIM(J64)&"|"&TRIM(P64),'Price List'!$O$5:$O$74,0)),0) -> 1.2 | X64: =IFERROR(INDEX('Price List'!$K$5:$K$74,MATCH(TRIM(J64)&"|"&TRIM(P64),'Price List'!$O$5:$O$74,0)),0) -> 0.12 | Y64: =W64*(1+X64) -> 1.344 | Z64: =Q64*(V64+Y64) -> 870.46066
C65: Civil and Structure | D65: =IFERROR(IF(TRIM($G65)="Sub Structure",IF(TRIM($H65)="Bored Pile","B.01","B.03"),IF(TRIM($G65)="Super Structure","B.04",IF(OR(TRIM($G65)="Exterior Wall and Partition",TRIM($G65)="External Wall and Partition"),"C.01",IF(TRIM($G65)="Exterior Wall Finishes","C.02",IF(TRIM($G65)="Interior Wall and Partition","C.09",IF(TRIM($G65)="Interior Door","C.10",IF(TRIM($G65)="External Windows and Louvers","C.04",IF(OR(TRIM($G65)="Interior Floor Finishes",TRIM($G65)="Internal Floor Finishes"),"D.02",IF(OR(TRIM($G65)="Interior Wall Finishes",TRIM($G65)="Internal Wall Finishes"),"D.01",IF(OR(TRIM($G65)="Ceiling Finshes",TRIM($G65)="Ceiling Finishes"),"D.03",IF(TRIM($G65)="Fittings, furnishings and equipment","E.04","")))))))))))," ") -> B.04 | E65: BA | F65: 02.GF | G65: Super Structure | H65: Structural Wall | I65: Concrete | J65: Normal Concrete, 35Mpa (Cylinder), Slump 13+-2.5 | P65: m3 | Q65: =R65 -> 23.43 | R65: =(5.2*4.2)+(1.325*2*0.3*2) -> 23.43 | T65: =IFERROR(INDEX('Price List'!$G$5:$G$74,MATCH(TRIM(J65)&"|"&TRIM(P65),'Price List'!$O$5:$O$74,0)),0) -> 10 | U65: =IFERROR(INDEX('Price List'!$H$5:$H$74,MATCH(TRIM(J65)&"|"&TRIM(P65),'Price List'!$O$5:$O$74,0)),0) -> 0.2 | V65: =T65*(1+U65) -> 12 | W65: =IFERROR(INDEX('Price List'!$J$5:$J$74,MATCH(TRIM(J65)&"|"&TRIM(P65),'Price List'!$O$5:$O$74,0)),0) -> 98 | X65: =IFERROR(INDEX('Price List'!$K$5:$K$74,MATCH(TRIM(J65)&"|"&TRIM(P65),'Price List'!$O$5:$O$74,0)),0) -> 0.12 | Y65: =W65*(1+X65) -> 109.76 | Z65: =Q65*(V65+Y65) -> 2852.8368
C66: Civil and Structure | D66: =IFERROR(IF(TRIM($G66)="Sub Structure",IF(TRIM($H66)="Bored Pile","B.01","B.03"),IF(TRIM($G66)="Super Structure","B.04",IF(OR(TRIM($G66)="Exterior Wall and Partition",TRIM($G66)="External Wall and Partition"),"C.01",IF(TRIM($G66)="Exterior Wall Finishes","C.02",IF(TRIM($G66)="Interior Wall and Partition","C.09",IF(TRIM($G66)="Interior Door","C.10",IF(TRIM($G66)="External Windows and Louvers","C.04",IF(OR(TRIM($G66)="Interior Floor Finishes",TRIM($G66)="Internal Floor Finishes"),"D.02",IF(OR(TRIM($G66)="Interior Wall Finishes",TRIM($G66)="Internal Wall Finishes"),"D.01",IF(OR(TRIM($G66)="Ceiling Finshes",TRIM($G66)="Ceiling Finishes"),"D.03",IF(TRIM($G66)="Fittings, furnishings and equipment","E.04","")))))))))))," ") -> B.04 | E66: BA | F66: 02.GF | G66: Super Structure | H66: Structural Wall | I66: Formwork | J66: Formwork | P66: m2 | Q66: =R66 -> 139.7 | R66: =(32*4.2)+(1.325*2*2) -> 139.7 | T66: =IFERROR(INDEX('Price List'!$G$5:$G$74,MATCH(TRIM(J66)&"|"&TRIM(P66),'Price List'!$O$5:$O$74,0)),0) -> 6 | U66: =IFERROR(INDEX('Price List'!$H$5:$H$74,MATCH(TRIM(J66)&"|"&TRIM(P66),'Price List'!$O$5:$O$74,0)),0) -> 0.2 | V66: =T66*(1+U66) -> 7.2 | W66: =IFERROR(INDEX('Price List'!$J$5:$J$74,MATCH(TRIM(J66)&"|"&TRIM(P66),'Price List'!$O$5:$O$74,0)),0) -> 5 | X66: =IFERROR(INDEX('Price List'!$K$5:$K$74,MATCH(TRIM(J66)&"|"&TRIM(P66),'Price List'!$O$5:$O$74,0)),0) -> 0.12 | Y66: =W66*(1+X66) -> 5.6 | Z66: =Q66*(V66+Y66) -> 1788.16
C67: Civil and Structure | D67: =IFERROR(IF(TRIM($G67)="Sub Structure",IF(TRIM($H67)="Bored Pile","B.01","B.03"),IF(TRIM($G67)="Super Structure","B.04",IF(OR(TRIM($G67)="Exterior Wall and Partition",TRIM($G67)="External Wall and Partition"),"C.01",IF(TRIM($G67)="Exterior Wall Finishes","C.02",IF(TRIM($G67)="Interior Wall and Partition","C.09",IF(TRIM($G67)="Interior Door","C.10",IF(TRIM($G67)="External Windows and Louvers","C.04",IF(OR(TRIM($G67)="Interior Floor Finishes",TRIM($G67)="Internal Floor Finishes"),"D.02",IF(OR(TRIM($G67)="Interior Wall Finishes",TRIM($G67)="Internal Wall Finishes"),"D.01",IF(OR(TRIM($G67)="Ceiling Finshes",TRIM($G67)="Ceiling Finishes"),"D.03",IF(TRIM($G67)="Fittings, furnishings and equipment","E.04","")))))))))))," ") -> B.04 | E67: BA | F67: 02.GF | G67: Super Structure | H67: Structural Wall | I67: Rebar | J67: Deform Bar, DB10(fy=390 Mpa) | P67: kg | Q67: =R67 -> 241.864 | R67: 241.864 | T67: =IFERROR(INDEX('Price List'!$G$5:$G$74,MATCH(TRIM(J67)&"|"&TRIM(P67),'Price List'!$O$5:$O$74,0)),0) -> 0.12 | U67: =IFERROR(INDEX('Price List'!$H$5:$H$74,MATCH(TRIM(J67)&"|"&TRIM(P67),'Price List'!$O$5:$O$74,0)),0) -> 0.2 | V67: =T67*(1+U67) -> 0.144 | W67: =IFERROR(INDEX('Price List'!$J$5:$J$74,MATCH(TRIM(J67)&"|"&TRIM(P67),'Price List'!$O$5:$O$74,0)),0) -> 0.78 | X67: =IFERROR(INDEX('Price List'!$K$5:$K$74,MATCH(TRIM(J67)&"|"&TRIM(P67),'Price List'!$O$5:$O$74,0)),0) -> 0.12 | Y67: =W67*(1+X67) -> 0.8736 | Z67: =Q67*(V67+Y67) -> 246.12081
C68: Civil and Structure | D68: =IFERROR(IF(TRIM($G68)="Sub Structure",IF(TRIM($H68)="Bored Pile","B.01","B.03"),IF(TRIM($G68)="Super Structure","B.04",IF(OR(TRIM($G68)="Exterior Wall and Partition",TRIM($G68)="External Wall and Partition"),"C.01",IF(TRIM($G68)="Exterior Wall Finishes","C.02",IF(TRIM($G68)="Interior Wall and Partition","C.09",IF(TRIM($G68)="Interior Door","C.10",IF(TRIM($G68)="External Windows and Louvers","C.04",IF(OR(TRIM($G68)="Interior Floor Finishes",TRIM($G68)="Internal Floor Finishes"),"D.02",IF(OR(TRIM($G68)="Interior Wall Finishes",TRIM($G68)="Internal Wall Finishes"),"D.01",IF(OR(TRIM($G68)="Ceiling Finshes",TRIM($G68)="Ceiling Finishes"),"D.03",IF(TRIM($G68)="Fittings, furnishings and equipment","E.04","")))))))))))," ") -> B.04 | E68: BA | F68: 02.GF | G68: Super Structure | H68: Structural Wall | I68: Rebar | J68: Deform Bar, DB12(fy=390 Mpa) | P68: kg | Q68: =R68 -> 1071.6384 | R68: 1071.6384 | T68: =IFERROR(INDEX('Price List'!$G$5:$G$74,MATCH(TRIM(J68)&"|"&TRIM(P68),'Price List'!$O$5:$O$74,0)),0) -> 0.11 | U68: =IFERROR(INDEX('Price List'!$H$5:$H$74,MATCH(TRIM(J68)&"|"&TRIM(P68),'Price List'!$O$5:$O$74,0)),0) -> 0.2 | V68: =T68*(1+U68) -> 0.132 | W68: =IFERROR(INDEX('Price List'!$J$5:$J$74,MATCH(TRIM(J68)&"|"&TRIM(P68),'Price List'!$O$5:$O$74,0)),0) -> 0.76 | X68: =IFERROR(INDEX('Price List'!$K$5:$K$74,MATCH(TRIM(J68)&"|"&TRIM(P68),'Price List'!$O$5:$O$74,0)),0) -> 0.12 | Y68: =W68*(1+X68) -> 0.8512 | Z68: =Q68*(V68+Y68) -> 1053.6349
C69: Civil and Structure | D69: =IFERROR(IF(TRIM($G69)="Sub Structure",IF(TRIM($H69)="Bored Pile","B.01","B.03"),IF(TRIM($G69)="Super Structure","B.04",IF(OR(TRIM($G69)="Exterior Wall and Partition",TRIM($G69)="External Wall and Partition"),"C.01",IF(TRIM($G69)="Exterior Wall Finishes","C.02",IF(TRIM($G69)="Interior Wall and Partition","C.09",IF(TRIM($G69)="Interior Door","C.10",IF(TRIM($G69)="External Windows and Louvers","C.04",IF(OR(TRIM($G69)="Interior Floor Finishes",TRIM($G69)="Internal Floor Finishes"),"D.02",IF(OR(TRIM($G69)="Interior Wall Finishes",TRIM($G69)="Internal Wall Finishes"),"D.01",IF(OR(TRIM($G69)="Ceiling Finshes",TRIM($G69)="Ceiling Finishes"),"D.03",IF(TRIM($G69)="Fittings, furnishings and equipment","E.04","")))))))))))," ") -> B.04 | E69: BA | F69: 02.GF | G69: Super Structure | H69: Structural Wall | I69: Rebar | J69: Deform Bar, DB16(fy=390 Mpa) | P69: kg | Q69: =R69 -> 1659.632 | R69: 1659.632 | T69: =IFERROR(INDEX('Price List'!$G$5:$G$74,MATCH(TRIM(J69)&"|"&TRIM(P69),'Price List'!$O$5:$O$74,0)),0) -> 0.1 | U69: =IFERROR(INDEX('Price List'!$H$5:$H$74,MATCH(TRIM(J69)&"|"&TRIM(P69),'Price List'!$O$5:$O$74,0)),0) -> 0.2 | V69: =T69*(1+U69) -> 0.12 | W69: =IFERROR(INDEX('Price List'!$J$5:$J$74,MATCH(TRIM(J69)&"|"&TRIM(P69),'Price List'!$O$5:$O$74,0)),0) -> 0.74 | X69: =IFERROR(INDEX('Price List'!$K$5:$K$74,MATCH(TRIM(J69)&"|"&TRIM(P69),'Price List'!$O$5:$O$74,0)),0) -> 0.12 | Y69: =W69*(1+X69) -> 0.8288 | Z69: =Q69*(V69+Y69) -> 1574.6588
C70: Civil and Structure | D70: =IFERROR(IF(TRIM($G70)="Sub Structure",IF(TRIM($H70)="Bored Pile","B.01","B.03"),IF(TRIM($G70)="Super Structure","B.04",IF(OR(TRIM($G70)="Exterior Wall and Partition",TRIM($G70)="External Wall and Partition"),"C.01",IF(TRIM($G70)="Exterior Wall Finishes","C.02",IF(TRIM($G70)="Interior Wall and Partition","C.09",IF(TRIM($G70)="Interior Door","C.10",IF(TRIM($G70)="External Windows and Louvers","C.04",IF(OR(TRIM($G70)="Interior Floor Finishes",TRIM($G70)="Internal Floor Finishes"),"D.02",IF(OR(TRIM($G70)="Interior Wall Finishes",TRIM($G70)="Internal Wall Finishes"),"D.01",IF(OR(TRIM($G70)="Ceiling Finshes",TRIM($G70)="Ceiling Finishes"),"D.03",IF(TRIM($G70)="Fittings, furnishings and equipment","E.04","")))))))))))," ") -> B.04 | E70: BA | F70: 02.GF | G70: Super Structure | H70: Structural Wall | I70: Rebar | J70: Deform Bar, DB20(fy=390 Mpa) | P70: kg | Q70: =R70 -> 822.016 | R70: 822.016 | T70: =IFERROR(INDEX('Price List'!$G$5:$G$74,MATCH(TRIM(J70)&"|"&TRIM(P70),'Price List'!$O$5:$O$74,0)),0) -> 0.09 | U70: =IFERROR(INDEX('Price List'!$H$5:$H$74,MATCH(TRIM(J70)&"|"&TRIM(P70),'Price List'!$O$5:$O$74,0)),0) -> 0.2 | V70: =T70*(1+U70) -> 0.108 | W70: =IFERROR(INDEX('Price List'!$J$5:$J$74,MATCH(TRIM(J70)&"|"&TRIM(P70),'Price List'!$O$5:$O$74,0)),0) -> 0.73 | X70: =IFERROR(INDEX('Price List'!$K$5:$K$74,MATCH(TRIM(J70)&"|"&TRIM(P70),'Price List'!$O$5:$O$74,0)),0) -> 0.12 | Y70: =W70*(1+X70) -> 0.8176 | Z70: =Q70*(V70+Y70) -> 760.85801
C71: Civil and Structure | D71: =IFERROR(IF(TRIM($G71)="Sub Structure",IF(TRIM($H71)="Bored Pile","B.01","B.03"),IF(TRIM($G71)="Super Structure","B.04",IF(OR(TRIM($G71)="Exterior Wall and Partition",TRIM($G71)="External Wall and Partition"),"C.01",IF(TRIM($G71)="Exterior Wall Finishes","C.02",IF(TRIM($G71)="Interior Wall and Partition","C.09",IF(TRIM($G71)="Interior Door","C.10",IF(TRIM($G71)="External Windows and Louvers","C.04",IF(OR(TRIM($G71)="Interior Floor Finishes",TRIM($G71)="Internal Floor Finishes"),"D.02",IF(OR(TRIM($G71)="Interior Wall Finishes",TRIM($G71)="Internal Wall Finishes"),"D.01",IF(OR(TRIM($G71)="Ceiling Finshes",TRIM($G71)="Ceiling Finishes"),"D.03",IF(TRIM($G71)="Fittings, furnishings and equipment","E.04","")))))))))))," ") -> B.04 | E71: BA | F71: 02.GF | G71: Super Structure | H71: Structural Wall | I71: Steel Tie Wire | J71: Steel Tie Wire 1mm (Estimated 4% of Total Rebar Weight) | P71: kg | Q71: =R71 -> 151.80602 | R71: =(R69+R70+R67+R68)*4% -> 151.80602 | T71: =IFERROR(INDEX('Price List'!$G$5:$G$74,MATCH(TRIM(J71)&"|"&TRIM(P71),'Price List'!$O$5:$O$74,0)),0) -> 0.05 | U71: =IFERROR(INDEX('Price List'!$H$5:$H$74,MATCH(TRIM(J71)&"|"&TRIM(P71),'Price List'!$O$5:$O$74,0)),0) -> 0.2 | V71: =T71*(1+U71) -> 0.06 | W71: =IFERROR(INDEX('Price List'!$J$5:$J$74,MATCH(TRIM(J71)&"|"&TRIM(P71),'Price List'!$O$5:$O$74,0)),0) -> 1.2 | X71: =IFERROR(INDEX('Price List'!$K$5:$K$74,MATCH(TRIM(J71)&"|"&TRIM(P71),'Price List'!$O$5:$O$74,0)),0) -> 0.12 | Y71: =W71*(1+X71) -> 1.344 | Z71: =Q71*(V71+Y71) -> 213.13565
C72: Civil and Structure | D72: =IFERROR(IF(TRIM($G72)="Sub Structure",IF(TRIM($H72)="Bored Pile","B.01","B.03"),IF(TRIM($G72)="Super Structure","B.04",IF(OR(TRIM($G72)="Exterior Wall and Partition",TRIM($G72)="External Wall and Partition"),"C.01",IF(TRIM($G72)="Exterior Wall Finishes","C.02",IF(TRIM($G72)="Interior Wall and Partition","C.09",IF(TRIM($G72)="Interior Door","C.10",IF(TRIM($G72)="External Windows and Louvers","C.04",IF(OR(TRIM($G72)="Interior Floor Finishes",TRIM($G72)="Internal Floor Finishes"),"D.02",IF(OR(TRIM($G72)="Interior Wall Finishes",TRIM($G72)="Internal Wall Finishes"),"D.01",IF(OR(TRIM($G72)="Ceiling Finshes",TRIM($G72)="Ceiling Finishes"),"D.03",IF(TRIM($G72)="Fittings, furnishings and equipment","E.04","")))))))))))," ") -> B.04 | E72: BA | F72: 02.GF | G72: Super Structure | H72: Structural Staircase | I72: Concrete | J72: Normal Concrete, 35Mpa (Cylinder), Slump 13+-2.5 | M72: slab, beam, column | P72: m3 | Q72: =R72 -> 26.016 | R72: =17.55+3.45+5.016 -> 26.016 | T72: =IFERROR(INDEX('Price List'!$G$5:$G$74,MATCH(TRIM(J72)&"|"&TRIM(P72),'Price List'!$O$5:$O$74,0)),0) -> 10 | U72: =IFERROR(INDEX('Price List'!$H$5:$H$74,MATCH(TRIM(J72)&"|"&TRIM(P72),'Price List'!$O$5:$O$74,0)),0) -> 0.2 | V72: =T72*(1+U72) -> 12 | W72: =IFERROR(INDEX('Price List'!$J$5:$J$74,MATCH(TRIM(J72)&"|"&TRIM(P72),'Price List'!$O$5:$O$74,0)),0) -> 98 | X72: =IFERROR(INDEX('Price List'!$K$5:$K$74,MATCH(TRIM(J72)&"|"&TRIM(P72),'Price List'!$O$5:$O$74,0)),0) -> 0.12 | Y72: =W72*(1+X72) -> 109.76 | Z72: =Q72*(V72+Y72) -> 3167.7082
C73: Civil and Structure | D73: =IFERROR(IF(TRIM($G73)="Sub Structure",IF(TRIM($H73)="Bored Pile","B.01","B.03"),IF(TRIM($G73)="Super Structure","B.04",IF(OR(TRIM($G73)="Exterior Wall and Partition",TRIM($G73)="External Wall and Partition"),"C.01",IF(TRIM($G73)="Exterior Wall Finishes","C.02",IF(TRIM($G73)="Interior Wall and Partition","C.09",IF(TRIM($G73)="Interior Door","C.10",IF(TRIM($G73)="External Windows and Louvers","C.04",IF(OR(TRIM($G73)="Interior Floor Finishes",TRIM($G73)="Internal Floor Finishes"),"D.02",IF(OR(TRIM($G73)="Interior Wall Finishes",TRIM($G73)="Internal Wall Finishes"),"D.01",IF(OR(TRIM($G73)="Ceiling Finshes",TRIM($G73)="Ceiling Finishes"),"D.03",IF(TRIM($G73)="Fittings, furnishings and equipment","E.04","")))))))))))," ") -> B.04 | E73: BA | F73: 02.GF | G73: Super Structure | H73: Structural Staircase | I73: Formwork | J73: Formwork | P73: m2 | Q73: =R73 -> 390.24 | R73: =R72*15 -> 390.24 | T73: =IFERROR(INDEX('Price List'!$G$5:$G$74,MATCH(TRIM(J73)&"|"&TRIM(P73),'Price List'!$O$5:$O$74,0)),0) -> 6 | U73: =IFERROR(INDEX('Price List'!$H$5:$H$74,MATCH(TRIM(J73)&"|"&TRIM(P73),'Price List'!$O$5:$O$74,0)),0) -> 0.2 | V73: =T73*(1+U73) -> 7.2 | W73: =IFERROR(INDEX('Price List'!$J$5:$J$74,MATCH(TRIM(J73)&"|"&TRIM(P73),'Price List'!$O$5:$O$74,0)),0) -> 5 | X73: =IFERROR(INDEX('Price List'!$K$5:$K$74,MATCH(TRIM(J73)&"|"&TRIM(P73),'Price List'!$O$5:$O$74,0)),0) -> 0.12 | Y73: =W73*(1+X73) -> 5.6 | Z73: =Q73*(V73+Y73) -> 4995.072
C74: Civil and Structure | D74: =IFERROR(IF(TRIM($G74)="Sub Structure",IF(TRIM($H74)="Bored Pile","B.01","B.03"),IF(TRIM($G74)="Super Structure","B.04",IF(OR(TRIM($G74)="Exterior Wall and Partition",TRIM($G74)="External Wall and Partition"),"C.01",IF(TRIM($G74)="Exterior Wall Finishes","C.02",IF(TRIM($G74)="Interior Wall and Partition","C.09",IF(TRIM($G74)="Interior Door","C.10",IF(TRIM($G74)="External Windows and Louvers","C.04",IF(OR(TRIM($G74)="Interior Floor Finishes",TRIM($G74)="Internal Floor Finishes"),"D.02",IF(OR(TRIM($G74)="Interior Wall Finishes",TRIM($G74)="Internal Wall Finishes"),"D.01",IF(OR(TRIM($G74)="Ceiling Finshes",TRIM($G74)="Ceiling Finishes"),"D.03",IF(TRIM($G74)="Fittings, furnishings and equipment","E.04","")))))))))))," ") -> B.04 | E74: BA | F74: 02.GF | G74: Super Structure | H74: Structural Staircase | I74: Rebar | J74: Round Bar, RB8(fy=250 Mpa) | P74: kg | Q74: =R74 -> 219.955 | R74: ='GF Staircase'!M12 -> 219.955 | T74: =IFERROR(INDEX('Price List'!$G$5:$G$74,MATCH(TRIM(J74)&"|"&TRIM(P74),'Price List'!$O$5:$O$74,0)),0) -> 0.12 | U74: =IFERROR(INDEX('Price List'!$H$5:$H$74,MATCH(TRIM(J74)&"|"&TRIM(P74),'Price List'!$O$5:$O$74,0)),0) -> 0.2 | V74: =T74*(1+U74) -> 0.144 | W74: =IFERROR(INDEX('Price List'!$J$5:$J$74,MATCH(TRIM(J74)&"|"&TRIM(P74),'Price List'!$O$5:$O$74,0)),0) -> 0.77 | X74: =IFERROR(INDEX('Price List'!$K$5:$K$74,MATCH(TRIM(J74)&"|"&TRIM(P74),'Price List'!$O$5:$O$74,0)),0) -> 0.12 | Y74: =W74*(1+X74) -> 0.8624 | Z74: =Q74*(V74+Y74) -> 221.36271 | AC74: =R74/$R$72 -> 8.4546049
C75: Civil and Structure | D75: =IFERROR(IF(TRIM($G75)="Sub Structure",IF(TRIM($H75)="Bored Pile","B.01","B.03"),IF(TRIM($G75)="Super Structure","B.04",IF(OR(TRIM($G75)="Exterior Wall and Partition",TRIM($G75)="External Wall and Partition"),"C.01",IF(TRIM($G75)="Exterior Wall Finishes","C.02",IF(TRIM($G75)="Interior Wall and Partition","C.09",IF(TRIM($G75)="Interior Door","C.10",IF(TRIM($G75)="External Windows and Louvers","C.04",IF(OR(TRIM($G75)="Interior Floor Finishes",TRIM($G75)="Internal Floor Finishes"),"D.02",IF(OR(TRIM($G75)="Interior Wall Finishes",TRIM($G75)="Internal Wall Finishes"),"D.01",IF(OR(TRIM($G75)="Ceiling Finshes",TRIM($G75)="Ceiling Finishes"),"D.03",IF(TRIM($G75)="Fittings, furnishings and equipment","E.04","")))))))))))," ") -> B.04 | E75: BA | F75: 02.GF | G75: Super Structure | H75: Structural Staircase | I75: Rebar | J75: Deform Bar, DB10(fy=390 Mpa) | P75: kg | Q75: =R75 -> 207 | R75: ='GF Staircase'!M13 -> 207 | T75: =IFERROR(INDEX('Price List'!$G$5:$G$74,MATCH(TRIM(J75)&"|"&TRIM(P75),'Price List'!$O$5:$O$74,0)),0) -> 0.12 | U75: =IFERROR(INDEX('Price List'!$H$5:$H$74,MATCH(TRIM(J75)&"|"&TRIM(P75),'Price List'!$O$5:$O$74,0)),0) -> 0.2 | V75: =T75*(1+U75) -> 0.144 | W75: =IFERROR(INDEX('Price List'!$J$5:$J$74,MATCH(TRIM(J75)&"|"&TRIM(P75),'Price List'!$O$5:$O$74,0)),0) -> 0.78 | X75: =IFERROR(INDEX('Price List'!$K$5:$K$74,MATCH(TRIM(J75)&"|"&TRIM(P75),'Price List'!$O$5:$O$74,0)),0) -> 0.12 | Y75: =W75*(1+X75) -> 0.8736 | Z75: =Q75*(V75+Y75) -> 210.6432 | AC75: =R75/$R$72 -> 7.9566421
C76: Civil and Structure | D76: =IFERROR(IF(TRIM($G76)="Sub Structure",IF(TRIM($H76)="Bored Pile","B.01","B.03"),IF(TRIM($G76)="Super Structure","B.04",IF(OR(TRIM($G76)="Exterior Wall and Partition",TRIM($G76)="External Wall and Partition"),"C.01",IF(TRIM($G76)="Exterior Wall Finishes","C.02",IF(TRIM($G76)="Interior Wall and Partition","C.09",IF(TRIM($G76)="Interior Door","C.10",IF(TRIM($G76)="External Windows and Louvers","C.04",IF(OR(TRIM($G76)="Interior Floor Finishes",TRIM($G76)="Internal Floor Finishes"),"D.02",IF(OR(TRIM($G76)="Interior Wall Finishes",TRIM($G76)="Internal Wall Finishes"),"D.01",IF(OR(TRIM($G76)="Ceiling Finshes",TRIM($G76)="Ceiling Finishes"),"D.03",IF(TRIM($G76)="Fittings, furnishings and equipment","E.04","")))))))))))," ") -> B.04 | E76: BA | F76: 02.GF | G76: Super Structure | H76: Structural Staircase | I76: Rebar | J76: Deform Bar, DB12(fy=390 Mpa) | P76: kg | Q76: =R76 -> 2914.92 | R76: ='GF Staircase'!M14 -> 2914.92 | T76: =IFERROR(INDEX('Price List'!$G$5:$G$74,MATCH(TRIM(J76)&"|"&TRIM(P76),'Price List'!$O$5:$O$74,0)),0) -> 0.11 | U76: =IFERROR(INDEX('Price List'!$H$5:$H$74,MATCH(TRIM(J76)&"|"&TRIM(P76),'Price List'!$O$5:$O$74,0)),0) -> 0.2 | V76: =T76*(1+U76) -> 0.132 | W76: =IFERROR(INDEX('Price List'!$J$5:$J$74,MATCH(TRIM(J76)&"|"&TRIM(P76),'Price List'!$O$5:$O$74,0)),0) -> 0.76 | X76: =IFERROR(INDEX('Price List'!$K$5:$K$74,MATCH(TRIM(J76)&"|"&TRIM(P76),'Price List'!$O$5:$O$74,0)),0) -> 0.12 | Y76: =W76*(1+X76) -> 0.8512 | Z76: =Q76*(V76+Y76) -> 2865.9493 | AC76: =R76/$R$72 -> 112.04336
C77: Civil and Structure | D77: =IFERROR(IF(TRIM($G77)="Sub Structure",IF(TRIM($H77)="Bored Pile","B.01","B.03"),IF(TRIM($G77)="Super Structure","B.04",IF(OR(TRIM($G77)="Exterior Wall and Partition",TRIM($G77)="External Wall and Partition"),"C.01",IF(TRIM($G77)="Exterior Wall Finishes","C.02",IF(TRIM($G77)="Interior Wall and Partition","C.09",IF(TRIM($G77)="Interior Door","C.10",IF(TRIM($G77)="External Windows and Louvers","C.04",IF(OR(TRIM($G77)="Interior Floor Finishes",TRIM($G77)="Internal Floor Finishes"),"D.02",IF(OR(TRIM($G77)="Interior Wall Finishes",TRIM($G77)="Internal Wall Finishes"),"D.01",IF(OR(TRIM($G77)="Ceiling Finshes",TRIM($G77)="Ceiling Finishes"),"D.03",IF(TRIM($G77)="Fittings, furnishings and equipment","E.04","")))))))))))," ") -> B.04 | E77: BA | F77: 02.GF | G77: Super Structure | H77: Structural Staircase | I77: Rebar | J77: Deform Bar, DB16(fy=390 Mpa) | P77: kg | Q77: =R77 -> 535.9848 | R77: ='GF Staircase'!M15 -> 535.9848 | T77: =IFERROR(INDEX('Price List'!$G$5:$G$74,MATCH(TRIM(J77)&"|"&TRIM(P77),'Price List'!$O$5:$O$74,0)),0) -> 0.1 | U77: =IFERROR(INDEX('Price List'!$H$5:$H$74,MATCH(TRIM(J77)&"|"&TRIM(P77),'Price List'!$O$5:$O$74,0)),0) -> 0.2 | V77: =T77*(1+U77) -> 0.12 | W77: =IFERROR(INDEX('Price List'!$J$5:$J$74,MATCH(TRIM(J77)&"|"&TRIM(P77),'Price List'!$O$5:$O$74,0)),0) -> 0.74 | X77: =IFERROR(INDEX('Price List'!$K$5:$K$74,MATCH(TRIM(J77)&"|"&TRIM(P77),'Price List'!$O$5:$O$74,0)),0) -> 0.12 | Y77: =W77*(1+X77) -> 0.8288 | Z77: =Q77*(V77+Y77) -> 508.54238 | AC77: =R77/$R$72 -> 20.602122
C78: Civil and Structure | D78: =IFERROR(IF(TRIM($G78)="Sub Structure",IF(TRIM($H78)="Bored Pile","B.01","B.03"),IF(TRIM($G78)="Super Structure","B.04",IF(OR(TRIM($G78)="Exterior Wall and Partition",TRIM($G78)="External Wall and Partition"),"C.01",IF(TRIM($G78)="Exterior Wall Finishes","C.02",IF(TRIM($G78)="Interior Wall and Partition","C.09",IF(TRIM($G78)="Interior Door","C.10",IF(TRIM($G78)="External Windows and Louvers","C.04",IF(OR(TRIM($G78)="Interior Floor Finishes",TRIM($G78)="Internal Floor Finishes"),"D.02",IF(OR(TRIM($G78)="Interior Wall Finishes",TRIM($G78)="Internal Wall Finishes"),"D.01",IF(OR(TRIM($G78)="Ceiling Finshes",TRIM($G78)="Ceiling Finishes"),"D.03",IF(TRIM($G78)="Fittings, furnishings and equipment","E.04","")))))))))))," ") -> B.04 | E78: BA | F78: 02.GF | G78: Super Structure | H78: Structural Staircase | I78: Rebar | J78: Deform Bar, DB20(fy=390 Mpa) | P78: kg | Q78: =R78 -> 254.384 | R78: ='GF Staircase'!M16 -> 254.384 | T78: =IFERROR(INDEX('Price List'!$G$5:$G$74,MATCH(TRIM(J78)&"|"&TRIM(P78),'Price List'!$O$5:$O$74,0)),0) -> 0.09 | U78: =IFERROR(INDEX('Price List'!$H$5:$H$74,MATCH(TRIM(J78)&"|"&TRIM(P78),'Price List'!$O$5:$O$74,0)),0) -> 0.2 | V78: =T78*(1+U78) -> 0.108 | W78: =IFERROR(INDEX('Price List'!$J$5:$J$74,MATCH(TRIM(J78)&"|"&TRIM(P78),'Price List'!$O$5:$O$74,0)),0) -> 0.73 | X78: =IFERROR(INDEX('Price List'!$K$5:$K$74,MATCH(TRIM(J78)&"|"&TRIM(P78),'Price List'!$O$5:$O$74,0)),0) -> 0.12 | Y78: =W78*(1+X78) -> 0.8176 | Z78: =Q78*(V78+Y78) -> 235.45783 | AC78: =R78/$R$72 -> 9.7779828
C79: Civil and Structure | D79: =IFERROR(IF(TRIM($G79)="Sub Structure",IF(TRIM($H79)="Bored Pile","B.01","B.03"),IF(TRIM($G79)="Super Structure","B.04",IF(OR(TRIM($G79)="Exterior Wall and Partition",TRIM($G79)="External Wall and Partition"),"C.01",IF(TRIM($G79)="Exterior Wall Finishes","C.02",IF(TRIM($G79)="Interior Wall and Partition","C.09",IF(TRIM($G79)="Interior Door","C.10",IF(TRIM($G79)="External Windows and Louvers","C.04",IF(OR(TRIM($G79)="Interior Floor Finishes",TRIM($G79)="Internal Floor Finishes"),"D.02",IF(OR(TRIM($G79)="Interior Wall Finishes",TRIM($G79)="Internal Wall Finishes"),"D.01",IF(OR(TRIM($G79)="Ceiling Finshes",TRIM($G79)="Ceiling Finishes"),"D.03",IF(TRIM($G79)="Fittings, furnishings and equipment","E.04","")))))))))))," ") -> B.04 | E79: BA | F79: 02.GF | G79: Super Structure | H79: Structural Staircase | I79: Steel Tie Wire | J79: Steel Tie Wire 1mm (Estimated 4% of Total Rebar Weight) | P79: kg | Q79: =R79 -> 165.28975 | R79: =(R77+R78+R75+R76+R74)*4% -> 165.28975 | T79: =IFERROR(INDEX('Price List'!$G$5:$G$74,MATCH(TRIM(J79)&"|"&TRIM(P79),'Price List'!$O$5:$O$74,0)),0) -> 0.05 | U79: =IFERROR(INDEX('Price List'!$H$5:$H$74,MATCH(TRIM(J79)&"|"&TRIM(P79),'Price List'!$O$5:$O$74,0)),0) -> 0.2 | V79: =T79*(1+U79) -> 0.06 | W79: =IFERROR(INDEX('Price List'!$J$5:$J$74,MATCH(TRIM(J79)&"|"&TRIM(P79),'Price List'!$O$5:$O$74,0)),0) -> 1.2 | X79: =IFERROR(INDEX('Price List'!$K$5:$K$74,MATCH(TRIM(J79)&"|"&TRIM(P79),'Price List'!$O$5:$O$74,0)),0) -> 0.12 | Y79: =W79*(1+X79) -> 1.344 | Z79: =Q79*(V79+Y79) -> 232.06681
C80: Civil and Structure | D80: =IFERROR(IF(TRIM($G80)="Sub Structure",IF(TRIM($H80)="Bored Pile","B.01","B.03"),IF(TRIM($G80)="Super Structure","B.04",IF(OR(TRIM($G80)="Exterior Wall and Partition",TRIM($G80)="External Wall and Partition"),"C.01",IF(TRIM($G80)="Exterior Wall Finishes","C.02",IF(TRIM($G80)="Interior Wall and Partition","C.09",IF(TRIM($G80)="Interior Door","C.10",IF(TRIM($G80)="External Windows and Louvers","C.04",IF(OR(TRIM($G80)="Interior Floor Finishes",TRIM($G80)="Internal Floor Finishes"),"D.02",IF(OR(TRIM($G80)="Interior Wall Finishes",TRIM($G80)="Internal Wall Finishes"),"D.01",IF(OR(TRIM($G80)="Ceiling Finshes",TRIM($G80)="Ceiling Finishes"),"D.03",IF(TRIM($G80)="Fittings, furnishings and equipment","E.04","")))))))))))," ") -> B.04 | E80: BA | F80: 03.MZ | G80: Super Structure | H80: Structural Beam | I80: Concrete | J80: Normal Concrete, 35Mpa (Cylinder), Slump 13+-2.5 | P80: m3 | Q80: =R80 -> 33.6095 | R80: ='mz beam'!H11 -> 33.6095 | T80: =IFERROR(INDEX('Price List'!$G$5:$G$74,MATCH(TRIM(J80)&"|"&TRIM(P80),'Price List'!$O$5:$O$74,0)),0) -> 10 | U80: =IFERROR(INDEX('Price List'!$H$5:$H$74,MATCH(TRIM(J80)&"|"&TRIM(P80),'Price List'!$O$5:$O$74,0)),0) -> 0.2 | V80: =T80*(1+U80) -> 12 | W80: =IFERROR(INDEX('Price List'!$J$5:$J$74,MATCH(TRIM(J80)&"|"&TRIM(P80),'Price List'!$O$5:$O$74,0)),0) -> 98 | X80: =IFERROR(INDEX('Price List'!$K$5:$K$74,MATCH(TRIM(J80)&"|"&TRIM(P80),'Price List'!$O$5:$O$74,0)),0) -> 0.12 | Y80: =W80*(1+X80) -> 109.76 | Z80: =Q80*(V80+Y80) -> 4092.2927
C81: Civil and Structure | D81: =IFERROR(IF(TRIM($G81)="Sub Structure",IF(TRIM($H81)="Bored Pile","B.01","B.03"),IF(TRIM($G81)="Super Structure","B.04",IF(OR(TRIM($G81)="Exterior Wall and Partition",TRIM($G81)="External Wall and Partition"),"C.01",IF(TRIM($G81)="Exterior Wall Finishes","C.02",IF(TRIM($G81)="Interior Wall and Partition","C.09",IF(TRIM($G81)="Interior Door","C.10",IF(TRIM($G81)="External Windows and Louvers","C.04",IF(OR(TRIM($G81)="Interior Floor Finishes",TRIM($G81)="Internal Floor Finishes"),"D.02",IF(OR(TRIM($G81)="Interior Wall Finishes",TRIM($G81)="Internal Wall Finishes"),"D.01",IF(OR(TRIM($G81)="Ceiling Finshes",TRIM($G81)="Ceiling Finishes"),"D.03",IF(TRIM($G81)="Fittings, furnishings and equipment","E.04","")))))))))))," ") -> B.04 | E81: BA | F81: 03.MZ | G81: Super Structure | H81: Structural Beam | I81: Formwork | J81: Formwork | P81: m2 | Q81: =R81 -> 319.12 | R81: ='mz beam'!G11 -> 319.12 | T81: =IFERROR(INDEX('Price List'!$G$5:$G$74,MATCH(TRIM(J81)&"|"&TRIM(P81),'Price List'!$O$5:$O$74,0)),0) -> 6 | U81: =IFERROR(INDEX('Price List'!$H$5:$H$74,MATCH(TRIM(J81)&"|"&TRIM(P81),'Price List'!$O$5:$O$74,0)),0) -> 0.2 | V81: =T81*(1+U81) -> 7.2 | W81: =IFERROR(INDEX('Price List'!$J$5:$J$74,MATCH(TRIM(J81)&"|"&TRIM(P81),'Price List'!$O$5:$O$74,0)),0) -> 5 | X81: =IFERROR(INDEX('Price List'!$K$5:$K$74,MATCH(TRIM(J81)&"|"&TRIM(P81),'Price List'!$O$5:$O$74,0)),0) -> 0.12 | Y81: =W81*(1+X81) -> 5.6 | Z81: =Q81*(V81+Y81) -> 4084.736
C82: Civil and Structure | D82: =IFERROR(IF(TRIM($G82)="Sub Structure",IF(TRIM($H82)="Bored Pile","B.01","B.03"),IF(TRIM($G82)="Super Structure","B.04",IF(OR(TRIM($G82)="Exterior Wall and Partition",TRIM($G82)="External Wall and Partition"),"C.01",IF(TRIM($G82)="Exterior Wall Finishes","C.02",IF(TRIM($G82)="Interior Wall and Partition","C.09",IF(TRIM($G82)="Interior Door","C.10",IF(TRIM($G82)="External Windows and Louvers","C.04",IF(OR(TRIM($G82)="Interior Floor Finishes",TRIM($G82)="Internal Floor Finishes"),"D.02",IF(OR(TRIM($G82)="Interior Wall Finishes",TRIM($G82)="Internal Wall Finishes"),"D.01",IF(OR(TRIM($G82)="Ceiling Finshes",TRIM($G82)="Ceiling Finishes"),"D.03",IF(TRIM($G82)="Fittings, furnishings and equipment","E.04","")))))))))))," ") -> B.04 | E82: BA | F82: 03.MZ | G82: Super Structure | H82: Structural Beam | I82: Rebar | J82: Round Bar, RB8(fy=250 Mpa) | P82: kg | Q82: =R82 -> 465.784 | R82: ='mz beam'!J14 -> 465.784 | T82: =IFERROR(INDEX('Price List'!$G$5:$G$74,MATCH(TRIM(J82)&"|"&TRIM(P82),'Price List'!$O$5:$O$74,0)),0) -> 0.12 | U82: =IFERROR(INDEX('Price List'!$H$5:$H$74,MATCH(TRIM(J82)&"|"&TRIM(P82),'Price List'!$O$5:$O$74,0)),0) -> 0.2 | V82: =T82*(1+U82) -> 0.144 | W82: =IFERROR(INDEX('Price List'!$J$5:$J$74,MATCH(TRIM(J82)&"|"&TRIM(P82),'Price List'!$O$5:$O$74,0)),0) -> 0.77 | X82: =IFERROR(INDEX('Price List'!$K$5:$K$74,MATCH(TRIM(J82)&"|"&TRIM(P82),'Price List'!$O$5:$O$74,0)),0) -> 0.12 | Y82: =W82*(1+X82) -> 0.8624 | Z82: =Q82*(V82+Y82) -> 468.76502
C83: Civil and Structure | D83: =IFERROR(IF(TRIM($G83)="Sub Structure",IF(TRIM($H83)="Bored Pile","B.01","B.03"),IF(TRIM($G83)="Super Structure","B.04",IF(OR(TRIM($G83)="Exterior Wall and Partition",TRIM($G83)="External Wall and Partition"),"C.01",IF(TRIM($G83)="Exterior Wall Finishes","C.02",IF(TRIM($G83)="Interior Wall and Partition","C.09",IF(TRIM($G83)="Interior Door","C.10",IF(TRIM($G83)="External Windows and Louvers","C.04",IF(OR(TRIM($G83)="Interior Floor Finishes",TRIM($G83)="Internal Floor Finishes"),"D.02",IF(OR(TRIM($G83)="Interior Wall Finishes",TRIM($G83)="Internal Wall Finishes"),"D.01",IF(OR(TRIM($G83)="Ceiling Finshes",TRIM($G83)="Ceiling Finishes"),"D.03",IF(TRIM($G83)="Fittings, furnishings and equipment","E.04","")))))))))))," ") -> B.04 | E83: BA | F83: 03.MZ | G83: Super Structure | H83: Structural Beam | I83: Rebar | J83: Deform Bar, DB10(fy=390 Mpa) | P83: kg | Q83: =R83 -> 2016.0933 | R83: ='mz beam'!J15 -> 2016.0933 | T83: =IFERROR(INDEX('Price List'!$G$5:$G$74,MATCH(TRIM(J83)&"|"&TRIM(P83),'Price List'!$O$5:$O$74,0)),0) -> 0.12 | U83: =IFERROR(INDEX('Price List'!$H$5:$H$74,MATCH(TRIM(J83)&"|"&TRIM(P83),'Price List'!$O$5:$O$74,0)),0) -> 0.2 | V83: =T83*(1+U83) -> 0.144 | W83: =IFERROR(INDEX('Price List'!$J$5:$J$74,MATCH(TRIM(J83)&"|"&TRIM(P83),'Price List'!$O$5:$O$74,0)),0) -> 0.78 | X83: =IFERROR(INDEX('Price List'!$K$5:$K$74,MATCH(TRIM(J83)&"|"&TRIM(P83),'Price List'!$O$5:$O$74,0)),0) -> 0.12 | Y83: =W83*(1+X83) -> 0.8736 | Z83: =Q83*(V83+Y83) -> 2051.5766
C84: Civil and Structure | D84: =IFERROR(IF(TRIM($G84)="Sub Structure",IF(TRIM($H84)="Bored Pile","B.01","B.03"),IF(TRIM($G84)="Super Structure","B.04",IF(OR(TRIM($G84)="Exterior Wall and Partition",TRIM($G84)="External Wall and Partition"),"C.01",IF(TRIM($G84)="Exterior Wall Finishes","C.02",IF(TRIM($G84)="Interior Wall and Partition","C.09",IF(TRIM($G84)="Interior Door","C.10",IF(TRIM($G84)="External Windows and Louvers","C.04",IF(OR(TRIM($G84)="Interior Floor Finishes",TRIM($G84)="Internal Floor Finishes"),"D.02",IF(OR(TRIM($G84)="Interior Wall Finishes",TRIM($G84)="Internal Wall Finishes"),"D.01",IF(OR(TRIM($G84)="Ceiling Finshes",TRIM($G84)="Ceiling Finishes"),"D.03",IF(TRIM($G84)="Fittings, furnishings and equipment","E.04","")))))))))))," ") -> B.04 | E84: BA | F84: 03.MZ | G84: Super Structure | H84: Structural Beam | I84: Rebar | J84: Deform Bar, DB12(fy=390 Mpa) | P84: kg | Q84: =R84 -> 281.1408 | R84: ='mz beam'!J16 -> 281.1408 | T84: =IFERROR(INDEX('Price List'!$G$5:$G$74,MATCH(TRIM(J84)&"|"&TRIM(P84),'Price List'!$O$5:$O$74,0)),0) -> 0.11 | U84: =IFERROR(INDEX('Price List'!$H$5:$H$74,MATCH(TRIM(J84)&"|"&TRIM(P84),'Price List'!$O$5:$O$74,0)),0) -> 0.2 | V84: =T84*(1+U84) -> 0.132 | W84: =IFERROR(INDEX('Price List'!$J$5:$J$74,MATCH(TRIM(J84)&"|"&TRIM(P84),'Price List'!$O$5:$O$74,0)),0) -> 0.76 | X84: =IFERROR(INDEX('Price List'!$K$5:$K$74,MATCH(TRIM(J84)&"|"&TRIM(P84),'Price List'!$O$5:$O$74,0)),0) -> 0.12 | Y84: =W84*(1+X84) -> 0.8512 | Z84: =Q84*(V84+Y84) -> 276.41763
C85: Civil and Structure | D85: =IFERROR(IF(TRIM($G85)="Sub Structure",IF(TRIM($H85)="Bored Pile","B.01","B.03"),IF(TRIM($G85)="Super Structure","B.04",IF(OR(TRIM($G85)="Exterior Wall and Partition",TRIM($G85)="External Wall and Partition"),"C.01",IF(TRIM($G85)="Exterior Wall Finishes","C.02",IF(TRIM($G85)="Interior Wall and Partition","C.09",IF(TRIM($G85)="Interior Door","C.10",IF(TRIM($G85)="External Windows and Louvers","C.04",IF(OR(TRIM($G85)="Interior Floor Finishes",TRIM($G85)="Internal Floor Finishes"),"D.02",IF(OR(TRIM($G85)="Interior Wall Finishes",TRIM($G85)="Internal Wall Finishes"),"D.01",IF(OR(TRIM($G85)="Ceiling Finshes",TRIM($G85)="Ceiling Finishes"),"D.03",IF(TRIM($G85)="Fittings, furnishings and equipment","E.04","")))))))))))," ") -> B.04 | E85: BA | F85: 03.MZ | G85: Super Structure | H85: Structural Beam | I85: Rebar | J85: Deform Bar, DB16(fy=390 Mpa) | P85: kg | Q85: =R85 -> 1600.7232 | R85: ='mz beam'!J17 -> 1600.7232 | T85: =IFERROR(INDEX('Price List'!$G$5:$G$74,MATCH(TRIM(J85)&"|"&TRIM(P85),'Price List'!$O$5:$O$74,0)),0) -> 0.1 | U85: =IFERROR(INDEX('Price List'!$H$5:$H$74,MATCH(TRIM(J85)&"|"&TRIM(P85),'Price List'!$O$5:$O$74,0)),0) -> 0.2 | V85: =T85*(1+U85) -> 0.12 | W85: =IFERROR(INDEX('Price List'!$J$5:$J$74,MATCH(TRIM(J85)&"|"&TRIM(P85),'Price List'!$O$5:$O$74,0)),0) -> 0.74 | X85: =IFERROR(INDEX('Price List'!$K$5:$K$74,MATCH(TRIM(J85)&"|"&TRIM(P85),'Price List'!$O$5:$O$74,0)),0) -> 0.12 | Y85: =W85*(1+X85) -> 0.8288 | Z85: =Q85*(V85+Y85) -> 1518.7662
