Workbook
Name _B001: 'Validation Lists'!$AP$5:$AP$11
Name _B002: 'Validation Lists'!$AQ$5:$AQ$10
Name _B003: 'Validation Lists'!$AR$5:$AR$16
Name _B004: 'Validation Lists'!$AS$5:$AS$9
Name _B005: 'Validation Lists'!$AT$5:$AT$15
Name _B006: 'Validation Lists'!$AU$5:$AU$15
Name _B007: 'Validation Lists'!$AV$5:$AV$11
Name _B008: 'Validation Lists'!$AW$5:$AW$14
Name _B009: 'Validation Lists'!$AX$5:$AX$15
Name _B010: 'Validation Lists'!$AY$5:$AY$15
Name _B011: 'Validation Lists'!$AZ$5:$AZ$12
Name _B012: 'Validation Lists'!$BA$5:$BA$13
Name _B013: 'Validation Lists'!$BB$5:$BB$10
Name _B014: 'Validation Lists'!$BC$5:$BC$8
Name _B015: 'Validation Lists'!$BD$5:$BD$10
Name _B016: 'Validation Lists'!$BE$5:$BE$9
Name _B017: 'Validation Lists'!$BF$5:$BF$8
Name _B018: 'Validation Lists'!$BG$5:$BG$8
Name _B019: 'Validation Lists'!$BH$5:$BH$9
Name _B020: 'Validation Lists'!$BI$5:$BI$8
Name _B021: 'Validation Lists'!$BJ$5:$BJ$18
Name _B022: 'Validation Lists'!$BK$5:$BK$12
Name _B023: 'Validation Lists'!$BL$5:$BL$8
Name _B024: 'Validation Lists'!$BM$5:$BM$9
Name _B025: 'Validation Lists'!$BN$5:$BN$7
Name _B026: 'Validation Lists'!$BO$5:$BO$7
Name _B027: 'Validation Lists'!$BP$5:$BP$6
Name _B028: 'Validation Lists'!$BQ$5:$BQ$8
Name _B029: 'Validation Lists'!$BR$5:$BR$7
Name _B030: 'Validation Lists'!$BS$5:$BS$7
Name _B031: 'Validation Lists'!$BT$5:$BT$6
Name _B032: 'Validation Lists'!$BU$5:$BU$6
Name _B033: 'Validation Lists'!$BV$5:$BV$6
Name _B034: 'Validation Lists'!$BW$5:$BW$6
Name _B035: 'Validation Lists'!$BX$5:$BX$6
Name _B036: 'Validation Lists'!$BY$5:$BY$6
Name _B037: 'Validation Lists'!$BZ$5:$BZ$8
Name _B038: 'Validation Lists'!$CA$5:$CA$8
Name _B039: 'Validation Lists'!$CB$5:$CB$6
Name _B040: 'Validation Lists'!$CC$5:$CC$8
Name _B041: 'Validation Lists'!$CD$5:$CD$6
Name _B042: 'Validation Lists'!$CE$5:$CE$6
Name _B043: 'Validation Lists'!$CF$5:$CF$6
Name _B044: 'Validation Lists'!$CG$5:$CG$7
Name _B045: 'Validation Lists'!$CH$5:$CH$8
Name _B046: 'Validation Lists'!$CI$5:$CI$7
Name _B047: 'Validation Lists'!$CJ$5:$CJ$8
Name _B048: 'Validation Lists'!$CK$5:$CK$8
Name _B049: 'Validation Lists'!$CL$5:$CL$8
Name _B050: 'Validation Lists'!$CM$5:$CM$8
Name _B051: 'Validation Lists'!$CN$5:$CN$6
Name _B052: 'Validation Lists'!$CO$5:$CO$8
Name _B053: 'Validation Lists'!$CP$5:$CP$6
Name _B054: 'Validation Lists'!$CQ$5:$CQ$6
Name _B055: 'Validation Lists'!$CR$5:$CR$7
Name _B056: 'Validation Lists'!$CS$5:$CS$6
Name _B057: 'Validation Lists'!$CT$5:$CT$5
Name _B058: 'Validation Lists'!$CU$5:$CU$6
Name _B059: 'Validation Lists'!$CV$5:$CV$6
Name _B060: 'Validation Lists'!$CW$5:$CW$9

Sheet Element Library
A1: QS ELEMENT LIBRARY — SECTION / SUB SECTION / SUB ELEMENT
A2: Standard coding list for BoQ takeoff — Structure, Architecture, MEP & External Works. Aligned to the project Budget Code framework.
A3: Each Sub Element links to one or more standard Descriptions on the Description Library sheet.
A5: No. | B5: Discipline | C5: Budget Code | D5: Section | E5: Sub Section | F5: Sub Element | G5: Typical Unit | H5: No. of Desc. | I5: Default Description | J5: Key
A6: 1 | B6: Civil and Structure | C6: A.04 | D6: Sub Structure | E6: Site Preparation & Earthwork | F6: Site Clearing | G6: m2 | H6: 1 | I6: Site clearing, grubbing and removal of vegetation and debris off site | J6: Sub Structure|Site Preparation & Earthwork|Site Clearing
A7: 2 | B7: Civil and Structure | C7: A.04 | D7: Sub Structure | E7: Site Preparation & Earthwork | F7: Excavation | G7: m3 | H7: 1 | I7: Bulk excavation by machine incl. trimming and levelling of formation | J7: Sub Structure|Site Preparation & Earthwork|Excavation
A8: 3 | B8: Civil and Structure | C8: A.04 | D8: Sub Structure | E8: Site Preparation & Earthwork | F8: Backfill | G8: m3 | H8: 1 | I8: Backfilling with approved material in 200mm layers incl. compaction to 95% MDD | J8: Sub Structure|Site Preparation & Earthwork|Backfill
A9: 4 | B9: Civil and Structure | C9: A.04 | D9: Sub Structure | E9: Site Preparation & Earthwork | F9: Soil Disposal | G9: m3 | H9: 1 | I9: Cart away surplus excavated material off site incl. tipping fee | J9: Sub Structure|Site Preparation & Earthwork|Soil Disposal
A10: 5 | B10: Civil and Structure | C10: A.04 | D10: Sub Structure | E10: Site Preparation & Earthwork | F10: Compaction | G10: m2 | H10: 1 | I10: Compaction of formation to 95% MDD incl. watering and testing | J10: Sub Structure|Site Preparation & Earthwork|Compaction
A11: 6 | B11: Civil and Structure | C11: A.04 | D11: Sub Structure | E11: Site Preparation & Earthwork | F11: Dewatering | G11: Lot | H11: 1 | I11: Dewatering incl. pumps, sump pits, piping and maintenance during construction | J11: Sub Structure|Site Preparation & Earthwork|Dewatering
A12: 7 | B12: Civil and Structure | C12: A.04 | D12: Sub Structure | E12: Site Preparation & Earthwork | F12: Levelling & Setting Out | G12: m2 | H12: 1 | I12: Setting out, levelling and establishment of benchmarks and grid lines | J12: Sub Structure|Site Preparation & Earthwork|Levelling & Setting Out
A13: 8 | B13: Civil and Structure | C13: B.02 | D13: Sub Structure | E13: Shoring & Sheet Pile | F13: Sheet Pile Supply | G13: m2 | H13: 1 | I13: Supply of steel sheet pile, hot rolled section as per design | J13: Sub Structure|Shoring & Sheet Pile|Sheet Pile Supply
A14: 9 | B14: Civil and Structure | C14: B.02 | D14: Sub Structure | E14: Shoring & Sheet Pile | F14: Sheet Pile Driving | G14: m2 | H14: 1 | I14: Driving of steel sheet pile to required depth incl. plant and equipment | J14: Sub Structure|Shoring & Sheet Pile|Sheet Pile Driving
A15: 10 | B15: Civil and Structure | C15: B.02 | D15: Sub Structure | E15: Shoring & Sheet Pile | F15: Sheet Pile Extraction | G15: m2 | H15: 1 | I15: Extraction of steel sheet pile and making good of voids | J15: Sub Structure|Shoring & Sheet Pile|Sheet Pile Extraction
A16: 11 | B16: Civil and Structure | C16: B.02 | D16: Sub Structure | E16: Shoring & Sheet Pile | F16: Strut & Waler | G16: kg | H16: 1 | I16: Steel strut and waler incl. fabrication, installation and removal | J16: Sub Structure|Shoring & Sheet Pile|Strut & Waler
A17: 12 | B17: Civil and Structure | C17: B.02 | D17: Sub Structure | E17: Shoring & Sheet Pile | F17: Ground Anchor | G17: Nos | H17: 1 | I17: Ground anchor incl. drilling, grouting, stressing and testing | J17: Sub Structure|Shoring & Sheet Pile|Ground Anchor
... A523: 518 | B523: External Works | C523: G.05 | D523: External Work | E523: External fixture | F523: Playground / sport court | G523: Lot | H523: 1 | I523: Playground / sport court incl. surfacing, marking and equipment | J523: External Work|External fixture|Playground / sport court

Sheet Description Library
A1: DESCRIPTION LIBRARY — STANDARD BoQ DESCRIPTIONS (MATERIAL TYPE)
A2: One or more standard descriptions per Sub Element. Units are synchronised with the Price List Library.
A3: Copy the Description into the Material Type column of Raw Data. Edit sizes / grades to match the specification before pricing.
A5: No. | B5: Discipline | C5: Budget Code | D5: Section | E5: Sub Section | F5: Sub Element | G5: Description (Material Type) | H5: Unit | I5: Rate Status | J5: Total Rate ($) | K5: Key
A6: 1 | B6: Civil and Structure | C6: A.04 | D6: Sub Structure | E6: Site Preparation & Earthwork | F6: Site Clearing | G6: Site clearing, grubbing and removal of vegetation and debris off site | H6: m2 | I6: =IFERROR(INDEX('Price List Library'!$P$6:$P$437,MATCH(TRIM($G6)&"|"&TRIM($H6),'Price List Library'!$S$6:$S$437,0)),"") -> Benchmark | J6: =IFERROR(INDEX('Price List Library'!$O$6:$O$437,MATCH(TRIM($G6)&"|"&TRIM($H6),'Price List Library'!$S$6:$S$437,0)),0) -> 0.828 | K6: Sub Structure|Site Preparation & Earthwork|Site Clearing|Site clearing, grubbing and removal of vegetation and debris off site
A7: 2 | B7: Civil and Structure | C7: A.04 | D7: Sub Structure | E7: Site Preparation & Earthwork | F7: Excavation | G7: Bulk excavation by machine incl. trimming and levelling of formation | H7: m3 | I7: =IFERROR(INDEX('Price List Library'!$P$6:$P$437,MATCH(TRIM($G7)&"|"&TRIM($H7),'Price List Library'!$S$6:$S$437,0)),"") -> Benchmark | J7: =IFERROR(INDEX('Price List Library'!$O$6:$O$437,MATCH(TRIM($G7)&"|"&TRIM($H7),'Price List Library'!$S$6:$S$437,0)),0) -> 3.448 | K7: Sub Structure|Site Preparation & Earthwork|Excavation|Bulk excavation by machine incl. trimming and levelling of formation
A8: 3 | B8: Civil and Structure | C8: A.04 | D8: Sub Structure | E8: Site Preparation & Earthwork | F8: Backfill | G8: Backfilling with approved material in 200mm layers incl. compaction to 95% MDD | H8: m3 | I8: =IFERROR(INDEX('Price List Library'!$P$6:$P$437,MATCH(TRIM($G8)&"|"&TRIM($H8),'Price List Library'!$S$6:$S$437,0)),"") -> Benchmark | J8: =IFERROR(INDEX('Price List Library'!$O$6:$O$437,MATCH(TRIM($G8)&"|"&TRIM($H8),'Price List Library'!$S$6:$S$437,0)),0) -> 4.848 | K8: Sub Structure|Site Preparation & Earthwork|Backfill|Backfilling with approved material in 200mm layers incl. compaction to 95% MDD
A9: 4 | B9: Civil and Structure | C9: A.04 | D9: Sub Structure | E9: Site Preparation & Earthwork | F9: Soil Disposal | G9: Cart away surplus excavated material off site incl. tipping fee | H9: m3 | I9: =IFERROR(INDEX('Price List Library'!$P$6:$P$437,MATCH(TRIM($G9)&"|"&TRIM($H9),'Price List Library'!$S$6:$S$437,0)),"") -> Benchmark | J9: =IFERROR(INDEX('Price List Library'!$O$6:$O$437,MATCH(TRIM($G9)&"|"&TRIM($H9),'Price List Library'!$S$6:$S$437,0)),0) -> 4.864 | K9: Sub Structure|Site Preparation & Earthwork|Soil Disposal|Cart away surplus excavated material off site incl. tipping fee
A10: 5 | B10: Civil and Structure | C10: A.04 | D10: Sub Structure | E10: Site Preparation & Earthwork | F10: Compaction | G10: Compaction of formation to 95% MDD incl. watering and testing | H10: m2 | I10: =IFERROR(INDEX('Price List Library'!$P$6:$P$437,MATCH(TRIM($G10)&"|"&TRIM($H10),'Price List Library'!$S$6:$S$437,0)),"") -> Benchmark | J10: =IFERROR(INDEX('Price List Library'!$O$6:$O$437,MATCH(TRIM($G10)&"|"&TRIM($H10),'Price List Library'!$S$6:$S$437,0)),0) -> 1.6 | K10: Sub Structure|Site Preparation & Earthwork|Compaction|Compaction of formation to 95% MDD incl. watering and testing
A11: 6 | B11: Civil and Structure | C11: A.04 | D11: Sub Structure | E11: Site Preparation & Earthwork | F11: Dewatering | G11: Dewatering incl. pumps, sump pits, piping and maintenance during construction | H11: Lot | I11: =IFERROR(INDEX('Price List Library'!$P$6:$P$437,MATCH(TRIM($G11)&"|"&TRIM($H11),'Price List Library'!$S$6:$S$437,0)),"") -> Benchmark | J11: =IFERROR(INDEX('Price List Library'!$O$6:$O$437,MATCH(TRIM($G11)&"|"&TRIM($H11),'Price List Library'!$S$6:$S$437,0)),0) -> 3504 | K11: Sub Structure|Site Preparation & Earthwork|Dewatering|Dewatering incl. pumps, sump pits, piping and maintenance during construction
A12: 7 | B12: Civil and Structure | C12: A.04 | D12: Sub Structure | E12: Site Preparation & Earthwork | F12: Levelling & Setting Out | G12: Setting out, levelling and establishment of benchmarks and grid lines | H12: m2 | I12: =IFERROR(INDEX('Price List Library'!$P$6:$P$437,MATCH(TRIM($G12)&"|"&TRIM($H12),'Price List Library'!$S$6:$S$437,0)),"") -> Benchmark | J12: =IFERROR(INDEX('Price List Library'!$O$6:$O$437,MATCH(TRIM($G12)&"|"&TRIM($H12),'Price List Library'!$S$6:$S$437,0)),0) -> 1.008 | K12: Sub Structure|Site Preparation & Earthwork|Levelling & Setting Out|Setting out, levelling and establishment of benchmarks and grid lines
A13: 8 | B13: Civil and Structure | C13: B.02 | D13: Sub Structure | E13: Shoring & Sheet Pile | F13: Sheet Pile Supply | G13: Supply of steel sheet pile, hot rolled section as per design | H13: m2 | I13: =IFERROR(INDEX('Price List Library'!$P$6:$P$437,MATCH(TRIM($G13)&"|"&TRIM($H13),'Price List Library'!$S$6:$S$437,0)),"") -> Benchmark | J13: =IFERROR(INDEX('Price List Library'!$O$6:$O$437,MATCH(TRIM($G13)&"|"&TRIM($H13),'Price List Library'!$S$6:$S$437,0)),0) -> 64.96 | K13: Sub Structure|Shoring & Sheet Pile|Sheet Pile Supply|Supply of steel sheet pile, hot rolled section as per design
A14: 9 | B14: Civil and Structure | C14: B.02 | D14: Sub Structure | E14: Shoring & Sheet Pile | F14: Sheet Pile Driving | G14: Driving of steel sheet pile to required depth incl. plant and equipment | H14: m2 | I14: =IFERROR(INDEX('Price List Library'!$P$6:$P$437,MATCH(TRIM($G14)&"|"&TRIM($H14),'Price List Library'!$S$6:$S$437,0)),"") -> Benchmark | J14: =IFERROR(INDEX('Price List Library'!$O$6:$O$437,MATCH(TRIM($G14)&"|"&TRIM($H14),'Price List Library'!$S$6:$S$437,0)),0) -> 23.52 | K14: Sub Structure|Shoring & Sheet Pile|Sheet Pile Driving|Driving of steel sheet pile to required depth incl. plant and equipment
A15: 10 | B15: Civil and Structure | C15: B.02 | D15: Sub Structure | E15: Shoring & Sheet Pile | F15: Sheet Pile Extraction | G15: Extraction of steel sheet pile and making good of voids | H15: m2 | I15: =IFERROR(INDEX('Price List Library'!$P$6:$P$437,MATCH(TRIM($G15)&"|"&TRIM($H15),'Price List Library'!$S$6:$S$437,0)),"") -> Benchmark | J15: =IFERROR(INDEX('Price List Library'!$O$6:$O$437,MATCH(TRIM($G15)&"|"&TRIM($H15),'Price List Library'!$S$6:$S$437,0)),0) -> 14.16 | K15: Sub Structure|Shoring & Sheet Pile|Sheet Pile Extraction|Extraction of steel sheet pile and making good of voids
A16: 11 | B16: Civil and Structure | C16: B.02 | D16: Sub Structure | E16: Shoring & Sheet Pile | F16: Strut & Waler | G16: Steel strut and waler incl. fabrication, installation and removal | H16: kg | I16: =IFERROR(INDEX('Price List Library'!$P$6:$P$437,MATCH(TRIM($G16)&"|"&TRIM($H16),'Price List Library'!$S$6:$S$437,0)),"") -> Benchmark | J16: =IFERROR(INDEX('Price List Library'!$O$6:$O$437,MATCH(TRIM($G16)&"|"&TRIM($H16),'Price List Library'!$S$6:$S$437,0)),0) -> 1.648 | K16: Sub Structure|Shoring & Sheet Pile|Strut & Waler|Steel strut and waler incl. fabrication, installation and removal
A17: 12 | B17: Civil and Structure | C17: B.02 | D17: Sub Structure | E17: Shoring & Sheet Pile | F17: Ground Anchor | G17: Ground anchor incl. drilling, grouting, stressing and testing | H17: Nos | I17: =IFERROR(INDEX('Price List Library'!$P$6:$P$437,MATCH(TRIM($G17)&"|"&TRIM($H17),'Price List Library'!$S$6:$S$437,0)),"") -> Benchmark | J17: =IFERROR(INDEX('Price List Library'!$O$6:$O$437,MATCH(TRIM($G17)&"|"&TRIM($H17),'Price List Library'!$S$6:$S$437,0)),0) -> 528 | K17: Sub Structure|Shoring & Sheet Pile|Ground Anchor|Ground anchor incl. drilling, grouting, stressing and testing
... A808: 803 | B808: Architecture | C808: D.01 | D808: Interior Wall Finishes | E808: Toilet Wall tile | F808: Toilet Wall tile | G808: tile size (300x600)mm | H808: m2 | I808: =IFERROR(INDEX('Price List Library'!$P$6:$P$437,MATCH(TRIM($G808)&"|"&TRIM($H808),'Price List Library'!$S$6:$S$437,0)),"") -> Priced | J808: =IFERROR(INDEX('Price List Library'!$O$6:$O$437,MATCH(TRIM($G808)&"|"&TRIM($H808),'Price List Library'!$S$6:$S$437,0)),0) -> 18.4 | K808: Interior Wall Finishes|Toilet Wall tile|Toilet Wall tile|tile size (300x600)mm

Sheet Price List Library
A1: PRICE LIST LIBRARY — LABOR / MATERIAL RATE BUILD-UP
A2: STANDARD LABOR MARGIN | C2: 0.2 | E2: Change these two cells to re-margin the whole library at once. Rate = Net Cost x (1 + Margin %).
A3: STANDARD MATERIAL MARGIN | C3: 0.12 | E3: Status: "Priced" = rate from your project Price List. "Benchmark" = Cambodia market estimate — obtain 3 quotations before submission.
I4: LABOR | L4: MATERIAL / SUPPLY & FIX
A5: Item Code | B5: Discipline | C5: Budget Code | D5: Section | E5: Sub Section | F5: Sub Element | G5: Description (Material Type) | H5: Unit | I5: Labor Net Cost ($) | J5: Labor Margin (%) | K5: Labor Rate ($) | L5: Material Net Cost ($) | M5: Material Margin (%) | N5: Material Rate ($) | O5: Total Rate ($) | P5: Status | Q5: Used in | R5: Basis / Source | S5: MatchKey | T5: src
A6: PL-001 | B6: Civil and Structure | C6: A.04 | D6: Sub Structure | E6: Site Preparation & Earthwork | F6: Site Clearing | G6: Site clearing, grubbing and removal of vegetation and debris off site | H6: m2 | I6: 0.55 | J6: =_STDLAB -> 0.2 | K6: =IFERROR(I6*(1+J6),0) -> 0.66 | L6: 0.15 | M6: =_STDMAT -> 0.12 | N6: =IFERROR(L6*(1+M6),0) -> 0.168 | O6: =K6+N6 -> 0.828 | P6: =IF(N(I6)+N(L6)=0,"To be quoted",IF($T6="P","Priced","Benchmark")) -> Benchmark | Q6: 1 | R6: BENCHMARK (CAM market) — Clear/grub by machine; CAM labour+plant | S6: =TRIM(G6)&"|"&TRIM(H6) -> Site clearing, grubbing and removal of vegetation and debris off site|m2 | T6: B
A7: PL-002 | B7: Civil and Structure | C7: A.04 | D7: Sub Structure | E7: Site Preparation & Earthwork | F7: Excavation | G7: Bulk excavation by machine incl. trimming and levelling of formation | H7: m3 | I7: 2.5 | J7: =_STDLAB -> 0.2 | K7: =IFERROR(I7*(1+J7),0) -> 3 | L7: 0.4 | M7: =_STDMAT -> 0.12 | N7: =IFERROR(L7*(1+M7),0) -> 0.448 | O7: =K7+N7 -> 3.448 | P7: =IF(N(I7)+N(L7)=0,"To be quoted",IF($T7="P","Priced","Benchmark")) -> Benchmark | Q7: 1 | R7: BENCHMARK (CAM market) — Machine excavation; PP plant hire benchmark | S7: =TRIM(G7)&"|"&TRIM(H7) -> Bulk excavation by machine incl. trimming and levelling of formation|m3 | T7: B
A8: PL-003 | B8: Civil and Structure | C8: A.04 | D8: Sub Structure | E8: Site Preparation & Earthwork | F8: Backfill | G8: Backfilling with approved material in 200mm layers incl. compaction to 95% MDD | H8: m3 | I8: 3.2 | J8: =_STDLAB -> 0.2 | K8: =IFERROR(I8*(1+J8),0) -> 3.84 | L8: 0.9 | M8: =_STDMAT -> 0.12 | N8: =IFERROR(L8*(1+M8),0) -> 1.008 | O8: =K8+N8 -> 4.848 | P8: =IF(N(I8)+N(L8)=0,"To be quoted",IF($T8="P","Priced","Benchmark")) -> Benchmark | Q8: 1 | R8: BENCHMARK (CAM market) — Layered fill + compaction | S8: =TRIM(G8)&"|"&TRIM(H8) -> Backfilling with approved material in 200mm layers incl. compaction to 95% MDD|m3 | T8: B
A9: PL-004 | B9: Civil and Structure | C9: A.04 | D9: Sub Structure | E9: Site Preparation & Earthwork | F9: Soil Disposal | G9: Cart away surplus excavated material off site incl. tipping fee | H9: m3 | I9: 3.4 | J9: =_STDLAB -> 0.2 | K9: =IFERROR(I9*(1+J9),0) -> 4.08 | L9: 0.7 | M9: =_STDMAT -> 0.12 | N9: =IFERROR(L9*(1+M9),0) -> 0.784 | O9: =K9+N9 -> 4.864 | P9: =IF(N(I9)+N(L9)=0,"To be quoted",IF($T9="P","Priced","Benchmark")) -> Benchmark | Q9: 1 | R9: BENCHMARK (CAM market) — Haul 15-25km + tipping | S9: =TRIM(G9)&"|"&TRIM(H9) -> Cart away surplus excavated material off site incl. tipping fee|m3 | T9: B
A10: PL-005 | B10: Civil and Structure | C10: A.04 | D10: Sub Structure | E10: Site Preparation & Earthwork | F10: Compaction | G10: Compaction of formation to 95% MDD incl. watering and testing | H10: m2 | I10: 1.1 | J10: =_STDLAB -> 0.2 | K10: =IFERROR(I10*(1+J10),0) -> 1.32 | L10: 0.25 | M10: =_STDMAT -> 0.12 | N10: =IFERROR(L10*(1+M10),0) -> 0.28 | O10: =K10+N10 -> 1.6 | P10: =IF(N(I10)+N(L10)=0,"To be quoted",IF($T10="P","Priced","Benchmark")) -> Benchmark | Q10: 2 | R10: BENCHMARK (CAM market) — Roller compaction to 95% MDD | S10: =TRIM(G10)&"|"&TRIM(H10) -> Compaction of formation to 95% MDD incl. watering and testing|m2 | T10: B
A11: PL-006 | B11: Civil and Structure | C11: A.04 | D11: Sub Structure | E11: Site Preparation & Earthwork | F11: Dewatering | G11: Dewatering incl. pumps, sump pits, piping and maintenance during construction | H11: Lot | I11: 1800 | J11: =_STDLAB -> 0.2 | K11: =IFERROR(I11*(1+J11),0) -> 2160 | L11: 1200 | M11: =_STDMAT -> 0.12 | N11: =IFERROR(L11*(1+M11),0) -> 1344 | O11: =K11+N11 -> 3504 | P11: =IF(N(I11)+N(L11)=0,"To be quoted",IF($T11="P","Priced","Benchmark")) -> Benchmark | Q11: 1 | R11: BENCHMARK (CAM market) — Pump, sump, piping for programme duration | S11: =TRIM(G11)&"|"&TRIM(H11) -> Dewatering incl. pumps, sump pits, piping and maintenance during construction|Lot | T11: B
A12: PL-007 | B12: Civil and Structure | C12: A.04 | D12: Sub Structure | E12: Site Preparation & Earthwork | F12: Levelling & Setting Out | G12: Setting out, levelling and establishment of benchmarks and grid lines | H12: m2 | I12: 0.7 | J12: =_STDLAB -> 0.2 | K12: =IFERROR(I12*(1+J12),0) -> 0.84 | L12: 0.15 | M12: =_STDMAT -> 0.12 | N12: =IFERROR(L12*(1+M12),0) -> 0.168 | O12: =K12+N12 -> 1.008 | P12: =IF(N(I12)+N(L12)=0,"To be quoted",IF($T12="P","Priced","Benchmark")) -> Benchmark | Q12: 1 | R12: BENCHMARK (CAM market) — Survey team + instrument | S12: =TRIM(G12)&"|"&TRIM(H12) -> Setting out, levelling and establishment of benchmarks and grid lines|m2 | T12: B
A13: PL-008 | B13: Civil and Structure | C13: B.02 | D13: Sub Structure | E13: Shoring & Sheet Pile | F13: Sheet Pile Supply | G13: Supply of steel sheet pile, hot rolled section as per design | H13: m2 | I13: 0 | J13: =_STDLAB -> 0.2 | K13: =IFERROR(I13*(1+J13),0) -> 0 | L13: 58 | M13: =_STDMAT -> 0.12 | N13: =IFERROR(L13*(1+M13),0) -> 64.96 | O13: =K13+N13 -> 64.96 | P13: =IF(N(I13)+N(L13)=0,"To be quoted",IF($T13="P","Priced","Benchmark")) -> Benchmark | Q13: 1 | R13: BENCHMARK (CAM market) — Hot rolled sheet pile ~$780/t delivered | S13: =TRIM(G13)&"|"&TRIM(H13) -> Supply of steel sheet pile, hot rolled section as per design|m2 | T13: B
A14: PL-009 | B14: Civil and Structure | C14: B.02 | D14: Sub Structure | E14: Shoring & Sheet Pile | F14: Sheet Pile Driving | G14: Driving of steel sheet pile to required depth incl. plant and equipment | H14: m2 | I14: 14 | J14: =_STDLAB -> 0.2 | K14: =IFERROR(I14*(1+J14),0) -> 16.8 | L14: 6 | M14: =_STDMAT -> 0.12 | N14: =IFERROR(L14*(1+M14),0) -> 6.72 | O14: =K14+N14 -> 23.52 | P14: =IF(N(I14)+N(L14)=0,"To be quoted",IF($T14="P","Priced","Benchmark")) -> Benchmark | Q14: 1 | R14: BENCHMARK (CAM market) — Vibro hammer + crane | S14: =TRIM(G14)&"|"&TRIM(H14) -> Driving of steel sheet pile to required depth incl. plant and equipment|m2 | T14: B
A15: PL-010 | B15: Civil and Structure | C15: B.02 | D15: Sub Structure | E15: Shoring & Sheet Pile | F15: Sheet Pile Extraction | G15: Extraction of steel sheet pile and making good of voids | H15: m2 | I15: 9 | J15: =_STDLAB -> 0.2 | K15: =IFERROR(I15*(1+J15),0) -> 10.8 | L15: 3 | M15: =_STDMAT -> 0.12 | N15: =IFERROR(L15*(1+M15),0) -> 3.36 | O15: =K15+N15 -> 14.16 | P15: =IF(N(I15)+N(L15)=0,"To be quoted",IF($T15="P","Priced","Benchmark")) -> Benchmark | Q15: 1 | R15: BENCHMARK (CAM market) — Extraction + void grouting | S15: =TRIM(G15)&"|"&TRIM(H15) -> Extraction of steel sheet pile and making good of voids|m2 | T15: B
A16: PL-011 | B16: Civil and Structure | C16: B.02 | D16: Sub Structure | E16: Shoring & Sheet Pile | F16: Strut & Waler | G16: Steel strut and waler incl. fabrication, installation and removal | H16: kg | I16: 0.3 | J16: =_STDLAB -> 0.2 | K16: =IFERROR(I16*(1+J16),0) -> 0.36 | L16: 1.15 | M16: =_STDMAT -> 0.12 | N16: =IFERROR(L16*(1+M16),0) -> 1.288 | O16: =K16+N16 -> 1.648 | P16: =IF(N(I16)+N(L16)=0,"To be quoted",IF($T16="P","Priced","Benchmark")) -> Benchmark | Q16: 1 | R16: BENCHMARK (CAM market) — Fabricated section, install + remove | S16: =TRIM(G16)&"|"&TRIM(H16) -> Steel strut and waler incl. fabrication, installation and removal|kg | T16: B
A17: PL-012 | B17: Civil and Structure | C17: B.02 | D17: Sub Structure | E17: Shoring & Sheet Pile | F17: Ground Anchor | G17: Ground anchor incl. drilling, grouting, stressing and testing | H17: Nos | I17: 160 | J17: =_STDLAB -> 0.2 | K17: =IFERROR(I17*(1+J17),0) -> 192 | L17: 300 | M17: =_STDMAT -> 0.12 | N17: =IFERROR(L17*(1+M17),0) -> 336 | O17: =K17+N17 -> 528 | P17: =IF(N(I17)+N(L17)=0,"To be quoted",IF($T17="P","Priced","Benchmark")) -> Benchmark | Q17: 1 | R17: BENCHMARK (CAM market) — Drill, grout, stress, test | S17: =TRIM(G17)&"|"&TRIM(H17) -> Ground anchor incl. drilling, grouting, stressing and testing|Nos | T17: B
... A20: PL-015 | B20: Civil and Structure | C20: B.01 | D20: Sub Structure | E20: Bored Pile | F20: Bored Pile Boring | G20: Bored piling D800mm incl. boring, casing and disposal of spoil | H20: m | I20: 20 | J20: =_STDLAB -> 0.2 | K20: =IFERROR(I20*(1+J20),0) -> 24 | L20: 13 | M20: =_STDMAT -> 0.12 | N20: =IFERROR(L20*(1+M20),0) -> 14.56 | O20: =K20+N20 -> 38.56 | P20: =IF(N(I20)+N(L20)=0,"To be quoted",IF($T20="P","Priced","Benchmark")) -> Benchmark | Q20: 1 | R20: BENCHMARK (CAM market) — Rig, casing, spoil removal D800 | S20: =TRIM(G20)&"|"&TRIM(H20) -> Bored piling D800mm incl. boring, casing and disposal of spoil|m | T20: B
A21: PL-016 | B21: Civil and Structure | C21: B.01 | D21: Sub Structure | E21: Bored Pile | F21: Concrete | G21: Normal Concrete, 35Mpa (Cylinder), Slump 13+-2.5 | H21: m3 | I21: 10 | J21: 0.2 | K21: =IFERROR(I21*(1+J21),0) -> 12 | L21: 98 | M21: 0.12 | N21: =IFERROR(L21*(1+M21),0) -> 109.76 | O21: =K21+N21 -> 121.76 | P21: =IF(N(I21)+N(L21)=0,"To be quoted",IF($T21="P","Priced","Benchmark")) -> Priced | Q21: 17 | R21: Ready-mix C35/30 +pump; CPAC list escalated 2026 | S21: =TRIM(G21)&"|"&TRIM(H21) -> Normal Concrete, 35Mpa (Cylinder), Slump 13+-2.5|m3 | T21: P
A22: PL-017 | B22: Civil and Structure | C22: B.01 | D22: Sub Structure | E22: Bored Pile | F22: Concrete | G22: Normal Concrete, 35Mpa (Cylinder), Slump 15+-2.5 | H22: m3 | I22: 8 | J22: 0.2 | K22: =IFERROR(I22*(1+J22),0) -> 9.6 | L22: 98 | M22: 0.12 | N22: =IFERROR(L22*(1+M22),0) -> 109.76 | O22: =K22+N22 -> 119.36 | P22: =IF(N(I22)+N(L22)=0,"To be quoted",IF($T22="P","Priced","Benchmark")) -> Priced | Q22: 17 | R22: Ready-mix C35/30 +pump; CPAC list escalated 2026 | S22: =TRIM(G22)&"|"&TRIM(H22) -> Normal Concrete, 35Mpa (Cylinder), Slump 15+-2.5|m3 | T22: P
A23: PL-018 | B23: Civil and Structure | C23: B.01 | D23: Sub Structure | E23: Bored Pile | F23: Concrete | G23: Normal Concrete, 25Mpa (Cylinder), Slump 10+-2.5 | H23: m3 | I23: 8 | J23: =_STDLAB -> 0.2 | K23: =IFERROR(I23*(1+J23),0) -> 9.6 | L23: 88 | M23: =_STDMAT -> 0.12 | N23: =IFERROR(L23*(1+M23),0) -> 98.56 | O23: =K23+N23 -> 108.16 | P23: =IF(N(I23)+N(L23)=0,"To be quoted",IF($T23="P","Priced","Benchmark")) -> Benchmark | Q23: 17 | R23: BENCHMARK (CAM market) — Ready-mix C25 PP delivered | S23: =TRIM(G23)&"|"&TRIM(H23) -> Normal Concrete, 25Mpa (Cylinder), Slump 10+-2.5|m3 | T23: B
A24: PL-019 | B24: Civil and Structure | C24: B.01 | D24: Sub Structure | E24: Bored Pile | F24: Concrete | G24: Normal Concrete, 30Mpa (Cylinder), Slump 13+-2.5 | H24: m3 | I24: 9 | J24: =_STDLAB -> 0.2 | K24: =IFERROR(I24*(1+J24),0) -> 10.8 | L24: 93 | M24: =_STDMAT -> 0.12 | N24: =IFERROR(L24*(1+M24),0) -> 104.16 | O24: =K24+N24 -> 114.96 | P24: =IF(N(I24)+N(L24)=0,"To be quoted",IF($T24="P","Priced","Benchmark")) -> Benchmark | Q24: 17 | R24: BENCHMARK (CAM market) — Ready-mix C30 PP delivered | S24: =TRIM(G24)&"|"&TRIM(H24) -> Normal Concrete, 30Mpa (Cylinder), Slump 13+-2.5|m3 | T24: B
A25: PL-020 | B25: Civil and Structure | C25: B.01 | D25: Sub Structure | E25: Bored Pile | F25: Rebar | G25: Deform Bar, DB10(fy=390 Mpa) | H25: kg | I25: 0.12 | J25: 0.2 | K25: =IFERROR(I25*(1+J25),0) -> 0.144 | L25: 0.78 | M25: 0.12 | N25: =IFERROR(L25*(1+M25),0) -> 0.8736 | O25: =K25+N25 -> 1.0176 | P25: =IF(N(I25)+N(L25)=0,"To be quoted",IF($T25="P","Priced","Benchmark")) -> Priced | Q25: 17 | R25: Deformed bar ~$720/t; small dia +labour | S25: =TRIM(G25)&"|"&TRIM(H25) -> Deform Bar, DB10(fy=390 Mpa)|kg | T25: P
A26: PL-021 | B26: Civil and Structure | C26: B.01 | D26: Sub Structure | E26: Bored Pile | F26: Rebar | G26: Deform Bar, DB12(fy=390 Mpa) | H26: kg | I26: 0.11 | J26: 0.2 | K26: =IFERROR(I26*(1+J26),0) -> 0.132 | L26: 0.76 | M26: 0.12 | N26: =IFERROR(L26*(1+M26),0) -> 0.8512 | O26: =K26+N26 -> 0.9832 | P26: =IF(N(I26)+N(L26)=0,"To be quoted",IF($T26="P","Priced","Benchmark")) -> Priced | Q26: 17 | R26: Deformed bar ~$720/t | S26: =TRIM(G26)&"|"&TRIM(H26) -> Deform Bar, DB12(fy=390 Mpa)|kg | T26: P
A27: PL-022 | B27: Civil and Structure | C27: B.01 | D27: Sub Structure | E27: Bored Pile | F27: Rebar | G27: Deform Bar, DB14(fy=390 Mpa) | H27: kg | I27: 0.1 | J27: 0.2 | K27: =IFERROR(I27*(1+J27),0) -> 0.12 | L27: 0.75 | M27: 0.12 | N27: =IFERROR(L27*(1+M27),0) -> 0.84 | O27: =K27+N27 -> 0.96 | P27: =IF(N(I27)+N(L27)=0,"To be quoted",IF($T27="P","Priced","Benchmark")) -> Priced | Q27: 17 | R27: Deformed bar ~$720/t | S27: =TRIM(G27)&"|"&TRIM(H27) -> Deform Bar, DB14(fy=390 Mpa)|kg | T27: P
A28: PL-023 | B28: Civil and Structure | C28: B.01 | D28: Sub Structure | E28: Bored Pile | F28: Rebar | G28: Deform Bar, DB16(fy=390 Mpa) | H28: kg | I28: 0.1 | J28: 0.2 | K28: =IFERROR(I28*(1+J28),0) -> 0.12 | L28: 0.74 | M28: 0.12 | N28: =IFERROR(L28*(1+M28),0) -> 0.8288 | O28: =K28+N28 -> 0.9488 | P28: =IF(N(I28)+N(L28)=0,"To be quoted",IF($T28="P","Priced","Benchmark")) -> Priced | Q28: 17 | R28: Deformed bar ~$720/t | S28: =TRIM(G28)&"|"&TRIM(H28) -> Deform Bar, DB16(fy=390 Mpa)|kg | T28: P
A29: PL-024 | B29: Civil and Structure | C29: B.01 | D29: Sub Structure | E29: Bored Pile | F29: Rebar | G29: Deform Bar, DB20(fy=390 Mpa) | H29: kg | I29: 0.09 | J29: 0.2 | K29: =IFERROR(I29*(1+J29),0) -> 0.108 | L29: 0.73 | M29: 0.12 | N29: =IFERROR(L29*(1+M29),0) -> 0.8176 | O29: =K29+N29 -> 0.9256 | P29: =IF(N(I29)+N(L29)=0,"To be quoted",IF($T29="P","Priced","Benchmark")) -> Priced | Q29: 17 | R29: Deformed bar ~$720/t | S29: =TRIM(G29)&"|"&TRIM(H29) -> Deform Bar, DB20(fy=390 Mpa)|kg | T29: P
A30: PL-025 | B30: Civil and Structure | C30: B.01 | D30: Sub Structure | E30: Bored Pile | F30: Rebar | G30: Deform Bar, DB25(fy=390 Mpa) | H30: kg | I30: 0.08 | J30: 0.2 | K30: =IFERROR(I30*(1+J30),0) -> 0.096 | L30: 0.72 | M30: 0.12 | N30: =IFERROR(L30*(1+M30),0) -> 0.8064 | O30: =K30+N30 -> 0.9024 | P30: =IF(N(I30)+N(L30)=0,"To be quoted",IF($T30="P","Priced","Benchmark")) -> Priced | Q30: 17 | R30: Deformed bar ~$720/t (large dia) | S30: =TRIM(G30)&"|"&TRIM(H30) -> Deform Bar, DB25(fy=390 Mpa)|kg | T30: P
A31: PL-026 | B31: Civil and Structure | C31: B.01 | D31: Sub Structure | E31: Bored Pile | F31: Rebar | G31: Deform Bar, DB32(fy=390 Mpa) | H31: kg | I31: 0.08 | J31: 0.2 | K31: =IFERROR(I31*(1+J31),0) -> 0.096 | L31: 0.71 | M31: 0.12 | N31: =IFERROR(L31*(1+M31),0) -> 0.7952 | O31: =K31+N31 -> 0.8912 | P31: =IF(N(I31)+N(L31)=0,"To be quoted",IF($T31="P","Priced","Benchmark")) -> Priced | Q31: 17 | R31: Deformed bar ~$720/t (large dia) | S31: =TRIM(G31)&"|"&TRIM(H31) -> Deform Bar, DB32(fy=390 Mpa)|kg | T31: P
A32: PL-027 | B32: Civil and Structure | C32: B.01 | D32: Sub Structure | E32: Bored Pile | F32: Rebar | G32: Round Bar, RB8(fy=250 Mpa) | H32: kg | I32: 0.12 | J32: 0.2 | K32: =IFERROR(I32*(1+J32),0) -> 0.144 | L32: 0.77 | M32: 0.12 | N32: =IFERROR(L32*(1+M32),0) -> 0.8624 | O32: =K32+N32 -> 1.0064 | P32: =IF(N(I32)+N(L32)=0,"To be quoted",IF($T32="P","Priced","Benchmark")) -> Priced | Q32: 17 | R32: Round mild bar ~$770/t | S32: =TRIM(G32)&"|"&TRIM(H32) -> Round Bar, RB8(fy=250 Mpa)|kg | T32: P
A33: PL-028 | B33: Civil and Structure | C33: B.01 | D33: Sub Structure | E33: Bored Pile | F33: Rebar | G33: Round Bar, RB6(fy=250 Mpa) | H33: kg | I33: 0.13 | J33: =_STDLAB -> 0.2 | K33: =IFERROR(I33*(1+J33),0) -> 0.156 | L33: 0.78 | M33: =_STDMAT -> 0.12 | N33: =IFERROR(L33*(1+M33),0) -> 0.8736 | O33: =K33+N33 -> 1.0296 | P33: =IF(N(I33)+N(L33)=0,"To be quoted",IF($T33="P","Priced","Benchmark")) -> Benchmark | Q33: 17 | R33: BENCHMARK (CAM market) — Mild round bar ~$780/t | S33: =TRIM(G33)&"|"&TRIM(H33) -> Round Bar, RB6(fy=250 Mpa)|kg | T33: B
A34: PL-029 | B34: Civil and Structure | C34: B.01 | D34: Sub Structure | E34: Bored Pile | F34: Steel Tie Wire | G34: Steel Tie Wire 1mm (Estimated 4% of Total Rebar Weight) | H34: kg | I34: 0.05 | J34: 0.2 | K34: =IFERROR(I34*(1+J34),0) -> 0.06 | L34: 1.2 | M34: 0.12 | N34: =IFERROR(L34*(1+M34),0) -> 1.344 | O34: =K34+N34 -> 1.404 | P34: =IF(N(I34)+N(L34)=0,"To be quoted",IF($T34="P","Priced","Benchmark")) -> Priced | Q34: 17 | R34: Annealed tie wire ~$1.2/kg | S34: =TRIM(G34)&"|"&TRIM(H34) -> Steel Tie Wire 1mm (Estimated 4% of Total Rebar Weight)|kg | T34: P
A35: PL-030 | B35: Civil and Structure | C35: B.01 | D35: Sub Structure | E35: Bored Pile | F35: Bentonite / Slurry | G35: Bentonite / polymer slurry incl. mixing, circulation and disposal | H35: Lot | I35: 2200 | J35: =_STDLAB -> 0.2 | K35: =IFERROR(I35*(1+J35),0) -> 2640 | L35: 4200 | M35: =_STDMAT -> 0.12 | N35: =IFERROR(L35*(1+M35),0) -> 4704 | O35: =K35+N35 -> 7344 | P35: =IF(N(I35)+N(L35)=0,"To be quoted",IF($T35="P","Priced","Benchmark")) -> Benchmark | Q35: 1 | R35: BENCHMARK (CAM market) — Mix, circulate, dispose | S35: =TRIM(G35)&"|"&TRIM(H35) -> Bentonite / polymer slurry incl. mixing, circulation and disposal|Lot | T35: B
A36: PL-031 | B36: Civil and Structure | C36: B.01 | D36: Sub Structure | E36: Bored Pile | F36: Bored Pile Head Cutting | G36: Pile Head Cutting up to required level D1000mm | H36: Nos | I36: 55 | J36: 0.2 | K36: =IFERROR(I36*(1+J36),0) -> 66 | L36: 0 | M36: 0 | N36: =IFERROR(L36*(1+M36),0) -> 0 | O36: =K36+N36 -> 66 | P36: =IF(N(I36)+N(L36)=0,"To be quoted",IF($T36="P","Priced","Benchmark")) -> Priced | Q36: 1 | R36: Pile head breaking D1000 - own labour+breaker, est. | S36: =TRIM(G36)&"|"&TRIM(H36) -> Pile Head Cutting up to required level D1000mm|Nos | T36: P
A37: PL-032 | B37: Civil and Structure | C37: B.01 | D37: Sub Structure | E37: Bored Pile | F37: Bored Pile Head Cutting | G37: Pile Head Cutting up to required level D800mm | H37: Nos | I37: 40 | J37: 0.2 | K37: =IFERROR(I37*(1+J37),0) -> 48 | L37: 0 | M37: 0 | N37: =IFERROR(L37*(1+M37),0) -> 0 | O37: =K37+N37 -> 48 | P37: =IF(N(I37)+N(L37)=0,"To be quoted",IF($T37="P","Priced","Benchmark")) -> Priced | Q37: 1 | R37: Pile head breaking D800 - own labour+breaker, est. | S37: =TRIM(G37)&"|"&TRIM(H37) -> Pile Head Cutting up to required level D800mm|Nos | T37: P
A38: PL-033 | B38: Civil and Structure | C38: B.01 | D38: Sub Structure | E38: Bored Pile | F38: Bored Pile Testing | G38: Sonic Logging Test (SLT) | H38: Nos | I38: 0 | J38: 0 | K38: =IFERROR(I38*(1+J38),0) -> 0 | L38: 50 | M38: 0.1 | N38: =IFERROR(L38*(1+M38),0) -> 55 | O38: =K38+N38 -> 55 | P38: =IF(N(I38)+N(L38)=0,"To be quoted",IF($T38="P","Priced","Benchmark")) -> Priced | Q38: 1 | R38: SLT specialist subcontract per pile, provisional | S38: =TRIM(G38)&"|"&TRIM(H38) -> Sonic Logging Test (SLT)|Nos | T38: P
A39: PL-034 | B39: Civil and Structure | C39: B.01 | D39: Sub Structure | E39: Bored Pile | F39: Bored Pile Testing | G39: Pile Integrity Test (PIT) | H39: Nos | I39: 0 | J39: 0 | K39: =IFERROR(I39*(1+J39),0) -> 0 | L39: 45 | M39: 0.1 | N39: =IFERROR(L39*(1+M39),0) -> 49.5 | O39: =K39+N39 -> 49.5 | P39: =IF(N(I39)+N(L39)=0,"To be quoted",IF($T39="P","Priced","Benchmark")) -> Benchmark | Q39: 1 | R39: SUBCONTRACT benchmark — PIT specialist subcontract | S39: =TRIM(G39)&"|"&TRIM(H39) -> Pile Integrity Test (PIT)|Nos | T39: B
A40: PL-035 | B40: Civil and Structure | C40: B.01 | D40: Sub Structure | E40: Bored Pile | F40: Bored Pile Coring | G40: Soil Coring for Bored Pile D1000mm, Depth 30m | H40: Nos | I40: 0 | J40: 0 | K40: =IFERROR(I40*(1+J40),0) -> 0 | L40: 350 | M40: 0.1 | N40: =IFERROR(L40*(1+M40),0) -> 385 | O40: =K40+N40 -> 385 | P40: =IF(N(I40)+N(L40)=0,"To be quoted",IF($T40="P","Priced","Benchmark")) -> Priced | Q40: 1 | R40: Coring D1000 30m subcontract, provisional | S40: =TRIM(G40)&"|"&TRIM(H40) -> Soil Coring for Bored Pile D1000mm, Depth 30m|Nos | T40: P
A41: PL-036 | B41: Civil and Structure | C41: B.01 | D41: Sub Structure | E41: Bored Pile | F41: Bored Pile Coring | G41: Soil Coring for Bored Pile D800mm, Depth 30m | H41: Nos | I41: 0 | J41: 0 | K41: =IFERROR(I41*(1+J41),0) -> 0 | L41: 300 | M41: 0.1 | N41: =IFERROR(L41*(1+M41),0) -> 330 | O41: =K41+N41 -> 330 | P41: =IF(N(I41)+N(L41)=0,"To be quoted",IF($T41="P","Priced","Benchmark")) -> Priced | Q41: 1 | R41: Coring D800 30m subcontract, provisional | S41: =TRIM(G41)&"|"&TRIM(H41) -> Soil Coring for Bored Pile D800mm, Depth 30m|Nos | T41: P
A42: PL-037 | B42: Civil and Structure | C42: B.01 | D42: Sub Structure | E42: Bored Pile | F42: Pile Load Test | G42: Dynamic pile load test (PDA) | H42: Nos | I42: 0 | J42: 0 | K42: =IFERROR(I42*(1+J42),0) -> 0 | L42: 2400 | M42: 0.1 | N42: =IFERROR(L42*(1+M42),0) -> 2640 | O42: =K42+N42 -> 2640 | P42: =IF(N(I42)+N(L42)=0,"To be quoted",IF($T42="P","Priced","Benchmark")) -> Benchmark | Q42: 2 | R42: SUBCONTRACT benchmark — PDA specialist subcontract | S42: =TRIM(G42)&"|"&TRIM(H42) -> Dynamic pile load test (PDA)|Nos | T42: B
A43: PL-038 | B43: Civil and Structure | C43: B.01 | D43: Sub Structure | E43: Bored Pile | F43: Pile Load Test | G43: Static pile load test to 200% design working load | H43: Nos | I43: 0 | J43: 0 | K43: =IFERROR(I43*(1+J43),0) -> 0 | L43: 9500 | M43: 0.1 | N43: =IFERROR(L43*(1+M43),0) -> 10450 | O43: =K43+N43 -> 10450 | P43: =IF(N(I43)+N(L43)=0,"To be quoted",IF($T43="P","Priced","Benchmark")) -> Benchmark | Q43: 2 | R43: SUBCONTRACT benchmark — Kentledge static test subcontract | S43: =TRIM(G43)&"|"&TRIM(H43) -> Static pile load test to 200% design working load|Nos | T43: B
A44: PL-039 | B44: Civil and Structure | C44: B.01 | D44: Sub Structure | E44: Bored Pile | F44: Concrete Testing | G44: Concrete cube / cylinder test as per specification | H44: Nos | I44: 0 | J44: 0 | K44: =IFERROR(I44*(1+J44),0) -> 0 | L44: 35 | M44: 0.1 | N44: =IFERROR(L44*(1+M44),0) -> 38.5 | O44: =K44+N44 -> 38.5 | P44: =IF(N(I44)+N(L44)=0,"To be quoted",IF($T44="P","Priced","Benchmark")) -> Benchmark | Q44: 2 | R44: SUBCONTRACT benchmark — Lab test per set | S44: =TRIM(G44)&"|"&TRIM(H44) -> Concrete cube / cylinder test as per specification|Nos | T44: B
A45: PL-040 | B45: Civil and Structure | C45: B.01 | D45: Sub Structure | E45: Driven Pile / Micro Pile | F45: Pile Supply | G45: Supply of precast / spun pile as per design section | H45: m | I45: 0 | J45: =_STDLAB -> 0.2 | K45: =IFERROR(I45*(1+J45),0) -> 0 | L45: 22 | M45: =_STDMAT -> 0.12 | N45: =IFERROR(L45*(1+M45),0) -> 24.64 | O45: =K45+N45 -> 24.64 | P45: =IF(N(I45)+N(L45)=0,"To be quoted",IF($T45="P","Priced","Benchmark")) -> Benchmark | Q45: 1 | R45: BENCHMARK (CAM market) — Spun pile supply delivered | S45: =TRIM(G45)&"|"&TRIM(H45) -> Supply of precast / spun pile as per design section|m | T45: B
A46: PL-041 | B46: Civil and Structure | C46: B.01 | D46: Sub Structure | E46: Driven Pile / Micro Pile | F46: Pile Driving | G46: Driving of precast / spun pile to required set incl. plant | H46: m | I46: 9 | J46: =_STDLAB -> 0.2 | K46: =IFERROR(I46*(1+J46),0) -> 10.8 | L46: 4 | M46: =_STDMAT -> 0.12 | N46: =IFERROR(L46*(1+M46),0) -> 4.48 | O46: =K46+N46 -> 15.28 | P46: =IF(N(I46)+N(L46)=0,"To be quoted",IF($T46="P","Priced","Benchmark")) -> Benchmark | Q46: 1 | R46: BENCHMARK (CAM market) — Drop/hydraulic hammer + rig | S46: =TRIM(G46)&"|"&TRIM(H46) -> Driving of precast / spun pile to required set incl. plant|m | T46: B
A47: PL-042 | B47: Civil and Structure | C47: B.01 | D47: Sub Structure | E47: Driven Pile / Micro Pile | F47: Pile Splicing | G47: Pile splicing by full penetration weld incl. splice plate | H47: Nos | I47: 35 | J47: =_STDLAB -> 0.2 | K47: =IFERROR(I47*(1+J47),0) -> 42 | L47: 45 | M47: =_STDMAT -> 0.12 | N47: =IFERROR(L47*(1+M47),0) -> 50.4 | O47: =K47+N47 -> 92.4 | P47: =IF(N(I47)+N(L47)=0,"To be quoted",IF($T47="P","Priced","Benchmark")) -> Benchmark | Q47: 1 | R47: BENCHMARK (CAM market) — Full penetration weld + plate | S47: =TRIM(G47)&"|"&TRIM(H47) -> Pile splicing by full penetration weld incl. splice plate|Nos | T47: B
A48: PL-043 | B48: Civil and Structure | C48: B.01 | D48: Sub Structure | E48: Driven Pile / Micro Pile | F48: Pile Head Cutting | G48: Pile head cutting and trimming to required cut-off level | H48: Nos | I48: 38 | J48: =_STDLAB -> 0.2 | K48: =IFERROR(I48*(1+J48),0) -> 45.6 | L48: 0 | M48: =_STDMAT -> 0.12 | N48: =IFERROR(L48*(1+M48),0) -> 0 | O48: =K48+N48 -> 45.6 | P48: =IF(N(I48)+N(L48)=0,"To be quoted",IF($T48="P","Priced","Benchmark")) -> Benchmark | Q48: 1 | R48: BENCHMARK (CAM market) — Breaker + labour | S48: =TRIM(G48)&"|"&TRIM(H48) -> Pile head cutting and trimming to required cut-off level|Nos | T48: B
A49: PL-044 | B49: Civil and Structure | C49: B.03 | D49: Sub Structure | E49: Pile Cap & Stump | F49: Earthwork | G49: Soil Backfill | H49: m3 | I49: 4 | J49: 0.2 | K49: =IFERROR(I49*(1+J49),0) -> 4.8 | L49: 0 | M49: 0 | N49: =IFERROR(L49*(1+M49),0) -> 0 | O49: =K49+N49 -> 4.8 | P49: =IF(N(I49)+N(L49)=0,"To be quoted",IF($T49="P","Priced","Benchmark")) -> Priced | Q49: 7 | R49: Backfill incl. compaction, est. $/m3 | S49: =TRIM(G49)&"|"&TRIM(H49) -> Soil Backfill|m3 | T49: P
A50: PL-045 | B50: Civil and Structure | C50: B.03 | D50: Sub Structure | E50: Pile Cap & Stump | F50: Earthwork | G50: Soil Disposal | H50: m3 | I50: 4 | J50: 0.2 | K50: =IFERROR(I50*(1+J50),0) -> 4.8 | L50: 0 | M50: 0 | N50: =IFERROR(L50*(1+M50),0) -> 0 | O50: =K50+N50 -> 4.8 | P50: =IF(N(I50)+N(L50)=0,"To be quoted",IF($T50="P","Priced","Benchmark")) -> Priced | Q50: 7 | R50: Cart-away + tipping, est. $/m3 | S50: =TRIM(G50)&"|"&TRIM(H50) -> Soil Disposal|m3 | T50: P
A51: PL-046 | B51: Civil and Structure | C51: B.03 | D51: Sub Structure | E51: Pile Cap & Stump | F51: Earthwork | G51: Soil Excavation | H51: m3 | I51: 3 | J51: 0.2 | K51: =IFERROR(I51*(1+J51),0) -> 3.6 | L51: 0 | M51: 0 | N51: =IFERROR(L51*(1+M51),0) -> 0 | O51: =K51+N51 -> 3.6 | P51: =IF(N(I51)+N(L51)=0,"To be quoted",IF($T51="P","Priced","Benchmark")) -> Priced | Q51: 7 | R51: Machine excavation, est. $/m3 | S51: =TRIM(G51)&"|"&TRIM(H51) -> Soil Excavation|m3 | T51: P
A52: PL-047 | B52: Civil and Structure | C52: B.03 | D52: Sub Structure | E52: Pile Cap & Stump | F52: Base Preparation | G52: Well Soil Compact | H52: m2 | I52: 2 | J52: 0.2 | K52: =IFERROR(I52*(1+J52),0) -> 2.4 | L52: 0 | M52: 0 | N52: =IFERROR(L52*(1+M52),0) -> 0 | O52: =K52+N52 -> 2.4 | P52: =IF(N(I52)+N(L52)=0,"To be quoted",IF($T52="P","Priced","Benchmark")) -> Priced | Q52: 5 | R52: Base compaction, est. $/m2 | S52: =TRIM(G52)&"|"&TRIM(H52) -> Well Soil Compact|m2 | T52: P
A53: PL-048 | B53: Civil and Structure | C53: B.03 | D53: Sub Structure | E53: Pile Cap & Stump | F53: Crush Stone | G53: Crush Stone 40x60mm 100mm Thk. | H53: m3 | I53: 3 | J53: 0.2 | K53: =IFERROR(I53*(1+J53),0) -> 3.6 | L53: 18 | M53: 0.12 | N53: =IFERROR(L53*(1+M53),0) -> 20.16 | O53: =K53+N53 -> 23.76 | P53: =IF(N(I53)+N(L53)=0,"To be quoted",IF($T53="P","Priced","Benchmark")) -> Priced | Q53: 5 | R53: Crushed stone base, est. $/m3 | S53: =TRIM(G53)&"|"&TRIM(H53) -> Crush Stone 40x60mm 100mm Thk.|m3 | T53: P
A54: PL-049 | B54: Civil and Structure | C54: B.03 | D54: Sub Structure | E54: Pile Cap & Stump | F54: Crush Stone | G54: Crush Stone 40x60mm 150mm Thk. | H54: m3 | I54: 3 | J54: 0.2 | K54: =IFERROR(I54*(1+J54),0) -> 3.6 | L54: 18 | M54: 0.12 | N54: =IFERROR(L54*(1+M54),0) -> 20.16 | O54: =K54+N54 -> 23.76 | P54: =IF(N(I54)+N(L54)=0,"To be quoted",IF($T54="P","Priced","Benchmark")) -> Priced | Q54: 5 | R54: Crushed stone base 150mm, as existing crush stone rate, est. | S54: =TRIM(G54)&"|"&TRIM(H54) -> Crush Stone 40x60mm 150mm Thk.|m3 | T54: P
A55: PL-050 | B55: Civil and Structure | C55: B.03 | D55: Sub Structure | E55: Pile Cap & Stump | F55: Lean Concrete | G55: Lean Concrete, 15Mpa (Cylinder) | H55: m3 | I55: 7 | J55: 0.2 | K55: =IFERROR(I55*(1+J55),0) -> 8.4 | L55: 75 | M55: 0.12 | N55: =IFERROR(L55*(1+M55),0) -> 84 | O55: =K55+N55 -> 92.4 | P55: =IF(N(I55)+N(L55)=0,"To be quoted",IF($T55="P","Priced","Benchmark")) -> Priced | Q55: 7 | R55: Lean concrete C15; CPAC list escalated 2026 | S55: =TRIM(G55)&"|"&TRIM(H55) -> Lean Concrete, 15Mpa (Cylinder)|m3 | T55: P
A56: PL-051 | B56: Civil and Structure | C56: B.03 | D56: Sub Structure | E56: Pile Cap & Stump | F56: Formwork | G56: Formwork | H56: m2 | I56: 6 | J56: 0.2 | K56: =IFERROR(I56*(1+J56),0) -> 7.2 | L56: 5 | M56: 0.12 | N56: =IFERROR(L56*(1+M56),0) -> 5.6 | O56: =K56+N56 -> 12.8 | P56: =IF(N(I56)+N(L56)=0,"To be quoted",IF($T56="P","Priced","Benchmark")) -> Priced | Q56: 1 | R56: Plywood formwork (cost per use) | S56: =TRIM(G56)&"|"&TRIM(H56) -> Formwork|m2 | T56: P
A57: PL-052 | B57: Civil and Structure | C57: B.03 | D57: Sub Structure | E57: Pile Cap & Stump | F57: Formwork | G57: Formwork to curved / special shape incl. erection and striking | H57: m2 | I57: 9 | J57: =_STDLAB -> 0.2 | K57: =IFERROR(I57*(1+J57),0) -> 10.8 | L57: 7 | M57: =_STDMAT -> 0.12 | N57: =IFERROR(L57*(1+M57),0) -> 7.84 | O57: =K57+N57 -> 18.64 | P57: =IF(N(I57)+N(L57)=0,"To be quoted",IF($T57="P","Priced","Benchmark")) -> Benchmark | Q57: 16 | R57: BENCHMARK (CAM market) — Special shape, higher labour | S57: =TRIM(G57)&"|"&TRIM(H57) -> Formwork to curved / special shape incl. erection and striking|m2 | T57: B
A58: PL-053 | B58: Civil and Structure | C58: B.03 | D58: Sub Structure | E58: Pile Cap & Stump | F58: Formwork | G58: Formwork, plywood 18mm thk. incl. erection, bracing, oiling and striking | H58: m2 | I58: 6 | J58: =_STDLAB -> 0.2 | K58: =IFERROR(I58*(1+J58),0) -> 7.2 | L58: 5 | M58: =_STDMAT -> 0.12 | N58: =IFERROR(L58*(1+M58),0) -> 5.6 | O58: =K58+N58 -> 12.8 | P58: =IF(N(I58)+N(L58)=0,"To be quoted",IF($T58="P","Priced","Benchmark")) -> Benchmark | Q58: 16 | R58: BENCHMARK (CAM market) — Matches project formwork rate | S58: =TRIM(G58)&"|"&TRIM(H58) -> Formwork, plywood 18mm thk. incl. erection, bracing, oiling and striking|m2 | T58: B
A59: PL-054 | B59: Civil and Structure | C59: B.03 | D59: Sub Structure | E59: Pile Cap & Stump | F59: Water Stop | G59: PVC Waterbar® V VN 20 (Width 200mm) | H59: m | I59: 1.5 | J59: 0.2 | K59: =IFERROR(I59*(1+J59),0) -> 1.8 | L59: 4 | M59: 0.12 | N59: =IFERROR(L59*(1+M59),0) -> 4.48 | O59: =K59+N59 -> 6.28 | P59: =IF(N(I59)+N(L59)=0,"To be quoted",IF($T59="P","Priced","Benchmark")) -> Priced | Q59: 8 | R59: PVC waterstop 200mm supply+install, est. | S59: =TRIM(G59)&"|"&TRIM(H59) -> PVC Waterbar® V VN 20 (Width 200mm)|m | T59: P
A60: PL-055 | B60: Civil and Structure | C60: B.03 | D60: Sub Structure | E60: Pile Cap & Stump | F60: Waterproofing | G60: Membrance sheet 2mm thk | H60: m2 | I60: 2 | J60: 0.2 | K60: =IFERROR(I60*(1+J60),0) -> 2.4 | L60: 6.5 | M60: 0.12 | N60: =IFERROR(L60*(1+M60),0) -> 7.28 | O60: =K60+N60 -> 9.68 | P60: =IF(N(I60)+N(L60)=0,"To be quoted",IF($T60="P","Priced","Benchmark")) -> Priced | Q60: 10 | R60: 2mm waterproof membrane supply+apply, est. | S60: =TRIM(G60)&"|"&TRIM(H60) -> Membrance sheet 2mm thk|m2 | T60: P
A61: PL-056 | B61: Civil and Structure | C61: B.03 | D61: Sub Structure | E61: Pile Cap & Stump | F61: Waterproofing | G61: Sika Waterproofing | H61: m2 | I61: 2 | J61: 0.2 | K61: =IFERROR(I61*(1+J61),0) -> 2.4 | L61: 6 | M61: 0.12 | N61: =IFERROR(L61*(1+M61),0) -> 6.72 | O61: =K61+N61 -> 9.12 | P61: =IF(N(I61)+N(L61)=0,"To be quoted",IF($T61="P","Priced","Benchmark")) -> Priced | Q61: 10 | R61: Sika cementitious/membrane WP to wet areas, supply+apply est. | S61: =TRIM(G61)&"|"&TRIM(H61) -> Sika Waterproofing|m2 | T61: P
A62: PL-057 | B62: Civil and Structure | C62: B.03 | D62: Sub Structure | E62: Pile Cap & Stump | F62: Waterproofing | G62: Cementitious waterproofing, 2 coats, to wet area incl. up-turn 300mm | H62: m2 | I62: 2.2 | J62: =_STDLAB -> 0.2 | K62: =IFERROR(I62*(1+J62),0) -> 2.64 | L62: 5.5 | M62: =_STDMAT -> 0.12 | N62: =IFERROR(L62*(1+M62),0) -> 6.16 | O62: =K62+N62 -> 8.8 | P62: =IF(N(I62)+N(L62)=0,"To be quoted",IF($T62="P","Priced","Benchmark")) -> Benchmark | Q62: 10 | R62: BENCHMARK (CAM market) — 2 coats + up-turn | S62: =TRIM(G62)&"|"&TRIM(H62) -> Cementitious waterproofing, 2 coats, to wet area incl. up-turn 300mm|m2 | T62: B
A63: PL-058 | B63: Civil and Structure | C63: B.03 | D63: Sub Structure | E63: Pile Cap & Stump | F63: Anti-Termite | G63: Anti-Termite with Plastic Membrane | H63: m2 | I63: 1 | J63: 0.2 | K63: =IFERROR(I63*(1+J63),0) -> 1.2 | L63: 2.5 | M63: 0.12 | N63: =IFERROR(L63*(1+M63),0) -> 2.8 | O63: =K63+N63 -> 4 | P63: =IF(N(I63)+N(L63)=0,"To be quoted",IF($T63="P","Priced","Benchmark")) -> Priced | Q63: 5 | R63: Anti-termite chemical + PE sheet, est. | S63: =TRIM(G63)&"|"&TRIM(H63) -> Anti-Termite with Plastic Membrane|m2 | T63: P
A64: PL-059 | B64: Civil and Structure | C64: B.03 | D64: Sub Structure | E64: Slab on Grade / Ground Slab | F64: Vapour Barrier | G64: Polyethylene vapour barrier 0.15mm thk. laid with 300mm laps | H64: m2 | I64: 0.4 | J64: =_STDLAB -> 0.2 | K64: =IFERROR(I64*(1+J64),0) -> 0.48 | L64: 1.1 | M64: =_STDMAT -> 0.12 | N64: =IFERROR(L64*(1+M64),0) -> 1.232 | O64: =K64+N64 -> 1.712 | P64: =IF(N(I64)+N(L64)=0,"To be quoted",IF($T64="P","Priced","Benchmark")) -> Benchmark | Q64: 1 | R64: BENCHMARK (CAM market) — 0.15mm PE sheet | S64: =TRIM(G64)&"|"&TRIM(H64) -> Polyethylene vapour barrier 0.15mm thk. laid with 300mm laps|m2 | T64: B
A65: PL-060 | B65: Civil and Structure | C65: B.02 | D65: Sub Structure | E65: Basement / Retaining Wall | F65: Protection Board | G65: Protection board 6mm thk. to waterproofing membrane | H65: m2 | I65: 1.2 | J65: =_STDLAB -> 0.2 | K65: =IFERROR(I65*(1+J65),0) -> 1.44 | L65: 3.2 | M65: =_STDMAT -> 0.12 | N65: =IFERROR(L65*(1+M65),0) -> 3.584 | O65: =K65+N65 -> 5.024 | P65: =IF(N(I65)+N(L65)=0,"To be quoted",IF($T65="P","Priced","Benchmark")) -> Benchmark | Q65: 1 | R65: BENCHMARK (CAM market) — Board to membrane | S65: =TRIM(G65)&"|"&TRIM(H65) -> Protection board 6mm thk. to waterproofing membrane|m2 | T65: B
A66: PL-061 | B66: Civil and Structure | C66: B.02 | D66: Sub Structure | E66: Basement / Retaining Wall | F66: Drainage Board | G66: Dimpled HDPE drainage board with filter fabric | H66: m2 | I66: 1.8 | J66: =_STDLAB -> 0.2 | K66: =IFERROR(I66*(1+J66),0) -> 2.16 | L66: 6.5 | M66: =_STDMAT -> 0.12 | N66: =IFERROR(L66*(1+M66),0) -> 7.28 | O66: =K66+N66 -> 9.44 | P66: =IF(N(I66)+N(L66)=0,"To be quoted",IF($T66="P","Priced","Benchmark")) -> Benchmark | Q66: 1 | R66: BENCHMARK (CAM market) — Drainage board + filter fabric | S66: =TRIM(G66)&"|"&TRIM(H66) -> Dimpled HDPE drainage board with filter fabric|m2 | T66: B
A67: PL-062 | B67: Civil and Structure | C67: B.04 | D67: Super Structure | E67: Structural Column | F67: Column Starter Bar | G67: Column starter bar incl. bending, fixing and tying | H67: kg | I67: 0.12 | J67: =_STDLAB -> 0.2 | K67: =IFERROR(I67*(1+J67),0) -> 0.144 | L67: 0.75 | M67: =_STDMAT -> 0.12 | N67: =IFERROR(L67*(1+M67),0) -> 0.84 | O67: =K67+N67 -> 0.984 | P67: =IF(N(I67)+N(L67)=0,"To be quoted",IF($T67="P","Priced","Benchmark")) -> Benchmark | Q67: 1 | R67: BENCHMARK (CAM market) — As rebar rate | S67: =TRIM(G67)&"|"&TRIM(H67) -> Column starter bar incl. bending, fixing and tying|kg | T67: B
A68: PL-063 | B68: Civil and Structure | C68: B.04 | D68: Super Structure | E68: Structural Column | F68: Grouting | G68: Non-shrink cementitious grout to base plate / gap | H68: Nos | I68: 4 | J68: =_STDLAB -> 0.2 | K68: =IFERROR(I68*(1+J68),0) -> 4.8 | L68: 9 | M68: =_STDMAT -> 0.12 | N68: =IFERROR(L68*(1+M68),0) -> 10.08 | O68: =K68+N68 -> 14.88 | P68: =IF(N(I68)+N(L68)=0,"To be quoted",IF($T68="P","Priced","Benchmark")) -> Benchmark | Q68: 1 | R68: BENCHMARK (CAM market) — Base plate grouting | S68: =TRIM(G68)&"|"&TRIM(H68) -> Non-shrink cementitious grout to base plate / gap|Nos | T68: B
A69: PL-064 | B69: Civil and Structure | C69: B.04 | D69: Super Structure | E69: Structural Slab | F69: Post-Tension Strand | G69: Post-tension strand incl. duct, anchorage, stressing and grouting | H69: kg | I69: 0.55 | J69: =_STDLAB -> 0.2 | K69: =IFERROR(I69*(1+J69),0) -> 0.66 | L69: 1.85 | M69: =_STDMAT -> 0.12 | N69: =IFERROR(L69*(1+M69),0) -> 2.072 | O69: =K69+N69 -> 2.732 | P69: =IF(N(I69)+N(L69)=0,"To be quoted",IF($T69="P","Priced","Benchmark")) -> Benchmark | Q69: 1 | R69: BENCHMARK (CAM market) — Strand, duct, anchorage, stressing | S69: =TRIM(G69)&"|"&TRIM(H69) -> Post-tension strand incl. duct, anchorage, stressing and grouting|kg | T69: B
A70: PL-065 | B70: Civil and Structure | C70: B.04 | D70: Super Structure | E70: Structural Slab | F70: Steel Deck | G70: Galvanised steel deck 0.75mm thk. incl. shear stud and end closure | H70: m2 | I70: 4.5 | J70: =_STDLAB -> 0.2 | K70: =IFERROR(I70*(1+J70),0) -> 5.4 | L70: 16 | M70: =_STDMAT -> 0.12 | N70: =IFERROR(L70*(1+M70),0) -> 17.92 | O70: =K70+N70 -> 23.32 | P70: =IF(N(I70)+N(L70)=0,"To be quoted",IF($T70="P","Priced","Benchmark")) -> Benchmark | Q70: 1 | R70: BENCHMARK (CAM market) — 0.75mm deck + shear stud | S70: =TRIM(G70)&"|"&TRIM(H70) -> Galvanised steel deck 0.75mm thk. incl. shear stud and end closure|m2 | T70: B
A71: PL-066 | B71: Civil and Structure | C71: B.04 | D71: Super Structure | E71: Structural Steel | F71: Steel Section / Beam | G71: Structural steel section (H/I beam) SS400 incl. fabrication and erection | H71: kg | I71: 0.45 | J71: =_STDLAB -> 0.2 | K71: =IFERROR(I71*(1+J71),0) -> 0.54 | L71: 1.25 | M71: =_STDMAT -> 0.12 | N71: =IFERROR(L71*(1+M71),0) -> 1.4 | O71: =K71+N71 -> 1.94 | P71: =IF(N(I71)+N(L71)=0,"To be quoted",IF($T71="P","Priced","Benchmark")) -> Benchmark | Q71: 1 | R71: BENCHMARK (CAM market) — SS400 ~$1.10/kg + fabrication | S71: =TRIM(G71)&"|"&TRIM(H71) -> Structural steel section (H/I beam) SS400 incl. fabrication and erection|kg | T71: B
A72: PL-067 | B72: Civil and Structure | C72: B.04 | D72: Super Structure | E72: Structural Steel | F72: Purlin | G72: Steel purlin C-channel incl. fabrication, erection and fixing | H72: kg | I72: 0.4 | J72: =_STDLAB -> 0.2 | K72: =IFERROR(I72*(1+J72),0) -> 0.48 | L72: 1.2 | M72: =_STDMAT -> 0.12 | N72: =IFERROR(L72*(1+M72),0) -> 1.344 | O72: =K72+N72 -> 1.824 | P72: =IF(N(I72)+N(L72)=0,"To be quoted",IF($T72="P","Priced","Benchmark")) -> Benchmark | Q72: 2 | R72: BENCHMARK (CAM market) — Purlin fabricate + fix | S72: =TRIM(G72)&"|"&TRIM(H72) -> Steel purlin C-channel incl. fabrication, erection and fixing|kg | T72: B
A73: PL-068 | B73: Civil and Structure | C73: B.04 | D73: Super Structure | E73: Structural Steel | F73: Bracing | G73: Steel bracing member incl. fabrication, erection and connection | H73: kg | I73: 0.5 | J73: =_STDLAB -> 0.2 | K73: =IFERROR(I73*(1+J73),0) -> 0.6 | L73: 1.25 | M73: =_STDMAT -> 0.12 | N73: =IFERROR(L73*(1+M73),0) -> 1.4 | O73: =K73+N73 -> 2 | P73: =IF(N(I73)+N(L73)=0,"To be quoted",IF($T73="P","Priced","Benchmark")) -> Benchmark | Q73: 2 | R73: BENCHMARK (CAM market) — Bracing fabricate + erect | S73: =TRIM(G73)&"|"&TRIM(H73) -> Steel bracing member incl. fabrication, erection and connection|kg | T73: B
A74: PL-069 | B74: Civil and Structure | C74: B.04 | D74: Super Structure | E74: Structural Steel | F74: Base Plate | G74: Steel base plate incl. drilling, welding and levelling | H74: kg | I74: 0.55 | J74: =_STDLAB -> 0.2 | K74: =IFERROR(I74*(1+J74),0) -> 0.66 | L74: 1.3 | M74: =_STDMAT -> 0.12 | N74: =IFERROR(L74*(1+M74),0) -> 1.456 | O74: =K74+N74 -> 2.116 | P74: =IF(N(I74)+N(L74)=0,"To be quoted",IF($T74="P","Priced","Benchmark")) -> Benchmark | Q74: 1 | R74: BENCHMARK (CAM market) — Plate + drilling + welding | S74: =TRIM(G74)&"|"&TRIM(H74) -> Steel base plate incl. drilling, welding and levelling|kg | T74: B
A75: PL-070 | B75: Civil and Structure | C75: B.04 | D75: Super Structure | E75: Structural Steel | F75: Anchor Bolt | G75: Anchor bolt incl. template, setting and grouting | H75: Nos | I75: 2.5 | J75: =_STDLAB -> 0.2 | K75: =IFERROR(I75*(1+J75),0) -> 3 | L75: 4.5 | M75: =_STDMAT -> 0.12 | N75: =IFERROR(L75*(1+M75),0) -> 5.04 | O75: =K75+N75 -> 8.04 | P75: =IF(N(I75)+N(L75)=0,"To be quoted",IF($T75="P","Priced","Benchmark")) -> Benchmark | Q75: 2 | R75: BENCHMARK (CAM market) — Template, set, grout | S75: =TRIM(G75)&"|"&TRIM(H75) -> Anchor bolt incl. template, setting and grouting|Nos | T75: B
... A81: PL-076 | B81: Civil and Structure | C81: B.04 | D81: Super Structure | E81: Roof Structure / Truss | F81: Truss | G81: Steel roof truss incl. fabrication, erection and connection | H81: kg | I81: 0.55 | J81: =_STDLAB -> 0.2 | K81: =IFERROR(I81*(1+J81),0) -> 0.66 | L81: 1.3 | M81: =_STDMAT -> 0.12 | N81: =IFERROR(L81*(1+M81),0) -> 1.456 | O81: =K81+N81 -> 2.116 | P81: =IF(N(I81)+N(L81)=0,"To be quoted",IF($T81="P","Priced","Benchmark")) -> Benchmark | Q81: 1 | R81: BENCHMARK (CAM market) — Truss fabricate + erect | S81: =TRIM(G81)&"|"&TRIM(H81) -> Steel roof truss incl. fabrication, erection and connection|kg | T81: B
A82: PL-077 | B82: Civil and Structure | C82: B.04 | D82: Super Structure | E82: Roof Structure / Truss | F82: Zinc sheet | G82: Zinc sheet 0.4mm | H82: m2 | I82: 2 | J82: 0.2 | K82: =IFERROR(I82*(1+J82),0) -> 2.4 | L82: 5.5 | M82: 0.12 | N82: =IFERROR(L82*(1+M82),0) -> 6.16 | O82: =K82+N82 -> 8.56 | P82: =IF(N(I82)+N(L82)=0,"To be quoted",IF($T82="P","Priced","Benchmark")) -> Priced | Q82: 1 | R82: GI/zinc roof sheet 0.4mm supply+fix, est. NEW | S82: =TRIM(G82)&"|"&TRIM(H82) -> Zinc sheet 0.4mm|m2 | T82: P
A83: PL-078 | B83: Civil and Structure | C83: B.04 | D83: Super Structure | E83: Roof Structure / Truss | F83: Flashing | G83: Flashing cover roof | H83: m | I83: 1 | J83: 0.2 | K83: =IFERROR(I83*(1+J83),0) -> 1.2 | L83: 2.5 | M83: 0.12 | N83: =IFERROR(L83*(1+M83),0) -> 2.8 | O83: =K83+N83 -> 4 | P83: =IF(N(I83)+N(L83)=0,"To be quoted",IF($T83="P","Priced","Benchmark")) -> Priced | Q83: 2 | R83: Bent metal flashing supply+fix, est. NEW | S83: =TRIM(G83)&"|"&TRIM(H83) -> Flashing cover roof|m | T83: P
A84: PL-079 | B84: Civil and Structure | C84: B.04 | D84: Super Structure | E84: Testing & Quality Control | F84: Non-Destructive Test | G84: Non-destructive test (rebound hammer / ultrasonic) as per specification | H84: Nos | I84: 0 | J84: 0 | K84: =IFERROR(I84*(1+J84),0) -> 0 | L84: 120 | M84: 0.1 | N84: =IFERROR(L84*(1+M84),0) -> 132 | O84: =K84+N84 -> 132 | P84: =IF(N(I84)+N(L84)=0,"To be quoted",IF($T84="P","Priced","Benchmark")) -> Benchmark | Q84: 1 | R84: SUBCONTRACT benchmark — NDT specialist subcontract | S84: =TRIM(G84)&"|"&TRIM(H84) -> Non-destructive test (rebound hammer / ultrasonic) as per specification|Nos | T84: B
A85: PL-080 | B85: Civil and Structure | C85: B.04 | D85: Super Structure | E85: Testing & Quality Control | F85: Survey & As-Built | G85: Setting out, survey and as-built record | H85: Lot | I85: 1500 | J85: =_STDLAB -> 0.2 | K85: =IFERROR(I85*(1+J85),0) -> 1800 | L85: 600 | M85: =_STDMAT -> 0.12 | N85: =IFERROR(L85*(1+M85),0) -> 672 | O85: =K85+N85 -> 2472 | P85: =IF(N(I85)+N(L85)=0,"To be quoted",IF($T85="P","Priced","Benchmark")) -> Benchmark | Q85: 1 | R85: BENCHMARK (CAM market) — Survey team + records | S85: =TRIM(G85)&"|"&TRIM(H85) -> Setting out, survey and as-built record|Lot | T85: B
A86: PL-081 | B86: Architecture | C86: C.01 | D86: Exterior Wall and Partition | E86: Hollow clay brick | F86: Hollow clay brick 100mm Thk. | G86: Hollow clay brick, thickness 100mm, laid in cement:sand mortar 1:4 | H86: m2 | I86: 3 | J86: =_STDLAB -> 0.2 | K86: =IFERROR(I86*(1+J86),0) -> 3.6 | L86: 6 | M86: =_STDMAT -> 0.12 | N86: =IFERROR(L86*(1+M86),0) -> 6.72 | O86: =K86+N86 -> 10.32 | P86: =IF(N(I86)+N(L86)=0,"To be quoted",IF($T86="P","Priced","Benchmark")) -> Benchmark | Q86: 1 | R86: BENCHMARK (CAM market) — As project 100mm brick rate | S86: =TRIM(G86)&"|"&TRIM(H86) -> Hollow clay brick, thickness 100mm, laid in cement:sand mortar 1:4|m2 | T86: B
A87: PL-082 | B87: Architecture | C87: C.01 | D87: Exterior Wall and Partition | E87: Hollow clay brick | F87: Hollow clay brick 200mm Thk. | G87: Hollow clay brick (80x80x180)mm, thickness 200mm Thk. | H87: m2 | I87: 4.5 | J87: 0.2 | K87: =IFERROR(I87*(1+J87),0) -> 5.4 | L87: 11 | M87: 0.12 | N87: =IFERROR(L87*(1+M87),0) -> 12.32 | O87: =K87+N87 -> 17.72 | P87: =IF(N(I87)+N(L87)=0,"To be quoted",IF($T87="P","Priced","Benchmark")) -> Priced | Q87: 1 | R87: Hollow clay brick wall 200mm thk, supply & lay only (plaster excl.), PP est. | S87: =TRIM(G87)&"|"&TRIM(H87) -> Hollow clay brick (80x80x180)mm, thickness 200mm Thk.|m2 | T87: P
A88: PL-083 | B88: Architecture | C88: C.01 | D88: Exterior Wall and Partition | E88: Hollow clay brick | F88: Hollow clay brick 400mm Thk. | G88: Hollow clay brick (80x80x180)mm, thickness 400mm Thk. | H88: m2 | I88: 7 | J88: 0.2 | K88: =IFERROR(I88*(1+J88),0) -> 8.4 | L88: 20 | M88: 0.12 | N88: =IFERROR(L88*(1+M88),0) -> 22.4 | O88: =K88+N88 -> 30.8 | P88: =IF(N(I88)+N(L88)=0,"To be quoted",IF($T88="P","Priced","Benchmark")) -> Priced | Q88: 1 | R88: Hollow clay brick wall 400mm thk, supply & lay only (plaster excl.), PP est. | S88: =TRIM(G88)&"|"&TRIM(H88) -> Hollow clay brick (80x80x180)mm, thickness 400mm Thk.|m2 | T88: P
A89: PL-084 | B89: Architecture | C89: C.01 | D89: Exterior Wall and Partition | E89: Hollow clay brick | F89: Hollow clay brick 500mm Thk. | G89: Hollow clay brick (80x80x180)mm, thickness 500mm Thk. | H89: m2 | I89: 8.5 | J89: 0.2 | K89: =IFERROR(I89*(1+J89),0) -> 10.2 | L89: 25 | M89: 0.12 | N89: =IFERROR(L89*(1+M89),0) -> 28 | O89: =K89+N89 -> 38.2 | P89: =IF(N(I89)+N(L89)=0,"To be quoted",IF($T89="P","Priced","Benchmark")) -> Priced | Q89: 1 | R89: Hollow clay brick wall 500mm thk, supply & lay only (plaster excl.), PP est. | S89: =TRIM(G89)&"|"&TRIM(H89) -> Hollow clay brick (80x80x180)mm, thickness 500mm Thk.|m2 | T89: P
A90: PL-085 | B90: Architecture | C90: C.01 | D90: Exterior Wall and Partition | E90: Hollow clay brick | F90: Hollow clay brick 800mm Thk. | G90: Hollow clay brick (80x80x180)mm, thickness 800mm Thk. | H90: m2 | I90: 12 | J90: 0.2 | K90: =IFERROR(I90*(1+J90),0) -> 14.4 | L90: 38 | M90: 0.12 | N90: =IFERROR(L90*(1+M90),0) -> 42.56 | O90: =K90+N90 -> 56.96 | P90: =IF(N(I90)+N(L90)=0,"To be quoted",IF($T90="P","Priced","Benchmark")) -> Priced | Q90: 1 | R90: Hollow clay brick wall 800mm thk, supply & lay only (plaster excl.), PP est. | S90: =TRIM(G90)&"|"&TRIM(H90) -> Hollow clay brick (80x80x180)mm, thickness 800mm Thk.|m2 | T90: P
A91: PL-086 | B91: Architecture | C91: C.01 | D91: Exterior Wall and Partition | E91: Concrete block | F91: Concrete block 100mm Thk. | G91: concrete block, thickness 100mm, laid in cement:sand mortar 1:4 | H91: m2 | I91: 3.2 | J91: =_STDLAB -> 0.2 | K91: =IFERROR(I91*(1+J91),0) -> 3.84 | L91: 6.5 | M91: =_STDMAT -> 0.12 | N91: =IFERROR(L91*(1+M91),0) -> 7.28 | O91: =K91+N91 -> 11.12 | P91: =IF(N(I91)+N(L91)=0,"To be quoted",IF($T91="P","Priced","Benchmark")) -> Benchmark | Q91: 1 | R91: BENCHMARK (CAM market) — Concrete block PP market | S91: =TRIM(G91)&"|"&TRIM(H91) -> concrete block, thickness 100mm, laid in cement:sand mortar 1:4|m2 | T91: B
A92: PL-087 | B92: Architecture | C92: C.01 | D92: Exterior Wall and Partition | E92: Concrete block | F92: Concrete block 150mm Thk. | G92: concrete block, thickness 150mm, laid in cement:sand mortar 1:4 | H92: m2 | I92: 3.8 | J92: =_STDLAB -> 0.2 | K92: =IFERROR(I92*(1+J92),0) -> 4.56 | L92: 8.5 | M92: =_STDMAT -> 0.12 | N92: =IFERROR(L92*(1+M92),0) -> 9.52 | O92: =K92+N92 -> 14.08 | P92: =IF(N(I92)+N(L92)=0,"To be quoted",IF($T92="P","Priced","Benchmark")) -> Benchmark | Q92: 1 | R92: BENCHMARK (CAM market) — Concrete block PP market | S92: =TRIM(G92)&"|"&TRIM(H92) -> concrete block, thickness 150mm, laid in cement:sand mortar 1:4|m2 | T92: B
A93: PL-088 | B93: Architecture | C93: C.01 | D93: Exterior Wall and Partition | E93: Concrete block | F93: Concrete block 200mm Thk. | G93: concrete block, thickness 200mm, laid in cement:sand mortar 1:4 | H93: m2 | I93: 4.2 | J93: =_STDLAB -> 0.2 | K93: =IFERROR(I93*(1+J93),0) -> 5.04 | L93: 10.5 | M93: =_STDMAT -> 0.12 | N93: =IFERROR(L93*(1+M93),0) -> 11.76 | O93: =K93+N93 -> 16.8 | P93: =IF(N(I93)+N(L93)=0,"To be quoted",IF($T93="P","Priced","Benchmark")) -> Benchmark | Q93: 1 | R93: BENCHMARK (CAM market) — Concrete block PP market | S93: =TRIM(G93)&"|"&TRIM(H93) -> concrete block, thickness 200mm, laid in cement:sand mortar 1:4|m2 | T93: B
A94: PL-089 | B94: Architecture | C94: C.01 | D94: Exterior Wall and Partition | E94: AAC block | F94: AAC block 100mm Thk. | G94: AAC lightweight block 100mm thk. laid in thin-bed adhesive mortar | H94: m2 | I94: 3.5 | J94: =_STDLAB -> 0.2 | K94: =IFERROR(I94*(1+J94),0) -> 4.2 | L94: 9.5 | M94: =_STDMAT -> 0.12 | N94: =IFERROR(L94*(1+M94),0) -> 10.64 | O94: =K94+N94 -> 14.84 | P94: =IF(N(I94)+N(L94)=0,"To be quoted",IF($T94="P","Priced","Benchmark")) -> Benchmark | Q94: 1 | R94: BENCHMARK (CAM market) — AAC + thin-bed adhesive | S94: =TRIM(G94)&"|"&TRIM(H94) -> AAC lightweight block 100mm thk. laid in thin-bed adhesive mortar|m2 | T94: B
A95: PL-090 | B95: Architecture | C95: C.01 | D95: Exterior Wall and Partition | E95: AAC block | F95: AAC block 150mm Thk. | G95: AAC lightweight block 150mm thk. laid in thin-bed adhesive mortar | H95: m2 | I95: 4 | J95: =_STDLAB -> 0.2 | K95: =IFERROR(I95*(1+J95),0) -> 4.8 | L95: 13 | M95: =_STDMAT -> 0.12 | N95: =IFERROR(L95*(1+M95),0) -> 14.56 | O95: =K95+N95 -> 19.36 | P95: =IF(N(I95)+N(L95)=0,"To be quoted",IF($T95="P","Priced","Benchmark")) -> Benchmark | Q95: 1 | R95: BENCHMARK (CAM market) — AAC + thin-bed adhesive | S95: =TRIM(G95)&"|"&TRIM(H95) -> AAC lightweight block 150mm thk. laid in thin-bed adhesive mortar|m2 | T95: B
A96: PL-091 | B96: Architecture | C96: C.01 | D96: Exterior Wall and Partition | E96: AAC block | F96: AAC block 200mm Thk. | G96: AAC lightweight block 200mm thk. laid in thin-bed adhesive mortar | H96: m2 | I96: 4.5 | J96: =_STDLAB -> 0.2 | K96: =IFERROR(I96*(1+J96),0) -> 5.4 | L96: 16.5 | M96: =_STDMAT -> 0.12 | N96: =IFERROR(L96*(1+M96),0) -> 18.48 | O96: =K96+N96 -> 23.88 | P96: =IF(N(I96)+N(L96)=0,"To be quoted",IF($T96="P","Priced","Benchmark")) -> Benchmark | Q96: 1 | R96: BENCHMARK (CAM market) — AAC + thin-bed adhesive | S96: =TRIM(G96)&"|"&TRIM(H96) -> AAC lightweight block 200mm thk. laid in thin-bed adhesive mortar|m2 | T96: B
A97: PL-092 | B97: Architecture | C97: C.01 | D97: Exterior Wall and Partition | E97: Precast concrete panel | F97: Precast wall panel | G97: Precast concrete wall panel incl. lifting, setting and jointing | H97: m2 | I97: 6 | J97: =_STDLAB -> 0.2 | K97: =IFERROR(I97*(1+J97),0) -> 7.2 | L97: 32 | M97: =_STDMAT -> 0.12 | N97: =IFERROR(L97*(1+M97),0) -> 35.84 | O97: =K97+N97 -> 43.04 | P97: =IF(N(I97)+N(L97)=0,"To be quoted",IF($T97="P","Priced","Benchmark")) -> Benchmark | Q97: 1 | R97: BENCHMARK (CAM market) — Panel supply + lift + set | S97: =TRIM(G97)&"|"&TRIM(H97) -> Precast concrete wall panel incl. lifting, setting and jointing|m2 | T97: B
A98: PL-093 | B98: Architecture | C98: C.01 | D98: Exterior Wall and Partition | E98: Precast concrete panel | F98: Panel jointing & sealant | G98: Panel joint backer rod and weatherproof silicone sealant | H98: m | I98: 1.2 | J98: =_STDLAB -> 0.2 | K98: =IFERROR(I98*(1+J98),0) -> 1.44 | L98: 2 | M98: =_STDMAT -> 0.12 | N98: =IFERROR(L98*(1+M98),0) -> 2.24 | O98: =K98+N98 -> 3.68 | P98: =IF(N(I98)+N(L98)=0,"To be quoted",IF($T98="P","Priced","Benchmark")) -> Benchmark | Q98: 1 | R98: BENCHMARK (CAM market) — Sealant + backer rod | S98: =TRIM(G98)&"|"&TRIM(H98) -> Panel joint backer rod and weatherproof silicone sealant|m | T98: B
A99: PL-094 | B99: Architecture | C99: C.01 | D99: Exterior Wall and Partition | E99: External façade | F99: External façade | G99: concrete block | H99: m2 | I99: 4 | J99: 0.2 | K99: =IFERROR(I99*(1+J99),0) -> 4.8 | L99: 9 | M99: 0.12 | N99: =IFERROR(L99*(1+M99),0) -> 10.08 | O99: =K99+N99 -> 14.88 | P99: =IF(N(I99)+N(L99)=0,"To be quoted",IF($T99="P","Priced","Benchmark")) -> Priced | Q99: 1 | R99: Concrete block facade wall supply+lay, est. | S99: =TRIM(G99)&"|"&TRIM(H99) -> concrete block|m2 | T99: P
A100: PL-095 | B100: Architecture | C100: C.01 | D100: Exterior Wall and Partition | E100: External façade | F100: External façade | G100: External façade | H100: m2 | I100: 8 | J100: =_STDLAB -> 0.2 | K100: =IFERROR(I100*(1+J100),0) -> 9.6 | L100: 45 | M100: =_STDMAT -> 0.12 | N100: =IFERROR(L100*(1+M100),0) -> 50.4 | O100: =K100+N100 -> 60 | P100: =IF(N(I100)+N(L100)=0,"To be quoted",IF($T100="P","Priced","Benchmark")) -> Benchmark | Q100: 1 | R100: BENCHMARK (CAM market) — Generic facade allowance - confirm system | S100: =TRIM(G100)&"|"&TRIM(H100) -> External façade|m2 | T100: B
A101: PL-096 | B101: Architecture | C101: C.01 | D101: Exterior Wall and Partition | E101: External façade | F101: Curtain wall | G101: Aluminium curtain wall system with 8mm tempered glass incl. framing and sealant | H101: m2 | I101: 18 | J101: =_STDLAB -> 0.2 | K101: =IFERROR(I101*(1+J101),0) -> 21.6 | L101: 95 | M101: =_STDMAT -> 0.12 | N101: =IFERROR(L101*(1+M101),0) -> 106.4 | O101: =K101+N101 -> 128 | P101: =IF(N(I101)+N(L101)=0,"To be quoted",IF($T101="P","Priced","Benchmark")) -> Benchmark | Q101: 1 | R101: BENCHMARK (CAM market) — Alu frame + 8mm tempered glass | S101: =TRIM(G101)&"|"&TRIM(H101) -> Aluminium curtain wall system with 8mm tempered glass incl. framing and sealant|m2 | T101: B
A102: PL-097 | B102: Architecture | C102: C.01 | D102: Exterior Wall and Partition | E102: External façade | F102: Aluminium composite panel | G102: Aluminium composite panel 4mm, PVDF finish, incl. sub-frame and sealant | H102: m2 | I102: 12 | J102: =_STDLAB -> 0.2 | K102: =IFERROR(I102*(1+J102),0) -> 14.4 | L102: 45 | M102: =_STDMAT -> 0.12 | N102: =IFERROR(L102*(1+M102),0) -> 50.4 | O102: =K102+N102 -> 64.8 | P102: =IF(N(I102)+N(L102)=0,"To be quoted",IF($T102="P","Priced","Benchmark")) -> Benchmark | Q102: 1 | R102: BENCHMARK (CAM market) — ACP 4mm PVDF + sub-frame | S102: =TRIM(G102)&"|"&TRIM(H102) -> Aluminium composite panel 4mm, PVDF finish, incl. sub-frame and sealant|m2 | T102: B
A103: PL-098 | B103: Architecture | C103: C.01 | D103: Exterior Wall and Partition | E103: External façade | F103: Louver screen | G103: Aluminium louver screen incl. sub-frame and fixing | H103: m2 | I103: 9 | J103: =_STDLAB -> 0.2 | K103: =IFERROR(I103*(1+J103),0) -> 10.8 | L103: 42 | M103: =_STDMAT -> 0.12 | N103: =IFERROR(L103*(1+M103),0) -> 47.04 | O103: =K103+N103 -> 57.84 | P103: =IF(N(I103)+N(L103)=0,"To be quoted",IF($T103="P","Priced","Benchmark")) -> Benchmark | Q103: 1 | R103: BENCHMARK (CAM market) — Alu louver screen + frame | S103: =TRIM(G103)&"|"&TRIM(H103) -> Aluminium louver screen incl. sub-frame and fixing|m2 | T103: B
A104: PL-099 | B104: Architecture | C104: C.02 | D104: Exterior Wall Finishes | E104: Plastering | F104: Plastering | G104: 20mm cement plaster | H104: m2 | I104: 2.5 | J104: 0.2 | K104: =IFERROR(I104*(1+J104),0) -> 3 | L104: 2 | M104: 0.12 | N104: =IFERROR(L104*(1+M104),0) -> 2.24 | O104: =K104+N104 -> 5.24 | P104: =IF(N(I104)+N(L104)=0,"To be quoted",IF($T104="P","Priced","Benchmark")) -> Priced | Q104: 3 | R104: 2-coat 20mm cement:sand plaster; ~6kg cement+sand/m2; PP est. | S104: =TRIM(G104)&"|"&TRIM(H104) -> 20mm cement plaster|m2 | T104: P
A105: PL-100 | B105: Architecture | C105: C.02 | D105: Exterior Wall Finishes | E105: Plastering | F105: Plastering | G105: 15mm cement plaster | H105: m2 | I105: 2.2 | J105: =_STDLAB -> 0.2 | K105: =IFERROR(I105*(1+J105),0) -> 2.64 | L105: 1.7 | M105: =_STDMAT -> 0.12 | N105: =IFERROR(L105*(1+M105),0) -> 1.904 | O105: =K105+N105 -> 4.544 | P105: =IF(N(I105)+N(L105)=0,"To be quoted",IF($T105="P","Priced","Benchmark")) -> Benchmark | Q105: 3 | R105: BENCHMARK (CAM market) — 1 coat 15mm; cement+sand PP | S105: =TRIM(G105)&"|"&TRIM(H105) -> 15mm cement plaster|m2 | T105: B
A106: PL-101 | B106: Architecture | C106: C.02 | D106: Exterior Wall Finishes | E106: Plastering | F106: Skim coat | G106: Skim coat, 2 coats, sanded ready to receive paint | H106: m2 | I106: 1.4 | J106: =_STDLAB -> 0.2 | K106: =IFERROR(I106*(1+J106),0) -> 1.68 | L106: 1.1 | M106: =_STDMAT -> 0.12 | N106: =IFERROR(L106*(1+M106),0) -> 1.232 | O106: =K106+N106 -> 2.912 | P106: =IF(N(I106)+N(L106)=0,"To be quoted",IF($T106="P","Priced","Benchmark")) -> Benchmark | Q106: 2 | R106: BENCHMARK (CAM market) — 2 coats skim, sanded | S106: =TRIM(G106)&"|"&TRIM(H106) -> Skim coat, 2 coats, sanded ready to receive paint|m2 | T106: B
A107: PL-102 | B107: Architecture | C107: C.02 | D107: Exterior Wall Finishes | E107: Plastering | F107: Molding / Cornice | G107: Cement molding / cornice incl. forming and finishing | H107: m | I107: 4.5 | J107: =_STDLAB -> 0.2 | K107: =IFERROR(I107*(1+J107),0) -> 5.4 | L107: 2.5 | M107: =_STDMAT -> 0.12 | N107: =IFERROR(L107*(1+M107),0) -> 2.8 | O107: =K107+N107 -> 8.2 | P107: =IF(N(I107)+N(L107)=0,"To be quoted",IF($T107="P","Priced","Benchmark")) -> Benchmark | Q107: 1 | R107: BENCHMARK (CAM market) — Formed cement molding | S107: =TRIM(G107)&"|"&TRIM(H107) -> Cement molding / cornice incl. forming and finishing|m | T107: B
...

Sheet Preliminaries Library
A1: PRELIMINARIES LIBRARY (Z) — TIME-RELATED, FIXED & QUANTITY-RELATED COST
A2: PROGRAMME DURATION (months) | C2: 18 | E2: Change the duration once — every Time-related item re-calculates. This single cell is the biggest driver of preliminaries cost.
A3: STANDARD PRELIM MARGIN | C3: 0 | E3: Margin normally 0% here: preliminaries are carried at cost and overhead / profit is added on the Tender Cover.
A5: Item Code | B5: Budget Code | C5: Section | D5: Sub Section | E5: Sub Element | F5: Description | G5: Unit | H5: Cost Type | I5: Include (Y/N) | J5: Qty | K5: Net Cost ($) | L5: Margin (%) | M5: Rate ($) | N5: Amount ($) | O5: Basis / Source
A6: PR-001 | B6: Z.01.01 | C6: Contractor's Preliminaries / Design / Other | D6: Temporary Works | E6: Site Preparation | F6: Site clearing and grubbing before mobilization | G6: Item | H6: Fixed lump sum | I6: Y | J6: 1 | K6: 3000 | L6: =_STDPRE -> 0 | M6: =IFERROR(K6*(1+L6),0) -> 3000 | N6: =IF($I6="Y",N(J6)*N(M6),0) -> 3000 | O6: Clear site prior to setting up
A7: PR-002 | B7: Z.01.01 | C7: Contractor's Preliminaries / Design / Other | D7: Temporary Works | E7: Site Preparation | F7: Temporary access road and hardstanding | G7: Item | H7: Fixed lump sum | I7: Y | J7: 1 | K7: 7000 | L7: =_STDPRE -> 0 | M7: =IFERROR(K7*(1+L7),0) -> 7000 | N7: =IF($I7="Y",N(J7)*N(M7),0) -> 7000 | O7: Project rate Z.17
A8: PR-003 | B8: Z.01.01 | C8: Contractor's Preliminaries / Design / Other | D8: Temporary Works | E8: Site Preparation | F8: Temporary laydown / stacking area formation | G8: Item | H8: Fixed lump sum | I8: Y | J8: 1 | K8: 3500 | L8: =_STDPRE -> 0 | M8: =IFERROR(K8*(1+L8),0) -> 3500 | N8: =IF($I8="Y",N(J8)*N(M8),0) -> 3500 | O8: Crushed stone laydown area
A9: PR-004 | B9: Z.01.01 | C9: Contractor's Preliminaries / Design / Other | D9: Temporary Works | E9: Site Preparation | F9: Temporary drainage and site dewatering | G9: Month | H9: Time-related | I9: Y | J9: =_MONTHS -> 18 | K9: 250 | L9: =_STDPRE -> 0 | M9: =IFERROR(K9*(1+L9),0) -> 250 | N9: =IF($I9="Y",N(J9)*N(M9),0) -> 4500 | O9: Pump, sump and discharge
A10: PR-005 | B10: Z.01.01 | C10: Contractor's Preliminaries / Design / Other | D10: Temporary Works | E10: Site Preparation | F10: Washing bay / wheel wash for trucks | G10: Item | H10: Fixed lump sum | I10: Y | J10: 1 | K10: 10000 | L10: =_STDPRE -> 0 | M10: =IFERROR(K10*(1+L10),0) -> 10000 | N10: =IF($I10="Y",N(J10)*N(M10),0) -> 10000 | O10: Project rate Z.21
A11: PR-006 | B11: Z.01.01 | C11: Contractor's Preliminaries / Design / Other | D11: Temporary Works | E11: Site Preparation | F11: Temporary sheet pile to site boundary, 6m depth | G11: m | H11: Quantity-related | I11: N | K11: 180 | L11: =_STDPRE -> 0 | M11: =IFERROR(K11*(1+L11),0) -> 180 | N11: =IF($I11="Y",N(J11)*N(M11),0) -> 0 | O11: Project rate Z.22 — only if required
A12: PR-007 | B12: Z.01.01 | C12: Contractor's Preliminaries / Design / Other | D12: Temporary Works | E12: Site Preparation | F12: Setting out, survey and benchmark establishment | G12: Month | H12: Time-related | I12: Y | J12: =_MONTHS -> 18 | K12: 400 | L12: =_STDPRE -> 0 | M12: =IFERROR(K12*(1+L12),0) -> 400 | N12: =IF($I12="Y",N(J12)*N(M12),0) -> 7200 | O12: Project rate Z.09
F13: Subtotal — Z.01.01 Site Preparation | N13: =SUM(N6:N12) -> 35200
A14: PR-008 | B14: Z.01.02 | C14: Contractor's Preliminaries / Design / Other | D14: Temporary Works | E14: General Protection | F14: Temporary fencing and hoarding to site boundary | G14: Item | H14: Fixed lump sum | I14: Y | J14: 1 | K14: 8000 | L14: =_STDPRE -> 0 | M14: =IFERROR(K14*(1+L14),0) -> 8000 | N14: =IF($I14="Y",N(J14)*N(M14),0) -> 8000 | O14: Project rate Z.03
A15: PR-009 | B15: Z.01.02 | C15: Contractor's Preliminaries / Design / Other | D15: Temporary Works | E15: General Protection | F15: Temporary site gate with lock | G15: Nos | H15: Quantity-related | I15: Y | K15: 800 | L15: =_STDPRE -> 0 | M15: =IFERROR(K15*(1+L15),0) -> 800 | N15: =IF($I15="Y",N(J15)*N(M15),0) -> 0 | O15: Main and secondary gate
A16: PR-010 | B16: Z.01.02 | C16: Contractor's Preliminaries / Design / Other | D16: Temporary Works | E16: General Protection | F16: Safety net to building perimeter | G16: Item | H16: Fixed lump sum | I16: Y | J16: 1 | K16: 6000 | L16: =_STDPRE -> 0 | M16: =IFERROR(K16*(1+L16),0) -> 6000 | N16: =IF($I16="Y",N(J16)*N(M16),0) -> 6000 | O16: Project rate Z.20
A17: PR-011 | B17: Z.01.02 | C17: Contractor's Preliminaries / Design / Other | D17: Temporary Works | E17: General Protection | F17: Edge protection and guard rail to slab edge | G17: m | H17: Quantity-related | I17: Y | K17: 12 | L17: =_STDPRE -> 0 | M17: =IFERROR(K17*(1+L17),0) -> 12 | N17: =IF($I17="Y",N(J17)*N(M17),0) -> 0 | O17: Per metre of exposed edge
A18: PR-012 | B18: Z.01.02 | C18: Contractor's Preliminaries / Design / Other | D18: Temporary Works | E18: General Protection | F18: Debris netting and catch fan | G18: Item | H18: Fixed lump sum | I18: Y | J18: 1 | K18: 4500 | L18: =_STDPRE -> 0 | M18: =IFERROR(K18*(1+L18),0) -> 4500 | N18: =IF($I18="Y",N(J18)*N(M18),0) -> 4500 | O18: High-rise debris control
A19: PR-013 | B19: Z.01.02 | C19: Contractor's Preliminaries / Design / Other | D19: Temporary Works | E19: General Protection | F19: Temporary protection to completed finishes | G19: Item | H19: Fixed lump sum | I19: Y | J19: 1 | K19: 3000 | L19: =_STDPRE -> 0 | M19: =IFERROR(K19*(1+L19),0) -> 3000 | N19: =IF($I19="Y",N(J19)*N(M19),0) -> 3000 | O19: Corner guard, floor covering
A20: PR-014 | B20: Z.01.02 | C20: Contractor's Preliminaries / Design / Other | D20: Temporary Works | E20: General Protection | F20: Weather protection and tarpaulin | G20: Item | H20: Fixed lump sum | I20: Y | J20: 1 | K20: 2000 | L20: =_STDPRE -> 0 | M20: =IFERROR(K20*(1+L20),0) -> 2000 | N20: =IF($I20="Y",N(J20)*N(M20),0) -> 2000 | O20: Rainy season protection
F21: Subtotal — Z.01.02 General Protection | N21: =SUM(N14:N20) -> 23500
A22: PR-015 | B22: Z.01.03 | C22: Contractor's Preliminaries / Design / Other | D22: Temporary Works | E22: Temporary Building | F22: Site office - main contractor | G22: Month | H22: Time-related | I22: Y | J22: =_MONTHS -> 18 | K22: 900 | L22: =_STDPRE -> 0 | M22: =IFERROR(K22*(1+L22),0) -> 900 | N22: =IF($I22="Y",N(J22)*N(M22),0) -> 16200 | O22: Container office hire, part of project Z.01
A23: PR-016 | B23: Z.01.03 | C23: Contractor's Preliminaries / Design / Other | D23: Temporary Works | E23: Temporary Building | F23: Site office - consultant / client | G23: Month | H23: Time-related | I23: Y | J23: =_MONTHS -> 18 | K23: 450 | L23: =_STDPRE -> 0 | M23: =IFERROR(K23*(1+L23),0) -> 450 | N23: =IF($I23="Y",N(J23)*N(M23),0) -> 8100 | O23: Client facility if required by contract
A24: PR-017 | B24: Z.01.03 | C24: Contractor's Preliminaries / Design / Other | D24: Temporary Works | E24: Temporary Building | F24: Meeting room | G24: Month | H24: Time-related | I24: Y | J24: =_MONTHS -> 18 | K24: 200 | L24: =_STDPRE -> 0 | M24: =IFERROR(K24*(1+L24),0) -> 200 | N24: =IF($I24="Y",N(J24)*N(M24),0) -> 3600 | O24: Shared meeting facility
A25: PR-018 | B25: Z.01.03 | C25: Contractor's Preliminaries / Design / Other | D25: Temporary Works | E25: Temporary Building | F25: Material store and workshop | G25: Month | H25: Time-related | I25: Y | J25: =_MONTHS -> 18 | K25: 350 | L25: =_STDPRE -> 0 | M25: =IFERROR(K25*(1+L25),0) -> 350 | N25: =IF($I25="Y",N(J25)*N(M25),0) -> 6300 | O25: Secure store
A26: PR-019 | B26: Z.01.03 | C26: Contractor's Preliminaries / Design / Other | D26: Temporary Works | E26: Temporary Building | F26: Worker rest area and canteen | G26: Month | H26: Time-related | I26: Y | J26: =_MONTHS -> 18 | K26: 250 | L26: =_STDPRE -> 0 | M26: =IFERROR(K26*(1+L26),0) -> 250 | N26: =IF($I26="Y",N(J26)*N(M26),0) -> 4500 | O26: Welfare facility
A27: PR-020 | B27: Z.01.03 | C27: Contractor's Preliminaries / Design / Other | D27: Temporary Works | E27: Temporary Building | F27: Site toilet and washing facility | G27: Month | H27: Time-related | I27: Y | J27: =_MONTHS -> 18 | K27: 200 | L27: =_STDPRE -> 0 | M27: =IFERROR(K27*(1+L27),0) -> 200 | N27: =IF($I27="Y",N(J27)*N(M27),0) -> 3600 | O27: Portable toilet hire and servicing
A28: PR-021 | B28: Z.01.03 | C28: Contractor's Preliminaries / Design / Other | D28: Temporary Works | E28: Temporary Building | F28: First aid room | G28: Month | H28: Time-related | I28: Y | J28: =_MONTHS -> 18 | K28: 100 | L28: =_STDPRE -> 0 | M28: =IFERROR(K28*(1+L28),0) -> 100 | N28: =IF($I28="Y",N(J28)*N(M28),0) -> 1800 | O28: Statutory welfare
A29: PR-022 | B29: Z.01.03 | C29: Contractor's Preliminaries / Design / Other | D29: Temporary Works | E29: Temporary Building | F29: Guard house | G29: Item | H29: Fixed lump sum | I29: Y | J29: 1 | K29: 1500 | L29: =_STDPRE -> 0 | M29: =IFERROR(K29*(1+L29),0) -> 1500 | N29: =IF($I29="Y",N(J29)*N(M29),0) -> 1500 | O29: Prefabricated guard post
A30: PR-023 | B30: Z.01.03 | C30: Contractor's Preliminaries / Design / Other | D30: Temporary Works | E30: Temporary Building | F30: Office furniture, equipment and IT | G30: Item | H30: Fixed lump sum | I30: Y | J30: 1 | K30: 4000 | L30: =_STDPRE -> 0 | M30: =IFERROR(K30*(1+L30),0) -> 4000 | N30: =IF($I30="Y",N(J30)*N(M30),0) -> 4000 | O30: Desk, chair, printer, computer
A31: PR-024 | B31: Z.01.03 | C31: Contractor's Preliminaries / Design / Other | D31: Temporary Works | E31: Temporary Building | F31: Project signboard and site branding | G31: Item | H31: Fixed lump sum | I31: Y | J31: 1 | K31: 1500 | L31: =_STDPRE -> 0 | M31: =IFERROR(K31*(1+L31),0) -> 1500 | N31: =IF($I31="Y",N(J31)*N(M31),0) -> 1500 | O31: Authority and client requirement
F32: Subtotal — Z.01.03 Temporary Building | N32: =SUM(N22:N31) -> 51100
A33: PR-025 | B33: Z.01.04 | C33: Contractor's Preliminaries / Design / Other | D33: Temporary Works | E33: Temporary site labor | F33: General site labour / helper gang | G33: Month | H33: Time-related | I33: Y | J33: =_MONTHS -> 18 | K33: 1200 | L33: =_STDPRE -> 0 | M33: =IFERROR(K33*(1+L33),0) -> 1200 | N33: =IF($I33="Y",N(J33)*N(M33),0) -> 21600 | O33: Attendance labour gang
A34: PR-026 | B34: Z.01.04 | C34: Contractor's Preliminaries / Design / Other | D34: Temporary Works | E34: Temporary site labor | F34: Progressive site cleaning labour | G34: Month | H34: Time-related | I34: Y | J34: =_MONTHS -> 18 | K34: 450 | L34: =_STDPRE -> 0 | M34: =IFERROR(K34*(1+L34),0) -> 450 | N34: =IF($I34="Y",N(J34)*N(M34),0) -> 8100 | O34: Part of project Z.08
A35: PR-027 | B35: Z.01.04 | C35: Contractor's Preliminaries / Design / Other | D35: Temporary Works | E35: Temporary site labor | F35: Waste collection, skip hire and disposal | G35: Month | H35: Time-related | I35: Y | J35: =_MONTHS -> 18 | K35: 150 | L35: =_STDPRE -> 0 | M35: =IFERROR(K35*(1+L35),0) -> 150 | N35: =IF($I35="Y",N(J35)*N(M35),0) -> 2700 | O35: Tipping and cart away
A36: PR-028 | B36: Z.01.04 | C36: Contractor's Preliminaries / Design / Other | D36: Temporary Works | E36: Temporary site labor | F36: Final cleaning before handover | G36: Item | H36: Fixed lump sum | I36: Y | J36: 1 | K36: 4500 | L36: =_STDPRE -> 0 | M36: =IFERROR(K36*(1+L36),0) -> 4500 | N36: =IF($I36="Y",N(J36)*N(M36),0) -> 4500 | O36: Builders clean at completion
A37: PR-029 | B37: Z.01.04 | C37: Contractor's Preliminaries / Design / Other | D37: Temporary Works | E37: Temporary site labor | F37: Traffic marshal / banksman | G37: Month | H37: Time-related | I37: Y | J37: =_MONTHS -> 18 | K37: 350 | L37: =_STDPRE -> 0 | M37: =IFERROR(K37*(1+L37),0) -> 350 | N37: =IF($I37="Y",N(J37)*N(M37),0) -> 6300 | O37: Vehicle and crane movement control
A38: PR-030 | B38: Z.01.04 | C38: Contractor's Preliminaries / Design / Other | D38: Temporary Works | E38: Temporary site labor | F38: Rigger and signalman for lifting | G38: Month | H38: Time-related | I38: Y | J38: =_MONTHS -> 18 | K38: 400 | L38: =_STDPRE -> 0 | M38: =IFERROR(K38*(1+L38),0) -> 400 | N38: =IF($I38="Y",N(J38)*N(M38),0) -> 7200 | O38: Crane lifting support
F39: Subtotal — Z.01.04 Temporary site labor | N39: =SUM(N33:N38) -> 50400
A40: PR-031 | B40: Z.01.05 | C40: Contractor's Preliminaries / Design / Other | D40: Temporary Works | E40: Machinery | F40: Tower crane - erection, foundation and dismantling | G40: Item | H40: Fixed lump sum | I40: Y | J40: 1 | K40: 18000 | L40: =_STDPRE -> 0 | M40: =IFERROR(K40*(1+L40),0) -> 18000 | N40: =IF($I40="Y",N(J40)*N(M40),0) -> 18000 | O40: One-off; separate from monthly hire
A41: PR-032 | B41: Z.01.05 | C41: Contractor's Preliminaries / Design / Other | D41: Temporary Works | E41: Machinery | F41: Tower crane - monthly hire | G41: Month | H41: Time-related | I41: Y | J41: =_MONTHS -> 18 | K41: 3200 | L41: =_STDPRE -> 0 | M41: =IFERROR(K41*(1+L41),0) -> 3200 | N41: =IF($I41="Y",N(J41)*N(M41),0) -> 57600 | O41: Part of project Z.19
A42: PR-033 | B42: Z.01.05 | C42: Contractor's Preliminaries / Design / Other | D42: Temporary Works | E42: Machinery | F42: Tower crane - operator and power | G42: Month | H42: Time-related | I42: Y | J42: =_MONTHS -> 18 | K42: 1300 | L42: =_STDPRE -> 0 | M42: =IFERROR(K42*(1+L42),0) -> 1300 | N42: =IF($I42="Y",N(J42)*N(M42),0) -> 23400 | O42: Operator plus running cost
A43: PR-034 | B43: Z.01.05 | C43: Contractor's Preliminaries / Design / Other | D43: Temporary Works | E43: Machinery | F43: Passenger / material hoist | G43: Month | H43: Time-related | I43: Y | J43: =_MONTHS -> 18 | K43: 1800 | L43: =_STDPRE -> 0 | M43: =IFERROR(K43*(1+L43),0) -> 1800 | N43: =IF($I43="Y",N(J43)*N(M43),0) -> 32400 | O43: Essential for 10 storeys
A44: PR-035 | B44: Z.01.05 | C44: Contractor's Preliminaries / Design / Other | D44: Temporary Works | E44: Machinery | F44: Mobile crane (call-out basis) | G44: Nos | H44: Quantity-related | I44: N | K44: 450 | L44: =_STDPRE -> 0 | M44: =IFERROR(K44*(1+L44),0) -> 450 | N44: =IF($I44="Y",N(J44)*N(M44),0) -> 0 | O44: Per lift / per day call-out
A45: PR-036 | B45: Z.01.05 | C45: Contractor's Preliminaries / Design / Other | D45: Temporary Works | E45: Machinery | F45: Concrete pump (call-out basis) | G45: Nos | H45: Quantity-related | I45: N | K45: 550 | L45: =_STDPRE -> 0 | M45: =IFERROR(K45*(1+L45),0) -> 550 | N45: =IF($I45="Y",N(J45)*N(M45),0) -> 0 | O45: Per pour if not in concrete rate
A46: PR-037 | B46: Z.01.05 | C46: Contractor's Preliminaries / Design / Other | D46: Temporary Works | E46: Machinery | F46: Excavator / backhoe | G46: Month | H46: Time-related | I46: N | J46: =_MONTHS -> 18 | K46: 2200 | L46: =_STDPRE -> 0 | M46: =IFERROR(K46*(1+L46),0) -> 2200 | N46: =IF($I46="Y",N(J46)*N(M46),0) -> 0 | O46: Substructure phase only
A47: PR-038 | B47: Z.01.05 | C47: Contractor's Preliminaries / Design / Other | D47: Temporary Works | E47: Machinery | F47: Truck and site transport | G47: Month | H47: Time-related | I47: Y | J47: =_MONTHS -> 18 | K47: 800 | L47: =_STDPRE -> 0 | M47: =IFERROR(K47*(1+L47),0) -> 800 | N47: =IF($I47="Y",N(J47)*N(M47),0) -> 14400 | O47: Material movement
A48: PR-039 | B48: Z.01.05 | C48: Contractor's Preliminaries / Design / Other | D48: Temporary Works | E48: Machinery | F48: Scaffolding - supply, erect and dismantle | G48: m2 | H48: Quantity-related | I48: Y | K48: 7 | L48: =_STDPRE -> 0 | M48: =IFERROR(K48*(1+L48),0) -> 7 | N48: =IF($I48="Y",N(J48)*N(M48),0) -> 0 | O48: Facade area; project Z.18 basis
A49: PR-040 | B49: Z.01.05 | C49: Contractor's Preliminaries / Design / Other | D49: Temporary Works | E49: Machinery | F49: Scaffolding - hire beyond base period | G49: m2 | H49: Quantity-related | I49: N | K49: 1.5 | L49: =_STDPRE -> 0 | M49: =IFERROR(K49*(1+L49),0) -> 1.5 | N49: =IF($I49="Y",N(J49)*N(M49),0) -> 0 | O49: Extended hire per month
A50: PR-041 | B50: Z.01.05 | C50: Contractor's Preliminaries / Design / Other | D50: Temporary Works | E50: Machinery | F50: Gondola / suspended platform for facade | G50: Month | H50: Time-related | I50: N | J50: =_MONTHS -> 18 | K50: 1500 | L50: =_STDPRE -> 0 | M50: =IFERROR(K50*(1+L50),0) -> 1500 | N50: =IF($I50="Y",N(J50)*N(M50),0) -> 0 | O50: Alternative to full scaffold
F51: Subtotal — Z.01.05 Machinery | N51: =SUM(N40:N50) -> 145800
A52: PR-042 | B52: Z.01.06 | C52: Contractor's Preliminaries / Design / Other | D52: Temporary Works | E52: Light equiment hand tools | F52: Small tools and consumables | G52: Month | H52: Time-related | I52: Y | J52: =_MONTHS -> 18 | K52: 600 | L52: =_STDPRE -> 0 | M52: =IFERROR(K52*(1+L52),0) -> 600 | N52: =IF($I52="Y",N(J52)*N(M52),0) -> 10800 | O52: Allowance per month
A53: PR-043 | B53: Z.01.06 | C53: Contractor's Preliminaries / Design / Other | D53: Temporary Works | E53: Light equiment hand tools | F53: Power tools and maintenance | G53: Month | H53: Time-related | I53: Y | J53: =_MONTHS -> 18 | K53: 350 | L53: =_STDPRE -> 0 | M53: =IFERROR(K53*(1+L53),0) -> 350 | N53: =IF($I53="Y",N(J53)*N(M53),0) -> 6300 | O53: Drills, grinders, saws
A54: PR-044 | B54: Z.01.06 | C54: Contractor's Preliminaries / Design / Other | D54: Temporary Works | E54: Light equiment hand tools | F54: Welding machine and consumables | G54: Month | H54: Time-related | I54: Y | J54: =_MONTHS -> 18 | K54: 300 | L54: =_STDPRE -> 0 | M54: =IFERROR(K54*(1+L54),0) -> 300 | N54: =IF($I54="Y",N(J54)*N(M54),0) -> 5400 | O54: Steelwork phase
A55: PR-045 | B55: Z.01.06 | C55: Contractor's Preliminaries / Design / Other | D55: Temporary Works | E55: Light equiment hand tools | F55: Survey instrument (total station / auto level) | G55: Month | H55: Time-related | I55: Y | J55: =_MONTHS -> 18 | K55: 250 | L55: =_STDPRE -> 0 | M55: =IFERROR(K55*(1+L55),0) -> 250 | N55: =IF($I55="Y",N(J55)*N(M55),0) -> 4500 | O55: Hire and calibration
A56: PR-046 | B56: Z.01.06 | C56: Contractor's Preliminaries / Design / Other | D56: Temporary Works | E56: Light equiment hand tools | F56: Compactor, poker vibrator and mixer | G56: Month | H56: Time-related | I56: Y | J56: =_MONTHS -> 18 | K56: 300 | L56: =_STDPRE -> 0 | M56: =IFERROR(K56*(1+L56),0) -> 300 | N56: =IF($I56="Y",N(J56)*N(M56),0) -> 5400 | O56: Concrete and earthwork plant
A57: PR-047 | B57: Z.01.06 | C57: Contractor's Preliminaries / Design / Other | D57: Temporary Works | E57: Light equiment hand tools | F57: Water pump and hose | G57: Month | H57: Time-related | I57: Y | J57: =_MONTHS -> 18 | K57: 150 | L57: =_STDPRE -> 0 | M57: =IFERROR(K57*(1+L57),0) -> 150 | N57: =IF($I57="Y",N(J57)*N(M57),0) -> 2700 | O57: Curing and dewatering
F58: Subtotal — Z.01.06 Light equiment hand tools | N58: =SUM(N52:N57) -> 35100
A59: PR-048 | B59: Z.01.07 | C59: Contractor's Preliminaries / Design / Other | D59: Temporary Works | E59: Temporary Elecrical Plumbing Drainage | F59: Temporary electricity - connection, meter and deposit | G59: Item | H59: Fixed lump sum | I59: Y | J59: 1 | K59: 3500 | L59: =_STDPRE -> 0 | M59: =IFERROR(K59*(1+L59),0) -> 3500 | N59: =IF($I59="Y",N(J59)*N(M59),0) -> 3500 | O59: Utility connection charge
A60: PR-049 | B60: Z.01.07 | C60: Contractor's Preliminaries / Design / Other | D60: Temporary Works | E60: Temporary Elecrical Plumbing Drainage | F60: Temporary electricity - monthly consumption | G60: Month | H60: Time-related | I60: Y | J60: =_MONTHS -> 18 | K60: 800 | L60: =_STDPRE -> 0 | M60: =IFERROR(K60*(1+L60),0) -> 800 | N60: =IF($I60="Y",N(J60)*N(M60),0) -> 14400 | O60: Project rate Z.05
A61: PR-050 | B61: Z.01.07 | C61: Contractor's Preliminaries / Design / Other | D61: Temporary Works | E61: Temporary Elecrical Plumbing Drainage | F61: Temporary distribution board and cabling | G61: Item | H61: Fixed lump sum | I61: Y | J61: 1 | K61: 4500 | L61: =_STDPRE -> 0 | M61: =IFERROR(K61*(1+L61),0) -> 4500 | N61: =IF($I61="Y",N(J61)*N(M61),0) -> 4500 | O61: Site power distribution
A62: PR-051 | B62: Z.01.07 | C62: Contractor's Preliminaries / Design / Other | D62: Temporary Works | E62: Temporary Elecrical Plumbing Drainage | F62: Temporary site and tower lighting | G62: Month | H62: Time-related | I62: Y | J62: =_MONTHS -> 18 | K62: 300 | L62: =_STDPRE -> 0 | M62: =IFERROR(K62*(1+L62),0) -> 300 | N62: =IF($I62="Y",N(J62)*N(M62),0) -> 5400 | O62: Working and security lighting
A63: PR-052 | B63: Z.01.07 | C63: Contractor's Preliminaries / Design / Other | D63: Temporary Works | E63: Temporary Elecrical Plumbing Drainage | F63: Standby generator | G63: Month | H63: Time-related | I63: N | J63: =_MONTHS -> 18 | K63: 900 | L63: =_STDPRE -> 0 | M63: =IFERROR(K63*(1+L63),0) -> 900 | N63: =IF($I63="Y",N(J63)*N(M63),0) -> 0 | O63: Backup power if supply unreliable
A64: PR-053 | B64: Z.01.07 | C64: Contractor's Preliminaries / Design / Other | D64: Temporary Works | E64: Temporary Elecrical Plumbing Drainage | F64: Temporary water - connection, meter and deposit | G64: Item | H64: Fixed lump sum | I64: Y | J64: 1 | K64: 1200 | L64: =_STDPRE -> 0 | M64: =IFERROR(K64*(1+L64),0) -> 1200 | N64: =IF($I64="Y",N(J64)*N(M64),0) -> 1200 | O64: Utility connection charge
A65: PR-054 | B65: Z.01.07 | C65: Contractor's Preliminaries / Design / Other | D65: Temporary Works | E65: Temporary Elecrical Plumbing Drainage | F65: Temporary water - monthly consumption | G65: Month | H65: Time-related | I65: Y | J65: =_MONTHS -> 18 | K65: 300 | L65: =_STDPRE -> 0 | M65: =IFERROR(K65*(1+L65),0) -> 300 | N65: =IF($I65="Y",N(J65)*N(M65),0) -> 5400 | O65: Project rate Z.04
A66: PR-055 | B66: Z.01.07 | C66: Contractor's Preliminaries / Design / Other | D66: Temporary Works | E66: Temporary Elecrical Plumbing Drainage | F66: Temporary plumbing and drainage | G66: Item | H66: Fixed lump sum | I66: Y | J66: 1 | K66: 2000 | L66: =_STDPRE -> 0 | M66: =IFERROR(K66*(1+L66),0) -> 2000 | N66: =IF($I66="Y",N(J66)*N(M66),0) -> 2000 | O66: Site pipework and discharge
A67: PR-056 | B67: Z.01.07 | C67: Contractor's Preliminaries / Design / Other | D67: Temporary Works | E67: Temporary Elecrical Plumbing Drainage | F67: Temporary telephone and internet | G67: Month | H67: Time-related | I67: Y | J67: =_MONTHS -> 18 | K67: 150 | L67: =_STDPRE -> 0 | M67: =IFERROR(K67*(1+L67),0) -> 150 | N67: =IF($I67="Y",N(J67)*N(M67),0) -> 2700 | O67: Site communication
F68: Subtotal — Z.01.07 Temporary Elecrical Plumbing Drainage | N68: =SUM(N59:N67) -> 39100
A69: PR-057 | B69: Z.01.08 | C69: Contractor's Preliminaries / Design / Other | D69: Temporary Works | E69: Safe and environment control | F69: Safety officer (site based) | G69: Month | H69: Time-related | I69: Y | J69: =_MONTHS -> 18 | K69: 600 | L69: =_STDPRE -> 0 | M69: =IFERROR(K69*(1+L69),0) -> 600 | N69: =IF($I69="Y",N(J69)*N(M69),0) -> 10800 | O69: Statutory requirement
A70: PR-058 | B70: Z.01.08 | C70: Contractor's Preliminaries / Design / Other | D70: Temporary Works | E70: Safe and environment control | F70: PPE - helmet, boots, vest, harness | G70: Month | H70: Time-related | I70: Y | J70: =_MONTHS -> 18 | K70: 350 | L70: =_STDPRE -> 0 | M70: =IFERROR(K70*(1+L70),0) -> 350 | N70: =IF($I70="Y",N(J70)*N(M70),0) -> 6300 | O70: Issue and replenishment; project Z.06
A71: PR-059 | B71: Z.01.08 | C71: Contractor's Preliminaries / Design / Other | D71: Temporary Works | E71: Safe and environment control | F71: Safety signage, barricade and cone | G71: Item | H71: Fixed lump sum | I71: Y | J71: 1 | K71: 2500 | L71: =_STDPRE -> 0 | M71: =IFERROR(K71*(1+L71),0) -> 2500 | N71: =IF($I71="Y",N(J71)*N(M71),0) -> 2500 | O71: Site-wide signage set
A72: PR-060 | B72: Z.01.08 | C72: Contractor's Preliminaries / Design / Other | D72: Temporary Works | E72: Safe and environment control | F72: Fire extinguisher and fire point | G72: Nos | H72: Quantity-related | I72: Y | K72: 45 | L72: =_STDPRE -> 0 | M72: =IFERROR(K72*(1+L72),0) -> 45 | N72: =IF($I72="Y",N(J72)*N(M72),0) -> 0 | O72: Per floor / per point
A73: PR-061 | B73: Z.01.08 | C73: Contractor's Preliminaries / Design / Other | D73: Temporary Works | E73: Safe and environment control | F73: First aid supplies and medical support | G73: Month | H73: Time-related | I73: Y | J73: =_MONTHS -> 18 | K73: 150 | L73: =_STDPRE -> 0 | M73: =IFERROR(K73*(1+L73),0) -> 150 | N73: =IF($I73="Y",N(J73)*N(M73),0) -> 2700 | O73: First aid kit and clinic access
A74: PR-062 | B74: Z.01.08 | C74: Contractor's Preliminaries / Design / Other | D74: Temporary Works | E74: Safe and environment control | F74: Dust control - water spray and screening | G74: Month | H74: Time-related | I74: Y | J74: =_MONTHS -> 18 | K74: 250 | L74: =_STDPRE -> 0 | M74: =IFERROR(K74*(1+L74),0) -> 250 | N74: =IF($I74="Y",N(J74)*N(M74),0) -> 4500 | O74: Environmental compliance
A75: PR-063 | B75: Z.01.08 | C75: Contractor's Preliminaries / Design / Other | D75: Temporary Works | E75: Safe and environment control | F75: Noise and vibration control | G75: Month | H75: Time-related | I75: Y | J75: =_MONTHS -> 18 | K75: 150 | L75: =_STDPRE -> 0 | M75: =IFERROR(K75*(1+L75),0) -> 150 | N75: =IF($I75="Y",N(J75)*N(M75),0) -> 2700 | O75: Environmental compliance
A76: PR-064 | B76: Z.01.08 | C76: Contractor's Preliminaries / Design / Other | D76: Temporary Works | E76: Safe and environment control | F76: Silt trap and water discharge control | G76: Item | H76: Fixed lump sum | I76: Y | J76: 1 | K76: 2500 | L76: =_STDPRE -> 0 | M76: =IFERROR(K76*(1+L76),0) -> 2500 | N76: =IF($I76="Y",N(J76)*N(M76),0) -> 2500 | O76: Prevent discharge to public drain
A77: PR-065 | B77: Z.01.08 | C77: Contractor's Preliminaries / Design / Other | D77: Temporary Works | E77: Safe and environment control | F77: Waste segregation and recycling facility | G77: Month | H77: Time-related | I77: Y | J77: =_MONTHS -> 18 | K77: 200 | L77: =_STDPRE -> 0 | M77: =IFERROR(K77*(1+L77),0) -> 200 | N77: =IF($I77="Y",N(J77)*N(M77),0) -> 3600 | O77: Green / environmental requirement
A78: PR-066 | B78: Z.01.08 | C78: Contractor's Preliminaries / Design / Other | D78: Temporary Works | E78: Safe and environment control | F78: Safety training and toolbox meeting | G78: Month | H78: Time-related | I78: Y | J78: =_MONTHS -> 18 | K78: 200 | L78: =_STDPRE -> 0 | M78: =IFERROR(K78*(1+L78),0) -> 200 | N78: =IF($I78="Y",N(J78)*N(M78),0) -> 3600 | O78: Induction and weekly toolbox
A79: PR-067 | B79: Z.01.08 | C79: Contractor's Preliminaries / Design / Other | D79: Temporary Works | E79: Safe and environment control | F79: Security guard service | G79: Month | H79: Time-related | I79: Y | J79: =_MONTHS -> 18 | K79: 900 | L79: =_STDPRE -> 0 | M79: =IFERROR(K79*(1+L79),0) -> 900 | N79: =IF($I79="Y",N(J79)*N(M79),0) -> 16200 | O79: Project rate Z.07
A80: PR-068 | B80: Z.01.08 | C80: Contractor's Preliminaries / Design / Other | D80: Temporary Works | E80: Safe and environment control | F80: CCTV and site access control | G80: Item | H80: Fixed lump sum | I80: Y | J80: 1 | K80: 4000 | L80: =_STDPRE -> 0 | M80: =IFERROR(K80*(1+L80),0) -> 4000 | N80: =IF($I80="Y",N(J80)*N(M80),0) -> 4000 | O80: Camera set and worker ID
F81: Subtotal — Z.01.08 Safe and environment control | N81: =SUM(N69:N80) -> 59400
A82: PR-069 | B82: Z.30.01 | C82: Contractor's Preliminaries / Design / Other | D82: Site Overhead | E82: Foreign Country Employee | F82: Expatriate project manager | G82: Month | H82: Time-related | I82: N | J82: =_MONTHS -> 18 | K82: 6500 | L82: =_STDPRE -> 0 | M82: =IFERROR(K82*(1+L82),0) -> 6500 | N82: =IF($I82="Y",N(J82)*N(M82),0) -> 0 | O82: Only if expatriate staffing required
A83: PR-070 | B83: Z.30.01 | C83: Contractor's Preliminaries / Design / Other | D83: Site Overhead | E83: Foreign Country Employee | F83: Expatriate construction manager | G83: Month | H83: Time-related | I83: N | J83: =_MONTHS -> 18 | K83: 5000 | L83: =_STDPRE -> 0 | M83: =IFERROR(K83*(1+L83),0) -> 5000 | N83: =IF($I83="Y",N(J83)*N(M83),0) -> 0 | O83: Optional
A84: PR-071 | B84: Z.30.01 | C84: Contractor's Preliminaries / Design / Other | D84: Site Overhead | E84: Foreign Country Employee | F84: Expatriate engineer / specialist | G84: Month | H84: Time-related | I84: N | J84: =_MONTHS -> 18 | K84: 4000 | L84: =_STDPRE -> 0 | M84: =IFERROR(K84*(1+L84),0) -> 4000 | N84: =IF($I84="Y",N(J84)*N(M84),0) -> 0 | O84: Optional
A85: PR-072 | B85: Z.30.01 | C85: Contractor's Preliminaries / Design / Other | D85: Site Overhead | E85: Foreign Country Employee | F85: Work permit, visa and statutory registration | G85: Nos | H85: Quantity-related | I85: N | K85: 900 | L85: =_STDPRE -> 0 | M85: =IFERROR(K85*(1+L85),0) -> 900 | N85: =IF($I85="Y",N(J85)*N(M85),0) -> 0 | O85: Per expatriate per year
A86: PR-073 | B86: Z.30.01 | C86: Contractor's Preliminaries / Design / Other | D86: Site Overhead | E86: Foreign Country Employee | F86: Expatriate accommodation and home flights | G86: Month | H86: Time-related | I86: N | J86: =_MONTHS -> 18 | K86: 1200 | L86: =_STDPRE -> 0 | M86: =IFERROR(K86*(1+L86),0) -> 1200 | N86: =IF($I86="Y",N(J86)*N(M86),0) -> 0 | O86: Per expatriate
F87: Subtotal — Z.30.01 Foreign Country Employee | N87: =SUM(N82:N86) -> 0
A88: PR-074 | B88: Z.30.02 | C88: Contractor's Preliminaries / Design / Other | D88: Site Overhead | E88: Local Country employee | F88: Project manager | G88: Month | H88: Time-related | I88: Y | J88: =_MONTHS -> 18 | K88: 1500 | L88: =_STDPRE -> 0 | M88: =IFERROR(K88*(1+L88),0) -> 1500 | N88: =IF($I88="Y",N(J88)*N(M88),0) -> 27000 | O88: Project Z.02 team build-up
A89: PR-075 | B89: Z.30.02 | C89: Contractor's Preliminaries / Design / Other | D89: Site Overhead | E89: Local Country employee | F89: Construction manager / site manager | G89: Month | H89: Time-related | I89: Y | J89: =_MONTHS -> 18 | K89: 1200 | L89: =_STDPRE -> 0 | M89: =IFERROR(K89*(1+L89),0) -> 1200 | N89: =IF($I89="Y",N(J89)*N(M89),0) -> 21600 | O89: Project Z.02 team build-up
A90: PR-076 | B90: Z.30.02 | C90: Contractor's Preliminaries / Design / Other | D90: Site Overhead | E90: Local Country employee | F90: Site engineer | G90: Month | H90: Time-related | I90: Y | J90: =_MONTHS -> 18 | K90: 1000 | L90: =_STDPRE -> 0 | M90: =IFERROR(K90*(1+L90),0) -> 1000 | N90: =IF($I90="Y",N(J90)*N(M90),0) -> 18000 | O90: Project Z.02 team build-up
A91: PR-077 | B91: Z.30.02 | C91: Contractor's Preliminaries / Design / Other | D91: Site Overhead | E91: Local Country employee | F91: Quantity surveyor | G91: Month | H91: Time-related | I91: Y | J91: =_MONTHS -> 18 | K91: 700 | L91: =_STDPRE -> 0 | M91: =IFERROR(K91*(1+L91),0) -> 700 | N91: =IF($I91="Y",N(J91)*N(M91),0) -> 12600 | O91: Project Z.02 team build-up
A92: PR-078 | B92: Z.30.02 | C92: Contractor's Preliminaries / Design / Other | D92: Site Overhead | E92: Local Country employee | F92: Safety officer (staff position) | G92: Month | H92: Time-related | I92: Y | J92: =_MONTHS -> 18 | K92: 600 | L92: =_STDPRE -> 0 | M92: =IFERROR(K92*(1+L92),0) -> 600 | N92: =IF($I92="Y",N(J92)*N(M92),0) -> 10800 | O92: Project Z.02 team build-up
A93: PR-079 | B93: Z.30.02 | C93: Contractor's Preliminaries / Design / Other | D93: Site Overhead | E93: Local Country employee | F93: Site supervisor / foreman | G93: Month | H93: Time-related | I93: Y | J93: =_MONTHS -> 18 | K93: 800 | L93: =_STDPRE -> 0 | M93: =IFERROR(K93*(1+L93),0) -> 800 | N93: =IF($I93="Y",N(J93)*N(M93),0) -> 14400 | O93: Project Z.02 team build-up
A94: PR-080 | B94: Z.30.02 | C94: Contractor's Preliminaries / Design / Other | D94: Site Overhead | E94: Local Country employee | F94: Land surveyor | G94: Month | H94: Time-related | I94: Y | J94: =_MONTHS -> 18 | K94: 600 | L94: =_STDPRE -> 0 | M94: =IFERROR(K94*(1+L94),0) -> 600 | N94: =IF($I94="Y",N(J94)*N(M94),0) -> 10800 | O94: Setting out and control
A95: PR-081 | B95: Z.30.02 | C95: Contractor's Preliminaries / Design / Other | D95: Site Overhead | E95: Local Country employee | F95: Storekeeper | G95: Month | H95: Time-related | I95: Y | J95: =_MONTHS -> 18 | K95: 400 | L95: =_STDPRE -> 0 | M95: =IFERROR(K95*(1+L95),0) -> 400 | N95: =IF($I95="Y",N(J95)*N(M95),0) -> 7200 | O95: Project Z.02 team build-up
A96: PR-082 | B96: Z.30.02 | C96: Contractor's Preliminaries / Design / Other | D96: Site Overhead | E96: Local Country employee | F96: Document controller / site admin | G96: Month | H96: Time-related | I96: Y | J96: =_MONTHS -> 18 | K96: 400 | L96: =_STDPRE -> 0 | M96: =IFERROR(K96*(1+L96),0) -> 400 | N96: =IF($I96="Y",N(J96)*N(M96),0) -> 7200 | O96: Records and correspondence
A97: PR-083 | B97: Z.30.02 | C97: Contractor's Preliminaries / Design / Other | D97: Site Overhead | E97: Local Country employee | F97: Accountant / cashier | G97: Month | H97: Time-related | I97: Y | J97: =_MONTHS -> 18 | K97: 450 | L97: =_STDPRE -> 0 | M97: =IFERROR(K97*(1+L97),0) -> 450 | N97: =IF($I97="Y",N(J97)*N(M97),0) -> 8100 | O97: Site accounts
A98: PR-084 | B98: Z.30.02 | C98: Contractor's Preliminaries / Design / Other | D98: Site Overhead | E98: Local Country employee | F98: Driver | G98: Month | H98: Time-related | I98: Y | J98: =_MONTHS -> 18 | K98: 300 | L98: =_STDPRE -> 0 | M98: =IFERROR(K98*(1+L98),0) -> 300 | N98: =IF($I98="Y",N(J98)*N(M98),0) -> 5400 | O98: Site vehicle
F99: Subtotal — Z.30.02 Local Country employee | N99: =SUM(N88:N98) -> 143100
A100: PR-085 | B100: Z.30.03 | C100: Contractor's Preliminaries / Design / Other | D100: Site Overhead | E100: Other personnel | F100: Part-time / temporary staff | G100: Month | H100: Time-related | I100: N | J100: =_MONTHS -> 18 | K100: 400 | L100: =_STDPRE -> 0 | M100: =IFERROR(K100*(1+L100),0) -> 400 | N100: =IF($I100="Y",N(J100)*N(M100),0) -> 0 | O100: Peak period support
A101: PR-086 | B101: Z.30.03 | C101: Contractor's Preliminaries / Design / Other | D101: Site Overhead | E101: Other personnel | F101: Subcontractor coordinator | G101: Month | H101: Time-related | I101: N | J101: =_MONTHS -> 18 | K101: 700 | L101: =_STDPRE -> 0 | M101: =IFERROR(K101*(1+L101),0) -> 700 | N101: =IF($I101="Y",N(J101)*N(M101),0) -> 0 | O101: Multi-package coordination
...

Sheet Entry Template
A1: BoQ TAKE-OFF ENTRY TEMPLATE
A2: Pick in order: Building → Level → Section → Sub Section → Sub Element → Description. Code, Unit and all rates fill in automatically from the Price List Library.
A3: Yellow = your input. If a drop-down looks empty, the cell to its left is still blank.
N4: TOTAL → | O4: =SUM(O6:O305) -> 0
A5: No. | B5: Building | C5: Level | D5: Discipline | E5: Section | F5: Sub Section | G5: Sub Element | H5: Description (Material Type) | I5: Budget Code | J5: Unit | K5: Quantity | L5: Labor Rate ($) | M5: Material Rate ($) | N5: Total Rate ($) | O5: Amount ($) | P5: Status | Q5: Remark | R5: h1 | S5: h2 | T5: h3
A6: =IF($E6="","",ROW()-5) | I6: =IFERROR(INDEX('Description Library'!$C$6:$C$808,MATCH($E6&"|"&$F6&"|"&$G6&"|"&$H6,'Description Library'!$K$6:$K$808,0)),"") | J6: =IFERROR(INDEX('Description Library'!$H$6:$H$808,MATCH($E6&"|"&$F6&"|"&$G6&"|"&$H6,'Description Library'!$K$6:$K$808,0)),"") | L6: =IFERROR(INDEX('Price List Library'!$K$6:$K$437,MATCH(TRIM($H6)&"|"&TRIM($J6),'Price List Library'!$S$6:$S$437,0)),0) -> 0 | M6: =IFERROR(INDEX('Price List Library'!$N$6:$N$437,MATCH(TRIM($H6)&"|"&TRIM($J6),'Price List Library'!$S$6:$S$437,0)),0) -> 0 | N6: =L6+M6 -> 0 | O6: =IF($K6="","",$K6*$N6) | P6: =IFERROR(INDEX('Price List Library'!$P$6:$P$437,MATCH(TRIM($H6)&"|"&TRIM($J6),'Price List Library'!$S$6:$S$437,0)),"") | R6: =IFERROR(VLOOKUP($E6,_MAPSEC,2,0),"_NONE") -> _NONE | S6: =IFERROR(VLOOKUP($E6&"|"&$F6,_MAPSUB,2,0),"_NONE") -> _NONE | T6: =IFERROR(VLOOKUP($E6&"|"&$F6&"|"&$G6,_MAPSE,2,0),"_NONE") -> _NONE
A7: =IF($E7="","",ROW()-5) | I7: =IFERROR(INDEX('Description Library'!$C$6:$C$808,MATCH($E7&"|"&$F7&"|"&$G7&"|"&$H7,'Description Library'!$K$6:$K$808,0)),"") | J7: =IFERROR(INDEX('Description Library'!$H$6:$H$808,MATCH($E7&"|"&$F7&"|"&$G7&"|"&$H7,'Description Library'!$K$6:$K$808,0)),"") | L7: =IFERROR(INDEX('Price List Library'!$K$6:$K$437,MATCH(TRIM($H7)&"|"&TRIM($J7),'Price List Library'!$S$6:$S$437,0)),0) -> 0 | M7: =IFERROR(INDEX('Price List Library'!$N$6:$N$437,MATCH(TRIM($H7)&"|"&TRIM($J7),'Price List Library'!$S$6:$S$437,0)),0) -> 0 | N7: =L7+M7 -> 0 | O7: =IF($K7="","",$K7*$N7) | P7: =IFERROR(INDEX('Price List Library'!$P$6:$P$437,MATCH(TRIM($H7)&"|"&TRIM($J7),'Price List Library'!$S$6:$S$437,0)),"") | R7: =IFERROR(VLOOKUP($E7,_MAPSEC,2,0),"_NONE") -> _NONE | S7: =IFERROR(VLOOKUP($E7&"|"&$F7,_MAPSUB,2,0),"_NONE") -> _NONE | T7: =IFERROR(VLOOKUP($E7&"|"&$F7&"|"&$G7,_MAPSE,2,0),"_NONE") -> _NONE
A8: =IF($E8="","",ROW()-5) | I8: =IFERROR(INDEX('Description Library'!$C$6:$C$808,MATCH($E8&"|"&$F8&"|"&$G8&"|"&$H8,'Description Library'!$K$6:$K$808,0)),"") | J8: =IFERROR(INDEX('Description Library'!$H$6:$H$808,MATCH($E8&"|"&$F8&"|"&$G8&"|"&$H8,'Description Library'!$K$6:$K$808,0)),"") | L8: =IFERROR(INDEX('Price List Library'!$K$6:$K$437,MATCH(TRIM($H8)&"|"&TRIM($J8),'Price List Library'!$S$6:$S$437,0)),0) -> 0 | M8: =IFERROR(INDEX('Price List Library'!$N$6:$N$437,MATCH(TRIM($H8)&"|"&TRIM($J8),'Price List Library'!$S$6:$S$437,0)),0) -> 0 | N8: =L8+M8 -> 0 | O8: =IF($K8="","",$K8*$N8) | P8: =IFERROR(INDEX('Price List Library'!$P$6:$P$437,MATCH(TRIM($H8)&"|"&TRIM($J8),'Price List Library'!$S$6:$S$437,0)),"") | R8: =IFERROR(VLOOKUP($E8,_MAPSEC,2,0),"_NONE") -> _NONE | S8: =IFERROR(VLOOKUP($E8&"|"&$F8,_MAPSUB,2,0),"_NONE") -> _NONE | T8: =IFERROR(VLOOKUP($E8&"|"&$F8&"|"&$G8,_MAPSE,2,0),"_NONE") -> _NONE
A9: =IF($E9="","",ROW()-5) | I9: =IFERROR(INDEX('Description Library'!$C$6:$C$808,MATCH($E9&"|"&$F9&"|"&$G9&"|"&$H9,'Description Library'!$K$6:$K$808,0)),"") | J9: =IFERROR(INDEX('Description Library'!$H$6:$H$808,MATCH($E9&"|"&$F9&"|"&$G9&"|"&$H9,'Description Library'!$K$6:$K$808,0)),"") | L9: =IFERROR(INDEX('Price List Library'!$K$6:$K$437,MATCH(TRIM($H9)&"|"&TRIM($J9),'Price List Library'!$S$6:$S$437,0)),0) -> 0 | M9: =IFERROR(INDEX('Price List Library'!$N$6:$N$437,MATCH(TRIM($H9)&"|"&TRIM($J9),'Price List Library'!$S$6:$S$437,0)),0) -> 0 | N9: =L9+M9 -> 0 | O9: =IF($K9="","",$K9*$N9) | P9: =IFERROR(INDEX('Price List Library'!$P$6:$P$437,MATCH(TRIM($H9)&"|"&TRIM($J9),'Price List Library'!$S$6:$S$437,0)),"") | R9: =IFERROR(VLOOKUP($E9,_MAPSEC,2,0),"_NONE") -> _NONE | S9: =IFERROR(VLOOKUP($E9&"|"&$F9,_MAPSUB,2,0),"_NONE") -> _NONE | T9: =IFERROR(VLOOKUP($E9&"|"&$F9&"|"&$G9,_MAPSE,2,0),"_NONE") -> _NONE
A10: =IF($E10="","",ROW()-5) | I10: =IFERROR(INDEX('Description Library'!$C$6:$C$808,MATCH($E10&"|"&$F10&"|"&$G10&"|"&$H10,'Description Library'!$K$6:$K$808,0)),"") | J10: =IFERROR(INDEX('Description Library'!$H$6:$H$808,MATCH($E10&"|"&$F10&"|"&$G10&"|"&$H10,'Description Library'!$K$6:$K$808,0)),"") | L10: =IFERROR(INDEX('Price List Library'!$K$6:$K$437,MATCH(TRIM($H10)&"|"&TRIM($J10),'Price List Library'!$S$6:$S$437,0)),0) -> 0 | M10: =IFERROR(INDEX('Price List Library'!$N$6:$N$437,MATCH(TRIM($H10)&"|"&TRIM($J10),'Price List Library'!$S$6:$S$437,0)),0) -> 0 | N10: =L10+M10 -> 0 | O10: =IF($K10="","",$K10*$N10) | P10: =IFERROR(INDEX('Price List Library'!$P$6:$P$437,MATCH(TRIM($H10)&"|"&TRIM($J10),'Price List Library'!$S$6:$S$437,0)),"") | R10: =IFERROR(VLOOKUP($E10,_MAPSEC,2,0),"_NONE") -> _NONE | S10: =IFERROR(VLOOKUP($E10&"|"&$F10,_MAPSUB,2,0),"_NONE") -> _NONE | T10: =IFERROR(VLOOKUP($E10&"|"&$F10&"|"&$G10,_MAPSE,2,0),"_NONE") -> _NONE
A11: =IF($E11="","",ROW()-5) | I11: =IFERROR(INDEX('Description Library'!$C$6:$C$808,MATCH($E11&"|"&$F11&"|"&$G11&"|"&$H11,'Description Library'!$K$6:$K$808,0)),"") | J11: =IFERROR(INDEX('Description Library'!$H$6:$H$808,MATCH($E11&"|"&$F11&"|"&$G11&"|"&$H11,'Description Library'!$K$6:$K$808,0)),"") | L11: =IFERROR(INDEX('Price List Library'!$K$6:$K$437,MATCH(TRIM($H11)&"|"&TRIM($J11),'Price List Library'!$S$6:$S$437,0)),0) -> 0 | M11: =IFERROR(INDEX('Price List Library'!$N$6:$N$437,MATCH(TRIM($H11)&"|"&TRIM($J11),'Price List Library'!$S$6:$S$437,0)),0) -> 0 | N11: =L11+M11 -> 0 | O11: =IF($K11="","",$K11*$N11) | P11: =IFERROR(INDEX('Price List Library'!$P$6:$P$437,MATCH(TRIM($H11)&"|"&TRIM($J11),'Price List Library'!$S$6:$S$437,0)),"") | R11: =IFERROR(VLOOKUP($E11,_MAPSEC,2,0),"_NONE") -> _NONE | S11: =IFERROR(VLOOKUP($E11&"|"&$F11,_MAPSUB,2,0),"_NONE") -> _NONE | T11: =IFERROR(VLOOKUP($E11&"|"&$F11&"|"&$G11,_MAPSE,2,0),"_NONE") -> _NONE
A12: =IF($E12="","",ROW()-5) | I12: =IFERROR(INDEX('Description Library'!$C$6:$C$808,MATCH($E12&"|"&$F12&"|"&$G12&"|"&$H12,'Description Library'!$K$6:$K$808,0)),"") | J12: =IFERROR(INDEX('Description Library'!$H$6:$H$808,MATCH($E12&"|"&$F12&"|"&$G12&"|"&$H12,'Description Library'!$K$6:$K$808,0)),"") | L12: =IFERROR(INDEX('Price List Library'!$K$6:$K$437,MATCH(TRIM($H12)&"|"&TRIM($J12),'Price List Library'!$S$6:$S$437,0)),0) -> 0 | M12: =IFERROR(INDEX('Price List Library'!$N$6:$N$437,MATCH(TRIM($H12)&"|"&TRIM($J12),'Price List Library'!$S$6:$S$437,0)),0) -> 0 | N12: =L12+M12 -> 0 | O12: =IF($K12="","",$K12*$N12) | P12: =IFERROR(INDEX('Price List Library'!$P$6:$P$437,MATCH(TRIM($H12)&"|"&TRIM($J12),'Price List Library'!$S$6:$S$437,0)),"") | R12: =IFERROR(VLOOKUP($E12,_MAPSEC,2,0),"_NONE") -> _NONE | S12: =IFERROR(VLOOKUP($E12&"|"&$F12,_MAPSUB,2,0),"_NONE") -> _NONE | T12: =IFERROR(VLOOKUP($E12&"|"&$F12&"|"&$G12,_MAPSE,2,0),"_NONE") -> _NONE
A13: =IF($E13="","",ROW()-5) | I13: =IFERROR(INDEX('Description Library'!$C$6:$C$808,MATCH($E13&"|"&$F13&"|"&$G13&"|"&$H13,'Description Library'!$K$6:$K$808,0)),"") | J13: =IFERROR(INDEX('Description Library'!$H$6:$H$808,MATCH($E13&"|"&$F13&"|"&$G13&"|"&$H13,'Description Library'!$K$6:$K$808,0)),"") | L13: =IFERROR(INDEX('Price List Library'!$K$6:$K$437,MATCH(TRIM($H13)&"|"&TRIM($J13),'Price List Library'!$S$6:$S$437,0)),0) -> 0 | M13: =IFERROR(INDEX('Price List Library'!$N$6:$N$437,MATCH(TRIM($H13)&"|"&TRIM($J13),'Price List Library'!$S$6:$S$437,0)),0) -> 0 | N13: =L13+M13 -> 0 | O13: =IF($K13="","",$K13*$N13) | P13: =IFERROR(INDEX('Price List Library'!$P$6:$P$437,MATCH(TRIM($H13)&"|"&TRIM($J13),'Price List Library'!$S$6:$S$437,0)),"") | R13: =IFERROR(VLOOKUP($E13,_MAPSEC,2,0),"_NONE") -> _NONE | S13: =IFERROR(VLOOKUP($E13&"|"&$F13,_MAPSUB,2,0),"_NONE") -> _NONE | T13: =IFERROR(VLOOKUP($E13&"|"&$F13&"|"&$G13,_MAPSE,2,0),"_NONE") -> _NONE
A14: =IF($E14="","",ROW()-5) | I14: =IFERROR(INDEX('Description Library'!$C$6:$C$808,MATCH($E14&"|"&$F14&"|"&$G14&"|"&$H14,'Description Library'!$K$6:$K$808,0)),"") | J14: =IFERROR(INDEX('Description Library'!$H$6:$H$808,MATCH($E14&"|"&$F14&"|"&$G14&"|"&$H14,'Description Library'!$K$6:$K$808,0)),"") | L14: =IFERROR(INDEX('Price List Library'!$K$6:$K$437,MATCH(TRIM($H14)&"|"&TRIM($J14),'Price List Library'!$S$6:$S$437,0)),0) -> 0 | M14: =IFERROR(INDEX('Price List Library'!$N$6:$N$437,MATCH(TRIM($H14)&"|"&TRIM($J14),'Price List Library'!$S$6:$S$437,0)),0) -> 0 | N14: =L14+M14 -> 0 | O14: =IF($K14="","",$K14*$N14) | P14: =IFERROR(INDEX('Price List Library'!$P$6:$P$437,MATCH(TRIM($H14)&"|"&TRIM($J14),'Price List Library'!$S$6:$S$437,0)),"") | R14: =IFERROR(VLOOKUP($E14,_MAPSEC,2,0),"_NONE") -> _NONE | S14: =IFERROR(VLOOKUP($E14&"|"&$F14,_MAPSUB,2,0),"_NONE") -> _NONE | T14: =IFERROR(VLOOKUP($E14&"|"&$F14&"|"&$G14,_MAPSE,2,0),"_NONE") -> _NONE
A15: =IF($E15="","",ROW()-5) | I15: =IFERROR(INDEX('Description Library'!$C$6:$C$808,MATCH($E15&"|"&$F15&"|"&$G15&"|"&$H15,'Description Library'!$K$6:$K$808,0)),"") | J15: =IFERROR(INDEX('Description Library'!$H$6:$H$808,MATCH($E15&"|"&$F15&"|"&$G15&"|"&$H15,'Description Library'!$K$6:$K$808,0)),"") | L15: =IFERROR(INDEX('Price List Library'!$K$6:$K$437,MATCH(TRIM($H15)&"|"&TRIM($J15),'Price List Library'!$S$6:$S$437,0)),0) -> 0 | M15: =IFERROR(INDEX('Price List Library'!$N$6:$N$437,MATCH(TRIM($H15)&"|"&TRIM($J15),'Price List Library'!$S$6:$S$437,0)),0) -> 0 | N15: =L15+M15 -> 0 | O15: =IF($K15="","",$K15*$N15) | P15: =IFERROR(INDEX('Price List Library'!$P$6:$P$437,MATCH(TRIM($H15)&"|"&TRIM($J15),'Price List Library'!$S$6:$S$437,0)),"") | R15: =IFERROR(VLOOKUP($E15,_MAPSEC,2,0),"_NONE") -> _NONE | S15: =IFERROR(VLOOKUP($E15&"|"&$F15,_MAPSUB,2,0),"_NONE") -> _NONE | T15: =IFERROR(VLOOKUP($E15&"|"&$F15&"|"&$G15,_MAPSE,2,0),"_NONE") -> _NONE
A16: =IF($E16="","",ROW()-5) | I16: =IFERROR(INDEX('Description Library'!$C$6:$C$808,MATCH($E16&"|"&$F16&"|"&$G16&"|"&$H16,'Description Library'!$K$6:$K$808,0)),"") | J16: =IFERROR(INDEX('Description Library'!$H$6:$H$808,MATCH($E16&"|"&$F16&"|"&$G16&"|"&$H16,'Description Library'!$K$6:$K$808,0)),"") | L16: =IFERROR(INDEX('Price List Library'!$K$6:$K$437,MATCH(TRIM($H16)&"|"&TRIM($J16),'Price List Library'!$S$6:$S$437,0)),0) -> 0 | M16: =IFERROR(INDEX('Price List Library'!$N$6:$N$437,MATCH(TRIM($H16)&"|"&TRIM($J16),'Price List Library'!$S$6:$S$437,0)),0) -> 0 | N16: =L16+M16 -> 0 | O16: =IF($K16="","",$K16*$N16) | P16: =IFERROR(INDEX('Price List Library'!$P$6:$P$437,MATCH(TRIM($H16)&"|"&TRIM($J16),'Price List Library'!$S$6:$S$437,0)),"") | R16: =IFERROR(VLOOKUP($E16,_MAPSEC,2,0),"_NONE") -> _NONE | S16: =IFERROR(VLOOKUP($E16&"|"&$F16,_MAPSUB,2,0),"_NONE") -> _NONE | T16: =IFERROR(VLOOKUP($E16&"|"&$F16&"|"&$G16,_MAPSE,2,0),"_NONE") -> _NONE
A17: =IF($E17="","",ROW()-5) | I17: =IFERROR(INDEX('Description Library'!$C$6:$C$808,MATCH($E17&"|"&$F17&"|"&$G17&"|"&$H17,'Description Library'!$K$6:$K$808,0)),"") | J17: =IFERROR(INDEX('Description Library'!$H$6:$H$808,MATCH($E17&"|"&$F17&"|"&$G17&"|"&$H17,'Description Library'!$K$6:$K$808,0)),"") | L17: =IFERROR(INDEX('Price List Library'!$K$6:$K$437,MATCH(TRIM($H17)&"|"&TRIM($J17),'Price List Library'!$S$6:$S$437,0)),0) -> 0 | M17: =IFERROR(INDEX('Price List Library'!$N$6:$N$437,MATCH(TRIM($H17)&"|"&TRIM($J17),'Price List Library'!$S$6:$S$437,0)),0) -> 0 | N17: =L17+M17 -> 0 | O17: =IF($K17="","",$K17*$N17) | P17: =IFERROR(INDEX('Price List Library'!$P$6:$P$437,MATCH(TRIM($H17)&"|"&TRIM($J17),'Price List Library'!$S$6:$S$437,0)),"") | R17: =IFERROR(VLOOKUP($E17,_MAPSEC,2,0),"_NONE") -> _NONE | S17: =IFERROR(VLOOKUP($E17&"|"&$F17,_MAPSUB,2,0),"_NONE") -> _NONE | T17: =IFERROR(VLOOKUP($E17&"|"&$F17&"|"&$G17,_MAPSE,2,0),"_NONE") -> _NONE
... A305: =IF($E305="","",ROW()-5) | I305: =IFERROR(INDEX('Description Library'!$C$6:$C$808,MATCH($E305&"|"&$F305&"|"&$G305&"|"&$H305,'Description Library'!$K$6:$K$808,0)),"") | J305: =IFERROR(INDEX('Description Library'!$H$6:$H$808,MATCH($E305&"|"&$F305&"|"&$G305&"|"&$H305,'Description Library'!$K$6:$K$808,0)),"") | L305: =IFERROR(INDEX('Price List Library'!$K$6:$K$437,MATCH(TRIM($H305)&"|"&TRIM($J305),'Price List Library'!$S$6:$S$437,0)),0) -> 0 | M305: =IFERROR(INDEX('Price List Library'!$N$6:$N$437,MATCH(TRIM($H305)&"|"&TRIM($J305),'Price List Library'!$S$6:$S$437,0)),0) -> 0 | N305: =L305+M305 -> 0 | O305: =IF($K305="","",$K305*$N305) | P305: =IFERROR(INDEX('Price List Library'!$P$6:$P$437,MATCH(TRIM($H305)&"|"&TRIM($J305),'Price List Library'!$S$6:$S$437,0)),"") | R305: =IFERROR(VLOOKUP($E305,_MAPSEC,2,0),"_NONE") -> _NONE | S305: =IFERROR(VLOOKUP($E305&"|"&$F305,_MAPSUB,2,0),"_NONE") -> _NONE | T305: =IFERROR(VLOOKUP($E305&"|"&$F305&"|"&$G305,_MAPSE,2,0),"_NONE") -> _NONE

Sheet Project Setup
A1: PROJECT SETUP — BUILDING & LEVEL REGISTER
A2: Edit these two tables per project. They drive the Building and Level drop-downs on the Entry Template.
A3: Keep the same codes you use in Raw Data so the take-off can be pasted straight in.
A5: Building Code | B5: Building Name | C5: Remark | E5: Level Code | F5: Level Name | G5: Remark
A6: BA | B6: Main School Building | C6: 10-storey teaching block | E6: 01.UG | F6: Underground / Pile & Foundation | G6: Substructure works
A7: BB | B7: (second building) | E7: 02.GF | F7: Ground Floor
A8: BC | B8: (third building) | E8: 03.MZ | F8: Mezzanine
A9: EXT | B9: External / Site Works | C9: Works outside building footprint | E9: 04.1F | F9: 1st Floor
A10: ALL | B10: All Buildings | C10: Project-wide items | E10: 05.2F | F10: 2nd Floor
E11: 06.3F | F11: 3rd Floor
E12: 07.4F | F12: 4th Floor
E13: 08.5F | F13: 5th Floor
E14: 09.6F | F14: 6th Floor
E15: 10.7F | F15: 7th Floor
E16: 11.8F | F16: 8th Floor
E17: 12.9F | F17: 9th Floor
E18: 13.10F | F18: 10th Floor | G18: Omitted on current project — delete row if not applicable
E19: 14.TR | F19: Truss / Roof Structure
E20: 15.RF | F20: Roof
E21: All | F21: All Levels | G21: Project-wide items

Sheet Validation Lists
A1: VALIDATION SOURCE LISTS — do not delete (drives the drop-downs on Entry Template)
A2: Every list is a named range starting with "_" so it can never clash with an Excel cell address.
A4: Section | C4: Section | D4: Name | F4: Section|SubSection | G4: Name | I4: Sec|Sub|SubElement | J4: Name | K4: (blank) | M4: _S001 | N4: _S002 | O4: _S003 | P4: _S004 | Q4: _S005 | R4: _S006 | S4: _S007 | T4: _S008 | U4: _S009 | V4: _S010 | W4: _S011 | X4: _S012 | Y4: _S013 | Z4: _S014 | AA4: _S015 | AB4: _S016 | AC4: _S017 | AD4: _S018 | AE4: _S019 | AF4: _S020 | AG4: _S021 | AH4: _S022 | AI4: _S023 | AJ4: _S024 | AK4: _S025 | AL4: _S026 | AM4: _S027 | AN4: _S028 | AO4: _S029 | AP4: _B001 | AQ4: _B002 | AR4: _B003 | AS4: _B004 | AT4: _B005 | AU4: _B006 | AV4: _B007 | AW4: _B008 | AX4: _B009 | AY4: _B010 | AZ4: _B011 | BA4: _B012 | BB4: _B013 | BC4: _B014 | BD4: _B015 | BE4: _B016 | BF4: _B017 | BG4: _B018 | BH4: _B019 | BI4: _B020 | BJ4: _B021 | BK4: _B022 | BL4: _B023 | BM4: _B024 | BN4: _B025 | BO4: _B026 | BP4: _B027 | BQ4: _B028 | BR4: _B029 | BS4: _B030 | BT4: _B031 | BU4: _B032 | BV4: _B033 | BW4: _B034 | BX4: _B035 | BY4: _B036 | BZ4: _B037 | CA4: _B038 | CB4: _B039 | CC4: _B040 | CD4: _B041 | CE4: _B042 | CF4: _B043 | CG4: _B044 | CH4: _B045 | CI4: _B046 | CJ4: _B047 | CK4: _B048 | CL4: _B049 | CM4: _B050 | CN4: _B051 | CO4: _B052 | CP4: _B053 | CQ4: _B054 | CR4: _B055 | CS4: _B056 | CT4: _B057 | CU4: _B058 | CV4: _B059 | CW4: _B060 | CX4: _B061 | CY4: _B062 | CZ4: _B063 | DA4: _B064 | DB4: _B065 | DC4: _B066 | DD4: _B067 | DE4: _B068 | DF4: _B069 | DG4: _B070 | DH4: _B071 | DI4: _B072 | DJ4: _B073 | DK4: _B074 | DL4: _B075 | DM4: _B076 | DN4: _B077 | DO4: _B078 | DP4: _B079 | DQ4: _B080 | DR4: _B081 | DS4: _B082 | DT4: _B083 | DU4: _B084 | DV4: _B085 | DW4: _B086 | DX4: _B087 | DY4: _B088 | DZ4: _B089 | EA4: _B090 | EB4: _B091 | EC4: _B092 | ED4: _B093 | EE4: _B094 | EF4: _B095 | EG4: _B096 | EH4: _B097 | EI4: _B098 | EJ4: _B099 | EK4: _B100 | EL4: _B101 | EM4: _B102 | EN4: _B103 | EO4: _B104 | EP4: _B105 | EQ4: _B106 | ER4: _B107 | ES4: _B108 | ET4: _B109 | EU4: _B110 | EV4: _B111 | EW4: _B112 | EX4: _B113 | EY4: _B114 | EZ4: _B115 | FA4: _B116 | FB4: _B117 | FC4: _B118 | FD4: _B119 | FE4: _B120 | FF4: _B121 | FG4: _B122 | FH4: _B123 | FI4: _B124 | FJ4: _D001 | FK4: _D002 | FL4: _D003 | FM4: _D004 | FN4: _D005 | FO4: _D006 | FP4: _D007 | FQ4: _D008 | FR4: _D009 | FS4: _D010 | FT4: _D011 | FU4: _D012 | FV4: _D013 | FW4: _D014 | FX4: _D015 | FY4: _D016 | FZ4: _D017 | GA4: _D018 | GB4: _D019 | GC4: _D020 | GD4: _D021 | GE4: _D022 | GF4: _D023 | GG4: _D024 | GH4: _D025 | GI4: _D026 | GJ4: _D027 | GK4: _D028 | GL4: _D029 | GM4: _D030 | GN4: _D031 | GO4: _D032 | GP4: _D033 | GQ4: _D034 | GR4: _D035 | GS4: _D036 | GT4: _D037 | GU4: _D038 | GV4: _D039 | GW4: _D040 | GX4: _D041 | GY4: _D042 | GZ4: _D043 | HA4: _D044 | HB4: _D045 | HC4: _D046 | HD4: _D047 | HE4: _D048 | HF4: _D049 | HG4: _D050 | HH4: _D051 | HI4: _D052 | HJ4: _D053 | HK4: _D054 | HL4: _D055 | HM4: _D056 | HN4: _D057 | HO4: _D058 | HP4: _D059 | HQ4: _D060 | HR4: _D061 | HS4: _D062 | HT4: _D063 | HU4: _D064 | HV4: _D065 | HW4: _D066 | HX4: _D067 | HY4: _D068 | HZ4: _D069 | IA4: _D070 | IB4: _D071 | IC4: _D072 | ID4: _D073 | IE4: _D074 | IF4: _D075 | IG4: _D076 | IH4: _D077 | II4: _D078 | IJ4: _D079 | IK4: _D080 | IL4: _D081 | IM4: _D082 | IN4: _D083 | IO4: _D084 | IP4: _D085 | IQ4: _D086 | IR4: _D087 | IS4: _D088 | IT4: _D089 | IU4: _D090 | IV4: _D091 | IW4: _D092 | IX4: _D093 | IY4: _D094 | IZ4: _D095 | JA4: _D096 | JB4: _D097 | JC4: _D098 | JD4: _D099 | JE4: _D100 | JF4: _D101 | JG4: _D102 | JH4: _D103 | JI4: _D104 | JJ4: _D105 | JK4: _D106 | JL4: _D107 | JM4: _D108 | JN4: _D109 | JO4: _D110 | JP4: _D111 | JQ4: _D112 | JR4: _D113 | JS4: _D114 | JT4: _D115 | JU4: _D116 | JV4: _D117 | JW4: _D118 | JX4: _D119 | JY4: _D120 | JZ4: _D121 | KA4: _D122 | KB4: _D123 | KC4: _D124 | KD4: _D125 | KE4: _D126 | KF4: _D127 | KG4: _D128 | KH4: _D129 | KI4: _D130 | KJ4: _D131 | KK4: _D132 | KL4: _D133 | KM4: _D134 | KN4: _D135 | KO4: _D136 | KP4: _D137 | KQ4: _D138 | KR4: _D139 | KS4: _D140 | KT4: _D141 | KU4: _D142 | KV4: _D143 | KW4: _D144 | KX4: _D145 | KY4: _D146 | KZ4: _D147 | LA4: _D148 | LB4: _D149 | LC4: _D150 | LD4: _D151 | LE4: _D152 | LF4: _D153 | LG4: _D154 | LH4: _D155 | LI4: _D156 | LJ4: _D157 | LK4: _D158 | LL4: _D159 | LM4: _D160 | LN4: _D161 | LO4: _D162 | LP4: _D163 | LQ4: _D164 | LR4: _D165 | LS4: _D166 | LT4: _D167 | LU4: _D168 | LV4: _D169 | LW4: _D170 | LX4: _D171 | LY4: _D172 | LZ4: _D173 | MA4: _D174 | MB4: _D175 | MC4: _D176 | MD4: _D177 | ME4: _D178 | MF4: _D179 | MG4: _D180 | MH4: _D181 | MI4: _D182 | MJ4: _D183 | MK4: _D184 | ML4: _D185 | MM4: _D186 | MN4: _D187 | MO4: _D188 | MP4: _D189 | MQ4: _D190 | MR4: _D191 | MS4: _D192 | MT4: _D193 | MU4: _D194 | MV4: _D195 | MW4: _D196 | MX4: _D197 | MY4: _D198 | MZ4: _D199 | NA4: _D200 | NB4: _D201 | NC4: _D202 | ND4: _D203 | NE4: _D204 | NF4: _D205 | NG4: _D206 | NH4: _D207 | NI4: _D208 | NJ4: _D209 | NK4: _D210 | NL4: _D211 | NM4: _D212 | NN4: _D213 | NO4: _D214 | NP4: _D215 | NQ4: _D216 | NR4: _D217 | NS4: _D218 | NT4: _D219 | NU4: _D220 | NV4: _D221 | NW4: _D222 | NX4: _D223 | NY4: _D224 | NZ4: _D225 | OA4: _D226 | OB4: _D227 | OC4: _D228 | OD4: _D229 | OE4: _D230 | OF4: _D231 | OG4: _D232 | OH4: _D233 | OI4: _D234 | OJ4: _D235 | OK4: _D236 | OL4: _D237 | OM4: _D238 | ON4: _D239 | OO4: _D240 | OP4: _D241 | OQ4: _D242 | OR4: _D243 | OS4: _D244 | OT4: _D245 | OU4: _D246 | OV4: _D247 | OW4: _D248 | OX4: _D249 | OY4: _D250 | OZ4: _D251 | PA4: _D252 | PB4: _D253 | PC4: _D254 | PD4: _D255 | PE4: _D256 | PF4: _D257 | PG4: _D258 | PH4: _D259 | PI4: _D260 | PJ4: _D261 | PK4: _D262 | PL4: _D263 | PM4: _D264 | PN4: _D265 | PO4: _D266 | PP4: _D267 | PQ4: _D268 | PR4: _D269 | PS4: _D270 | PT4: _D271 | PU4: _D272 | PV4: _D273 | PW4: _D274 | PX4: _D275 | PY4: _D276 | PZ4: _D277 | QA4: _D278 | QB4: _D279 | QC4: _D280 | QD4: _D281 | QE4: _D282 | QF4: _D283 | QG4: _D284 | QH4: _D285 | QI4: _D286 | QJ4: _D287 | QK4: _D288 | QL4: _D289 | QM4: _D290 | QN4: _D291 | QO4: _D292 | QP4: _D293 | QQ4: _D294 | QR4: _D295 | QS4: _D296 | QT4: _D297 | QU4: _D298 | QV4: _D299 | QW4: _D300 | QX4: _D301 | QY4: _D302 | QZ4: _D303 | RA4: _D304 | RB4: _D305 | RC4: _D306 | RD4: _D307 | RE4: _D308 | RF4: _D309 | RG4: _D310 | RH4: _D311 | RI4: _D312 | RJ4: _D313 | RK4: _D314 | RL4: _D315 | RM4: _D316 | RN4: _D317 | RO4: _D318 | RP4: _D319 | RQ4: _D320 | RR4: _D321 | RS4: _D322 | RT4: _D323 | RU4: _D324 | RV4: _D325 | RW4: _D326 | RX4: _D327 | RY4: _D328 | RZ4: _D329 | SA4: _D330 | SB4: _D331 | SC4: _D332 | SD4: _D333 | SE4: _D334 | SF4: _D335 | SG4: _D336 | SH4: _D337 | SI4: _D338 | SJ4: _D339 | SK4: _D340 | SL4: _D341 | SM4: _D342 | SN4: _D343 | SO4: _D344 | SP4: _D345 | SQ4: _D346 | SR4: _D347 | SS4: _D348 | ST4: _D349 | SU4: _D350 | SV4: _D351 | SW4: _D352 | SX4: _D353 | SY4: _D354 | SZ4: _D355 | TA4: _D356 | TB4: _D357 | TC4: _D358 | TD4: _D359 | TE4: _D360 | TF4: _D361 | TG4: _D362 | TH4: _D363 | TI4: _D364 | TJ4: _D365 | TK4: _D366 | TL4: _D367 | TM4: _D368 | TN4: _D369 | TO4: _D370 | TP4: _D371 | TQ4: _D372 | TR4: _D373 | TS4: _D374 | TT4: _D375 | TU4: _D376 | TV4: _D377 | TW4: _D378 | TX4: _D379 | TY4: _D380 | TZ4: _D381 | UA4: _D382 | UB4: _D383 | UC4: _D384 | UD4: _D385 | UE4: _D386 | UF4: _D387 | UG4: _D388 | UH4: _D389 | UI4: _D390 | UJ4: _D391 | UK4: _D392 | UL4: _D393 | UM4: _D394 | UN4: _D395 | UO4: _D396 | UP4: _D397 | UQ4: _D398 | UR4: _D399 | US4: _D400 | UT4: _D401 | UU4: _D402 | UV4: _D403 | UW4: _D404 | UX4: _D405 | UY4: _D406 | UZ4: _D407 | VA4: _D408 | VB4: _D409 | VC4: _D410 | VD4: _D411 | VE4: _D412 | VF4: _D413 | VG4: _D414 | VH4: _D415 | VI4: _D416 | VJ4: _D417 | VK4: _D418 | VL4: _D419 | VM4: _D420 | VN4: _D421 | VO4: _D422 | VP4: _D423 | VQ4: _D424 | VR4: _D425 | VS4: _D426 | VT4: _D427 | VU4: _D428 | VV4: _D429 | VW4: _D430 | VX4: _D431 | VY4: _D432 | VZ4: _D433 | WA4: _D434 | WB4: _D435 | WC4: _D436 | WD4: _D437 | WE4: _D438 | WF4: _D439 | WG4: _D440 | WH4: _D441 | WI4: _D442 | WJ4: _D443 | WK4: _D444 | WL4: _D445 | WM4: _D446 | WN4: _D447 | WO4: _D448 | WP4: _D449 | WQ4: _D450 | WR4: _D451 | WS4: _D452 | WT4: _D453 | WU4: _D454 | WV4: _D455 | WW4: _D456 | WX4: _D457 | WY4: _D458 | WZ4: _D459 | XA4: _D460 | XB4: _D461 | XC4: _D462 | XD4: _D463 | XE4: _D464 | XF4: _D465 | XG4: _D466 | XH4: _D467 | XI4: _D468 | XJ4: _D469 | XK4: _D470 | XL4: _D471 | XM4: _D472 | XN4: _D473 | XO4: _D474 | XP4: _D475 | XQ4: _D476 | XR4: _D477 | XS4: _D478 | XT4: _D479 | XU4: _D480 | XV4: _D481 | XW4: _D482 | XX4: _D483 | XY4: _D484 | XZ4: _D485 | YA4: _D486 | YB4: _D487 | YC4: _D488 | YD4: _D489 | YE4: _D490 | YF4: _D491 | YG4: _D492 | YH4: _D493 | YI4: _D494 | YJ4: _D495 | YK4: _D496 | YL4: _D497 | YM4: _D498 | YN4: _D499 | YO4: _D500 | YP4: _D501 | YQ4: _D502 | YR4: _D503 | YS4: _D504 | YT4: _D505 | YU4: _D506 | YV4: _D507 | YW4: _D508 | YX4: _D509 | YY4: _D510 | YZ4: _D511 | ZA4: _D512 | ZB4: _D513 | ZC4: _D514 | ZD4: _D515 | ZE4: _D516 | ZF4: _D517 | ZG4: _D518 | ZH4: _D519 | ZI4: _D520
A5: Sub Structure | C5: Sub Structure | D5: _S001 | F5: Sub Structure|Site Preparation & Earthwork | G5: _B001 | I5: Sub Structure|Site Preparation & Earthwork|Site Clearing | J5: _D001 | M5: Site Preparation & Earthwork | N5: Structural Column | O5: Hollow clay brick | P5: Plastering | Q5: Steel Door | R5: Glass Window | S5: Screeding | T5: Soffit finishes | U5: Stair & Ramp finishes | V5: Roof covering | W5: Hollow clay brick | X5: Wood door | Y5: Gas installation | Z5: Plastering | AA5: Screeding | AB5: Suspended ceiling | AC5: General Fitting | AD5: Sanitary ware | AE5: Split unit system | AF5: Ventilation fan | AG5: Ductwork | AH5: Main distribution | AI5: Fire alarm system | AJ5: Water supply | AK5: Hydrant & hose reel | AL5: Renewable & specialist | AM5: Lift | AN5: Testing & Commissioning | AO5: Site preparation | AP5: Site Clearing | AQ5: Sheet Pile Supply | AR5: Bored Pile Boring | AS5: Pile Supply | AT5: Earthwork | AU5: Earthwork | AV5: Earthwork | AW5: Base Preparation | AX5: Earthwork | AY5: Earthwork | AZ5: Earthwork | BA5: Earthwork | BB5: Concrete | BC5: Concrete | BD5: Concrete | BE5: Concrete | BF5: Concrete | BG5: Concrete | BH5: Concrete | BI5: Concrete | BJ5: Steel Section / Beam | BK5: Truss | BL5: Concrete Testing | BM5: Hollow clay brick 100mm Thk. | BN5: Concrete block 100mm Thk. | BO5: AAC block 100mm Thk. | BP5: Precast wall panel | BQ5: External façade | BR5: Plastering | BS5: Painting | BT5: Wall tiling | BU5: Expansion joint | BV5: Steel Door | BW5: Aluminium door | BX5: Frameless glass door | BY5: Rolling shutter | BZ5: Lockset | CA5: Glass Window | CB5: Aluminium louver | CC5: Window fence / grille | CD5: Screeding | CE5: Floor tiling | CF5: Waterproofing | CG5: Plastering | CH5: Stair tread & riser finish | CI5: Handrail | CJ5: Metal roof sheet | CK5: Waterproofing membrane | CL5: Gutter | CM5: Skylight | CN5: Hollow clay brick 100mm Thk. | CO5: Gypsum board partition | CP5: Frameless glass partition | CQ5: Toilet cubicle | CR5: Handrail | CS5: Wood door | CT5: PVC door | CU5: Steel Door | CV5: Aluminium door | CW5: Lockset | CX5: Interior glass window | CY5: LPG gas system | CZ5: Plastering | DA5: Painting | DB5: Wall tiling | DC5: Wall cladding | DD5: Skirting | DE5: Screeding | DF5: Floor tiling | DG5: Marble on staircase | DH5: Vinyl flooring | DI5: Waterproofing | DJ5: Skirting | DK5: Suspended ceiling | DL5: Acoustic ceiling tile | DM5: Aluminium strip ceiling | DN5: Ceiling access panel | DO5: Toilet accessories | DP5: Kitchen cabinet | DQ5: Laboratory bench | DR5: Signage | DS5: Water closet | DT5: Tap / faucet | DU5: Toilet paper holder | DV5: Wall mounted split unit | DW5: VRF indoor unit | DX5: Chiller | DY5: Refrigerant piping | DZ5: Toilet exhaust fan | EA5: Kitchen hood | EB5: GI ductwork | EC5: Supply air diffuser | ED5: Volume control damper | EE5: Main switchboard (MSB) | EF5: Power cable | EG5: Socket outlet | EH5: Interior luminaire | EI5: Earthing system | EJ5: Generator set | EK5: Fire alarm control panel | EL5: CCTV camera | EM5: Structured cabling outlet | EN5: Public address (PA) system | EO5: BMS control panel | EP5: Cold water piping | EQ5: Water tank | ER5: Soil pipe | ES5: Septic tank (precast) | ET5: Fire hydrant | EU5: Sprinkler head | EV5: Fire pump set | EW5: Fire extinguisher | EX5: Solar PV system | EY5: Passenger lift | EZ5: Escalator | FA5: Lift shaft ladder | FB5: Testing & commissioning | FC5: Site clearing | FD5: Concrete paving | FE5: Top soil | FF5: Boundary fence | FG5: Flag pole | FH5: Toilet Floor tile | FI5: Toilet Wall tile | FJ5: Site clearing, grubbing and removal of vegetation and debris off site | FK5: Bulk excavation by machine incl. trimming and levelling of formation | FL5: Backfilling with approved material in 200mm layers incl. compaction to 95% MDD | FM5: Cart away surplus excavated material off site incl. tipping fee | FN5: Compaction of formation to 95% MDD incl. watering and testing | FO5: Dewatering incl. pumps, sump pits, piping and maintenance during construction | FP5: Setting out, levelling and establishment of benchmarks and grid lines | FQ5: Supply of steel sheet pile, hot rolled section as per design | FR5: Driving of steel sheet pile to required depth incl. plant and equipment | FS5: Extraction of steel sheet pile and making good of voids | FT5: Steel strut and waler incl. fabrication, installation and removal | FU5: Ground anchor incl. drilling, grouting, stressing and testing | FV5: Reinforced concrete guide wall incl. concrete, rebar and formwork | FW5: Bored piling D1000mm incl. boring, casing and disposal of spoil | FX5: Normal Concrete, 35Mpa (Cylinder), Slump 13+-2.5 | FY5: Deform Bar, DB10(fy=390 Mpa) | FZ5: Steel Tie Wire 1mm (Estimated 4% of Total Rebar Weight) | GA5: Steel Round Pipe (D49x2mm) with rush primer and paint | GB5: Bentonite / polymer slurry incl. mixing, circulation and disposal | GC5: Pile Head Cutting up to required level D1000mm | GD5: Sonic Logging Test (SLT) | GE5: Soil Coring for Bored Pile D1000mm, Depth 30m | GF5: Dynamic pile load test (PDA) | GG5: Rebar Testing as per Specification | GH5: Concrete cube / cylinder test as per specification | GI5: Supply of precast / spun pile as per design section | GJ5: Driving of precast / spun pile to required set incl. plant | GK5: Pile splicing by full penetration weld incl. splice plate | GL5: Pile head cutting and trimming to required cut-off level | GM5: Dynamic pile load test (PDA) | GN5: Soil Backfill | GO5: Well Soil Compact | GP5: Crush Stone 40x60mm 100mm Thk. | GQ5: Lean Concrete, 15Mpa (Cylinder) | GR5: Normal Concrete, 35Mpa (Cylinder), Slump 13+-2.5 | GS5: Formwork | GT5: Deform Bar, DB10(fy=390 Mpa) | GU5: Steel Tie Wire 1mm (Estimated 4% of Total Rebar Weight) | GV5: PVC Waterbar® V VN 20 (Width 200mm) | GW5: Membrance sheet 2mm thk | GX5: Anti-Termite with Plastic Membrane | GY5: Soil Backfill | GZ5: Well Soil Compact | HA5: Crush Stone 40x60mm 100mm Thk. | HB5: Lean Concrete, 15Mpa (Cylinder) | HC5: Normal Concrete, 35Mpa (Cylinder), Slump 13+-2.5 | HD5: Formwork to curved / special shape incl. erection and striking | HE5: Deform Bar, DB10(fy=390 Mpa) | HF5: Steel Tie Wire 1mm (Estimated 4% of Total Rebar Weight) | HG5: PVC Waterbar® V VN 20 (Width 200mm) | HH5: Membrance sheet 2mm thk | HI5: Anti-Termite with Plastic Membrane | HJ5: Soil Backfill | HK5: Lean Concrete, 15Mpa (Cylinder) | HL5: Normal Concrete, 35Mpa (Cylinder), Slump 13+-2.5 | HM5: Formwork to curved / special shape incl. erection and striking | HN5: Deform Bar, DB10(fy=390 Mpa) | HO5: Steel Tie Wire 1mm (Estimated 4% of Total Rebar Weight) | HP5: Membrance sheet 2mm thk | HQ5: Well Soil Compact | HR5: Crush Stone 40x60mm 100mm Thk. | HS5: Anti-Termite with Plastic Membrane | HT5: Polyethylene vapour barrier 0.15mm thk. laid with 300mm laps | HU5: Lean Concrete, 15Mpa (Cylinder) | HV5: Normal Concrete, 35Mpa (Cylinder), Slump 13+-2.5 | HW5: Formwork to curved / special shape incl. erection and striking | HX5: Deform Bar, DB10(fy=390 Mpa) | HY5: Steel Tie Wire 1mm (Estimated 4% of Total Rebar Weight) | HZ5: Membrance sheet 2mm thk | IA5: Soil Backfill | IB5: Well Soil Compact | IC5: Crush Stone 40x60mm 100mm Thk. | ID5: Lean Concrete, 15Mpa (Cylinder) | IE5: Normal Concrete, 35Mpa (Cylinder), Slump 13+-2.5 | IF5: Formwork to curved / special shape incl. erection and striking | IG5: Deform Bar, DB10(fy=390 Mpa) | IH5: Steel Tie Wire 1mm (Estimated 4% of Total Rebar Weight) | II5: PVC Waterbar® V VN 20 (Width 200mm) | IJ5: Membrance sheet 2mm thk | IK5: Anti-Termite with Plastic Membrane | IL5: Soil Backfill | IM5: Well Soil Compact | IN5: Crush Stone 40x60mm 100mm Thk. | IO5: Lean Concrete, 15Mpa (Cylinder) | IP5: Normal Concrete, 35Mpa (Cylinder), Slump 13+-2.5 | IQ5: Formwork to curved / special shape incl. erection and striking | IR5: Deform Bar, DB10(fy=390 Mpa) | IS5: Steel Tie Wire 1mm (Estimated 4% of Total Rebar Weight) | IT5: PVC Waterbar® V VN 20 (Width 200mm) | IU5: Membrance sheet 2mm thk | IV5: Anti-Termite with Plastic Membrane | IW5: Soil Backfill | IX5: Lean Concrete, 15Mpa (Cylinder) | IY5: Normal Concrete, 35Mpa (Cylinder), Slump 13+-2.5 | IZ5: Formwork to curved / special shape incl. erection and striking | JA5: Deform Bar, DB10(fy=390 Mpa) | JB5: Steel Tie Wire 1mm (Estimated 4% of Total Rebar Weight) | JC5: PVC Waterbar® V VN 20 (Width 200mm) | JD5: Membrance sheet 2mm thk | JE5: Soil Backfill | JF5: Normal Concrete, 35Mpa (Cylinder), Slump 13+-2.5 | JG5: Formwork to curved / special shape incl. erection and striking | JH5: Deform Bar, DB10(fy=390 Mpa) | JI5: Steel Tie Wire 1mm (Estimated 4% of Total Rebar Weight) | JJ5: PVC Waterbar® V VN 20 (Width 200mm) | JK5: Membrance sheet 2mm thk | JL5: Protection board 6mm thk. to waterproofing membrane | JM5: Dimpled HDPE drainage board with filter fabric | JN5: Normal Concrete, 35Mpa (Cylinder), Slump 13+-2.5 | JO5: Formwork to curved / special shape incl. erection and striking | JP5: Deform Bar, DB10(fy=390 Mpa) | JQ5: Steel Tie Wire 1mm (Estimated 4% of Total Rebar Weight) | JR5: Column starter bar incl. bending, fixing and tying | JS5: Non-shrink cementitious grout to base plate / gap | JT5: Normal Concrete, 35Mpa (Cylinder), Slump 13+-2.5 | JU5: Formwork to curved / special shape incl. erection and striking | JV5: Deform Bar, DB10(fy=390 Mpa) | JW5: Steel Tie Wire 1mm (Estimated 4% of Total Rebar Weight) | JX5: Normal Concrete, 35Mpa (Cylinder), Slump 13+-2.5 | JY5: Formwork to curved / special shape incl. erection and striking | JZ5: Deform Bar, DB10(fy=390 Mpa) | KA5: Steel Tie Wire 1mm (Estimated 4% of Total Rebar Weight) | KB5: Post-tension strand incl. duct, anchorage, stressing and grouting | KC5: Galvanised steel deck 0.75mm thk. incl. shear stud and end closure | KD5: Normal Concrete, 35Mpa (Cylinder), Slump 13+-2.5 | KE5: Formwork to curved / special shape incl. erection and striking | KF5: Deform Bar, DB10(fy=390 Mpa) | KG5: Steel Tie Wire 1mm (Estimated 4% of Total Rebar Weight) | KH5: PVC Waterbar® V VN 20 (Width 200mm) | KI5: Normal Concrete, 35Mpa (Cylinder), Slump 13+-2.5 | KJ5: Formwork to curved / special shape incl. erection and striking | KK5: Deform Bar, DB10(fy=390 Mpa) | KL5: Steel Tie Wire 1mm (Estimated 4% of Total Rebar Weight) | KM5: Normal Concrete, 35Mpa (Cylinder), Slump 13+-2.5 | KN5: Formwork to curved / special shape incl. erection and striking | KO5: Deform Bar, DB10(fy=390 Mpa) | KP5: Steel Tie Wire 1mm (Estimated 4% of Total Rebar Weight) | KQ5: Normal Concrete, 35Mpa (Cylinder), Slump 13+-2.5 | KR5: Formwork to curved / special shape incl. erection and striking | KS5: Deform Bar, DB10(fy=390 Mpa) | KT5: Steel Tie Wire 1mm (Estimated 4% of Total Rebar Weight) | KU5: PVC Waterbar® V VN 20 (Width 200mm) | KV5: Normal Concrete, 35Mpa (Cylinder), Slump 13+-2.5 | KW5: Formwork to curved / special shape incl. erection and striking | KX5: Deform Bar, DB10(fy=390 Mpa) | KY5: Steel Tie Wire 1mm (Estimated 4% of Total Rebar Weight) | KZ5: Structural steel section (H/I beam) SS400 incl. fabrication and erection | LA5: U-50*100*5mm | LB5: Tub-50*100*2mm | LC5: Steel purlin C-channel incl. fabrication, erection and fixing | LD5: Sag rod 12mm | LE5: Steel bracing member incl. fabrication, erection and connection | LF5: Steel base plate incl. drilling, welding and levelling | LG5: Steel plate 200x230x12mm | LH5: J bolt M12, L=600mm, grade 5.6 | LI5: Anchor bolt incl. template, setting and grouting | LJ5: High tensile bolt, nut and washer grade 8.8 | LK5: Site welding incl. electrode, preparation and testing | LL5: Anti-corrosive primer and 2 coats finish paint to steelwork | LM5: Intumescent fire protection coating to steelwork, 2 hour rating | LN5: Steel roof truss incl. fabrication, erection and connection | LO5: Steel purlin C-channel incl. fabrication, erection and fixing | LP5: Sag rod 12mm | LQ5: Steel bracing member incl. fabrication, erection and connection | LR5: Zinc sheet 0.4mm | LS5: Flashing cover roof | LT5: Anchor bolt incl. template, setting and grouting | LU5: Anti-corrosive primer and 2 coats finish paint to steelwork | LV5: Concrete cube / cylinder test as per specification | LW5: Rebar Testing as per Specification | LX5: Non-destructive test (rebound hammer / ultrasonic) as per specification | LY5: Setting out, survey and as-built record | LZ5: Hollow clay brick, thickness 100mm, laid in cement:sand mortar 1:4 | MA5: Hollow clay brick (80x80x180)mm, thickness 200mm Thk. | MB5: Hollow clay brick (80x80x180)mm, thickness 400mm Thk. | MC5: Hollow clay brick (80x80x180)mm, thickness 500mm Thk. | MD5: Hollow clay brick (80x80x180)mm, thickness 800mm Thk. | ME5: concrete block, thickness 100mm, laid in cement:sand mortar 1:4 | MF5: concrete block, thickness 150mm, laid in cement:sand mortar 1:4 | MG5: concrete block, thickness 200mm, laid in cement:sand mortar 1:4 | MH5: AAC lightweight block 100mm thk. laid in thin-bed adhesive mortar | MI5: AAC lightweight block 150mm thk. laid in thin-bed adhesive mortar | MJ5: AAC lightweight block 200mm thk. laid in thin-bed adhesive mortar | MK5: Precast concrete wall panel incl. lifting, setting and jointing | ML5: Panel joint backer rod and weatherproof silicone sealant | MM5: concrete block | MN5: Aluminium curtain wall system with 8mm tempered glass incl. framing and sealant | MO5: Aluminium composite panel 4mm, PVDF finish, incl. sub-frame and sealant | MP5: Aluminium louver screen incl. sub-frame and fixing | MQ5: 20mm cement plaster | MR5: Skim coat, 2 coats, sanded ready to receive paint | MS5: Cement molding / cornice incl. forming and finishing | MT5: Painting | MU5: Alkali resistant primer, 1 coat | MV5: Weather-shield exterior coating, primer + 2 coats | MW5: Wall tile Size 0.6x0.6m,Height 1.2m, at cooridor | MX5: Natural stone cladding incl. adhesive, anchor and pointing | MY5: Expansion joint incl. backer rod, sealant and cover profile | MZ5: Weatherproof silicone sealant incl. backer rod | NA5: Steel Door, W:900,H:2100mm incl. frame, ironmongery and painting | NB5: Fire rated steel door 2 hour incl. frame, closer and panic bar | NC5: Aluminium framed door with 6mm tempered glass incl. ironmongery | ND5: Aluminium sliding door with 6mm tempered glass incl. track and ironmongery | NE5: Frameless tempered glass door 12mm incl. floor spring and patch fitting | NF5: Aluminium framed glass door incl. ironmongery | NG5: Galvanised steel rolling shutter incl. guide rail and lock | NH5: Roller shutter motor and control panel incl. wiring | NI5: Mortice lockset, stainless steel lever handle | NJ5: Overhead door closer, adjustable | NK5: Stainless steel butt hinge 100mm | NL5: Floor / wall mounted door stopper | NM5: Internal Fix Windoor (L:1200,H:500)mm & Slide window (L:1200,H:1000)mm | NN5: Fixed aluminium window with 6mm tempered glass incl. sealant | NO5: Sliding aluminium window with 6mm tempered glass incl. track and lock | NP5: Casement aluminium window with 6mm glass incl. friction stay | NQ5: Aluminium louver incl. frame and fixing | NR5: Steel louver incl. frame, fixing and painting | NS5: Steel window grille incl. painting and fixing | NT5: Aluminium frame mosquito / insect screen | NU5: Weatherproof silicone sealant incl. backer rod | NV5: Cement / stone window sill incl. forming and finishing | NW5: Cement:sand screed 1:3, 40mm thk. steel trowel finish | NX5: Non-metallic floor hardener 3kg/m2 incl. power trowel finish | NY5: Floor tile Size 0.3x0.3m incl. adhesive and grout | NZ5: Anti-slip ceramic tile incl. adhesive and grout | OA5: Membrance sheet 2mm thk | OB5: Protection screed 40mm thk. to waterproofing membrane | OC5: 20mm cement plaster | OD5: Painting | OE5: Soffit cladding board incl. sub-frame and jointing | OF5: Stair tread and riser tile / stone finish incl. adhesive | OG5: Ramp anti-slip floor finish incl. adhesive and grout | OH5: Aluminium stair nosing with anti-slip insert | OI5: Tactile warning paving for accessibility incl. adhesive | OJ5: Steel handrail with paiting H=1m | OK5: Stainless steel / glass balustrade H=1.1m incl. fixing | OL5: Steel guard rail incl. fabrication, painting and fixing | OM5: Metal roof sheet 0.47mm thk. colour coated incl. fixing accessories | ON5: Concrete / clay roof tile incl. batten, ridge and fixing | OO5: Translucent polycarbonate roof sheet incl. fixing | OP5: Colour coated ridge cap incl. sealing and fixing | OQ5: Torch-on bituminous waterproofing membrane 3mm incl. primer and up-turn | OR5: Roof thermal insulation, glasswool 50mm with foil facing | OS5: Vapour barrier; supply and install complete incl. all accessories, jointing and making good. | OT5: Protection screed 40mm thk. to waterproofing membrane | OU5: Colour coated metal gutter incl. bracket and outlet | OV5: uPVC downpipe incl. bracket, bend and shoe | OW5: Cast iron / uPVC roof drain with dome grating | OX5: Flashing cover roof | OY5: Skylight with laminated glass incl. aluminium frame and flashing | OZ5: Roof access hatch incl. frame, cover and lock | PA5: Steel cat ladder incl. safety hoop and painting | PB5: Lightning air terminal base incl. fixing to roof structure | PC5: Hollow clay brick (80x80x180)mm, thickness 100mm Thk. | PD5: Hollow clay brick, thickness 200mm, laid in cement:sand mortar 1:4 | PE5: Gypsum board partition 2x12mm both sides on 76mm metal stud incl. jointing | PF5: Fibre cement board partition 2x9mm both sides on metal stud incl. jointing | PG5: Galvanised metal stud and track framing at 600mm c/c | PH5: Rockwool acoustic infill 50mm thk. density 60kg/m3 to partition cavity | PI5: Frameless tempered glass partition 12mm thk. incl. patch fitting and sealant | PJ5: Aluminium framed glass partition with 8mm tempered glass | PK5: Toilet cubicle, compact laminate 12mm thk. incl. door, hardware and pilaster | PL5: Urinal divider, compact laminate 12mm thk. incl. bracket | PM5: Steel handrail with paiting H=1m | PN5: Steel handrail with paiting Handrail on staircase, H=1m | PO5: Wall mounted guard rail / crash rail incl. bracket and fixing | PP5: Wood door size (L:1600,H:2100,W:500)mm | PQ5: Solid core timber door with laminate finish incl. frame and ironmongery | PR5: PVC door size (L:750,H:2000,W:400)mm | PS5: Steel door size (L:880,H:2100,W:400)mm | PT5: Fire rated door 1 hour, steel, incl. frame, closer and ironmongery | PU5: Aluminium framed door with 6mm tempered glass incl. ironmongery | PV5: Tempered glass door 12mm thk. incl. patch fitting and floor spring | PW5: Mortice lockset, stainless steel lever handle | PX5: Overhead door closer, adjustable | PY5: Stainless steel butt hinge 100mm | PZ5: Floor / wall mounted door stopper | QA5: Panic exit device / push bar to fire escape door | QB5: Interior aluminium framed glass window with 6mm glass | QC5: Interior aluminium louver incl. frame | QD5: LPG gas piping system incl. regulator, valve and testing | QE5: Laboratory gas outlet point incl. piping, valve and testing | QF5: 20mm cement plaster | QG5: Skim coat, 2 coats, sanded ready to receive paint | QH5: Painting | QI5: Alkali resistant primer, 1 coat | QJ5: Wall tile Size 0.6x0.6m,Height 1.2m, at cooridor | QK5: Toilet Wall tile Size 0.3x0.6m incl. adhesive and grout | QL5: Decorative wall cladding panel incl. sub-frame and fixing | QM5: Acoustic wall panel incl. sub-frame and fixing | QN5: Vinyl wallpaper incl. adhesive and surface preparation | QO5: Silver mirror 5mm thk. incl. backing and fixing | QP5: Tile / cement skirting 100mm high incl. adhesive and grout | QQ5: Cement:sand screed 1:3, 40mm thk. steel trowel finish | QR5: Self-levelling screed 5mm thk. to receive floor finish | QS5: Floor tile Size 0.3x0.3m incl. adhesive and grout | QT5: Toilet Floor tile Size 0.3x0.3m, anti-slip, incl. adhesive and grout | QU5: Homogeneous tile 600x600mm incl. adhesive and grout | QV5: Marble on staircase | QW5: Marble slab flooring 20mm thk. incl. bedding, polishing and sealing | QX5: Granite slab flooring 20mm thk. incl. bedding and polishing | QY5: Homogeneous vinyl sheet flooring 2mm thk. incl. adhesive and welding rod | QZ5: Epoxy floor coating, self-levelling 2mm thk. incl. primer | RA5: Engineered timber flooring incl. underlay and skirting | RB5: Carpet tile 500x500mm incl. adhesive | RC5: Raised access floor 600x600mm panel incl. pedestal | RD5: Membrance sheet 2mm thk | RE5: anti termite | RF5: Tile / cement skirting 100mm high incl. adhesive and grout | RG5: Aluminium stair nosing with anti-slip insert | RH5: Aluminium floor trim / divider strip | RI5: 10mm Plasterboard with 600mm ceiling frame height | RJ5: Gypsum board ceiling 9mm thk. on metal furring incl. jointing | RK5: Fibre cement board ceiling 4.5mm thk. on metal furring | RL5: Acoustic ceiling tile 600x600mm on exposed T-grid | RM5: Mineral fibre ceiling board 600x1200mm on T-grid system | RN5: Aluminium strip ceiling incl. carrier and trim | RO5: Metal open grid ceiling incl. suspension system | RP5: Ceiling access panel 600x600mm incl. frame and lock | RQ5: Gypsum cornice incl. fixing and jointing | RR5: Ceiling bulkhead incl. framing, board and jointing | RS5: Ceiling painting, primer + 2 coats emulsion | RT5: Curtain box / pelmet incl. framing and finishing | RU5: Toilet accessories set: paper holder, soap dispenser, coat hook, grab bar | RV5: Silver mirror 5mm thk. incl. backing and fixing | RW5: Solid surface counter top 12mm thk. incl. support and sealing | RX5: Steel locker unit incl. lock and fixing | RY5: Melamine faced shelving incl. bracket and fixing | RZ5: Roller blind / curtain incl. track and bracket | SA5: Magnetic white board incl. frame and fixing | SB5: Kitchen cabinet, melamine faced carcass incl. hardware | SC5: Solid surface counter top 12mm thk. incl. support and sealing | SD5: Stainless steel sink incl. tap, waste and P-trap | SE5: Laboratory bench with chemical resistant top incl. base cabinet | SF5: Library shelving unit incl. fixing | SG5: Sport / gymnasium equipment as per schedule | SH5: Signage | SI5: External round logo include framing | SJ5: Khmer and chinesse text | SK5: Wayfinding directional sign incl. frame and fixing | SL5: Room identification sign incl. fixing | SM5: Statutory / safety signage incl. fixing | SN5: Water closet, close-couple, vitreous china, incl. seat cover, cistern and connector | SO5: Wash basin, vitreous china, incl. tap, bottle trap, waste and bracket | SP5: Urinal, vitreous china, incl. flush valve, waste and bracket | SQ5: Shower set incl. mixer, riser rail, hand shower and hose | SR5: Squat pan incl. flush pipe, connector and floor fixing | SS5: Stainless steel sink incl. tap, waste and P-trap | ST5: Chromed brass tap / faucet incl. connector | SU5: Flush valve, exposed type, incl. connector | SV5: Chromed brass angle valve incl. flexible connector | SW5: Stainless steel floor drain with removable grating | SX5: Floor trap with water seal incl. grating | SY5: Clean out / rodding eye incl. cover | SZ5: Stainless steel toilet paper holder incl. fixing | TA5: Wall mounted soap dispenser incl. fixing | TB5: Stainless steel grab bar for accessible toilet incl. fixing | TC5: Electric hand dryer incl. wiring connection | TD5: Wall mounted split type air conditioner incl. indoor unit, bracket and control | TE5: Ceiling cassette type air conditioner incl. panel and control | TF5: Outdoor condensing unit incl. base, anti-vibration mount and wiring | TG5: VRF indoor unit incl. drain pump, control and commissioning | TH5: VRF outdoor unit incl. base, anti-vibration mount and wiring | TI5: VRF refnet joint / header incl. insulation | TJ5: Water cooled / air cooled chiller incl. base, connection and commissioning | TK5: Air handling unit incl. filter, coil, fan, drain pan and control | TL5: Fan coil unit incl. filter, drain pan, valve and control | TM5: Chilled water pump incl. base, coupling, valve and control | TN5: Cooling tower incl. base, make-up water and control | TO5: Copper refrigerant piping incl. insulation, fitting and gas charging | TP5: Chilled water piping incl. valve, fitting, insulation and support | TQ5: Condensate drain piping uPVC incl. insulation, fitting and support | TR5: Closed cell / rockwool pipe insulation incl. vapour barrier and cladding | TS5: Room thermostat / wired controller incl. wiring | TT5: Toilet exhaust fan incl. bracket, damper and wiring | TU5: Kitchen exhaust fan incl. bracket, damper and wiring | TV5: Car park ventilation fan incl. support and wiring | TW5: Fresh air supply fan incl. filter, damper and wiring | TX5: Staircase pressurization fan incl. relief damper and control | TY5: Stainless steel kitchen hood incl. grease filter and light | TZ5: Smoke extraction fan, 250°C/2hr rated, incl. control | UA5: Laboratory fume hood incl. exhaust fan, duct and control | UB5: Galvanised iron ductwork incl. flange, gasket, support and sealing | UC5: Insulated flexible duct incl. clamp and connection | UD5: Duct thermal insulation incl. vapour barrier and finish | UE5: Duct hanger and support incl. anchor and rod | UF5: Supply air diffuser incl. plenum box and damper | UG5: Return air grille incl. filter and frame | UH5: Exhaust air grille incl. frame and damper | UI5: Weather louver with bird screen incl. frame | UJ5: Volume control damper incl. actuator quadrant | UK5: Fire damper 2 hour rated incl. fusible link and access panel | UL5: Motorized damper incl. actuator and wiring | UM5: Air / water testing, adjusting and balancing incl. report | UN5: Main switchboard incl. ACB/MCCB, busbar, metering and testing | UO5: Sub distribution board incl. MCB/RCBO, enclosure and labelling | UP5: Busduct / busway incl. joint, support and tap-off unit | UQ5: Distribution transformer incl. base, connection and testing | UR5: Automatic power factor correction capacitor bank incl. controller | US5: Metering panel incl. CT, meter and wiring | UT5: XLPE/PVC power cable incl. termination, gland and lug | UU5: Control cable incl. termination and gland | UV5: Hot dip galvanised cable tray incl. support, bend and accessories | UW5: Metal cable trunking incl. cover, support and accessories | UX5: uPVC / GI conduit incl. bend, coupling, box and support | UY5: Cable ladder incl. support, bend and accessories | UZ5: 13A switched socket outlet point incl. wiring, conduit and accessories | VA5: Lighting switch point incl. wiring, conduit and accessories | VB5: Weatherproof isolator incl. wiring and fixing | VC5: Wiring point incl. cable, conduit and termination | VD5: LED interior luminaire incl. lamp, driver, wiring and fixing | VE5: LED exterior / flood luminaire IP65 incl. pole/bracket and wiring | VF5: LED emergency light with 3 hour battery backup incl. testing | VG5: LED exit sign with battery backup incl. fixing and testing | VH5: Occupancy / daylight sensor incl. wiring and commissioning | VI5: Earthing system incl. conductor, bonding and testing | VJ5: Copper earth rod with inspection pit incl. clamp and testing | VK5: Lightning air terminal incl. base, mast and connection | VL5: Lightning down conductor incl. clamp, tape and test joint | VM5: Diesel generator set incl. canopy, base, exhaust and commissioning | VN5: Automatic transfer switch incl. controller and wiring | VO5: Uninterruptible power supply incl. battery, cabinet and commissioning | VP5: Diesel fuel tank incl. piping, valve, level gauge and bund | VQ5: Addressable fire alarm control panel incl. battery and programming | VR5: Addressable smoke / heat detector incl. base and wiring | VS5: Manual call point incl. back box and wiring | VT5: Alarm bell / sounder incl. wiring and testing | VU5: IP CCTV camera incl. bracket, cabling and configuration | VV5: Network video recorder incl. hard disk, rack and configuration | VW5: Door access control set incl. reader, EM lock, button and controller | VX5: Audio / video intercom incl. wiring and commissioning | VY5: Cat6 data outlet incl. cable, patch panel termination and testing | VZ5: Network switch and 19" rack incl. patch panel, PDU and accessories | WA5: Telephone system incl. exchange, handset and cabling | WB5: MATV / TV outlet incl. coaxial cable, splitter and termination | WC5: Wireless access point incl. PoE cabling and configuration | WD5: Public address system incl. amplifier, mixer, microphone and zoning | WE5: Ceiling / wall speaker incl. cabling and termination | WF5: School bell and master clock system incl. programming | WG5: Projector with motorized screen incl. mount, cabling and commissioning | WH5: Classroom audio visual system incl. panel, speaker and cabling | WI5: Building management system panel incl. controller and graphics | WJ5: BMS field device / sensor incl. wiring and calibration | WK5: PPR / uPVC cold water piping incl. fitting, valve, support and testing | WL5: PPR hot water piping incl. insulation, fitting and testing | WM5: Closed cell / rockwool pipe insulation incl. vapour barrier and cladding | WN5: Gate / check / ball valve incl. flange, gasket and bolt | WO5: Water meter incl. strainer, valve and connection | WP5: Water storage tank incl. base, level control, pipework and cleaning | WQ5: Water transfer pump set incl. base, valve, control panel and wiring | WR5: Booster pump set with pressure vessel incl. control panel | WS5: Electric water heater incl. safety valve, bracket and wiring | WT5: Water level control system incl. electrode, relay and wiring | WU5: uPVC soil pipe incl. fitting, support, jointing and testing | WV5: uPVC waste pipe incl. fitting, trap, support and testing | WW5: uPVC vent pipe incl. fitting, cowl and support | WX5: uPVC rainwater downpipe incl. fitting, bracket and shoe | WY5: Manhole / inspection chamber incl. excavation, concrete, benching and cover | WZ5: Grease trap incl. excavation, installation, cover and connection | XA5: Precast septic tank incl. excavation, bedding, connection and backfill | XB5: Package sewage treatment plant incl. blower, control and commissioning | XC5: Connection to public sewer incl. excavation, pipe, chamber and reinstatement | XD5: Fire hydrant / landing valve incl. cabinet, hose and accessories | XE5: Fire hose reel 30m incl. cabinet, nozzle and valve | XF5: Landing valve incl. cabinet and blank cap | XG5: Fire riser piping, galvanised steel, incl. fitting, support and testing | XH5: Pendent / upright sprinkler head incl. escutcheon and testing | XI5: Sprinkler piping incl. fitting, hanger, support and hydrostatic testing | XJ5: Sprinkler alarm valve set incl. gauge, drain and trim | XK5: Flow switch / tamper switch incl. wiring to fire alarm panel | XL5: Fire pump set (electric + diesel + jockey) incl. controller and commissioning | XM5: Jockey pump incl. pressure switch and control | XN5: Fire water storage tank incl. base, level control and connection | XO5: Portable fire extinguisher incl. bracket, sign and servicing | XP5: Fire blanket incl. cabinet and fixing | XQ5: FM200 / CO2 clean agent suppression system incl. cylinder, nozzle and panel | XR5: Kitchen hood wet chemical suppression system incl. nozzle and control | XS5: Solar PV system incl. panel, inverter, mounting, cabling and commissioning | XT5: Water treatment plant incl. filter, dosing, control and commissioning | XU5: Swimming pool filtration system incl. pump, filter, dosing and control | XV5: Commercial kitchen equipment incl. connection and commissioning | XW5: Passenger lift, 1000kg / 13 person, incl. car, door, control and commissioning | XX5: Service / goods lift incl. car, door, control and commissioning | XY5: Firefighting lift incl. fireman switch, control and commissioning | XZ5: Platform / accessibility lift incl. control and commissioning | YA5: Escalator incl. truss, balustrade, control and commissioning | YB5: Lift pit access ladder incl. fixing | YC5: Lift shaft lighting and socket incl. wiring and switch | YD5: Lift machine room equipment incl. ventilation, lighting and hoisting beam | YE5: Testing, adjusting and commissioning of complete installation incl. report | YF5: As-built drawings incl. printing and soft copy submission | YG5: Operation and maintenance manual incl. warranty documents | YH5: Training of client operating personnel | YI5: Recommended spare parts as per specification | YJ5: Site clearing; supply and lay complete incl. base preparation and jointing. | YK5: Cut and fill to formation level incl. compaction | YL5: Compaction of formation to 95% MDD incl. watering and testing | YM5: Reinforced concrete paving 150mm thk. incl. base, mesh and joint | YN5: Asphalt concrete wearing course 50mm thk. incl. prime coat and base | YO5: Interlocking concrete paver 60mm thk. incl. sand bedding and jointing | YP5: Precast concrete kerb incl. bedding, haunching and jointing | YQ5: Thermoplastic road marking incl. surface preparation | YR5: Car park surfacing incl. marking, wheel stop and signage | YS5: Approved top soil spread and levelled | YT5: Turfing incl. top soil, fertiliser and watering to establishment | YU5: Supply and plant tree / shrub incl. pit, soil mix, stake and maintenance | YV5: Planter box incl. waterproofing, drainage layer and soil | YW5: Landscape irrigation system incl. piping, sprinkler, valve and controller | YX5: Boundary fence incl. post, mesh/panel, foundation and painting | YY5: Main entrance gate incl. frame, leaf, hardware, motor and painting | YZ5: Steel guard rail incl. fabrication, painting and fixing | ZA5: Boundary wall incl. foundation, blockwork, plaster and paint | ZB5: Flag pole incl. foundation, halyard and finishing | ZC5: Bollard incl. foundation and finishing | ZD5: Bicycle rack incl. fixing to slab | ZE5: Covered walkway incl. steel structure, roofing and finishes | ZF5: Guard house incl. structure, finishes and services | ZG5: Playground / sport court incl. surfacing, marking and equipment | ZH5: tile size (300x300)mm | ZI5: tile size (300x600)mm
A6: Super Structure | C6: Super Structure | D6: _S002 | F6: Sub Structure|Shoring & Sheet Pile | G6: _B002 | I6: Sub Structure|Site Preparation & Earthwork|Excavation | J6: _D002 | M6: Shoring & Sheet Pile | N6: Structural Beam | O6: Concrete block | P6: Painting | Q6: Aluminium door | R6: Aluminium louver | S6: Floor tiling | U6: Handrail & Balustrade | V6: Roof waterproofing & insulation | W6: Dry wall partition | X6: PVC door | Z6: Painting | AA6: Floor tiling | AB6: Acoustic ceiling | AC6: Kitchen Fitting | AD6: Sanitary fitting | AE6: VRF / VRV system | AF6: Specialist ventilation | AG6: Air terminal | AH6: Cable & containment | AI6: Security system | AJ6: Water storage & pump | AK6: Sprinkler system | AM6: Escalator | AO6: Roads, path, paving | AP6: Excavation | AQ6: Sheet Pile Driving | AR6: Concrete | AS6: Pile Driving | AT6: Base Preparation | AU6: Base Preparation | AV6: Lean Concrete | AW6: Crush Stone | AX6: Base Preparation | AY6: Base Preparation | AZ6: Lean Concrete | BA6: Concrete | BB6: Formwork | BC6: Formwork | BD6: Formwork | BE6: Formwork | BF6: Formwork | BG6: Formwork | BH6: Formwork | BI6: Formwork | BJ6: U steel | BK6: Purlin | BL6: Rebar Testing | BM6: Hollow clay brick 200mm Thk. | BN6: Concrete block 150mm Thk. | BO6: AAC block 150mm Thk. | BP6: Panel jointing & sealant | BQ6: Curtain wall | BR6: Skim coat | BS6: Primer coat | BT6: Stone cladding | BU6: Sealant | BV6: Fire rated steel door | BW6: Aluminium sliding door | BX6: Framed glass door | BY6: Motor & control | BZ6: Door closer | CA6: Fixed glass window | CB6: Steel louver | CC6: Mosquito screen | CD6: Floor hardener | CE6: Anti-slip tile | CF6: Protection screed | CG6: Painting | CH6: Ramp finish | CI6: Balustrade | CJ6: Roof tile | CK6: Thermal insulation | CL6: Downpipe | CM6: Roof access hatch | CN6: Hollow clay brick 200mm Thk. | CO6: Cement board partition | CP6: Framed glass partition | CQ6: Urinal divider | CR6: Handrail on staircase | CS6: Solid core wood door | CU6: Fire rated door | CV6: Glass door | CW6: Door closer | CX6: Interior louver | CY6: Laboratory gas outlet | CZ6: Skim coat | DA6: Primer coat | DB6: Toilet Wall tile | DC6: Acoustic panel | DE6: Self-levelling screed | DF6: Toilet Floor tile | DG6: Marble flooring | DH6: Epoxy flooring | DI6: anti termite | DJ6: Stair nosing | DK6: Gypsum board ceiling | DL6: Mineral fibre ceiling | DM6: Metal grid ceiling | DN6: Cornice | DO6: Mirror | DP6: Counter top | DQ6: Library shelving | DR6: External round logo | DS6: Wash basin | DT6: Flush valve | DU6: Soap dispenser | DV6: Cassette type unit | DW6: VRF outdoor unit | DX6: Air handling unit (AHU) | DY6: Chilled water piping | DZ6: Kitchen exhaust fan | EA6: Smoke extraction fan | EB6: Flexible duct | EC6: Return air grille | ED6: Fire damper | EE6: Sub-distribution board (DB) | EF6: Control cable | EG6: Switch | EH6: Exterior luminaire | EI6: Earth rod & pit | EJ6: Automatic transfer switch (ATS) | EK6: Smoke / heat detector | EL6: NVR / recorder | EM6: Network switch / rack | EN6: Speaker | EO6: Field device & sensor | EP6: Hot water piping | EQ6: Transfer pump | ER6: Waste pipe | ES6: Sewage treatment plant (STP) | ET6: Hose reel | EU6: Sprinkler piping | EV6: Jockey pump | EW6: Fire blanket | EX6: Water treatment plant | EY6: Service / goods lift | FA6: Shaft lighting & socket | FB6: As-built drawing | FC6: Cut & fill | FD6: Asphalt paving | FE6: Turfing | FF6: Main gate | FG6: Bollard | FW6: Bored piling D800mm incl. boring, casing and disposal of spoil | FX6: Normal Concrete, 35Mpa (Cylinder), Slump 15+-2.5 | FY6: Deform Bar, DB12(fy=390 Mpa) | GC6: Pile Head Cutting up to required level D800mm | GD6: Pile Integrity Test (PIT) | GE6: Soil Coring for Bored Pile D800mm, Depth 30m | GF6: Static pile load test to 200% design working load | GM6: Static pile load test to 200% design working load | GN6: Soil Disposal | GP6: Crush Stone 40x60mm 150mm Thk. | GR6: Normal Concrete, 35Mpa (Cylinder), Slump 15+-2.5 | GS6: Formwork to curved / special shape incl. erection and striking | GT6: Deform Bar, DB12(fy=390 Mpa) | GW6: Sika Waterproofing | GY6: Soil Disposal | HA6: Crush Stone 40x60mm 150mm Thk. | HC6: Normal Concrete, 35Mpa (Cylinder), Slump 15+-2.5 | HD6: Formwork, plywood 18mm thk. incl. erection, bracing, oiling and striking | HE6: Deform Bar, DB12(fy=390 Mpa) | HH6: Sika Waterproofing | HJ6: Soil Disposal | HL6: Normal Concrete, 35Mpa (Cylinder), Slump 15+-2.5 | HM6: Formwork, plywood 18mm thk. incl. erection, bracing, oiling and striking | HN6: Deform Bar, DB12(fy=390 Mpa) | HP6: Sika Waterproofing | HR6: Crush Stone 40x60mm 150mm Thk. | HV6: Normal Concrete, 35Mpa (Cylinder), Slump 15+-2.5 | HW6: Formwork, plywood 18mm thk. incl. erection, bracing, oiling and striking | HX6: Deform Bar, DB12(fy=390 Mpa) | HZ6: Sika Waterproofing | IA6: Soil Disposal | IC6: Crush Stone 40x60mm 150mm Thk. | IE6: Normal Concrete, 35Mpa (Cylinder), Slump 15+-2.5 | IF6: Formwork, plywood 18mm thk. incl. erection, bracing, oiling and striking | IG6: Deform Bar, DB12(fy=390 Mpa) | IJ6: Sika Waterproofing | IL6: Soil Disposal | IN6: Crush Stone 40x60mm 150mm Thk. | IP6: Normal Concrete, 35Mpa (Cylinder), Slump 15+-2.5 | IQ6: Formwork, plywood 18mm thk. incl. erection, bracing, oiling and striking | IR6: Deform Bar, DB12(fy=390 Mpa) | IU6: Sika Waterproofing | IW6: Soil Disposal | IY6: Normal Concrete, 35Mpa (Cylinder), Slump 15+-2.5 | IZ6: Formwork, plywood 18mm thk. incl. erection, bracing, oiling and striking | JA6: Deform Bar, DB12(fy=390 Mpa) | JD6: Sika Waterproofing | JE6: Soil Disposal | JF6: Normal Concrete, 35Mpa (Cylinder), Slump 15+-2.5 | JG6: Formwork, plywood 18mm thk. incl. erection, bracing, oiling and striking | JH6: Deform Bar, DB12(fy=390 Mpa) | JK6: Sika Waterproofing | JN6: Normal Concrete, 35Mpa (Cylinder), Slump 15+-2.5 | JO6: Formwork, plywood 18mm thk. incl. erection, bracing, oiling and striking | JP6: Deform Bar, DB12(fy=390 Mpa) | JT6: Normal Concrete, 35Mpa (Cylinder), Slump 15+-2.5 | JU6: Formwork, plywood 18mm thk. incl. erection, bracing, oiling and striking | JV6: Deform Bar, DB12(fy=390 Mpa) | JX6: Normal Concrete, 35Mpa (Cylinder), Slump 15+-2.5 | JY6: Formwork, plywood 18mm thk. incl. erection, bracing, oiling and striking | JZ6: Deform Bar, DB12(fy=390 Mpa) | KD6: Normal Concrete, 35Mpa (Cylinder), Slump 15+-2.5 | KE6: Formwork, plywood 18mm thk. incl. erection, bracing, oiling and striking | KF6: Deform Bar, DB12(fy=390 Mpa) | KI6: Normal Concrete, 35Mpa (Cylinder), Slump 15+-2.5 | KJ6: Formwork, plywood 18mm thk. incl. erection, bracing, oiling and striking | KK6: Deform Bar, DB12(fy=390 Mpa) | KM6: Normal Concrete, 35Mpa (Cylinder), Slump 15+-2.5 | KN6: Formwork, plywood 18mm thk. incl. erection, bracing, oiling and striking | KO6: Deform Bar, DB12(fy=390 Mpa) | KQ6: Normal Concrete, 35Mpa (Cylinder), Slump 15+-2.5 | KR6: Formwork, plywood 18mm thk. incl. erection, bracing, oiling and striking | KS6: Deform Bar, DB12(fy=390 Mpa) | KV6: Normal Concrete, 35Mpa (Cylinder), Slump 15+-2.5 | KW6: Formwork, plywood 18mm thk. incl. erection, bracing, oiling and striking | KX6: Deform Bar, DB12(fy=390 Mpa) | LL6: Hot dip galvanizing to steelwork, 85 micron minimum | LU6: Hot dip galvanizing to steelwork, 85 micron minimum | MM6: External façade | MQ6: 15mm cement plaster | MT6: Painting, primer + 2 coats emulsion (interior) | NM6: Internal Fix Windoor (L:1800,H:500)mm | NY6: Floor tile Size 0.6x0.6m incl. adhesive and grout | OA6: Sika Waterproofing | OC6: 15mm cement plaster | OD6: Painting, primer + 2 coats emulsion (interior) | PP6: Wood door size (L:900,H:2100,W:400)mm | PR6: PVC door size (L:800,H:2100,W:400)mm | PS6: Steel Door, W:900,H:2100mm incl. frame, ironmongery and painting | QF6: 15mm cement plaster | QH6: Painting, primer + 2 coats emulsion (interior) | QS6: Floor tile Size 0.6x0.6m incl. adhesive and grout | RD6: Sika Waterproofing
A7: Exterior Wall and Partition | C7: Exterior Wall and Partition | D7: _S003 | F7: Sub Structure|Bored Pile | G7: _B003 | I7: Sub Structure|Site Preparation & Earthwork|Backfill | J7: _D003 | M7: Bored Pile | N7: Structural Slab | O7: AAC block | P7: Wall tiling | Q7: Glass door | R7: Window accessories | S7: Waterproofing | V7: Roof drainage | W7: Glass partition | X7: Steel Door | Z7: Wall tiling | AA7: Stone flooring | AB7: Metal ceiling | AC7: Special purpose Fitting | AD7: Sanitary accessories | AE7: Chilled water system | AG7: Damper & control | AH7: Power & wiring accessories | AI7: Communication system | AJ7: Drainage | AK7: Fire pump & tank | AM7: Lift shaft equipment | AO7: Landscape | AP7: Backfill | AQ7: Sheet Pile Extraction | AR7: Rebar | AS7: Pile Splicing | AT7: Crush Stone | AU7: Crush Stone | AV7: Concrete | AW7: Anti-Termite | AX7: Crush Stone | AY7: Crush Stone | AZ7: Concrete | BA7: Formwork | BB7: Rebar | BC7: Rebar | BD7: Rebar | BE7: Rebar | BF7: Rebar | BG7: Rebar | BH7: Rebar | BI7: Rebar | BJ7: Hollow steel tube | BK7: Sag rod | BL7: Non-Destructive Test | BM7: Hollow clay brick 400mm Thk. | BN7: Concrete block 200mm Thk. | BO7: AAC block 200mm Thk. | BQ7: Aluminium composite panel | BR7: Molding / Cornice | BS7: Weather-shield coating | BZ7: Hinge | CA7: Sliding glass window | CC7: Sealant | CG7: Soffit cladding | CH7: Stair nosing | CI7: Guard rail | CJ7: Translucent sheet | CK7: Vapour barrier | CL7: Roof drain | CM7: Roof ladder | CO7: Metal stud framing | CR7: Wall guard rail | CW7: Hinge | DC7: Wallpaper | DF7: Homogeneous tile | DG7: Granite flooring | DH7: Wooden flooring | DJ7: Floor trim / divider | DK7: Cement board ceiling | DN7: Bulkhead | DO7: Counter top | DP7: Sink | DQ7: Sport / gym equipment | DR7: Khmer and Chinese text | DS7: Urinal | DT7: Angle valve | DU7: Grab bar | DV7: Outdoor condensing unit | DW7: Refnet joint | DX7: Fan coil unit (FCU) | DY7: Condensate drain piping | DZ7: Car park ventilation fan | EA7: Laboratory fume hood | EB7: Duct insulation | EC7: Exhaust grille | ED7: Motorized damper | EE7: Busduct / Busway | EF7: Cable tray | EG7: Isolator | EH7: Emergency light | EI7: Lightning air terminal | EJ7: UPS | EK7: Manual call point | EL7: Access control door | EM7: Telephone system | EN7: Bell / clock system | EP7: Pipe insulation | EQ7: Booster pump | ER7: Vent pipe | ES7: Sewer connection | ET7: Landing valve | EU7: Alarm valve set | EV7: Fire water tank | EW7: FM200 / CO2 system | EX7: Swimming pool system | EY7: Firefighting lift | FA7: Machine room equipment | FB7: O&M manual | FC7: Compaction | FD7: Interlocking paver | FE7: Tree & shrub | FF7: Guard rail | FG7: Bicycle rack | FX7: Normal Concrete, 25Mpa (Cylinder), Slump 10+-2.5 | FY7: Deform Bar, DB14(fy=390 Mpa) | GN7: Soil Excavation | GR7: Normal Concrete, 25Mpa (Cylinder), Slump 10+-2.5 | GS7: Formwork, plywood 18mm thk. incl. erection, bracing, oiling and striking | GT7: Deform Bar, DB14(fy=390 Mpa) | GW7: Cementitious waterproofing, 2 coats, to wet area incl. up-turn 300mm | GY7: Soil Excavation | HC7: Normal Concrete, 25Mpa (Cylinder), Slump 10+-2.5 | HE7: Deform Bar, DB14(fy=390 Mpa) | HH7: Cementitious waterproofing, 2 coats, to wet area incl. up-turn 300mm | HJ7: Soil Excavation | HL7: Normal Concrete, 25Mpa (Cylinder), Slump 10+-2.5 | HN7: Deform Bar, DB14(fy=390 Mpa) | HP7: Cementitious waterproofing, 2 coats, to wet area incl. up-turn 300mm | HV7: Normal Concrete, 25Mpa (Cylinder), Slump 10+-2.5 | HX7: Deform Bar, DB14(fy=390 Mpa) | HZ7: Cementitious waterproofing, 2 coats, to wet area incl. up-turn 300mm | IA7: Soil Excavation | IE7: Normal Concrete, 25Mpa (Cylinder), Slump 10+-2.5 | IG7: Deform Bar, DB14(fy=390 Mpa) | IJ7: Cementitious waterproofing, 2 coats, to wet area incl. up-turn 300mm | IL7: Soil Excavation | IP7: Normal Concrete, 25Mpa (Cylinder), Slump 10+-2.5 | IR7: Deform Bar, DB14(fy=390 Mpa) | IU7: Cementitious waterproofing, 2 coats, to wet area incl. up-turn 300mm | IW7: Soil Excavation | IY7: Normal Concrete, 25Mpa (Cylinder), Slump 10+-2.5 | JA7: Deform Bar, DB14(fy=390 Mpa) | JD7: Cementitious waterproofing, 2 coats, to wet area incl. up-turn 300mm | JE7: Soil Excavation | JF7: Normal Concrete, 25Mpa (Cylinder), Slump 10+-2.5 | JH7: Deform Bar, DB14(fy=390 Mpa) | JK7: Cementitious waterproofing, 2 coats, to wet area incl. up-turn 300mm | JN7: Normal Concrete, 25Mpa (Cylinder), Slump 10+-2.5 | JP7: Deform Bar, DB14(fy=390 Mpa) | JT7: Normal Concrete, 25Mpa (Cylinder), Slump 10+-2.5 | JV7: Deform Bar, DB14(fy=390 Mpa) | JX7: Normal Concrete, 25Mpa (Cylinder), Slump 10+-2.5 | JZ7: Deform Bar, DB14(fy=390 Mpa) | KD7: Normal Concrete, 25Mpa (Cylinder), Slump 10+-2.5 | KF7: Deform Bar, DB14(fy=390 Mpa) | KI7: Normal Concrete, 25Mpa (Cylinder), Slump 10+-2.5 | KK7: Deform Bar, DB14(fy=390 Mpa) | KM7: Normal Concrete, 25Mpa (Cylinder), Slump 10+-2.5 | KO7: Deform Bar, DB14(fy=390 Mpa) | KQ7: Normal Concrete, 25Mpa (Cylinder), Slump 10+-2.5 | KS7: Deform Bar, DB14(fy=390 Mpa) | KV7: Normal Concrete, 25Mpa (Cylinder), Slump 10+-2.5 | KX7: Deform Bar, DB14(fy=390 Mpa) | MT7: Painting, primer + 2 coats weather-shield (exterior) | NM7: Internal Fix Windoor (L:2000,H:500)mm & Slide window (L:2000,H:1000)mm | OA7: Cementitious waterproofing, 2 coats, to wet area incl. up-turn 300mm | OD7: Painting, primer + 2 coats weather-shield (exterior) | PP7: Wood door size (L:900,H:2100,W:500)mm | PR7: PVC door size (L:900,H:2100,W:400)mm | QH7: Painting, primer + 2 coats weather-shield (exterior) | RD7: Cementitious waterproofing, 2 coats, to wet area incl. up-turn 300mm
A8: Exterior Wall Finishes | C8: Exterior Wall Finishes | D8: _S004 | F8: Sub Structure|Driven Pile / Micro Pile | G8: _B004 | I8: Sub Structure|Site Preparation & Earthwork|Soil Disposal | J8: _D004 | M8: Driven Pile / Micro Pile | N8: Structural Wall | O8: Precast concrete panel | P8: Expansion joint | Q8: Rolling shutter | V8: Roof accessories | W8: Toilet cubicle | X8: Aluminium / Glass door | Z8: Wall cladding | AA8: Resilient flooring | AB8: Ceiling accessories | AC8: Signage | AE8: AC piping & accessories | AH8: Lighting | AI8: Audio visual & school system | AJ8: Sewage treatment | AK8: Portable & special suppression | AO8: Fence, railing & wall | AP8: Soil Disposal | AQ8: Strut & Waler | AR8: Steel Tie Wire | AS8: Pile Head Cutting | AT8: Lean Concrete | AU8: Lean Concrete | AV8: Formwork | AW8: Vapour Barrier | AX8: Lean Concrete | AY8: Lean Concrete | AZ8: Formwork | BA8: Rebar | BB8: Steel Tie Wire | BC8: Steel Tie Wire | BD8: Steel Tie Wire | BE8: Steel Tie Wire | BF8: Steel Tie Wire | BG8: Steel Tie Wire | BH8: Steel Tie Wire | BI8: Steel Tie Wire | BJ8: Purlin | BK8: Bracing | BL8: Survey & As-Built | BM8: Hollow clay brick 500mm Thk. | BQ8: Louver screen | BZ8: Door stopper | CA8: Casement window | CC8: Window sill | CH8: Tactile paving | CJ8: Ridge cap | CK8: Protection screed | CL8: Flashing | CM8: Lightning terminal base | CO8: Acoustic infill | CW8: Door stopper | DC8: Mirror | DH8: Carpet | DN8: Ceiling painting | DO8: Locker | DR8: Wayfinding sign | DS8: Shower set | DT8: Floor drain | DU8: Hand dryer | DX8: Chilled water pump | DY8: Pipe insulation | DZ8: Fresh air fan | EB8: Duct support | EC8: Louver | ED8: Testing & balancing | EE8: Transformer | EF8: Cable trunking | EG8: Wiring point | EH8: Exit sign | EI8: Down conductor | EJ8: Fuel tank & piping | EK8: Alarm bell / sounder | EL8: Intercom | EM8: MATV / TV outlet | EN8: Projector & screen | EP8: Valve & fitting | EQ8: Water heater | ER8: Rainwater downpipe | ET8: Fire riser piping | EU8: Flow switch | EW8: Kitchen suppression system | EX8: Kitchen equipment | EY8: Platform / accessibility lift | FB8: Training | FD8: Kerb | FE8: Planter | FF8: Boundary wall | FG8: Covered walkway | FX8: Normal Concrete, 30Mpa (Cylinder), Slump 13+-2.5 | FY8: Deform Bar, DB16(fy=390 Mpa) | GR8: Normal Concrete, 30Mpa (Cylinder), Slump 13+-2.5 | GT8: Deform Bar, DB16(fy=390 Mpa) | HC8: Normal Concrete, 30Mpa (Cylinder), Slump 13+-2.5 | HE8: Deform Bar, DB16(fy=390 Mpa) | HL8: Normal Concrete, 30Mpa (Cylinder), Slump 13+-2.5 | HN8: Deform Bar, DB16(fy=390 Mpa) | HV8: Normal Concrete, 30Mpa (Cylinder), Slump 13+-2.5 | HX8: Deform Bar, DB16(fy=390 Mpa) | IE8: Normal Concrete, 30Mpa (Cylinder), Slump 13+-2.5 | IG8: Deform Bar, DB16(fy=390 Mpa) | IP8: Normal Concrete, 30Mpa (Cylinder), Slump 13+-2.5 | IR8: Deform Bar, DB16(fy=390 Mpa) | IY8: Normal Concrete, 30Mpa (Cylinder), Slump 13+-2.5 | JA8: Deform Bar, DB16(fy=390 Mpa) | JF8: Normal Concrete, 30Mpa (Cylinder), Slump 13+-2.5 | JH8: Deform Bar, DB16(fy=390 Mpa) | JN8: Normal Concrete, 30Mpa (Cylinder), Slump 13+-2.5 | JP8: Deform Bar, DB16(fy=390 Mpa) | JT8: Normal Concrete, 30Mpa (Cylinder), Slump 13+-2.5 | JV8: Deform Bar, DB16(fy=390 Mpa) | JX8: Normal Concrete, 30Mpa (Cylinder), Slump 13+-2.5 | JZ8: Deform Bar, DB16(fy=390 Mpa) | KD8: Normal Concrete, 30Mpa (Cylinder), Slump 13+-2.5 | KF8: Deform Bar, DB16(fy=390 Mpa) | KI8: Normal Concrete, 30Mpa (Cylinder), Slump 13+-2.5 | KK8: Deform Bar, DB16(fy=390 Mpa) | KM8: Normal Concrete, 30Mpa (Cylinder), Slump 13+-2.5 | KO8: Deform Bar, DB16(fy=390 Mpa) | KQ8: Normal Concrete, 30Mpa (Cylinder), Slump 13+-2.5 | KS8: Deform Bar, DB16(fy=390 Mpa) | KV8: Normal Concrete, 30Mpa (Cylinder), Slump 13+-2.5 | KX8: Deform Bar, DB16(fy=390 Mpa) | NM8: Internal Fix Windoor (L:2000,H:500)mm & Slide window (L:2000,H:10300)mm | PP8: Double leaf wood door, W:1600,H:2100mm incl. frame and ironmongery | PR8: PVC door, W:700,H:2000mm incl. frame and ironmongery
A9: Exterior Door | C9: Exterior Door | D9: _S005 | F9: Sub Structure|Pile Cap & Stump | G9: _B005 | I9: Sub Structure|Site Preparation & Earthwork|Compaction | J9: _D005 | M9: Pile Cap & Stump | N9: Structural Staircase | O9: External façade | Q9: Door ironmongery | W9: Handrail | X9: Door ironmongery | Z9: Skirting | AA9: Waterproofing | AH9: Earthing & lightning protection | AI9: Building management | AO9: External fixture | AP9: Compaction | AQ9: Ground Anchor | AR9: Steel Round Pipe | AS9: Pile Load Test | AT9: Concrete | AU9: Concrete | AV9: Rebar | AW9: Lean Concrete | AX9: Concrete | AY9: Concrete | AZ9: Rebar | BA9: Steel Tie Wire | BB9: Column Starter Bar | BD9: Post-Tension Strand | BE9: Water Stop | BH9: Water Stop | BJ9: Sag rod | BK9: Zinc sheet | BM9: Hollow clay brick 800mm Thk. | CW9: Panic bar | DH9: Raised floor | DN9: Curtain box | DO9: Shelving | DR9: Room sign | DS9: Squat pan | DT9: Floor trap | DX9: Cooling tower | DY9: Thermostat / control | DZ9: Staircase pressurization fan | EE9: Capacitor bank | EF9: Conduit | EH9: Lighting control / sensor | EM9: WiFi access point | EN9: Classroom AV system | EP9: Water meter | EQ9: Level control | ER9: Manhole / inspection chamber | FB9: Spare parts | FD9: Road marking | FE9: Irrigation system | FG9: Guard house | FY9: Deform Bar, DB20(fy=390 Mpa) | GT9: Deform Bar, DB20(fy=390 Mpa) | HE9: Deform Bar, DB20(fy=390 Mpa) | HN9: Deform Bar, DB20(fy=390 Mpa) | HX9: Deform Bar, DB20(fy=390 Mpa) | IG9: Deform Bar, DB20(fy=390 Mpa) | IR9: Deform Bar, DB20(fy=390 Mpa) | JA9: Deform Bar, DB20(fy=390 Mpa) | JH9: Deform Bar, DB20(fy=390 Mpa) | JP9: Deform Bar, DB20(fy=390 Mpa) | JV9: Deform Bar, DB20(fy=390 Mpa) | JZ9: Deform Bar, DB20(fy=390 Mpa) | KF9: Deform Bar, DB20(fy=390 Mpa) | KK9: Deform Bar, DB20(fy=390 Mpa) | KO9: Deform Bar, DB20(fy=390 Mpa) | KS9: Deform Bar, DB20(fy=390 Mpa) | KX9: Deform Bar, DB20(fy=390 Mpa) | NM9: Internal Fix Windoor (L:3000,H:500)mm | PP9: Wood door, W:800,H:2100mm incl. frame, ironmongery and painting | PR9: PVC door, W:800,H:2000mm incl. frame and ironmongery
A10: Exterior Window and Louver | C10: Exterior Window and Louver | D10: _S006 | F10: Sub Structure|Footing / Raft Foundation | G10: _B006 | I10: Sub Structure|Site Preparation & Earthwork|Dewatering | J10: _D006 | M10: Footing / Raft Foundation | N10: Parapet wall & Stiffener Column | X10: Interior window / louver | Z10: Toilet Wall tile | AA10: Floor accessories | AH10: Standby power | AP10: Dewatering | AQ10: Guide Wall | AR10: Bentonite / Slurry | AT10: Formwork | AU10: Formwork | AV10: Steel Tie Wire | AW10: Concrete | AX10: Formwork | AY10: Formwork | AZ10: Steel Tie Wire | BA10: Water Stop | BB10: Grouting | BD10: Steel Deck | BJ10: Bracing | BK10: Flashing | DO10: Blind & curtain | DR10: Statutory / safety sign | DS10: Sink | DT10: Clean out | EE10: Metering panel | EF10: Cable ladder | ER10: Grease trap | FD10: Car park | FG10: Playground / sport court | FY10: Deform Bar, DB25(fy=390 Mpa) | GT10: Deform Bar, DB25(fy=390 Mpa) | HE10: Deform Bar, DB25(fy=390 Mpa) | HN10: Deform Bar, DB25(fy=390 Mpa) | HX10: Deform Bar, DB25(fy=390 Mpa) | IG10: Deform Bar, DB25(fy=390 Mpa) | IR10: Deform Bar, DB25(fy=390 Mpa) | JA10: Deform Bar, DB25(fy=390 Mpa) | JH10: Deform Bar, DB25(fy=390 Mpa) | JP10: Deform Bar, DB25(fy=390 Mpa) | JV10: Deform Bar, DB25(fy=390 Mpa) | JZ10: Deform Bar, DB25(fy=390 Mpa) | KF10: Deform Bar, DB25(fy=390 Mpa) | KK10: Deform Bar, DB25(fy=390 Mpa) | KO10: Deform Bar, DB25(fy=390 Mpa) | KS10: Deform Bar, DB25(fy=390 Mpa) | KX10: Deform Bar, DB25(fy=390 Mpa) | NM10: Internal Fix Windoor (L:3000,H:500)mm & Slide window (L:3000,H:1000)mm | PP10: Wood door, W:900,H:2100mm incl. frame, ironmongery and painting | PR10: PVC door, W:900,H:2000mm incl. frame and ironmongery
A11: Exterior floor | C11: Exterior floor | D11: _S007 | F11: Sub Structure|Ground Beam / Tie Beam | G11: _B007 | I11: Sub Structure|Site Preparation & Earthwork|Levelling & Setting Out | J11: _D007 | M11: Ground Beam / Tie Beam | N11: Lift Core / Shear Core | AA11: Toilet Floor tile | AP11: Levelling & Setting Out | AR11: Bored Pile Head Cutting | AT11: Rebar | AU11: Rebar | AV11: Waterproofing | AW11: Formwork | AX11: Rebar | AY11: Rebar | AZ11: Water Stop | BA11: Waterproofing | BJ11: Base Plate | BK11: Anchor Bolt | DO11: White board | FY11: Deform Bar, DB32(fy=390 Mpa) | GT11: Deform Bar, DB32(fy=390 Mpa) | HE11: Deform Bar, DB32(fy=390 Mpa) | HN11: Deform Bar, DB32(fy=390 Mpa) | HX11: Deform Bar, DB32(fy=390 Mpa) | IG11: Deform Bar, DB32(fy=390 Mpa) | IR11: Deform Bar, DB32(fy=390 Mpa) | JA11: Deform Bar, DB32(fy=390 Mpa) | JH11: Deform Bar, DB32(fy=390 Mpa) | JP11: Deform Bar, DB32(fy=390 Mpa) | JV11: Deform Bar, DB32(fy=390 Mpa) | JZ11: Deform Bar, DB32(fy=390 Mpa) | KF11: Deform Bar, DB32(fy=390 Mpa) | KK11: Deform Bar, DB32(fy=390 Mpa) | KO11: Deform Bar, DB32(fy=390 Mpa) | KS11: Deform Bar, DB32(fy=390 Mpa) | KX11: Deform Bar, DB32(fy=390 Mpa) | NM11: Internal Fix Windoor (L:4000,H:500)mm & Slide window (L:4000,H:1700)mm
A12: Exterior soffit | C12: Exterior soffit | D12: _S008 | F12: Sub Structure|Slab on Grade / Ground Slab | G12: _B008 | I12: Sub Structure|Shoring & Sheet Pile|Sheet Pile Supply | J12: _D008 | M12: Slab on Grade / Ground Slab | N12: Ramp | AR12: Bored Pile Testing | AT12: Steel Tie Wire | AU12: Steel Tie Wire | AW12: Rebar | AX12: Steel Tie Wire | AY12: Steel Tie Wire | AZ12: Waterproofing | BA12: Protection Board | BJ12: Steel plate | BK12: Painting / Galvanizing | FY12: Round Bar, RB8(fy=250 Mpa) | GT12: Round Bar, RB8(fy=250 Mpa) | HE12: Round Bar, RB8(fy=250 Mpa) | HN12: Round Bar, RB8(fy=250 Mpa) | HX12: Round Bar, RB8(fy=250 Mpa) | IG12: Round Bar, RB8(fy=250 Mpa) | IR12: Round Bar, RB8(fy=250 Mpa) | JA12: Round Bar, RB8(fy=250 Mpa) | JH12: Round Bar, RB8(fy=250 Mpa) | JP12: Round Bar, RB8(fy=250 Mpa) | JV12: Round Bar, RB8(fy=250 Mpa) | JZ12: Round Bar, RB8(fy=250 Mpa) | KF12: Round Bar, RB8(fy=250 Mpa) | KK12: Round Bar, RB8(fy=250 Mpa) | KO12: Round Bar, RB8(fy=250 Mpa) | KS12: Round Bar, RB8(fy=250 Mpa) | KX12: Round Bar, RB8(fy=250 Mpa) | NM12: Internal Fix Windoor (L:900,H:1000)mm
A13: Exterior Stair Ramp | C13: Exterior Stair Ramp | D13: _S009 | F13: Sub Structure|Septic tank | G13: _B009 | I13: Sub Structure|Shoring & Sheet Pile|Sheet Pile Driving | J13: _D009 | M13: Septic tank | N13: Structural Steel | AR13: Bored Pile Coring | AT13: Water Stop | AU13: Water Stop | AW13: Steel Tie Wire | AX13: Water Stop | AY13: Water Stop | BA13: Drainage Board | BJ13: J bolt | FY13: Round Bar, RB6(fy=250 Mpa) | GT13: Round Bar, RB6(fy=250 Mpa) | HE13: Round Bar, RB6(fy=250 Mpa) | HN13: Round Bar, RB6(fy=250 Mpa) | HX13: Round Bar, RB6(fy=250 Mpa) | IG13: Round Bar, RB6(fy=250 Mpa) | IR13: Round Bar, RB6(fy=250 Mpa) | JA13: Round Bar, RB6(fy=250 Mpa) | JH13: Round Bar, RB6(fy=250 Mpa) | JP13: Round Bar, RB6(fy=250 Mpa) | JV13: Round Bar, RB6(fy=250 Mpa) | JZ13: Round Bar, RB6(fy=250 Mpa) | KF13: Round Bar, RB6(fy=250 Mpa) | KK13: Round Bar, RB6(fy=250 Mpa) | KO13: Round Bar, RB6(fy=250 Mpa) | KS13: Round Bar, RB6(fy=250 Mpa) | KX13: Round Bar, RB6(fy=250 Mpa) | NM13: Windoor Aluminium frame with 6mm tempered glass, fix + slide panel
A14: Roofing | C14: Roofing | D14: _S010 | F14: Sub Structure|Water Tank / Sump Pit | G14: _B010 | I14: Sub Structure|Shoring & Sheet Pile|Sheet Pile Extraction | J14: _D010 | M14: Water Tank / Sump Pit | N14: Roof Structure / Truss | AR14: Pile Load Test | AT14: Waterproofing | AU14: Waterproofing | AW14: Waterproofing | AX14: Waterproofing | AY14: Waterproofing | BJ14: Anchor Bolt | NM14: Windoor Aluminium frame with 6mm tempered glass, fix panel
A15: Interior Wall and Partition | C15: Interior Wall and Partition | D15: _S011 | F15: Sub Structure|Lift Pit | G15: _B011 | I15: Sub Structure|Shoring & Sheet Pile|Strut & Waler | J15: _D011 | M15: Lift Pit | N15: Testing & Quality Control | AR15: Rebar Testing | AT15: Anti-Termite | AU15: Anti-Termite | AX15: Anti-Termite | AY15: Anti-Termite | BJ15: Bolt & Nut
A16: Interior Doors | C16: Interior Doors | D16: _S012 | F16: Sub Structure|Basement / Retaining Wall | G16: _B012 | I16: Sub Structure|Shoring & Sheet Pile|Ground Anchor | J16: _D012 | M16: Basement / Retaining Wall | AR16: Concrete Testing | BJ16: Welding
A17: Special installation | C17: Special installation | D17: _S013 | F17: Super Structure|Structural Column | G17: _B013 | I17: Sub Structure|Shoring & Sheet Pile|Guide Wall | J17: _D013 | BJ17: Painting / Galvanizing
A18: Interior Wall Finishes | C18: Interior Wall Finishes | D18: _S014 | F18: Super Structure|Structural Beam | G18: _B014 | I18: Sub Structure|Bored Pile|Bored Pile Boring | J18: _D014 | BJ18: Fire Proofing
A19: Interior Floor Finishes | C19: Interior Floor Finishes | D19: _S015 | F19: Super Structure|Structural Slab | G19: _B015 | I19: Sub Structure|Bored Pile|Concrete | J19: _D015
A20: Ceiling Finishes | C20: Ceiling Finishes | D20: _S016 | F20: Super Structure|Structural Wall | G20: _B016 | I20: Sub Structure|Bored Pile|Rebar | J20: _D016
A21: Fittings, furnishings and equipment | C21: Fittings, furnishings and equipment | D21: _S017 | F21: Super Structure|Structural Staircase | G21: _B017 | I21: Sub Structure|Bored Pile|Steel Tie Wire | J21: _D017
A22: Sanitary Installations | C22: Sanitary Installations | D22: _S018 | F22: Super Structure|Parapet wall & Stiffener Column | G22: _B018 | I22: Sub Structure|Bored Pile|Steel Round Pipe | J22: _D018
A23: AIR-CONDITIONAL SYSTEM | C23: AIR-CONDITIONAL SYSTEM | D23: _S019 | F23: Super Structure|Lift Core / Shear Core | G23: _B019 | I23: Sub Structure|Bored Pile|Bentonite / Slurry | J23: _D019
A24: MECHANICAL VENTILATION SYSTEM | C24: MECHANICAL VENTILATION SYSTEM | D24: _S020 | F24: Super Structure|Ramp | G24: _B020 | I24: Sub Structure|Bored Pile|Bored Pile Head Cutting | J24: _D020
A25: MV DISTRIBUTION SYSTEM | C25: MV DISTRIBUTION SYSTEM | D25: _S021 | F25: Super Structure|Structural Steel | G25: _B021 | I25: Sub Structure|Bored Pile|Bored Pile Testing | J25: _D021
A26: ELECTRICAL SYSTEM | C26: ELECTRICAL SYSTEM | D26: _S022 | F26: Super Structure|Roof Structure / Truss | G26: _B022 | I26: Sub Structure|Bored Pile|Bored Pile Coring | J26: _D022
A27: ELV INSTALLATION | C27: ELV INSTALLATION | D27: _S023 | F27: Super Structure|Testing & Quality Control | G27: _B023 | I27: Sub Structure|Bored Pile|Pile Load Test | J27: _D023
A28: PLUMBING SYSTEM | C28: PLUMBING SYSTEM | D28: _S024 | F28: Exterior Wall and Partition|Hollow clay brick | G28: _B024 | I28: Sub Structure|Bored Pile|Rebar Testing | J28: _D024
A29: FIRE FIGHTING SYSTEM | C29: FIRE FIGHTING SYSTEM | D29: _S025 | F29: Exterior Wall and Partition|Concrete block | G29: _B025 | I29: Sub Structure|Bored Pile|Concrete Testing | J29: _D025
A30: Specialist Installations | C30: Specialist Installations | D30: _S026 | F30: Exterior Wall and Partition|AAC block | G30: _B026 | I30: Sub Structure|Driven Pile / Micro Pile|Pile Supply | J30: _D026
... A33: External Work | C33: External Work | D33: _S029 | F33: Exterior Wall Finishes|Plastering | G33: _B029 | I33: Sub Structure|Driven Pile / Micro Pile|Pile Head Cutting | J33: _D029
F34: Exterior Wall Finishes|Painting | G34: _B030 | I34: Sub Structure|Driven Pile / Micro Pile|Pile Load Test | J34: _D030
F35: Exterior Wall Finishes|Wall tiling | G35: _B031 | I35: Sub Structure|Pile Cap & Stump|Earthwork | J35: _D031
F36: Exterior Wall Finishes|Expansion joint | G36: _B032 | I36: Sub Structure|Pile Cap & Stump|Base Preparation | J36: _D032
F37: Exterior Door|Steel Door | G37: _B033 | I37: Sub Structure|Pile Cap & Stump|Crush Stone | J37: _D033
F38: Exterior Door|Aluminium door | G38: _B034 | I38: Sub Structure|Pile Cap & Stump|Lean Concrete | J38: _D034
F39: Exterior Door|Glass door | G39: _B035 | I39: Sub Structure|Pile Cap & Stump|Concrete | J39: _D035
F40: Exterior Door|Rolling shutter | G40: _B036 | I40: Sub Structure|Pile Cap & Stump|Formwork | J40: _D036
F41: Exterior Door|Door ironmongery | G41: _B037 | I41: Sub Structure|Pile Cap & Stump|Rebar | J41: _D037
F42: Exterior Window and Louver|Glass Window | G42: _B038 | I42: Sub Structure|Pile Cap & Stump|Steel Tie Wire | J42: _D038
F43: Exterior Window and Louver|Aluminium louver | G43: _B039 | I43: Sub Structure|Pile Cap & Stump|Water Stop | J43: _D039
F44: Exterior Window and Louver|Window accessories | G44: _B040 | I44: Sub Structure|Pile Cap & Stump|Waterproofing | J44: _D040
F45: Exterior floor|Screeding | G45: _B041 | I45: Sub Structure|Pile Cap & Stump|Anti-Termite | J45: _D041
... F128: Interior Wall Finishes|Toilet Wall tile | G128: _B124 | I128: Super Structure|Structural Slab|Steel Deck | J128: _D124
I129: Super Structure|Structural Wall|Concrete | J129: _D125
I130: Super Structure|Structural Wall|Formwork | J130: _D126
I131: Super Structure|Structural Wall|Rebar | J131: _D127
I132: Super Structure|Structural Wall|Steel Tie Wire | J132: _D128
I133: Super Structure|Structural Wall|Water Stop | J133: _D129
I134: Super Structure|Structural Staircase|Concrete | J134: _D130
I135: Super Structure|Structural Staircase|Formwork | J135: _D131
I136: Super Structure|Structural Staircase|Rebar | J136: _D132
I137: Super Structure|Structural Staircase|Steel Tie Wire | J137: _D133
I138: Super Structure|Parapet wall & Stiffener Column|Concrete | J138: _D134
I139: Super Structure|Parapet wall & Stiffener Column|Formwork | J139: _D135
I140: Super Structure|Parapet wall & Stiffener Column|Rebar | J140: _D136
... I524: Interior Wall Finishes|Toilet Wall tile|Toilet Wall tile | J524: _D520

Sheet Naming Standard
A1: NAMING STANDARD & DUPLICATE WARNING
A2: Inconsistent spelling splits SUMIFS roll-ups. These variants exist in the current project file — standardise on the left column.
A4: Use this (standard) | B4: Do NOT use (variant found) | C4: Why it matters
A5: Interior Wall Finishes | B5: Internal Wall Finishes | C5: Two spellings = two separate D.01 groups in the BoQ
A6: Interior Floor Finishes | B6: Internal Floor Finishes | C6: Two spellings = two separate D.02 groups
A7: Ceiling Finishes | B7: Ceiling Finshes | C7: Typo in current file — breaks lookup against Budget Code list
A8: Exterior Wall and Partition | B8: External Wall and Partition | C8: Budget Code C.01 wording
A9: Exterior Window and Louver | B9: External Windows and Louvers | C9: Budget Code C.04 wording
A10: Interior Doors | B10: Interior Door | C10: Budget Code C.10 wording
A11: Handrail | B11: Handrail on staircase | C11: Keep Sub Section = Handrail; put location in Sub Element / Description
A12: (no trailing spaces) | B12: "Formwork " / "Marble on staircase " | C12: Trailing spaces silently zero-out SUMIFS — always TRIM
A14: RULES OF USE
A15: 1. Section = Budget Code element (e.g. Interior Wall Finishes). One Section = one Budget Code.
A16: 2. Sub Section = work type / trade package (e.g. Plastering, Hollow clay brick, Lighting).
A17: 3. Sub Element = the item measured (e.g. Toilet Wall tile, Emergency light).
A18: 4. Description (Material Type) = the priced specification wording. THIS is what the rate attaches to.
A19: 5. Structure differs: Sub Section = structural element (Structural Beam); Sub Element = work type (Concrete, Rebar, Formwork).
A20: 6. Descriptions marked "In Price List = Yes" already carry a rate in the current project — reuse them for consistency.
A21: 7. Always edit sizes / grades in the Description to match the specification before pricing.
A22: 8. Never retype a Section or Description — copy from this library so the spelling never drifts.
